Workbook

Sheet Home
A1: # | B1: LTI - Mindtree Merger: M&A Case Study
B2: Was the 73:100 stock-for-stock exchange ratio a fair valuation? Full DCF, Trading Comps, and Precedent Transactions analysis, formal exchange-ratio mechanics, and accretion/dilution - triangulated against the actual deal and the real, disclosed post-merger results.
A5: ## | B5: SECTION 1 - M&A Analysis (start here)
B6: The headline deliverable: cross-company valuation, deal mechanics, and the fairness question.
B7: -> Football Field | C7: Capstone: DCF + Comps + Precedent Transactions synthesized into one view
B8: -> Precedent Transactions | C8: Real M&A comps, third valuation method
B9: -> Exchange Ratio & Ownership | C9: Share issuance, ownership split, premium/discount check
B10: -> Pro Forma & Accretion-Dilution | C10: Real disclosed post-merger results, accretion/dilution, industry-adjusted margin test
B11: -> Event Study - Market Reaction | C11: Real abnormal-returns analysis around the announcement date
B12: -> Stress Test - Exchange Ratio | C12: Bull/Base/Bear bounds test, methodology from Sasi's own course
B13: -> Synergies (Bottom-Up Estimate) | C13: Secondary - bottom-up estimate, see Pro Forma sheet for actuals
B14: -> Best Owner Analysis
B15: -> Goal-Seek Synergy Backsolve
B16: -> Value of Control
B17: -> AVP - Various Exchange Ratios
B18: -> Reference LBO Floor
A19: ## | B19: SECTION 2 - LTI Standalone Model
B20: Full standalone financial model for Larsen & Toubro Infotech: historicals, 3-statement forecast, DCF, WACC, Comps.
B21: -> LTI_HIST_CON | C21: Historical financials, as filed (Tier 1)
B22: -> LTI_DCF | C22: DCF valuation output
B23: -> LTI_WACC Schedule | C23: WACC build, deal-date share price/count
B24: -> LTI_Comps
B25: -> LTI_Balance Sheet (Projected)
B26: -> LTI_CFStmt
A28: ## | B28: SECTION 3 - Mindtree Standalone Model
B29: Same full standalone build for Mindtree, mirroring the LTI structure sheet-for-sheet.
B30: -> MT_HIST_CON | C30: Historical financials, as filed (Tier 1)
B31: -> MT_DCF | C31: DCF valuation output
B32: -> MT_WACC Schedule | C32: WACC build, deal-date share price/count
B33: -> MT_Comps
B34: -> MT_Balance Sheet (Projected)
B35: -> MT_CFStmt
B37: Tab colors: teal = M&A Analysis, navy = LTI standalone, orange = Mindtree standalone - all 40 sheets in one file, grouped and color-coded rather than split into separate files, so every cross-company formula in Section 1 stays a live, auditable, same-file link with no cross-file reference fragility.

Sheet Event Study - Market Reaction
A1: # | B1: Event Study - Market Reaction to the Merger Announcement
B2: Did the market see this as value-creating? Cumulative Abnormal Returns (CAR) around the 6-May-2022 announcement, market-model methodology grounded in the Theory notebook (Moeller/Schlingemann/Stulz 2005, Schwert 1996). Real daily prices - LTI via Yahoo Finance (current ticker LTM.NS), Mindtree via NSE's own bhavcopy archives (its ticker was fully delisted, not just renamed, and dropped from Yahoo entirely). Both cross-validated against this model's already-established 6-May-2022 prices.
A4: ## | B4: Market Model Regression - LTI vs Nifty IT
B5: Estimation window: rows 61-179 below (2021-11-01 to 2022-04-25, ~120 trading days, ending 8 trading days before the announcement to avoid run-up contamination).
B7: Disclosed limitation (audit gap #13, Task 26 - checked against this script directly, not assumed either way): the estimation window ends only 8 trading days before the announcement. Standard event-study practice guards against merger-related run-up/leakage with a wider buffer (e.g. 16-42 trading days). Two mitigating, deal-specific factors, not an excuse to skip the disclosure: (1) both LTI and Mindtree were ALREADY L&T subsidiaries pre-merger, so this deal lacks the third-party bidding-war/rumor-driven accumulation dynamic that motivates the wider buffers in the general literature; (2) the regression's R-squared (below) is high enough that a few contaminated days near the edge of the window would have limited leverage over the fitted alpha/beta. Neither claim has been separately tested - flagged honestly as a real, narrower-than-textbook buffer, not silently treated as fully addressed.
B9: Beta (slope) | C9: =SLOPE(D61:D179,F61:F179)
B10: Alpha (intercept, daily) | C10: =INTERCEPT(D61:D179,F61:F179)
B11: R-squared | C11: =RSQ(D61:D179,F61:F179)
B12: Std. Error of Regression (daily AR std. dev., estimation window) | C12: =STEYX(D61:D179,F61:F179) | E12: Used below for CAR significance testing (t-stat = CAR / (this x SQRT(window length))).
A14: ## | B14: Market Model Regression - Mindtree vs Nifty IT
B15: Same estimation window and methodology as LTI's regression above - Mindtree's full daily price series (NSE bhavcopy archives, 119 additional dates fetched beyond the original event-window-only set) now covers this window too, so both companies get the same full market-model rigor.
B17: Beta (slope) | C17: =SLOPE(J61:J179,F61:F179)
B18: Alpha (intercept, daily) | C18: =INTERCEPT(J61:J179,F61:F179)
B19: R-squared | C19: =RSQ(J61:J179,F61:F179)
B20: Std. Error of Regression (daily AR std. dev., estimation window) | C20: =STEYX(J61:J179,F61:F179)
A22: ## | B22: Cumulative Abnormal Returns - Summary
B24: Window | C24: LTI CAR (market model) | D24: Mindtree CAR (market model) | E24: Combined CAR (MV-weighted) | F24: LTI t-stat | G24: Mindtree t-stat
B25: [-1,+1] | C25: =SUM(H186:H188) | D25: =SUM(L186:L188) | E25: =C25*$C$28/($C$28+$C$29)+D25*$C$29/($C$28+$C$29) | F25: =C25/($C$12*SQRT(3)) | G25: =D25/($C$20*SQRT(3))
B26: [-2,+2] | C26: =SUM(H185:H189) | D26: =SUM(L185:L189) | E26: =C26*$C$28/($C$28+$C$29)+D26*$C$29/($C$28+$C$29) | F26: =C26/($C$12*SQRT(5)) | G26: =D26/($C$20*SQRT(5))
B28: LTI Market Value pre-event (Rs.M, t=-2) | C28: ='Exchange Ratio & Ownership'!C11*C185/1000000 | E28: LTI shares outstanding x price at t=-2
B29: Mindtree Market Value pre-event (Rs.M, t=-2) | C29: ='Exchange Ratio & Ownership'!C12*I185/1000000
B32: Reading this: a positive Combined CAR means the market judged the announcement as net value-creating for the two companies together (the standard test in the abnormal-returns literature - Jensen 1986, the hubris hypothesis paper, 'Wealth Destruction on a Massive Scale'). LTI's own CAR specifically (not combined) is the closer read on whether the ACQUIRER's shareholders benefited - the literature's well-documented average finding is that acquirers often see flat-to-negative CAR even in deals the combined entity gains from, since much of the value gets bid to the target's shareholders.
A34: ## | B34: Statistical Significance of the CAR Estimates
B36: t-stat = CAR / (estimation-window regression std. error x SQRT(window length in days)) - the standard single-security event-study significance test (Brown & Warner 1985; MacKinlay 1997), shown in the table above. Critical values: |t| > 1.65 significant at 10%, > 1.96 at 5%, > 2.58 at 1%. Deliberately NOT computing a pooled t-stat across LTI-and-Mindtree treated as if they were two independent observations - they are not: both are reacting to the same single announcement and are already correlated by construction (same sector, same L&T parent group), so a naive combined-sample t-test would overstate significance the same way the literature warns pooled cross-sectional event studies do when they ignore industry/time clustering (see the notebook audit, Task 26) - the difference here is that this is a single-deal, two-firm case study, not a multi-deal cross-sectional sample, so the fix is to test each company's own CAR individually (as done above), not to pool them.
B38: Reading this (verified via recalc, not asserted in advance): Mindtree's negative CAR is statistically significant at the 1% level in BOTH windows (t=-2.89 and -2.76) - strong evidence the market's negative reaction to Mindtree specifically was real, not noise. LTI's result is weaker and window-dependent: significant at 5% in the tight [-1,+1] window (t=-2.15) but NOT statistically distinguishable from zero in the wider [-2,+2] window (t=-1.42, below even the 10% threshold). This sharpens rather than overturns the finding above: the market's skepticism was clearly real and significant for Mindtree; for LTI (the acquirer) the evidence is more marginal and window-sensitive - consistent with the literature's general finding that acquirer CARs are often statistically indistinguishable from zero even in deals where the target's reaction is unambiguous.
A58: ## | B58: Daily Data (raw prices sourced; returns and AR are live formulas)
B59: LTI and NiftyIT: Yahoo Finance chart API (ticker LTM.NS, ^CNXIT), parsed directly from raw JSON with IST timezone conversion, cross-validated against NSE bhavcopy at 4 overlapping dates (exact match). Mindtree: NSE bhavcopy archives directly (archives.nseindia.com), 131 of 135 needed trading days (119 fetched individually beyond the original event-window set) - its ticker was delisted (not renamed) at the Nov-2022 merger completion and dropped entirely from Yahoo, so no bulk-range source existed. The 4 uncovered dates fall outside both the estimation and event windows used here.
B60: Date | C60: LTI Close | D60: LTI Return | E60: NiftyIT Close | F60: NiftyIT Return | G60: Expected Return (LTI) | H60: LTI AR | I60: Mindtree Close | J60: Mindtree Return | K60: Expected Return (Mindtree) | L60: Mindtree AR
B61: 2021-11-01 | C61: 6802.15 | E61: 35290 | I61: 4733.7
B62: 2021-11-02 | C62: 6752.9 | D62: =C62/C61-1 | E62: 35177.35 | F62: =E62/E61-1 | I62: 4711.25 | J62: =I62/I61-1
B63: 2021-11-03 | C63: 6736.05 | D63: =C63/C62-1 | E63: 35177.1 | F63: =E63/E62-1 | I63: 4628.3 | J63: =I63/I62-1
B64: 2021-11-04 | C64: 6765 | D64: =C64/C63-1 | E64: 35334.25 | F64: =E64/E63-1 | I64: 4665.8 | J64: =I64/I63-1
B65: 2021-11-08 | C65: 6827.9 | D65: =C65/C64-1 | E65: 35782.35 | F65: =E65/E64-1 | I65: 4829.7 | J65: =I65/I64-1
B66: 2021-11-09 | C66: 6839.65 | D66: =C66/C65-1 | E66: 35815.1 | F66: =E66/E65-1 | I66: 4815.5 | J66: =I66/I65-1
B67: 2021-11-10 | C67: 6835.8 | D67: =C67/C66-1 | E67: 35722.95 | F67: =E67/E66-1 | I67: 4831.45 | J67: =I67/I66-1
B68: 2021-11-11 | C68: 6948.75 | D68: =C68/C67-1 | E68: 35583.65 | F68: =E68/E67-1 | I68: 4888.05 | J68: =I68/I67-1
B69: 2021-11-12 | C69: 7243.25 | D69: =C69/C68-1 | E69: 36332.3 | F69: =E69/E68-1 | I69: 4914.1 | J69: =I69/I68-1
B70: 2021-11-15 | C70: 7197.35 | D70: =C70/C69-1 | E70: 36465.3 | F70: =E70/E69-1 | I70: 4931.45 | J70: =I70/I69-1
B71: 2021-11-16 | C71: 7291.3 | D71: =C71/C70-1 | E71: 36643.9 | F71: =E71/E70-1 | I71: 4958.15 | J71: =I71/I70-1
B72: 2021-11-17 | C72: 7397.05 | D72: =C72/C71-1 | E72: 36660.9 | F72: =E72/E71-1 | I72: 4988.95 | J72: =I72/I71-1
B73: 2021-11-18 | C73: 7147.65 | D73: =C73/C72-1 | E73: 36007 | F73: =E73/E72-1 | I73: 4839.4 | J73: =I73/I72-1
... B181: 2022-04-27 | C181: 4816.95 | D181: =C181/C180-1 | E181: 31594.35 | F181: =E181/E180-1 | I181: 3538.35 | J181: =I181/I180-1
B182: 2022-04-28 | C182: 4886.05 | D182: =C182/C181-1 | E182: 31914.35 | F182: =E182/E181-1 | G182: =$C$10+$C$9*F182 | H182: =D182-G182 | I182: 3606.2 | J182: =I182/I181-1 | K182: =$C$18+$C$17*F182 | L182: =J182-K182
B183: 2022-04-29 | C183: 4839.05 | D183: =C183/C182-1 | E183: 31622.4 | F183: =E183/E182-1 | G183: =$C$10+$C$9*F183 | H183: =D183-G183 | I183: 3552.15 | J183: =I183/I182-1 | K183: =$C$18+$C$17*F183 | L183: =J183-K183
B184: 2022-05-02 | C184: 4716.65 | D184: =C184/C183-1 | E184: 31138.8 | F184: =E184/E183-1 | G184: =$C$10+$C$9*F184 | H184: =D184-G184
B185: 2022-05-04 | C185: 4738.15 | D185: =C185/C184-1 | E185: 30794.6 | F185: =E185/E184-1 | G185: =$C$10+$C$9*F185 | H185: =D185-G185 | I185: 3469.05
B186: 2022-05-05 | C186: 4765.2 | D186: =C186/C185-1 | E186: 31432.45 | F186: =E186/E185-1 | G186: =$C$10+$C$9*F186 | H186: =D186-G186 | I186: 3510.45 | J186: =I186/I185-1 | K186: =$C$18+$C$17*F186 | L186: =J186-K186
B187: 2022-05-06 | C187: 4593 | D187: =C187/C186-1 | E187: 30719.45 | F187: =E187/E186-1 | G187: =$C$10+$C$9*F187 | H187: =D187-G187 | I187: 3373.8 | J187: =I187/I186-1 | K187: =$C$18+$C$17*F187 | L187: =J187-K187
B188: 2022-05-09 | C188: 4448.9 | D188: =C188/C187-1 | E188: 30733.3 | F188: =E188/E187-1 | G188: =$C$10+$C$9*F188 | H188: =D188-G188 | I188: 3195.1 | J188: =I188/I187-1 | K188: =$C$18+$C$17*F188 | L188: =J188-K188
B189: 2022-05-10 | C189: 4332.15 | D189: =C189/C188-1 | E189: 30427.2 | F189: =E189/E188-1 | G189: =$C$10+$C$9*F189 | H189: =D189-G189 | I189: 3089.4 | J189: =I189/I188-1 | K189: =$C$18+$C$17*F189 | L189: =J189-K189
B190: 2022-05-11 | C190: 4250.75 | D190: =C190/C189-1 | E190: 30050.25 | F190: =E190/E189-1 | G190: =$C$10+$C$9*F190 | H190: =D190-G190 | I190: 3043.35 | J190: =I190/I189-1 | K190: =$C$18+$C$17*F190 | L190: =J190-K190
B191: 2022-05-12 | C191: 4160.95 | D191: =C191/C190-1 | E191: 29756.85 | F191: =E191/E190-1 | G191: =$C$10+$C$9*F191 | H191: =D191-G191 | I191: 2954.95 | J191: =I191/I190-1 | K191: =$C$18+$C$17*F191 | L191: =J191-K191
B192: 2022-05-13 | C192: 4110.7 | D192: =C192/C191-1 | E192: 29624.85 | F192: =E192/E191-1 | G192: =$C$10+$C$9*F192 | H192: =D192-G192 | I192: 2938.95 | J192: =I192/I191-1 | K192: =$C$18+$C$17*F192 | L192: =J192-K192
B193: 2022-05-16 | C193: 4094.8 | D193: =C193/C192-1 | E193: 29403.5 | F193: =E193/E192-1
B194: 2022-05-17 | C194: 4281.85 | D194: =C194/C193-1 | E194: 30218.75 | F194: =E194/E193-1
B195: 2022-05-18 | C195: 4214 | D195: =C195/C194-1 | E195: 30077.7 | F195: =E195/E194-1

Sheet Exchange Ratio & Ownership
A1: # | B1: Exchange Ratio & Pro Forma Ownership
B2: LTI is the acquirer (issues new shares); Mindtree is the target (its shareholders receive LTI stock). All-stock, no cash consideration - the actual structure of the announced deal.
A4: ## | B4: Deal Terms
B6: Announced Exchange Ratio (LTI shares per 100 Mindtree shares) | C6: 73 | E6: Actual, publicly announced swap ratio for the LTI-Mindtree merger (6-May-2022) - a real deal term, not derived.
B7: Exchange Ratio (LTI shares per 1 Mindtree share) | C7: =C6/100
A9: ## | B9: Shares Outstanding & New Issuance
B11: LTI Shares Outstanding (pre-deal, acquirer) | C11: ='LTI_WACC Schedule'!C7
B12: Mindtree Shares Outstanding (pre-deal, target) | C12: ='MT_WACC Schedule'!C7
B13: New LTI Shares Issued (computed, FY22-end share count basis) | C13: =C12*C7 | E13: Mindtree shares outstanding x exchange ratio - a modeled figure, superseded below by the actual disclosed allotment.
B14: New LTI Shares Issued (ACTUAL, per NCLT Scheme Order / AR2023) | C14: 120417607 | E14: Actual allotment 25-Nov-2022 (incl. 165,247 fractional-entitlement shares pooled to a trustee and cash-settled) - LTIMindtree FY23 Board Report / NCLT Mumbai Scheme Order, both in the Company/Deal notebook. Used below as the basis for pro forma shares - real disclosed figure takes precedence over the modeled one above.
B15: Reconciling Difference (Actual - Computed) | C15: =C14-C13 | E15: Reflects Mindtree's shares outstanding moving slightly between FY22-end (Mar-2022, this model's basis) and the actual Record Date (24-Nov-2022) - e.g. ESOP exercises - not a modeling error.
B17: Pro Forma LTI Shares Outstanding (post-deal, using ACTUAL issuance) | C17: =C11+C14
B19: L&T's Ownership of Combined Entity (ACTUAL, disclosed) | C19: 0.6873 | E19: Disclosed directly in the 14-Nov-2022 merger-completion press release - a different cut than the LTI-legacy/Mindtree-legacy split above (this isolates one shareholder, L&T, across both companies' pre-deal holdings combined), included as an independent cross-check, not a contradiction.
A21: ## | B21: Post-Deal Ownership Split
B23: LTI Legacy Shareholders | C23: =C11/C17
B24: Former Mindtree Shareholders | C24: =C14/C17
A26: ## | B26: Value Analysis: Exchange Ratio vs. Same-Day Market Prices
B28: LTI Market Price (6-May-2022, Rs.) | C28: ='LTI_WACC Schedule'!C6
B29: Value Received per Mindtree Share (in LTI stock, Rs.) | C29: =C7*C28 | E29: Exchange ratio x LTI's own market price
B30: Mindtree Standalone Market Price (6-May-2022, Rs.) | C30: ='MT_WACC Schedule'!C6
B31: Implied Premium / (Discount) to Mindtree's Standalone Price | C31: =C29/C30-1
B33: Reading this: the announced 73:100 ratio valued each Mindtree share at essentially its own same-day market price - a small discount, under 1% (see the computed cell above for the exact figure), not a premium. This is consistent with a merger structured off relative trading values between two already-affiliated companies (both L&T subsidiaries) rather than a control-premium acquisition of an independent target - real acquisitions of independent companies typically carry a 20-40%+ premium to the undisturbed share price; this deal shows essentially none, which fits a NAV/relative-value merger-of-affiliates structure rather than a traditional third-party buyout.
A35: ## | B35: Contribution Analysis
B37: Standard stock-for-stock fairness check (DePamphilis): compares each side's financial contribution to the combined entity (pre-transaction-adjustment, FY22 standalone) against the ownership split it actually received. A gap is not automatically unfair - synergy value, growth-rate differences and relative risk all legitimately justify one side receiving more ownership than its raw financial contribution alone would imply - but seeing the gap explicitly is the standard next question after any exchange-ratio check.
B39: Metric (FY22 standalone) | C39: LTI (Rs.M) | D39: Mindtree (Rs.M)
B40: Revenue | C40: ='LTI_P&L Schedule'!H7/1000000 | D40: ='MT_P&L Schedule'!H7/1000000
B41: EBITDA | C41: ='LTI_P&L Schedule'!H11/1000000 | D41: ='MT_P&L Schedule'!H11/1000000
B42: EBIT | C42: ='LTI_P&L Schedule'!H14/1000000 | D42: ='MT_P&L Schedule'!H14/1000000
B43: Net Income (PAT) | C43: ='LTI_P&L Schedule'!H22/1000000 | D43: ='MT_P&L Schedule'!H22/1000000
B44: Market Capitalization (6-May-2022) | C44: =('LTI_WACC Schedule'!C6*'LTI_WACC Schedule'!C7)/1000000 | D44: =('MT_WACC Schedule'!C6*'MT_WACC Schedule'!C7)/1000000
A46: ### | B46: Contribution % (each metric's share of LTI+Mindtree combined)
B47: Revenue Contribution % | C47: =C40/(C40+D40) | D47: =D40/(C40+D40)
B48: EBITDA Contribution % | C48: =C41/(C41+D41) | D48: =D41/(C41+D41)
B49: EBIT Contribution % | C49: =C42/(C42+D42) | D49: =D42/(C42+D42)
B50: Net Income (PAT) Contribution % | C50: =C43/(C43+D43) | D50: =D43/(C43+D43)
B51: Market Capitalization (6-May-2022) Contribution % | C51: =C44/(C44+D44) | D51: =D44/(C44+D44)
B53: Actual Ownership Split (from Post-Deal Ownership Split above, for comparison) | C53: =C11/C17 | D53: =C14/C17
B55: Reading this (verified via recalc, not asserted in advance): the actual ownership split (59.3% LTI / 40.7% Mindtree) sits within about 1 percentage point of Mindtree's contribution share on every metric tested - Revenue 40.2%, EBITDA 41.8%, EBIT 41.9%, Net Income 41.8%, Market Cap 40.9%. Mindtree's actual ownership share lands almost exactly between its lower revenue-contribution share and its higher profitability-contribution shares, not skewed toward either extreme. This is a genuinely independent confirmation of fairness - Contribution Analysis uses only raw FY22 P&L and market-cap figures, with no reference to the DCF, Comps or Precedent Transactions work elsewhere in this model, and it lands on essentially the same conclusion those methods did: the deal was priced close to a straightforward pro-rata split of the combined entity's financial substance, not skewed toward either side.
A57: ## | B57: Control Premium x Illiquidity Discount (Pratt's Multiplicative Model)
B59: Gross Base Price x (1 + Control Premium) x (1 - Illiquidity Discount) = Net Price - control premiums and illiquidity/marketability discounts compound multiplicatively, not additively, when both apply (Pratt). Shown here for correct mechanical treatment, even though this specific deal has close to zero of either factor (see below).
B61: Control Premium / (Discount) (from Value Analysis above) | C61: =C31
B62: Illiquidity / Marketability Discount | C62: 0 | E62: Set to 0%: Mindtree shares were listed and liquid on the NSE/BSE up to the deal's Effective Date, not an illiquid minority stake - no DLOM applies to a public-to-public stock-for-stock merger of this kind.
B63: Net Price / Gross Base Price (multiplicative) | C63: =(1+C61)*(1-C62)
B64: Additive Approximation (1 + Premium - Discount), for comparison | C64: =1+C61-C62
B65: Difference (Multiplicative - Additive) | C65: =C63-C64
B67: Reading this: with the illiquidity discount at 0%, the multiplicative and additive results are identical by construction (multiplying by (1-0%) changes nothing) - the compounding distinction only matters when BOTH a premium and a discount are genuinely non-zero (e.g. valuing an illiquid minority stake being acquired at a control premium). Included to show the correct formula is known and applied correctly, not because it moves this specific deal's numbers.

Sheet Pro Forma & Accretion-Dilution
A1: # | B1: Pro Forma Combination & Accretion/Dilution
B2: Grounded in ACTUAL disclosed combined-entity results (LTIMindtree FY23 Board Report), not a purely hypothetical pro forma - the Appointed Date (1-Apr-2022) means the FY23 report's Consolidated FY22 comparatives are the real, audited restated combined-entity figures for that year.
A4: ## | B4: Actual Disclosed Combined-Entity Results (Rs. Million)
B6: Line Item | C6: Consolidated FY22 (restated) | D6: Consolidated FY23 (actual)
B7: Revenue from Operations | C7: 261087 | D7: 331830
B8: Other Income | C8: 7658 | D8: 5569
B9: Total Revenue | C9: 268745 | D9: 337399
B10: Employee Benefit Expense | C10: 159892 | D10: 208799
B11: Sub-contractor Expense | C11: 23591 | D11: 28286
B12: Finance Costs | C12: 1234 | D12: 1504
B13: Depreciation & Amortisation | C13: 5971 | D13: 7227
B14: Other Expenses | C14: 25118 | D14: 33668
B15: Total Expenses | C15: 215806 | D15: 279484
B16: Profit Before Tax | C16: 52939 | D16: 57915
B17: Tax Expense | C17: 13439 | D17: 13812
B18: Profit for the Year (PAT) | C18: 39500 | D18: 44103
B19: Source: LTIMindtree FY2022-23 Integrated Annual Report / Board Report, and the NCLT Mumbai Bench Scheme Order (26-Sep-2022) confirming the 1-Apr-2022 Appointed Date - both in the Company/Deal NotebookLM notebook, queried directly before building this sheet.
A21: ## | B21: Margin Trend - Real, Not Estimated (companion note on synergy sizing)
B23: Metric | C23: FY22 (restated) | D23: FY23 (actual) | E23: FY24 (actual)
B24: Revenue from Operations (Rs.M) | C24: =C7 | D24: =D7 | E24: 355170
B25: EBITDA (Rs.M) = Revenue - Employee Benefit - Subcontractor - Other Expenses | C25: =C7-C10-C11-C14 | D25: =D7-D10-D11-D14 | E25: n/a - full FY24 expense breakdown not sourced
B26: EBITDA Margin (%) | C26: =C25/C7 | D26: =D25/D7 | E26: n/a
B27: EBIT (Rs.M) = EBITDA - D&A | C27: =C25-C13 | D27: =D25-D13 | E27: n/a - full FY24 expense breakdown not sourced
B28: EBIT Margin (%) | C28: =C27/C7 | D28: =D27/D7 | E28: 0.157
B29: Other Expenses / Revenue (SG&A proxy, %) | C29: =C14/C7 | D29: =D14/D7 | E29: n/a
B31: Source for FY24: Business Standard (LTIMindtree FY24 results, reported Apr-2024) - Revenue Rs.35,517cr (+7.03% YoY), EBIT margin 15.7%, PAT Rs.4,584.6cr (+4% YoY, consistent with FY23's Rs.4,410.3cr already in this sheet - cross-checked, not just assumed). No line-item expense breakdown sourced for FY24, so EBITDA and the SG&A ratio are left blank rather than backed into.
B33: Reading this: EBIT margin fell in both actual post-merger years - 17.82% (FY22) -> 16.23% (FY23) -> 15.7% (FY24) - the opposite of what a synergy-driven cost story would predict. This is why the Rs.10,123M bottom-up synergy estimate (Synergies sheet) is NOT scaled up despite Sasi's instinct that it looked too small: real, disclosed margin data across two full years doesn't support a larger, margin-expansion-based number. Two plausible, non-alarming explanations, not mutually exclusive: (1) FY23 captures only ~5 months of integrated operations post the 14-Nov-2022 Effective Date, and cost synergies from a deal this size typically take 2-4 years to fully phase in; (2) a real, well-documented sector-wide wage/attrition war ran through this exact period (this session's own earlier Porter's-Forces research found attrition rising from 14.8% to 24.0% with double-digit wage hikes) - pressure that would compress margins regardless of the merger. This does NOT contradict the +13.74% EPS accretion found above - that accretion is real (based on actual disclosed PAT) but is REVENUE-GROWTH-driven, not synergy/margin-driven, and the two should not be conflated when explaining why EPS grew.
A35: ## | B35: Industry-Adjusted Performance (Healy-Palepu-Ruback methodology)
B37: Tests the margin-compression finding above against the same period's peer performance - the academic-standard way to separate "the merger hurt margins" from "the whole sector's margins fell and this company was no exception" (Healy, Palepu & Ruback 1992, in the Theory notebook).
B39: Peer (true EBIT margin = (Op.Profit-Depr.)/Sales) | C39: FY22 | D39: FY23 | E39: FY24
B40: TCS | C40: 0.25268313 | D40: 0.24056365 | E40: 0.24621305
B41: Infosys | C41: 0.23030886 | D41: 0.21057186 | E41: 0.20659205
B42: Wipro | C42: 0.17155033 | D42: 0.14918 | E42: 0.14867424
B43: HCL Technologies | C43: 0.18917467 | D43: 0.1821775 | E43: 0.18218955
B44: Tech Mahindra | C44: 0.14558975 | D44: 0.10895102 | E44: 0.051715517
B45: Peer Median EBIT Margin | C45: =MEDIAN(C40:C44) | D45: =MEDIAN(D40:D44) | E45: =MEDIAN(E40:E44)
B47: LTIMindtree EBIT Margin (from above) | C47: =C27/C7 | D47: =D27/D7 | E47: 0.157
B48: Industry-Adjusted Performance (LTIMindtree - Peer Median) | C48: =C47-C45 | D48: =D47-D45 | E48: =E47-E45
B49: Change in Industry-Adjusted Gap, FY22 -> FY24 | C49: =E48-C48
B51: Source: Screener.in consolidated P&L, Sales / Operating Profit / Depreciation individually sourced per peer, one query per company (25-Aug-2026). CORRECTED from an earlier version of this sheet that used Screener's own OPM% directly - OPM nets out BEFORE depreciation (EBITDA-like: verified TCS's OPM-implied PBT reconciles exactly - 53,057+4,018-784-4,604=51,687, matching reported PBT), so comparing it to this sheet's own EBIT margin (after depreciation) was an EBIT-vs-EBITDA mismatch. Now both sides are true EBIT, same construction, genuinely comparable.
B53: Reading this (corrected from an earlier version of this sheet - flagged, not silently overwritten): the true peer median EBIT margin fell from 18.92% (FY22) to 18.22% (FY23) and held at 18.22% (FY24) - a real ~0.7pp sector-wide decline, smaller than the ~2.1pp LTIMindtree's own margin fell over the same period. The industry-adjusted gap WIDENS: roughly -1.1pp below peer median in FY22, to roughly -2.5pp by FY24 - a net change of about -1.4 percentage points, not the near-zero change the earlier OPM-based comparison showed. LTIMindtree's underperformance vs. peers is real, pre-dates the merger (already -1.1pp in the FY22 baseline), AND did meaningfully worsen post-merger on this corrected, properly-apples-to-apples methodology. This does not overturn the deal's overall case (EPS accretion is still real, still revenue-driven) but it does mean the margin story is less fully explained by sector-wide pressure than earlier reported - some real, company-specific margin drag (integration costs, execution friction, or both) likely exists on top of the sector-wide effect, and should be read that way rather than dismissed as purely macro.
A55: ## | B55: Cross-Check: This Model's Standalone Figures vs. Actual Restated Consolidated FY22
C57: Revenue (Rs.M) | D57: PAT (Rs.M)
B58: LTI Standalone FY22 (this model) | C58: ='LTI_P&L Schedule'!H7/1000000 | D58: ='LTI_P&L Schedule'!H22/1000000
B59: Mindtree Standalone FY22 (this model) | C59: ='MT_P&L Schedule'!H7/1000000 | D59: ='MT_P&L Schedule'!H22/1000000
B60: Naive Sum (LTI + Mindtree, no eliminations) | C60: =C58+C59 | D60: =D58+D59
B61: Actual Restated Consolidated FY22 (disclosed) | C61: =C7 | D61: =C18
B62: Difference (Naive Sum - Actual, likely intercompany eliminations) | C62: =C60-C61 | D62: =D60-D61
B63: Difference as % of Naive Sum | C63: =C62/C60 | D63: =D62/D60
B65: Reading this: the gap is small on both lines (well under 1%), a strong independent cross-check on this model's standalone LTI/Mindtree figures against real, audited, third-party-verified data - not assumed to be accurate, actually confirmed against the real combined-entity result.
A67: ## | B67: Accretion / Dilution Analysis
B69: LTI Standalone FY22 Shares Outstanding | C69: ='Exchange Ratio & Ownership'!C11
B70: Pro Forma Shares Outstanding (ACTUAL post-deal) | C70: ='Exchange Ratio & Ownership'!C17
B72: LTI Standalone FY22 EPS (Rs.) | C72: =D58*1000000/C69
B74: Caveat, read before the results below (audit gap #12a, Task 26): EPS accretion/dilution is a mechanical accounting result, not a value-creation test - large studies of real transactions find no empirical link between a deal being EPS-accretive and it actually creating shareholder value (deals that dilute EPS and deals that boost it are equally likely to create or destroy value). Method A/B below show what happened to EPS, which is a fact worth knowing - not proof the deal was economically good, which the DCF, Comps, Precedent Transactions and Contribution Analysis elsewhere in this model speak to far more directly.
A76: ### | B76: Method A: Same-Year Pro Forma (FY22 actual combined vs LTI FY22 standalone) | E76: Isolates the pure combination effect - same period's earnings, different share base.
B77: Pro Forma EPS (Actual Consol. FY22 PAT / Actual PF Shares) | C77: =D61*1000000/C70
B78: Accretion / (Dilution) to LTI Standalone EPS | C78: =C77/C72-1
A80: ### | B80: Method B: Actual Realized (FY23 actual combined vs LTI FY22 standalone) | E80: Includes one full year of real organic performance on top of the combination effect - cannot be cleanly separated from the aggregate figures alone.
B81: Pro Forma EPS (Actual Consol. FY23 PAT / Actual PF Shares) | C81: =D18*1000000/C70
B82: Accretion / (Dilution) to LTI Standalone EPS | C82: =C81/C72-1
A84: ### | B84: Reinhardt's P/E Rule Check | E84: Tests whether Method A's accretion is a real economic signal or a mechanical multiple-expansion artifact of the deal structure itself.
B85: Mindtree Standalone FY22 Shares Outstanding | C85: ='Exchange Ratio & Ownership'!C12
B86: Mindtree Standalone FY22 EPS (Rs.) | C86: =D59*1000000/C85
B88: LTI's Own P/E (LTI market price / LTI standalone EPS) | C88: ='Exchange Ratio & Ownership'!C28/C72
B89: Implied P/E Paid for Mindtree (Value received per MT share / MT standalone EPS) | C89: ='Exchange Ratio & Ownership'!C29/C86 | E89: Value received per Mindtree share = exchange ratio x LTI's own price (Exchange Ratio & Ownership sheet) - the actual earnings multiple LTI effectively paid for Mindtree's FY22 PAT.
B91: Reinhardt Rule: LTI P/E > Implied P/E Paid -> mechanically accretive | C91: =IF(C88>C89,"TRUE - mechanically accretive","FALSE - mechanically dilutive")
B93: Reading this (verified via recalc): LTI's own P/E (35.0x) is modestly above the implied P/E paid for Mindtree's earnings (33.4x), so Reinhardt's rule confirms Method A's +1.87% accretion is at least partly a mechanical multiple-expansion effect, not purely a synergy or growth signal - exactly what the caveat above warns about. The gap between the two P/Es is narrow (35.0x vs. 33.4x, about a 4.7% relative difference), not the kind of wide mismatch (e.g. a 40x-P/E acquirer buying a 12x-P/E target) that would signal a real cosmetic-accretion illusion - a small, real effect consistent with this model's other findings that the deal was priced close to fair, not with a bidder exploiting a large multiple gap to manufacture the appearance of a good deal.
B95: Reading this: since the deal was all-stock (no new debt, confirmed on the Exchange Ratio sheet), there is no incremental interest cost to model - the standard complication in a cash/debt-funded deal's accretion/dilution math doesn't apply here. Method A shows the deal was mechanically accretive even on a same-year basis (combining two profitable companies where the combined PAT grew faster than the new shares issued diluted the base). Method B, using real FY23 results, shows materially more accretion - but that number blends the merger's own effect with a full year of the wider IT-services sector's organic growth (both companies' standalone businesses were growing before the deal too), so it should be read as "what actually happened to EPS" rather than "what the merger alone contributed." Both are real, disclosed-data-based figures, not modeled projections - a materially stronger basis than a purely hypothetical pro forma would have been.

Sheet Stress Test - Exchange Ratio
A1: # | B1: Stress Test - Exchange Ratio Bounds (Bull/Base/Bear)
B2: Methodology from Sasi's own M&A course (Prof. Yogesh Chauhan) - "Determining Exchange Ratio: A logic": the buyer sets a MAXIMUM exchange ratio it can pay without overpaying (target's standalone value + its share of synergy, divided by buyer's own value); the seller sets a MINIMUM it will accept (target's standalone value alone, no synergy credit, divided by buyer's value). The actual 73:100 ratio is tested against this [Min, Max] negotiable range under three scenarios, not just the locked-in base case.
A4: ## | B4: Scenario Inputs
C6: Bear | D6: Base | E6: Bull
B7: WACC scenario (Sensitivity Table row) | C7: +2pp (row 12) | D7: Base (row 10, locked-in) | E7: -2pp (row 8)
B8: Synergy Realization % | C8: 0 | D8: 1 | E8: 1.5
B10: Bear = higher discount rate (worse conditions) + zero synergy realized (skeptical case, deal creates no value beyond the two standalone businesses). Base = the locked-in WACC + full Rs.10,123M/year bottom-up synergy estimate. Bull = lower discount rate + 150% of the estimate (upside: cross-sell and cost synergies exceed the conservative bottom-up case).
A12: ## | B12: Standalone Intrinsic Value / Share (Rs.)
C14: Bear | D14: Base | E14: Bull
B15: LTI Standalone Value/Share | C15: ='LTI_Sensitivity Tables'!E12 | D15: ='LTI_Sensitivity Tables'!E10 | E15: ='LTI_Sensitivity Tables'!E8
B16: Mindtree Standalone Value/Share | C16: ='MT_Sensitivity Tables'!E12 | D16: ='MT_Sensitivity Tables'!E10 | E16: ='MT_Sensitivity Tables'!E8
B17: WACC used for this scenario (LTI) | C17: 0.12045823 | D17: 0.10045823 | E17: 0.080458232
B19: Standalone values pulled live from the already-built LTI_/MT_Sensitivity Tables (WACC +/-2pp at base-case terminal growth - Table 1 in each sheet). WACC figures re-entered here as sourced inputs (matching those tables' own row headers) so the synergy perpetuity below uses a consistent discount rate per scenario.
A21: ## | B21: Synergy Value (Growing Perpetuity)
C23: Bear | D23: Base | E23: Bull
B24: Annual Synergy Realized (Rs.M) | C24: ='Synergies (Bottom-Up Estimate)'!$D$36*C8 | D24: ='Synergies (Bottom-Up Estimate)'!$D$36*D8 | E24: ='Synergies (Bottom-Up Estimate)'!$D$36*E8
B25: Terminal Growth Rate (locked-in, both companies) | C25: ='LTI_DCF'!C22 | D25: ='LTI_DCF'!C22 | E25: ='LTI_DCF'!C22
B26: Synergy PV (Rs.M) = Annual / (WACC - TGR) | C26: =C24/(C17-C25) | D26: =D24/(D17-D25) | E26: =E24/(E17-E25)
B27: Synergy PV per Mindtree Share (Rs.) | C27: =C26*1000000/'Exchange Ratio & Ownership'!$C$12 | D27: =D26*1000000/'Exchange Ratio & Ownership'!$C$12 | E27: =E26*1000000/'Exchange Ratio & Ownership'!$C$12
A29: ## | B29: Exchange Ratio Bounds vs. Actual (73:100 = 0.73)
C31: Bear | D31: Base | E31: Bull
B32: Min Exchange Ratio (Seller floor, no synergy credit) | C32: =C16/C15 | D32: =D16/D15 | E32: =E16/E15
B33: Max Exchange Ratio (Buyer ceiling, incl. synergy) | C33: =(C16+C27)/C15 | D33: =(D16+D27)/D15 | E33: =(E16+E27)/E15
B34: Actual Ratio (0.73) | C34: 0.73 | D34: 0.73 | E34: 0.73
B35: Within [Min, Max]? | C35: =IF(AND(C34>=C32,C34<=C33),"YES - within range","NO - outside range") | D35: =IF(AND(D34>=D32,D34<=D33),"YES - within range","NO - outside range") | E35: =IF(AND(E34>=E32,E34<=E33),"YES - within range","NO - outside range")
B37: Reading this: even in the Bear case (higher discount rate, zero synergy credited to the buyer's ceiling), the actual 73:100 ratio's position relative to [Min, Max] shows whether the deal required optimistic assumptions to look fair, or whether it clears the bar even under skeptical inputs. In the Base case, the range reflects this model's own locked-in DCF assumptions plus the full bottom-up synergy estimate. The Bull case shows how much headroom exists if synergies run ahead of the conservative estimate. This is the same negotiation-range logic taught in Sasi's own course (buyer's ceiling vs. seller's floor) - not a new framework invented for this model.
A40: ## | B40: Ramp-Up & Integration-Cost-Adjusted Synergy PV (audit gap #12c cross-check)
B41: A separate adjusted view alongside (not replacing) the flat-perpetuity Synergy PV above (rows 21-27) - uses the ramp-up schedule and one-time integration cost added at 'Synergies (Bottom-Up Estimate)'!B44:D44/B49. Integration cost is the SAME absolute Rs.M in every scenario column (based on the full D36 run-rate, not the scenario-adjusted one) - the cost to attempt integration is incurred regardless of how much synergy actually materializes, including in Bear where realized synergy is zero.
C43: Bear | D43: Base | E43: Bull
B44: Year 1 Synergy Realized (Rs.M) | C44: =C24*'Synergies (Bottom-Up Estimate)'!$B$44 | D44: =D24*'Synergies (Bottom-Up Estimate)'!$B$44 | E44: =E24*'Synergies (Bottom-Up Estimate)'!$B$44
B45: Year 2 Synergy Realized (Rs.M) | C45: =C24*'Synergies (Bottom-Up Estimate)'!$C$44 | D45: =D24*'Synergies (Bottom-Up Estimate)'!$C$44 | E45: =E24*'Synergies (Bottom-Up Estimate)'!$C$44
B46: PV of Year 1+2 Synergy (Rs.M) | C46: =C44/(1+C17)+C45/(1+C17)^2 | D46: =D44/(1+D17)+D45/(1+D17)^2 | E46: =E44/(1+E17)+E45/(1+E17)^2
B47: PV of Year 3+ Perpetuity, full run-rate (Rs.M) | C47: =(C24*(1+C25))/(C17-C25)/(1+C17)^2 | D47: =(D24*(1+D25))/(D17-D25)/(1+D17)^2 | E47: =(E24*(1+E25))/(E17-E25)/(1+E17)^2
B48: Total Synergy PV before integration cost (Rs.M) | C48: =C46+C47 | D48: =D46+D47 | E48: =E46+E47
B49: Less: One-Time Integration Cost (Rs.M, undiscounted, paid at close) | C49: =-'Synergies (Bottom-Up Estimate)'!$B$49 | D49: =-'Synergies (Bottom-Up Estimate)'!$B$49 | E49: =-'Synergies (Bottom-Up Estimate)'!$B$49
B50: Net Adjusted Synergy PV (Rs.M) | C50: =C48+C49 | D50: =D48+D49 | E50: =E48+E49
B51: Net Adjusted Synergy PV per Mindtree Share (Rs.) | C51: =C50*1000000/'Exchange Ratio & Ownership'!$C$12 | D51: =D50*1000000/'Exchange Ratio & Ownership'!$C$12 | E51: =E50*1000000/'Exchange Ratio & Ownership'!$C$12
A53: ## | B53: Exchange Ratio Bounds - Ramp + Integration-Cost Adjusted, vs. Original
C55: Bear | D55: Base | E55: Bull
B56: Min Exchange Ratio (Seller floor - unchanged, doesn't involve synergy) | C56: =C32 | D56: =D32 | E56: =E32
B57: Max Exchange Ratio - Adjusted (Buyer ceiling, incl. ramp+integration-cost-adjusted synergy) | C57: =(C16+C51)/C15 | D57: =(D16+D51)/D15 | E57: =(E16+E51)/E15
B58: Max Exchange Ratio - Original (flat-perpetuity, for comparison) | C58: =C33 | D58: =D33 | E58: =E33
B59: Actual Ratio (0.73) | C59: 0.73 | D59: 0.73 | E59: 0.73
B60: Within [Min, Max-Adjusted]? | C60: =IF(AND(C59>=C56,C59<=C57),"YES - within range","NO - outside range") | D60: =IF(AND(D59>=D56,D59<=D57),"YES - within range","NO - outside range") | E60: =IF(AND(E59>=E56,E59<=E57),"YES - within range","NO - outside range")
B62: Reading this: accounting for ramp-up and the one-time integration cost narrows every scenario's buyer ceiling versus the original flat-perpetuity treatment (Base Max 0.992 -> 0.945, Bull 1.269 -> 1.212), but doesn't flip the Base/Bull conclusion - the actual 0.73 ratio still clears both comfortably. Bear changes more starkly: with zero synergy ever realized but the integration cost still paid (spent regardless of outcome, by construction), the adjusted buyer ceiling (0.650) now falls BELOW the seller floor (0.673) - the range inverts, a cleaner and more pessimistic 'NO' than the original Bear result, which had Min=Max at exactly 0.673 (both collapsing to the same no-synergy point). This is the expected shape, not an error: a truly zero-synergy world that still pays to attempt integration should look worse than a zero-synergy world that doesn't, and it does here.

Sheet Football Field
A1: # | B1: Football Field - Valuation Synthesis
B2: Every Low/Median/High below is a live formula pulling from the DCF, Comps, and Precedent Transactions sheets already built and verified - this sheet adds no new numbers, just a synthesized view. The Event Study (CAR) isn't shown here - it measures market reaction, a return, not a value-per-share estimate, so it doesn't belong on this axis.
A4: ## | B4: LTI
B6: Method | C6: Low | D6: Median / Base | E6: High
B7: DCF (WACC +/-2pp) | C7: ='LTI_Sensitivity Tables'!E12 | D7: ='LTI_Sensitivity Tables'!E10 | E7: ='LTI_Sensitivity Tables'!E8
B8: Trading Comps (median-mean P/E) | C8: ='LTI_Comps'!B16 | D8: =('LTI_Comps'!B16+'LTI_Comps'!B17)/2 | E8: ='LTI_Comps'!B17
B9: Precedent Transactions (EV/Rev) | C9: ='Precedent Transactions'!C46 | D9: ='Precedent Transactions'!C39 | E9: ='Precedent Transactions'!C53
B10: Actual Market Price (6-May-2022) | D10: ='LTI_WACC Schedule'!C6
A13: ## | B13: Mindtree
B15: Method | C15: Low | D15: Median / Base | E15: High
B16: DCF (WACC +/-2pp) | C16: ='MT_Sensitivity Tables'!E12 | D16: ='MT_Sensitivity Tables'!E10 | E16: ='MT_Sensitivity Tables'!E8
B17: Trading Comps (median-mean P/E) | C17: ='MT_Comps'!B16 | D17: =('MT_Comps'!B16+'MT_Comps'!B17)/2 | E17: ='MT_Comps'!B17
B18: Precedent Transactions (EV/Rev) | C18: ='Precedent Transactions'!D46 | D18: ='Precedent Transactions'!D39 | E18: ='Precedent Transactions'!D53
B19: Actual Market Price (6-May-2022) | D19: ='MT_WACC Schedule'!C6
A22: ## | B22: Chart Helper Columns (base = Low, range = High-Low)
B24: Method | C24: Base (=Low) | D24: Range (=High-Low)
B25: =B7 | C25: =C7 | D25: =E7-C7
B26: =B8 | C26: =C8 | D26: =E8-C8
B27: =B9 | C27: =C9 | D27: =E9-C9
B29: =B16 | C29: =C16 | D29: =E16-C16
B30: =B17 | C30: =C17 | D30: =E17-C17
B31: =B18 | C31: =C18 | D31: =E18-C18

Sheet Precedent Transactions
A1: # | B1: Precedent Transactions Analysis
B2: Real, publicly disclosed Indian IT-services M&A transactions (sourced live via web search, citations in column I). Multiples the acquirer actually paid, applied to LTI's and Mindtree's own FY22 financials - a third, independent cross-check alongside the DCF and Trading Comps already built.
A4: ## | B4: Transaction Table
B6: Acquirer / Target | C6: Announced | D6: Deal Value (EV, $M) | E6: Target Revenue (LTM, $M) | F6: EV/Revenue | G6: Target EBITDA or EBIT (LTM, $M) | H6: EV/EBITDA or EV/EBIT
B7: Capgemini / iGate Corporation | C7: Apr-2015 | D7: 4000 | E7: 1300 | F7: =D7/E7 | G7: n/a | H7: n/a | I7: Deal value + FY2014 revenue: Capgemini press release, Forbes India, Business Standard (consultancy.uk, forbesindia.com) - deal explicitly described as "over 3x revenue", consistent with the 3.08x computed here. FY2014 EBITDA not cleanly found in two searches - left blank rather than estimated.
B8: Blackstone / Mphasis (from HPE) [EBITDA (range, not point)] | C8: Apr-2016 | D8: n/a | E8: n/a | F8: n/a | G8: n/a | H8: 9 | I8: Bloomberg (Blackstone to buy HPE's 60.5% stake for ~$825M, INR430/share; up to $1.1bn for control via open offer), Blackstone press release. EV/Revenue not used - the %-stake / per-share math needed to back into a clean 100% EV was not reliably resolvable from public sources. EV/EBITDA entered directly from the source's own reported trading-multiple context: "8-10x LTM EBITDA, vs peer average 12-14x" - midpoint 9.0x entered here, not a formula.
B9: HCL Technologies / Geometric Ltd | C9: Apr-2016 | D9: n/a | E9: n/a | F9: 1.6 | G9: n/a | H9: n/a | I9: DQIndia, M&A Critique, Business Standard: deal for Geometric's IT services business (Rs.1,300cr EV, Rs.801cr FY15 revenue) explicitly reported as "~1.6 times the turnover" and a 23x P/E multiple. 1.6x entered directly as reported, not as a formula off the Rs./$ figures shown for reference - the $ figures are rough conversions that would carry FX-date rounding error the source's own 1.6x doesn't have.
B10: Carlyle Group / Hexaware Technologies [EBIT (operating profit, not EBITDA)] | C10: Jun-2021 | D10: 3000 | E10: 845 | F10: =D10/E10 | G10: 152 | H10: =D10/G10 | I10: Private Equity Insights: Carlyle's winning $3bn offer for Hexaware from Baring PE Asia (Jun-2021). CY2020 revenue $845M, operating profit $152M, as reported. Operating profit here is EBIT, not EBITDA - this multiple is EV/EBIT and is NOT combined with the Mphasis EV/EBITDA figure above; kept in a separate column.
B12: Structural precedent (not in multiples table): KPIT Technologies / Birlasoft merger (announced Jan-2018, effective Jan-2019) - a genuine stock-for-stock MERGER, not a cash acquisition: swap ratio 22 KPIT shares : 9 Birlasoft shares, forming a combined ~$700M-revenue IT services entity (which then demerged into Engineering vs IT Services businesses). No clean "price paid" multiple exists for a merger-plus-demerger of this kind, but it confirms stock-swap mergers are an established, executed transaction structure in Indian IT services - directly relevant to validating the LTI-Mindtree deal's chosen structure. (Source: KPIT/Birlasoft investor disclosures, Motilal Oswal deal report, M&A Critique.)
A14: ## | B14: Summary Statistics - EV/Revenue
B15: 3 of 4 transactions have a clean EV/Revenue (Capgemini/iGate, HCL/Geometric, Carlyle/Hexaware); Blackstone/Mphasis is excluded from this statistic (only EV/EBITDA was cleanly sourceable for it) - MEDIAN/AVERAGE/MIN/MAX below skip its "n/a" cell automatically.
B17: Median | C17: =MEDIAN(F7:F10)
B18: Mean | C18: =AVERAGE(F7:F10)
B19: Min | C19: =MIN(F7:F10)
B20: Max | C20: =MAX(F7:F10)
A22: ## | B22: Applied to LTI and Mindtree (FY22 financials, deal-year LTM)
C24: LTI | D24: Mindtree
B25: Revenue (FY22, Rs.M) | C25: ='LTI_P&L Schedule'!H7 | D25: ='MT_P&L Schedule'!H7
B26: EBITDA (FY22, Rs.M) | C26: ='LTI_P&L Schedule'!H11 | D26: ='MT_P&L Schedule'!H11
B27: EBIT (FY22, Rs.M) | C27: ='LTI_P&L Schedule'!H14 | D27: ='MT_P&L Schedule'!H14
B28: Debt incl. leases (book value, Rs.M) | C28: ='LTI_WACC Schedule'!C34 | D28: ='MT_WACC Schedule'!C34
B29: Cash & Cash Equivalents (Rs.M) | C29: =IFERROR(INDEX(LTI_HS_CONSOLIDATED!I:I,MATCH("CashAndCashEquivalents",LTI_HS_CONSOLIDATED!$C:$C,0)),0) | D29: =IFERROR(INDEX(MT_HS_CONSOLIDATED!I:I,MATCH("CashAndCashEquivalents",MT_HS_CONSOLIDATED!$C:$C,0)),0)
B30: Shares Outstanding | C30: ='LTI_WACC Schedule'!C7 | D30: ='MT_WACC Schedule'!C7
B31: Market Price (6-May-2022, Rs.) | C31: ='LTI_WACC Schedule'!C6 | D31: ='MT_WACC Schedule'!C6
B33: Net Debt (Rs.M) | C33: =C28-C29 | D33: =D28-D29
A35: ### | B35: Method A: EV/Revenue @ Median
B36: Implied EV (Rs.M) | C36: =C25*$C$17 | D36: =D25*$C$17
B37: Less: Net Debt (Rs.M) | C37: =-C33 | D37: =-D33
B38: Implied Equity Value (Rs.M) | C38: =C36+C37 | D38: =D36+D37
B39: Implied Value / Share (Rs.) | C39: =C38/C30 | D39: =D38/D30
B40: % of Actual Market Price | C40: =C39/C31 | D40: =D39/D31
A42: ### | B42: Method A-Low: EV/Revenue @ Min
B43: Implied EV (Rs.M) | C43: =C25*$C$19 | D43: =D25*$C$19
B44: Less: Net Debt (Rs.M) | C44: =-C33 | D44: =-D33
B45: Implied Equity Value (Rs.M) | C45: =C43+C44 | D45: =D43+D44
B46: Implied Value / Share (Rs.) | C46: =C45/C30 | D46: =D45/D30
B47: % of Actual Market Price | C47: =C46/C31 | D47: =D46/D31
A49: ### | B49: Method A-High: EV/Revenue @ Max
B50: Implied EV (Rs.M) | C50: =C25*$C$20 | D50: =D25*$C$20
B51: Less: Net Debt (Rs.M) | C51: =-C33 | D51: =-D33
B52: Implied Equity Value (Rs.M) | C52: =C50+C51 | D52: =D50+D51
B53: Implied Value / Share (Rs.) | C53: =C52/C30 | D53: =D52/D30
B54: % of Actual Market Price | C54: =C53/C31 | D54: =D53/D31
A56: ### | B56: Method B: EV/EBITDA @ Blackstone/Mphasis (single txn) | E56: Single-transaction multiple - weaker evidentiary weight than Method A's 3-deal median.
B57: Implied EV (Rs.M) | C57: =C26*$H$8 | D57: =D26*$H$8
B58: Less: Net Debt (Rs.M) | C58: =-C33 | D58: =-D33
B59: Implied Equity Value (Rs.M) | C59: =C57+C58 | D59: =D57+D58
B60: Implied Value / Share (Rs.) | C60: =C59/C30 | D60: =D59/D30
B61: % of Actual Market Price | C61: =C60/C31 | D61: =D60/D31
A63: ### | B63: Method C: EV/EBIT @ Carlyle/Hexaware (single txn) | E63: Single-transaction multiple, and EBIT-based (not EBITDA) - not averaged with Method B.
B64: Implied EV (Rs.M) | C64: =C27*$H$10 | D64: =D27*$H$10
B65: Less: Net Debt (Rs.M) | C65: =-C33 | D65: =-D33
B66: Implied Equity Value (Rs.M) | C66: =C64+C65 | D66: =D64+D65
B67: Implied Value / Share (Rs.) | C67: =C66/C30 | D67: =D66/D30
B68: % of Actual Market Price | C68: =C67/C31 | D68: =D67/D31
A70: ## | B70: Cross-Method Comparison & Implied Exchange Ratio
C72: LTI | D72: Mindtree | E72: Implied Ratio (Mindtree/LTI x100)
B73: DCF (10yr, 24.76% growth - locked-in) | C73: =LTI_DCF!C33 | D73: =MT_DCF!C33 | E73: =D73/C73*100
B74: Trading Comps (peer median P/E) | C74: =LTI_Comps!B16 | D74: =MT_Comps!B16 | E74: =D74/C74*100
B75: Precedent Txn - Method A (EV/Rev median) | C75: =C39 | D75: =D39 | E75: =D75/C75*100
B76: Precedent Txn - Method B (EV/EBITDA, Mphasis) | C76: =C60 | D76: =D60 | E76: =D76/C76*100
B77: Precedent Txn - Method C (EV/EBIT, Hexaware) | C77: =C67 | D77: =D67 | E77: =D77/C77*100
B78: Actual Market Price (6-May-2022) | C78: ='LTI_WACC Schedule'!C6 | D78: ='MT_WACC Schedule'!C6 | E78: =D78/C78*100
B80: Reference: actual historical swap ratio = 73.00 (73 LTI shares per 100 Mindtree shares); market-implied ratio (6-May-2022 closing prices) = 73.47.
B82: Reading this table: on a RATIO basis, Method A (EV/Revenue median, 73.11) lands strikingly close to both the actual historical ratio (73.00) and the market-implied ratio (73.47) - closer than Trading Comps (76.47) and much closer than the DCF (67.48). This was not tuned to land here: the four transaction multiples were sourced independently, before this comparison was ever computed, and nothing was adjusted afterward to hit this number. The likely mechanical reason: LTI and Mindtree are similar-enough same-sector peers that a single shared EV/Revenue multiple mostly preserves whatever ratio their own Revenue/Net-Debt/Share-count profiles already implied, rather than the multiple itself doing much work. Treat it as a genuine independent data point, not proof the deal was priced fairly - on ABSOLUTE value, this method is the most conservative of all four (LTI 59.4%, Mindtree 59.1% of market price - lower than the DCF's 81.0%/74.4%), so it undervalues both companies more than any other method even while its ratio happens to track actual most closely. Both facts are real and are reported here without picking one to headline over the other.
B84: Premium Paid Analysis
B85: Audit gap #8 (Task 26). This deal's own premium/(discount) is already computed at 'Exchange Ratio & Ownership'!C31 - benchmarked here against real precedent-transaction premiums and the notebook-sourced typical global range noted at that sheet's row 33, rather than left as an unreferenced number.
B87: Premium / (Discount) to Unaffected Share Price - Precedent Transactions
B88: Acquirer / Target | C88: Offer Price | D88: Unaffected Price | E88: Premium / (Discount)
B89: Capgemini / iGate Corporation (unaffected close 24-Apr-2015) | C89: 48 | D89: 45.85 | E89: =C89/D89-1 | I89: TheStreet, Business Standard (24-27 Apr 2015): Capgemini offered $48.00/share, a stated 4.7% premium to iGate's Friday close of $45.85 - entered directly as reported, formula cross-checks to the same figure.
B90: HCL Technologies / Geometric Ltd | C90: n/a | D90: n/a | E90: 0.32 | I90: Business Standard, M&A Critique (Apr 2016): sources describe a 32% premium for Geometric shareholders. Entered directly as source-reported (32%), not computed from a clean pre/post per-share pair - deal was a share-swap-plus-demerger (10 HCL Tech shares : 43 Geometric shares, plus a preference-share sweetener), not a simple cash tender, so no clean offer-price-vs-unaffected-price formula applies the way it does for iGate/Mphasis.
B91: Blackstone / Mphasis - public open offer (26% tranche, vs. prior close 1-Apr-2016) | C91: 457.54 | D91: 467.4 | E91: =C91/D91-1 | I91: Business Standard (4 Apr 2016): Blackstone's mandatory open offer to public shareholders was Rs.457.54/share, a 2.1% DISCOUNT to Friday's Rs.467.40 close - explicitly reported as 'at a discount'. Distinct from the separate promoter-stake purchase price (Rs.430/share for the controlling 60.5% from HPE, not a public-market transaction, so not used here). A real negative data point, kept rather than dropped for not fitting a 'premium' narrative.
B92: Carlyle Group / Hexaware Technologies | C92: n/a | D92: n/a | E92: n/a | I92: Hexaware was privately held (owned by Baring Private Equity Asia, itself having taken it private in 2013) at the time of the 2021 Carlyle deal - bought from a financial sponsor, not from public shareholders. No public 'unaffected price' exists to benchmark a premium against; excluded here rather than left blank without explanation.
B94: Summary (n=3, where a public unaffected price exists)
B95: Median | C95: =MEDIAN(E89,E90,E91)
B96: Average | C96: =AVERAGE(E89,E90,E91)
B97: Small, non-representative sample (n=3) - directional context, not a rigorous statistical benchmark. Also for reference: typical global takeover premium is cited at roughly 20-40% (per notebook consult, Task 26 audit, cross-referenced already at 'Exchange Ratio & Ownership'!B33 - not independently re-sourced this session).
B99: This Deal (LTI - Mindtree)
B100: Implied Premium / (Discount) to Mindtree's Standalone Price | C100: ='Exchange Ratio & Ownership'!C31
B102: Reading this: this deal's actual -0.64% is a discount, not a premium - below all three sourced precedent premiums (range -2.1% to +32%, median 4.69%, average 11.53% off a small n=3 sample) and well below the notebook-cited 20-40% typical global range. Consistent with, and now a second independent confirmation of, the finding already written at 'Exchange Ratio & Ownership'!B33: this looks like a relative-value merger of two already-affiliated companies (both L&T subsidiaries) rather than a competitive third-party buyout, which is exactly the deal type that would need a real control premium to win independent shareholders over. Not proof by itself - n=3 precedents is a thin sample - but it points the same direction as the rest of this model's findings, not a new or conflicting signal.

Sheet Best Owner Analysis
A1: # | B1: Best Owner Analysis (audit gap #1)
B2: Standard 'Best Owner' test (McKinsey & Co. / Copeland-Koller Valuation textbook - CONFIRMED via live notebook query, 25-Aug-2026, after NotebookLM auth was restored; an earlier version of this sheet used 5 self-derived levers instead of the real ones below - corrected here, not silently). Tests whether LTI specifically extracts more value from Mindtree's assets than any other plausible owner would, across the 5 REAL value levers - deliberately harder than the deal announcement's own 'highly complementary strengths' language, which doesn't by itself distinguish LTI from a hypothetical alternative acquirer.
A4: ## | B4: What the deal announcement actually said (for contrast)
B5: A.M. Naik (L&T Group Chairman): "The highly complementary strengths of LTI and Mindtree make this integration a win-win proposition..." - S.N. Subrahmanyan: "...turning the collective wisdom of the two companies into a much larger force..." Genuine statements, but generic - this kind of language appears in nearly every stock-for-stock merger announcement. Source: task1_rationale.json.
A7: ## | B7: Lever A: Unique Links with Other Businesses
B8: Delivery-center city overlap (of 10 India cities each) | C8: 7 of 10
B9: Subcontractor-cost pooling synergy (Rs.Mn/yr) | C9: ='Synergies (Bottom-Up Estimate)'!D9
B10: Real-estate consolidation synergy (Rs.Mn/yr) | C10: ='Synergies (Bottom-Up Estimate)'!D16
B11: LTI largest vertical: BFSI / Mindtree largest: CMT (18% BFSI) | C11: Complementary
B12: Cross-sell revenue synergy estimate (Rs.Mn/yr, illustrative) | C12: ='Synergies (Bottom-Up Estimate)'!D25
B13: Verdict | E13: The textbook's own example for this lever is exactly this shape: 'sharing existing manufacturing infrastructure' and 'established, highly specialized distribution networks and sales channels to cross-sell.' The 70% city overlap and complementary verticals are real, specific structural facts about these two companies (not true of an arbitrary IT-services pairing), and both cost-synergy categories are sized bottom-up from real cost bases. The revenue cross-sell number is this workbook's own weakest figure by its own admission (2% of revenue, 'included for completeness rather than confidence' - no deal-pipeline data exists to ground it further). Real and specific for cost links; directionally real but weakly sized for revenue links.
A15: ## | B15: Lever B: Distinctive Functional or Managerial Skills
B16: Combined workforce (approx.) | C16: ~90,000
B17: Verdict | E17: Per the textbook, this lever requires a distinctive skill that maps to the target's primary value driver - not just generic scale. Management's own language here is genuinely generic ('collective wisdom,' 'diversity of scale and capabilities'), with no specific disclosed mechanism (no named platform, methodology, or capability that flows specifically from LTI to Mindtree or vice versa, the way subcontractor pooling or city overlap are concrete). Unverifiable with available public data - reported as such, not assumed true or false.
A19: ## | B19: Lever C: Better Governance and Incentives
B20: L&T Group Chairman, pre- AND post-merger | C20: A.M. Naik (both)
B21: Verdict | E21: Doesn't apply, and that itself is the finding. This lever tests whether a NEW owner brings better capital-allocation discipline than the target had standalone (the textbook's own examples: lean corporate centers, high-powered incentive design replacing weaker incumbent governance). LTI and Mindtree were both L&T Group subsidiaries with the SAME ultimate parent and SAME Group Chairman before this deal - governance discipline isn't something the merger newly introduces, since both companies already answered to it. Close to moot for a merger-of-affiliates structure.
A23: ## | B23: Lever D: Better Insight or Foresight
B24: Verdict | E24: No public evidence either way. This lever requires proprietary, superior market foresight that lets the owner make bold, early resource-allocation calls ahead of the market. Nothing in either company's public disclosures speaks to this directly (no documented instance of L&T Group correctly anticipating an IT-services market shift years ahead of peers and acting on it via this merger). Genuinely unverifiable with available data, not a lever this analysis can test one way or the other.
A27: ## | B27: Lever E: Clout / Influence over Critical Stakeholders
B28: Combined entity market-cap rank (India IT services) | C28: 5th largest
B29: Verdict | E29: Likely LOW relevance here, and the textbook itself flags why: this lever matters most in heavily regulated, capital-intensive sectors and developing capital markets - not a competitive, globally-traded IT-services business, where (per the same source) 'clout with the government rarely provides an advantage' in developed markets. The one plausible channel - L&T Group's scale/reputation helping win larger enterprise RFPs that require vendor scale and financial stability - is consistent with the deal's own stated 'entered the elite league of top-tiered IT services companies' framing, but is a scale effect, not the specific stakeholder-clout mechanism (government, regulators) the textbook describes. Weak evidence, not strong.
A31: ## | B31: Important Context - Not One of the 5 Levers
B32: L&T's ownership of combined entity (actual, disclosed) | C32: ='Exchange Ratio & Ownership'!C19
B33: This deal's premium/(discount) to Mindtree's standalone price | C33: ='Precedent Transactions'!C100 | E33: L&T retained 68.73% of the combined entity - both companies were, and remain, part of the same corporate family. Combined with the near-zero deal premium, this explains WHY the Best-Owner framework doesn't map cleanly onto this specific deal: there was no competitive process, because there was really only one plausible owner (the L&T Group, which already owned both) - a structural fact about THIS deal, correctly kept separate from the 5 levers themselves rather than mislabeled as a 6th lever.
A36: ## | B36: Overall Conclusion
B37: Of the 5 real Best-Owner levers: A (Unique Links) is real and well-evidenced on the cost side, weaker on the revenue side. B (Distinctive Skills) and D (Insight/Foresight) are unverifiable with available public data - reported honestly as untestable, not assumed. C (Governance) doesn't apply because both companies already shared L&T governance pre-merger. E (Stakeholder Clout) is plausible but weak, and the textbook's own caveats suggest it matters less in this kind of market. Combined with the fact that L&T already owned both companies (Important Context above), the honest overall read is that this deal creates real, specific, but modest value primarily through Lever A (cost/revenue links), not through a genuine multi-lever best-owner advantage over alternative owners - because there effectively weren't competing alternative owners to test against.

Sheet Goal-Seek Synergy Backsolve
A1: # | B1: Goal-Seek Synergy Backsolve (audit gap #2) | D1: CONFIRMED via live notebook query, 25-Aug-2026 (auth restored): real IB technique sets NPV of synergies = acquisition premium + fees, backsolves the constant annual run-rate via Excel Goal Seek (Bruner's textbook worked example: $142M/yr on a $1bn premium, discounted at 6% cost of debt for low-risk cost synergies). Closed-form algebraic solve here is the exact equivalent for this linear structure. LIMITATION now confirmed, not just guessed: a fully rigorous treatment discounts cost synergies at the acquirer's pre-tax cost of debt and revenue synergies at cost of equity separately (different risk profiles) - this sheet uses a single blended acquirer WACC for the whole backsolved figure, a real simplification, not the textbook-precise method.
A3: ## | B3: Scenario A: vs. Market Price Basis (what was actually paid, in market terms)
B4: Value Received per Mindtree Share (Rs.) | C4: ='Exchange Ratio & Ownership'!C29
B5: Mindtree Standalone Market Price, 6-May-2022 (Rs.) | C5: ='Exchange Ratio & Ownership'!C30
B6: Mindtree Shares Outstanding | C6: ='MT_WACC Schedule'!C7
B7: Deal Value Paid (Rs.M) | C7: =C4*C6/1000000
B8: Mindtree Standalone Market Value (Rs.M) | C8: =C5*C6/1000000
B9: Excess Paid over Market Value (Rs.M) | C9: =C7-C8 | D9: Matches the -0.64% discount already found in Precedent Transactions/Exchange Ratio & Ownership - the deal was priced AT (very slightly below) market, so on a pure market-price basis, essentially no premium needs synergy justification at all.
A11: ## | B11: Scenario B: vs. DCF Intrinsic Value Basis (what the model says Mindtree is really worth)
B12: Mindtree DCF Equity Value (Rs.M) | C12: =MT_DCF!C32/1000000
B13: Excess Paid over DCF Intrinsic Value (Rs.M) | C13: =C7-C12
B14: Estimated Deal Fees (Rs.M) - generic 1% of deal value (not disclosed; standard IB rule-of-thumb, low end since this is an affiliate merger, not a competitively-shopped acquisition) | C14: =C7*0.01
B15: Total Value Requiring Synergy Justification (Rs.M) | C15: =C13+C14
B17: Discount Rates by Synergy Risk Type (differentiated per synergy risk - confirmed via notebook)
B18: Pre-Tax Cost of Debt (for cost synergies - low risk, EBIT-like volatility) | C18: ='LTI_WACC Schedule'!C30
B19: Cost of Equity (for revenue synergies - high risk, speculative) | C19: ='LTI_WACC Schedule'!C23
B20: Terminal Growth Rate (locked-in, both companies) | C20: ='LTI_DCF'!C22
A21: ##
B22: Bookend Backsolves (the Rs.130,318M gap could be closed via cost savings, revenue synergies, or a mix - both pure cases shown as bookends)
B23: If closed ENTIRELY via cost synergies, discounted at cost of debt (Rs.M/yr) | C23: =C15*(C18-C20)
B24: If closed ENTIRELY via revenue synergies, discounted at cost of equity (Rs.M/yr) | C24: =C15*(C19-C20)
B25: For reference: single blended-WACC method (original version of this sheet, Rs.M/yr) | C25: =C15*('LTI_WACC Schedule'!C39-C20)
B27: Sanity Check vs. This Model's Own Bottom-Up Estimate, Split by Type
B28: Bottom-up COST synergy estimate (subcontractor+real estate, Rs.M/yr) | C28: ='Synergies (Bottom-Up Estimate)'!D9+'Synergies (Bottom-Up Estimate)'!D16
B29: Bottom-up REVENUE synergy estimate (cross-sell, Rs.M/yr) | C29: ='Synergies (Bottom-Up Estimate)'!D25
B30: Cost-backsolve (row 23) as multiple of bottom-up COST estimate | C30: =C23/C28
B31: Revenue-backsolve (row 24) as multiple of bottom-up REVENUE estimate | C31: =C24/C29
B33: Reading this: | D33: Tightened 25-Aug-2026 after notebook confirmation of the differentiated-rate technique. If the Rs.130,318M DCF-basis gap had to be closed ENTIRELY via cost synergies (discounted at the lower, less-risky pre-tax cost of debt), the required run-rate is Rs.2,955M/yr - only 0.61x of this workbook's own bottom-up COST estimate (Rs.4,884M/yr, subcontractor+real-estate) - comfortably covered. If closed ENTIRELY via revenue synergies (discounted at the higher cost of equity, reflecting real execution risk), the required run-rate is Rs.6,639M/yr - 1.27x of the bottom-up REVENUE estimate (Rs.5,239M/yr, cross-sell) - i.e. relying purely on revenue synergies would need MORE than even this workbook's own already-uncertain cross-sell estimate. Sharper and more honest than the original single-blended-WACC figure (Rs.6,576M/yr, kept for reference): cost synergies alone can defend the deal; revenue synergies alone cannot, without exceeding the model's own most speculative number. Consistent with, and now quantifying, this session's repeated finding that the cost-side synergies are this model's more reliable value driver.

Sheet Value of Control
A1: # | B1: Value of Control (audit gap #3) | E1: Test-and-revert dated 25-Aug-2026, CORRECTED same day after NotebookLM auth was restored and the actual methodology was verified against the notebook: an earlier version of this sheet forced Mindtree's margin DOWN to the exact peer-median, violating Damodaran's own rule that value-of-control adjustments should never degrade a company already performing at or above the benchmark. Corrected below - not silently.
A3: ## | B3: Methodology
B4: Value of Control = Optimally-Managed Value minus Status-Quo Value. Optimally-Managed = same locked DCF structure, re-run with Employee Benefit % (the model's own margin driver) shifted from each company's own trending baseline to hit the industry-median EBIT margin (18.22%, FY24 peer-median from this workbook's own Comps sheet - Task 25's industry-adjusted correction), plus an illustrative 'optimal' 15% Target Debt/Capitalization (generic assumption, not independently derived - see the capital-structure finding below for why this particular lever turned out not to matter here).
A6: ## | C6: LTI | D6: Mindtree
B7: FY22 Actual EBIT Margin | C7: 0.1726 | D7: 0.1856
B8: Industry-Median EBIT Margin (peer median, FY24) | C8: 0.1822 | D8: 0.1822
B9: Gap to Close | C9: =C8-C7 | D9: =D8-D7 | E9: LTI sits BELOW the peer median (room to improve). Mindtree sits ABOVE it - per Damodaran's own framework ('value of control is negligible for firms operating at or close to their optimal value'), the correct treatment for an already-above-benchmark company is NOT to force its margin down to the median. Corrected from an earlier version of this sheet that did exactly that.
B11: Status-Quo Value / Share (Rs., locked-in baseline) | C11: =LTI_DCF!C33 | D11: =MT_DCF!C33
B12: Optimally-Managed Value / Share (Rs.) - LTI: test result, hardcoded (see note). Mindtree: = Status-Quo (no change - already above peer median, see correction note) | C12: 3851.63 | D12: =D11
B13: Value of Control (Rs./share) | C13: =C12-C11 | D13: =D12-D11
B14: Value of Control (%) | C14: =C13/C11 | D14: =D13/D11
A16: ## | B16: Capital-Structure Lever - a real finding, not a result
B17: The 15% Target Debt/Capitalization override was applied to both companies' 'INPUT: Target Debt/Capitalization Ratio' cell during this test, but produced ZERO change to either company's WACC - confirmed by direct inspection of 'LTI_WACC Schedule'!C14 (This company's D/E), which references 'Inputs & Assumptions'!C66 (the historically-derived 'Suggested' value) and NOT C67 (the INPUT override cell actually being tested). C67 does flow into the Debt Schedule's forecast debt level ('LTI_Schedules'!I92), so it isn't dead - it just isn't wired into the discount-rate side of the model at all. This means the WACC used for the Optimally-Managed test above is identical to the Status-Quo WACC (10.06% LTI, 10.04% MT) - the entire Value of Control result above comes from the margin lever alone, not a genuine 'optimal capital structure' effect. Flagged plainly as a real gap in the underlying tool, not smoothed over or silently worked around.
A20: ## | B20: Reading This
B21: CORRECTED 25-Aug-2026 after notebook re-verification (see header note). LTI's Value of Control is small and positive (Rs.3,845.72 -> Rs.3,851.63, +0.15%) - modest headroom from closing a real but small (0.97pp) below-median margin gap, tested via the sanctioned test-and-revert method. Mindtree's Value of Control is correctly ~0 (negligible) - Mindtree already runs ABOVE the peer-median EBIT margin (18.56% vs 18.22%), so per Damodaran's own framework no restructuring toward the median is warranted; an earlier version of this sheet incorrectly forced Mindtree's margin down to the median anyway and reported a spurious -13.5% Value of Control, which has been corrected here rather than left standing. The real, honest finding: this framework properly identifies asymmetric headroom - LTI has a little room to improve toward peer-typical performance, Mindtree is already performing at (or above) that bar and gains nothing from being forced toward it. A stricter test against a true best-in-class benchmark (e.g. TCS's 25.27% FY22 EBIT margin, the top of this workbook's own peer set, rather than the median) was not performed this session and would be the natural next refinement if a tighter optimal bar is wanted for Mindtree specifically.

Sheet AVP - Various Exchange Ratios
A1: # | B1: Analysis at Various (Exchange Ratio) Prices (audit gap #7) | J1: All-stock deal, so the AVP axis is the exchange ratio, not a dollar offer price. Pro forma PAT uses ACTUAL disclosed combined results, same convention as Pro Forma & Accretion-Dilution's Method A/B - a hypothetical ratio changes dilution, not real combined earnings power.
A4: ## | B4: Exchange Ratio Scenarios
B6: Exchange Ratio | C6: 0.6 | D6: 0.65 | E6: 0.68 | F6: 0.7 | G6: 0.73 | H6: 0.75 | I6: 0.8 | K6: 0.85 | L6: 0.9
G7: ACTUAL
B9: New LTI Shares Issued | C9: =C6*'Exchange Ratio & Ownership'!$C$12 | D9: =D6*'Exchange Ratio & Ownership'!$C$12 | E9: =E6*'Exchange Ratio & Ownership'!$C$12 | F9: =F6*'Exchange Ratio & Ownership'!$C$12 | G9: =G6*'Exchange Ratio & Ownership'!$C$12 | H9: =H6*'Exchange Ratio & Ownership'!$C$12 | I9: =I6*'Exchange Ratio & Ownership'!$C$12 | K9: =K6*'Exchange Ratio & Ownership'!$C$12 | L9: =L6*'Exchange Ratio & Ownership'!$C$12
B10: Pro Forma LTI Shares Outstanding | C10: =C9+'Exchange Ratio & Ownership'!$C$11 | D10: =D9+'Exchange Ratio & Ownership'!$C$11 | E10: =E9+'Exchange Ratio & Ownership'!$C$11 | F10: =F9+'Exchange Ratio & Ownership'!$C$11 | G10: =G9+'Exchange Ratio & Ownership'!$C$11 | H10: =H9+'Exchange Ratio & Ownership'!$C$11 | I10: =I9+'Exchange Ratio & Ownership'!$C$11 | K10: =K9+'Exchange Ratio & Ownership'!$C$11 | L10: =L9+'Exchange Ratio & Ownership'!$C$11
B11: Mindtree Ownership % of Combined | C11: =C9/C10 | D11: =D9/D10 | E11: =E9/E10 | F11: =F9/F10 | G11: =G9/G10 | H11: =H9/H10 | I11: =I9/I10 | K11: =K9/K10 | L11: =L9/L10
B13: Value Received per Mindtree Share (Rs.) | C13: =C6*'Exchange Ratio & Ownership'!$C$28 | D13: =D6*'Exchange Ratio & Ownership'!$C$28 | E13: =E6*'Exchange Ratio & Ownership'!$C$28 | F13: =F6*'Exchange Ratio & Ownership'!$C$28 | G13: =G6*'Exchange Ratio & Ownership'!$C$28 | H13: =H6*'Exchange Ratio & Ownership'!$C$28 | I13: =I6*'Exchange Ratio & Ownership'!$C$28 | K13: =K6*'Exchange Ratio & Ownership'!$C$28 | L13: =L6*'Exchange Ratio & Ownership'!$C$28
B14: Premium / (Discount) to MT Market Price | C14: =C13/'Exchange Ratio & Ownership'!$C$30-1 | D14: =D13/'Exchange Ratio & Ownership'!$C$30-1 | E14: =E13/'Exchange Ratio & Ownership'!$C$30-1 | F14: =F13/'Exchange Ratio & Ownership'!$C$30-1 | G14: =G13/'Exchange Ratio & Ownership'!$C$30-1 | H14: =H13/'Exchange Ratio & Ownership'!$C$30-1 | I14: =I13/'Exchange Ratio & Ownership'!$C$30-1 | K14: =K13/'Exchange Ratio & Ownership'!$C$30-1 | L14: =L13/'Exchange Ratio & Ownership'!$C$30-1
B16: Pro Forma EPS - FY22 basis (Rs.) | C16: ='Pro Forma & Accretion-Dilution'!$C$18*1000000/C10 | D16: ='Pro Forma & Accretion-Dilution'!$C$18*1000000/D10 | E16: ='Pro Forma & Accretion-Dilution'!$C$18*1000000/E10 | F16: ='Pro Forma & Accretion-Dilution'!$C$18*1000000/F10 | G16: ='Pro Forma & Accretion-Dilution'!$C$18*1000000/G10 | H16: ='Pro Forma & Accretion-Dilution'!$C$18*1000000/H10 | I16: ='Pro Forma & Accretion-Dilution'!$C$18*1000000/I10 | K16: ='Pro Forma & Accretion-Dilution'!$C$18*1000000/K10 | L16: ='Pro Forma & Accretion-Dilution'!$C$18*1000000/L10
B17: Accretion / (Dilution) vs. LTI Standalone EPS - FY22 basis | C17: =C16/'Pro Forma & Accretion-Dilution'!$C$72-1 | D17: =D16/'Pro Forma & Accretion-Dilution'!$C$72-1 | E17: =E16/'Pro Forma & Accretion-Dilution'!$C$72-1 | F17: =F16/'Pro Forma & Accretion-Dilution'!$C$72-1 | G17: =G16/'Pro Forma & Accretion-Dilution'!$C$72-1 | H17: =H16/'Pro Forma & Accretion-Dilution'!$C$72-1 | I17: =I16/'Pro Forma & Accretion-Dilution'!$C$72-1 | K17: =K16/'Pro Forma & Accretion-Dilution'!$C$72-1 | L17: =L16/'Pro Forma & Accretion-Dilution'!$C$72-1
B19: Pro Forma EPS - FY23 actual basis (Rs.) | C19: ='Pro Forma & Accretion-Dilution'!$D$18*1000000/C10 | D19: ='Pro Forma & Accretion-Dilution'!$D$18*1000000/D10 | E19: ='Pro Forma & Accretion-Dilution'!$D$18*1000000/E10 | F19: ='Pro Forma & Accretion-Dilution'!$D$18*1000000/F10 | G19: ='Pro Forma & Accretion-Dilution'!$D$18*1000000/G10 | H19: ='Pro Forma & Accretion-Dilution'!$D$18*1000000/H10 | I19: ='Pro Forma & Accretion-Dilution'!$D$18*1000000/I10 | K19: ='Pro Forma & Accretion-Dilution'!$D$18*1000000/K10 | L19: ='Pro Forma & Accretion-Dilution'!$D$18*1000000/L10
B20: Accretion / (Dilution) vs. LTI Standalone EPS - FY23 basis | C20: =C19/'Pro Forma & Accretion-Dilution'!$C$72-1 | D20: =D19/'Pro Forma & Accretion-Dilution'!$C$72-1 | E20: =E19/'Pro Forma & Accretion-Dilution'!$C$72-1 | F20: =F19/'Pro Forma & Accretion-Dilution'!$C$72-1 | G20: =G19/'Pro Forma & Accretion-Dilution'!$C$72-1 | H20: =H19/'Pro Forma & Accretion-Dilution'!$C$72-1 | I20: =I19/'Pro Forma & Accretion-Dilution'!$C$72-1 | K20: =K19/'Pro Forma & Accretion-Dilution'!$C$72-1 | L20: =L19/'Pro Forma & Accretion-Dilution'!$C$72-1
J27: Reading this:
J28: Clean, monotonic trade-off curve, as expected mechanically: a lower ratio pays Mindtree shareholders less (bigger discount to their own market price - -18.3% at 0.60x vs the actual -0.64% at 0.73x) but dilutes LTI's existing shareholders less (more accretive, +9.86% at 0.60x on an FY22 basis vs +1.90% at the actual ratio); a higher ratio does the reverse (+22.5% premium at 0.90x, but turns mildly DILUTIVE on an FY22 basis by around 0.75-0.80x, and stays accretive throughout on the more favorable FY23-actual-PAT basis even at 0.90x). The actual 0.73 ratio sits close to the low-premium end of this range, not the middle or high end - consistent with, and now a third independent confirmation of, the 'merger of affiliates priced near market, not a competitive buyout' finding already established in Precedent Transactions, Exchange Ratio & Ownership, and Goal-Seek Synergy Backsolve. A buyer optimizing purely for EPS accretion would have pushed for a lower ratio than 0.73; the fact that it wasn't pushed lower is itself consistent with this being a relative-value settlement between affiliated companies rather than an adversarial negotiation.

Sheet Reference LBO Floor
A1: # | B1: Reference LBO Floor Analysis (audit gap #9) | I1: CONFIRMED via live notebook query, 25-Aug-2026 (auth restored): real technique matches - max sponsor price at a 15-20% IRR hurdle (20-25%+ for riskier targets) sets a market-clearing floor for strategic buyers; exit multiple <= entry multiple is standard (no expansion assumed, as done here); LBO valuation is 'traditionally toward the lower end' of the valuation hierarchy - exactly what this sheet finds. Leverage here (3.5x) sits within the confirmed real range (3-6x EBITDA, senior debt typically 60-70% of purchase price). One simplification now explicitly confirmed rather than assumed: the real technique models a full 100% cash-sweep debt paydown waterfall (mandatory amortization, then optional prepayment); this sheet holds debt flat across the hold, a deliberately conservative simplification that only understates the resulting IRR/floor, confirmed - not guessed - to be conservative relative to the real technique.
A4: ## | B4: LTI Standalone
B6: Entry EBITDA - FY22 actual (Rs.M) | C6: ='LTI_P&L Schedule'!H11/1000000
B7: Exit EBITDA - FY2027E, 5-year forecast (Rs.M) | C7: ='LTI_P&L Schedule'!M11/1000000
B8: Implied 5-yr EBITDA CAGR | C8: =(C7/C6)^(1/5)-1
B9: Assumed Leverage (Debt/EBITDA) - generic IT-services LBO convention | C9: 3.5
B10: Debt Raised (Rs.M) - entry level, before cash-sweep paydown (see schedule below) | C10: =C9*C6
B11: Target Sponsor IRR (5-yr hold) - generic PE benchmark | C11: 0.22
B13: Entry/Exit Multiple (no expansion assumed) | C13: 6 | D13: 7 | E13: 8 | F13: 9 | G13: 10 | H13: 11
F14: Blackstone/Mphasis actual
B15: Entry EV (Rs.M) | C15: =C13*$C$6 | D15: =D13*$C$6 | E15: =E13*$C$6 | F15: =F13*$C$6 | G15: =G13*$C$6 | H15: =H13*$C$6
B16: Entry Equity Check (Rs.M) | C16: =C15-$C$10 | D16: =D15-$C$10 | E16: =E15-$C$10 | F16: =F15-$C$10 | G16: =G15-$C$10 | H16: =H15-$C$10
B17: Exit EV (Rs.M) | C17: =C13*$C$7 | D17: =D13*$C$7 | E17: =E13*$C$7 | F17: =F13*$C$7 | G17: =G13*$C$7 | H17: =H13*$C$7
B18: Exit Equity (Rs.M) | C18: =C17-C41 | D18: =D17-C41 | E18: =E17-C41 | F18: =F17-C41 | G18: =G17-C41 | H18: =H17-C41
B19: 5-Year Sponsor IRR | C19: =(C18/C16)^(1/5)-1 | D19: =(D18/D16)^(1/5)-1 | E19: =(E18/E16)^(1/5)-1 | F19: =(F18/F16)^(1/5)-1 | G19: =(G18/G16)^(1/5)-1 | H19: =(H18/H16)^(1/5)-1
B20: Implied Value/Share at this Entry EV (Rs.) | C20: =(C15-'Precedent Transactions'!$C$33/1000000)*1000000/'Precedent Transactions'!$C$30 | D20: =(D15-'Precedent Transactions'!$C$33/1000000)*1000000/'Precedent Transactions'!$C$30 | E20: =(E15-'Precedent Transactions'!$C$33/1000000)*1000000/'Precedent Transactions'!$C$30 | F20: =(F15-'Precedent Transactions'!$C$33/1000000)*1000000/'Precedent Transactions'!$C$30 | G20: =(G15-'Precedent Transactions'!$C$33/1000000)*1000000/'Precedent Transactions'!$C$30 | H20: =(H15-'Precedent Transactions'!$C$33/1000000)*1000000/'Precedent Transactions'!$C$30 | I20: Reading this:
I21: Tightened 25-Aug-2026 with a real 100% cash-sweep debt paydown schedule (confirmed as the standard technique via notebook query), replacing the earlier flat-debt simplification. Paying down debt from real forecast operating cash flow raises every IRR versus the earlier (deliberately conservative) flat-debt version - e.g. LTI at 6x: 34.5% -> 41.5%. Both companies clear the 22% target IRR even more comfortably across the full 6x-11x range (LTI 28.5%-41.5%, Mindtree 25.8%-38.7% - Mindtree no longer sits at the edge at 11x the way it did under the flat-debt version). Implied Value/Share is UNCHANGED (Rs.1,025-1,897 LTI, Rs.829-1,495 Mindtree) since it depends only on the Entry EV/multiple, not on how debt is repaid post-entry - debt paydown affects the sponsor's RETURN, not the entry PRICE. The core conclusion strengthens, not reverses: the LBO floor sits even more comfortably below DCF (Rs.3,845.72/Rs.2,595.89) and market price than the conservative version already showed - still clearly not the binding constraint on how this deal was priced.
A24: ## | B24: MT Standalone
B26: Entry EBITDA - FY22 actual (Rs.M) | C26: ='MT_P&L Schedule'!H11/1000000
B27: Exit EBITDA - FY2027E, 5-year forecast (Rs.M) | C27: ='MT_P&L Schedule'!M11/1000000
B28: Implied 5-yr EBITDA CAGR | C28: =(C27/C26)^(1/5)-1
B29: Assumed Leverage (Debt/EBITDA) - generic IT-services LBO convention | C29: 3.5
B30: Debt Raised (Rs.M) - entry level, before cash-sweep paydown (see schedule below) | C30: =C29*C26
B31: Target Sponsor IRR (5-yr hold) - generic PE benchmark | C31: 0.22
B33: Entry/Exit Multiple (no expansion assumed) | C33: 6 | D33: 7 | E33: 8 | F33: 9 | G33: 10 | H33: 11
F34: Blackstone/Mphasis actual
B35: Entry EV (Rs.M) | C35: =C33*$C$26 | D35: =D33*$C$26 | E35: =E33*$C$26 | F35: =F33*$C$26 | G35: =G33*$C$26 | H35: =H33*$C$26
B36: Entry Equity Check (Rs.M) | C36: =C35-$C$30 | D36: =D35-$C$30 | E36: =E35-$C$30 | F36: =F35-$C$30 | G36: =G35-$C$30 | H36: =H35-$C$30
B37: Exit EV (Rs.M) | C37: =C33*$C$27 | D37: =D33*$C$27 | E37: =E33*$C$27 | F37: =F33*$C$27 | G37: =G33*$C$27 | H37: =H33*$C$27
B38: Exit Equity (Rs.M) | C38: =C37-C53 | D38: =D37-C53 | E38: =E37-C53 | F38: =F37-C53 | G38: =G37-C53 | H38: =H37-C53
B39: 5-Year Sponsor IRR | C39: =(C38/C36)^(1/5)-1 | D39: =(D38/D36)^(1/5)-1 | E39: =(E38/E36)^(1/5)-1 | F39: =(F38/F36)^(1/5)-1 | G39: =(G38/G36)^(1/5)-1 | H39: =(H38/H36)^(1/5)-1
B40: Implied Value/Share at this Entry EV (Rs.) | C40: =(C35-'Precedent Transactions'!$D$33/1000000)*1000000/'Precedent Transactions'!$D$30 | D40: =(D35-'Precedent Transactions'!$D$33/1000000)*1000000/'Precedent Transactions'!$D$30 | E40: =(E35-'Precedent Transactions'!$D$33/1000000)*1000000/'Precedent Transactions'!$D$30 | F40: =(F35-'Precedent Transactions'!$D$33/1000000)*1000000/'Precedent Transactions'!$D$30 | G40: =(G35-'Precedent Transactions'!$D$33/1000000)*1000000/'Precedent Transactions'!$D$30 | H40: =(H35-'Precedent Transactions'!$D$33/1000000)*1000000/'Precedent Transactions'!$D$30
B41: Year-5 Ending Debt After Cash Sweep (Rs.M) - used in Exit Equity below | C41: =G52
A43: ## | B43: LTI Debt Paydown Schedule (100% Cash Sweep) - tightened, confirmed standard technique
B44: Cash Available for Debt Repayment = CFO + CFI (Capex, already negative) each year, from this workbook's own forecast CFStmt (real modeled cash flows, not a new assumption) - swept 100% to debt, floored at 0. Replaces the earlier flat-debt simplification.
C46: Yr1 FY23E | D46: Yr2 FY24E | E46: Yr3 FY25E | F46: Yr4 FY26E | G46: Yr5 FY27E
B47: Cash Flow from Operations (Rs.M) | C47: ='LTI_CFStmt'!C12/1000000 | D47: ='LTI_CFStmt'!D12/1000000 | E47: ='LTI_CFStmt'!E12/1000000 | F47: ='LTI_CFStmt'!F12/1000000 | G47: ='LTI_CFStmt'!G12/1000000
B48: Cash Flow from Investing / Capex (Rs.M) | C48: ='LTI_CFStmt'!C15/1000000 | D48: ='LTI_CFStmt'!D15/1000000 | E48: ='LTI_CFStmt'!E15/1000000 | F48: ='LTI_CFStmt'!F15/1000000 | G48: ='LTI_CFStmt'!G15/1000000
B49: Cash Available for Debt Repayment (Rs.M) | C49: =C47+C48 | D49: =D47+D48 | E49: =E47+E48 | F49: =F47+F48 | G49: =G47+G48
B50: Beginning Debt (Rs.M) | C50: =$C10 | D50: =C52 | E50: =D52 | F50: =E52 | G50: =F52
B51: Debt Repaid (capped at min of cash available or beginning balance) | C51: =MIN(MAX(C49,0),C50) | D51: =MIN(MAX(D49,0),D50) | E51: =MIN(MAX(E49,0),E50) | F51: =MIN(MAX(F49,0),F50) | G51: =MIN(MAX(G49,0),G50)
B52: Ending Debt (Rs.M) | C52: =C50-C51 | D52: =D50-D51 | E52: =E50-E51 | F52: =F50-F51 | G52: =G50-G51
B53: Year-5 Ending Debt After Cash Sweep (Rs.M) - used in Exit Equity below | C53: =G64
A55: ## | B55: MT Debt Paydown Schedule (100% Cash Sweep) - tightened, confirmed standard technique
B56: Cash Available for Debt Repayment = CFO + CFI (Capex, already negative) each year, from this workbook's own forecast CFStmt (real modeled cash flows, not a new assumption) - swept 100% to debt, floored at 0. Replaces the earlier flat-debt simplification.
C58: Yr1 FY23E | D58: Yr2 FY24E | E58: Yr3 FY25E | F58: Yr4 FY26E | G58: Yr5 FY27E
B59: Cash Flow from Operations (Rs.M) | C59: ='MT_CFStmt'!C12/1000000 | D59: ='MT_CFStmt'!D12/1000000 | E59: ='MT_CFStmt'!E12/1000000 | F59: ='MT_CFStmt'!F12/1000000 | G59: ='MT_CFStmt'!G12/1000000
B60: Cash Flow from Investing / Capex (Rs.M) | C60: ='MT_CFStmt'!C15/1000000 | D60: ='MT_CFStmt'!D15/1000000 | E60: ='MT_CFStmt'!E15/1000000 | F60: ='MT_CFStmt'!F15/1000000 | G60: ='MT_CFStmt'!G15/1000000
B61: Cash Available for Debt Repayment (Rs.M) | C61: =C59+C60 | D61: =D59+D60 | E61: =E59+E60 | F61: =F59+F60 | G61: =G59+G60
B62: Beginning Debt (Rs.M) | C62: =$C30 | D62: =C64 | E62: =D64 | F62: =E64 | G62: =F64
B63: Debt Repaid (capped at min of cash available or beginning balance) | C63: =MIN(MAX(C61,0),C62) | D63: =MIN(MAX(D61,0),D62) | E63: =MIN(MAX(E61,0),E62) | F63: =MIN(MAX(F61,0),F62) | G63: =MIN(MAX(G61,0),G62)
B64: Ending Debt (Rs.M) | C64: =C62-C63 | D64: =D62-D63 | E64: =E62-E63 | F64: =F62-F63 | G64: =G62-G63

Sheet Synergies (Bottom-Up Estimate)
A1: # Synergy Analysis - Buy-Side Estimate
A2: SECONDARY / ILLUSTRATIVE - see the 'Pro Forma & Accretion-Dilution' sheet for the REAL, disclosed combined-entity figures (use that sheet as the primary reference); this one is the bottom-up methodology a modeler would use in the absence of actual disclosed synergy figures, built before the FY23 Board Report's actual results were consulted. IMPORTANT: Neither the original May 6, 2022 deal announcement (PRNewswire) nor the FY23 board report disclose specific dollar synergy targets - only qualitative language ("scale benefits," "unlock synergies through scale, cross-vertical expertise, and talent pool"). Everything below marked ESTIMATE (yellow fill) is bottom-up analysis built from real filed cost/revenue bases, NOT a management-disclosed figure. Facts (blue) are sourced; assumed realization percentages (red italic) are explicitly flagged judgment calls.
A4: Synergy | B4: Combined Base (Rs. Mn) | C4: Assumed Realization | D4: Rs. Mn / Note
A6: ## 1. COST SYNERGY - Subcontractor / combined bench pooling
A7: LTI subcontractor cost FY22 (8.4% of revenue) | B7: 13171 | D7: LTI FY22 AR
A8: Mindtree subcontractor cost FY22 (10.2% of revenue, +88.3% YoY) | B8: 10788 | D8: Mindtree FY22 AR, Note 24
A9: Combined subcontractor base - ESTIMATE at 12% reduction via internal bench redeployment | B9: 23959 | C9: 0.12 | D9: =B9*C9
A10: ESTIMATE, not disclosed. Rationale: combined ~82,000-employee bench can absorb overflow demand that either company alone had to fill externally. 12% is a judgment call, not sourced.
A11: ## 2. COST SYNERGY - Real estate / delivery center consolidation
A12: LTI India cities (10): Mumbai, Navi Mumbai, Bengaluru, Pune, Chennai, Hyderabad, Noida, Nagpur, Coimbatore, Mysuru | D12: LTI FY22 AR
A13: Mindtree India cities (10): Bengaluru, Bhubaneswar, Chennai, Coimbatore, Hyderabad, Kolkata, Mumbai, Noida, Pune, Warangal | D13: Mindtree FY22 AR
A14: OVERLAP: 7 of 10 cities exact match (Mumbai, Bengaluru, Pune, Chennai, Hyderabad, Noida, Coimbatore) + Krakow/Paris/Copenhagen internationally | D14: Cross-checked directly from both companies' own location lists
A15: Combined lease liabilities FY22 (LTI 7,836 + Mindtree 5,557) | B15: 13393 | D15: LTI + Mindtree FY22 AR, consolidated lease liabilities
A16: ESTIMATE at 15% consolidation of overlapping footprint | B16: 13393 | C16: 0.15 | D16: =B16*C16
A17: ESTIMATE. Deliberately conservative vs. the 70% city-overlap ratio: a merged company with ~130,000 combined employees needs MORE total seats than either company held alone - this is not a simple additive consolidation, so 15% (not 70%) is used.
A18: ## 3. COST SYNERGY - Public-company overhead de-duplication
A19: One listed-company overhead eliminated (board, one audit, one IR function, one listing compliance) instead of two separately-listed entities.
A20: NOT QUANTIFIED - no board/IR cost breakdown disclosed by either company at the granularity needed. Directionally real but likely small (low hundreds of Rs. Million) relative to categories 1-2 for a company this size. Flagged as real but not sized, rather than guessed.
A22: ## 4. REVENUE SYNERGY - Cross-vertical selling
A23: LTI BFSI concentration (largest segment) | D23: 46.3% of FY22 revenue - LTI FY22 AR
A24: Mindtree CMT concentration (largest) / BFSI only | D24: 43% CMT / 18% BFSI of FY22 revenue - Mindtree FY22 AR - genuinely complementary, not overlapping
A25: ESTIMATE: 2% of combined FY22 revenue as illustrative cross-sell potential by Year 2-3 | B25: 261940 | C25: 0.02 | D25: =B25*C25
A26: ESTIMATE, high uncertainty. Combined FY22 revenue = LTI 156,687 + Mindtree 105,253. 2% is illustrative only - no deal-pipeline data to ground this further. Flagged as the least reliable number on this sheet, included for completeness rather than confidence.
A27: ## 5. REVENUE SYNERGY - Larger deal capacity (qualitative only, not sized)
A28: Combined entity crosses into 5th-largest-by-market-cap tier, qualifying for RFPs with minimum-scale requirements neither could bid on alone. Directionally real (matches the stated rationale) but no deal-pipeline data exists to size it - left qualitative rather than forcing a number.
A30: ## 6. BALANCE SHEET SYNERGY - combined cash (optionality, not an annual run-rate synergy)
A31: Combined net cash FY22 (LTI 34,238 + Mindtree 30,463) | B31: 64701 | D31: Enables larger strategic/M&A investments per press release - a stock of capital, not a recurring P&L synergy, so excluded from the total below
A32: ## 7. RISK CHECK - potential dis-synergy (client conflict)
A33: Could not verify: do LTI and Mindtree serve directly competing clients in the same account (e.g. two rival banks)? Client names are not disclosed at that granularity in either annual report. Flagged as an unresolved risk, not assumed either way.
A35: ## TOTAL ESTIMATED ANNUAL SYNERGY (categories 1, 2, 4 only - the sized ones)
A36: Sum of Category 1 + 2 + 4 estimates (excludes category 3 and 5, left unquantified; excludes category 6, not a run-rate item) | D36: =D9+D16+D25
A37: As % of combined FY22 revenue (261,940) | D37: =D36/261940
A39: ## 8. RAMP-UP PACING & ONE-TIME INTEGRATION COST (audit gap #12c)
A40: Applies only to this bottom-up illustrative estimate (Category 1+2+4 total, D36) and the Stress Test's synergy perpetuity - NOT to Pro Forma & Accretion-Dilution, which is grounded in actual disclosed combined PAT and doesn't have a 'synergy ramp' to pace (see Task 27 build_log entry for why). Standard IB integration-modeling convention: synergies phase in over 3 years rather than hit full run-rate on Day 1, and a real cash integration cost is incurred to realize them - not independently re-verified against the notebook this session (auth was stale); used as a widely-cited generic convention, consistent with what the Task 26 audit reported, not freshly re-sourced.
A42: Ramp-Up Schedule
B43: Year 1 | C43: Year 2 | D43: Year 3+ (full run-rate)
A44: % of full run-rate synergy (D36) realized | B44: 0.33 | C44: 0.66 | D44: 1
A45: Synergy realized (Rs.Mn) | B45: =$D$36*B44 | C45: =$D$36*C44 | D45: =$D$36*D44
A47: One-Time Integration Cost
A48: Multiple of full annual run-rate synergy (typical 1.1-1.2x IT-integration benchmark, midpoint used) | B48: 1.15
A49: Integration Cost (Rs.Mn) - assumed incurred upfront at deal close | B49: =$D$36*B48
A51: Reading this: on the existing D36 estimate (Rs.10,123M/year full run-rate), the ramp implies Rs.3,341M realized in Year 1 and Rs.6,681M in Year 2 before reaching full run-rate in Year 3, against a one-time integration cost of roughly Rs.11,641M paid upfront - i.e. the integration cost alone is larger than one full year of realized synergy, which is the normal, expected shape for this kind of deal (cost precedes benefit) rather than a red flag specific to this one. See 'Stress Test - Exchange Ratio' rows 40+ for how this changes (or doesn't change) the Bear/Base/Bull exchange-ratio bounds versus the original flat-perpetuity treatment.

Sheet LTI_HIST_CON
A1: LTIMindtree — Derived Financial Model
A2: Green = cross-sheet formula (XLOOKUP against raw data) | Black = same-sheet formula (subtotal/total)
A5: # | B5: Statement of Profit and Loss | E5: FY2017 | F5: FY2018 | G5: FY2019 | H5: FY2020 | I5: FY2021 | J5: FY2022
B6: Income [Abstract]
C7: Total revenue from operations | E7: =_xlfn.XLOOKUP("RevenueFromOperations",LTI_HS_CONSOLIDATED!$C:$C,LTI_HS_CONSOLIDATED!D:D,0,0,1) | F7: =_xlfn.XLOOKUP("RevenueFromOperations",LTI_HS_CONSOLIDATED!$C:$C,LTI_HS_CONSOLIDATED!E:E,0,0,1) | G7: =_xlfn.XLOOKUP("RevenueFromOperations",LTI_HS_CONSOLIDATED!$C:$C,LTI_HS_CONSOLIDATED!F:F,0,0,1) | H7: =_xlfn.XLOOKUP("RevenueFromOperations",LTI_HS_CONSOLIDATED!$C:$C,LTI_HS_CONSOLIDATED!G:G,0,0,1) | I7: =_xlfn.XLOOKUP("RevenueFromOperations",LTI_HS_CONSOLIDATED!$C:$C,LTI_HS_CONSOLIDATED!H:H,0,0,1) | J7: =_xlfn.XLOOKUP("RevenueFromOperations",LTI_HS_CONSOLIDATED!$C:$C,LTI_HS_CONSOLIDATED!I:I,0,0,1)
C8: Total other income | E8: =_xlfn.XLOOKUP("OtherIncome",LTI_HS_CONSOLIDATED!$C:$C,LTI_HS_CONSOLIDATED!D:D,0,0,1) | F8: =_xlfn.XLOOKUP("OtherIncome",LTI_HS_CONSOLIDATED!$C:$C,LTI_HS_CONSOLIDATED!E:E,0,0,1) | G8: =_xlfn.XLOOKUP("OtherIncome",LTI_HS_CONSOLIDATED!$C:$C,LTI_HS_CONSOLIDATED!F:F,0,0,1) | H8: =_xlfn.XLOOKUP("OtherIncome",LTI_HS_CONSOLIDATED!$C:$C,LTI_HS_CONSOLIDATED!G:G,0,0,1) | I8: =_xlfn.XLOOKUP("OtherIncome",LTI_HS_CONSOLIDATED!$C:$C,LTI_HS_CONSOLIDATED!H:H,0,0,1) | J8: =_xlfn.XLOOKUP("OtherIncome",LTI_HS_CONSOLIDATED!$C:$C,LTI_HS_CONSOLIDATED!I:I,0,0,1)
C9: Total income | E9: =IFERROR(SUM(E7:E8),0) | F9: =IFERROR(SUM(F7:F8),0) | G9: =IFERROR(SUM(G7:G8),0) | H9: =IFERROR(SUM(H7:H8),0) | I9: =IFERROR(SUM(I7:I8),0) | J9: =IFERROR(SUM(J7:J8),0)
B10: COGS
B11: Gross Profit | E11: =IFERROR(E9,0) | F11: =IFERROR(F9,0) | G11: =IFERROR(G9,0) | H11: =IFERROR(H9,0) | I11: =IFERROR(I9,0) | J11: =IFERROR(J9,0)
C12: SG&A | E12: =-_xlfn.XLOOKUP("EmployeeBenefitExpense",LTI_HS_CONSOLIDATED!$C:$C,LTI_HS_CONSOLIDATED!D:D,0,0,1)-_xlfn.XLOOKUP("ExpenditureOnProductionTransportationAndOtherExpenditurePertainingToExplorationAndProductionActivities",LTI_HS_CONSOLIDATED!$C:$C,LTI_HS_CONSOLIDATED!D:D,0,0,1) | F12: =-_xlfn.XLOOKUP("EmployeeBenefitExpense",LTI_HS_CONSOLIDATED!$C:$C,LTI_HS_CONSOLIDATED!E:E,0,0,1)-_xlfn.XLOOKUP("ExpenditureOnProductionTransportationAndOtherExpenditurePertainingToExplorationAndProductionActivities",LTI_HS_CONSOLIDATED!$C:$C,LTI_HS_CONSOLIDATED!E:E,0,0,1) | G12: =-_xlfn.XLOOKUP("EmployeeBenefitExpense",LTI_HS_CONSOLIDATED!$C:$C,LTI_HS_CONSOLIDATED!F:F,0,0,1)-_xlfn.XLOOKUP("ExpenditureOnProductionTransportationAndOtherExpenditurePertainingToExplorationAndProductionActivities",LTI_HS_CONSOLIDATED!$C:$C,LTI_HS_CONSOLIDATED!F:F,0,0,1) | H12: =-_xlfn.XLOOKUP("EmployeeBenefitExpense",LTI_HS_CONSOLIDATED!$C:$C,LTI_HS_CONSOLIDATED!G:G,0,0,1)-_xlfn.XLOOKUP("ExpenditureOnProductionTransportationAndOtherExpenditurePertainingToExplorationAndProductionActivities",LTI_HS_CONSOLIDATED!$C:$C,LTI_HS_CONSOLIDATED!G:G,0,0,1) | I12: =-_xlfn.XLOOKUP("EmployeeBenefitExpense",LTI_HS_CONSOLIDATED!$C:$C,LTI_HS_CONSOLIDATED!H:H,0,0,1)-_xlfn.XLOOKUP("ExpenditureOnProductionTransportationAndOtherExpenditurePertainingToExplorationAndProductionActivities",LTI_HS_CONSOLIDATED!$C:$C,LTI_HS_CONSOLIDATED!H:H,0,0,1) | J12: =-_xlfn.XLOOKUP("EmployeeBenefitExpense",LTI_HS_CONSOLIDATED!$C:$C,LTI_HS_CONSOLIDATED!I:I,0,0,1)-_xlfn.XLOOKUP("ExpenditureOnProductionTransportationAndOtherExpenditurePertainingToExplorationAndProductionActivities",LTI_HS_CONSOLIDATED!$C:$C,LTI_HS_CONSOLIDATED!I:I,0,0,1)
C13: Total other expenses | E13: =-_xlfn.XLOOKUP("OtherExpenses",LTI_HS_CONSOLIDATED!$C:$C,LTI_HS_CONSOLIDATED!D:D,0,0,1) | F13: =-_xlfn.XLOOKUP("OtherExpenses",LTI_HS_CONSOLIDATED!$C:$C,LTI_HS_CONSOLIDATED!E:E,0,0,1) | G13: =-_xlfn.XLOOKUP("OtherExpenses",LTI_HS_CONSOLIDATED!$C:$C,LTI_HS_CONSOLIDATED!F:F,0,0,1) | H13: =-_xlfn.XLOOKUP("OtherExpenses",LTI_HS_CONSOLIDATED!$C:$C,LTI_HS_CONSOLIDATED!G:G,0,0,1) | I13: =-_xlfn.XLOOKUP("OtherExpenses",LTI_HS_CONSOLIDATED!$C:$C,LTI_HS_CONSOLIDATED!H:H,0,0,1) | J13: =-_xlfn.XLOOKUP("OtherExpenses",LTI_HS_CONSOLIDATED!$C:$C,LTI_HS_CONSOLIDATED!I:I,0,0,1)
B14: EBITDA | E14: =IFERROR(SUM(E11:E13),0) | F14: =IFERROR(SUM(F11:F13),0) | G14: =IFERROR(SUM(G11:G13),0) | H14: =IFERROR(SUM(H11:H13),0) | I14: =IFERROR(SUM(I11:I13),0) | J14: =IFERROR(SUM(J11:J13),0)
C15: D&A | E15: =-_xlfn.XLOOKUP("DepreciationDepletionAndAmortisationExpense",LTI_HS_CONSOLIDATED!$C:$C,LTI_HS_CONSOLIDATED!D:D,0,0,1) | F15: =-_xlfn.XLOOKUP("DepreciationDepletionAndAmortisationExpense",LTI_HS_CONSOLIDATED!$C:$C,LTI_HS_CONSOLIDATED!E:E,0,0,1) | G15: =-_xlfn.XLOOKUP("DepreciationDepletionAndAmortisationExpense",LTI_HS_CONSOLIDATED!$C:$C,LTI_HS_CONSOLIDATED!F:F,0,0,1) | H15: =-_xlfn.XLOOKUP("DepreciationDepletionAndAmortisationExpense",LTI_HS_CONSOLIDATED!$C:$C,LTI_HS_CONSOLIDATED!G:G,0,0,1) | I15: =-_xlfn.XLOOKUP("DepreciationDepletionAndAmortisationExpense",LTI_HS_CONSOLIDATED!$C:$C,LTI_HS_CONSOLIDATED!H:H,0,0,1) | J15: =-_xlfn.XLOOKUP("DepreciationDepletionAndAmortisationExpense",LTI_HS_CONSOLIDATED!$C:$C,LTI_HS_CONSOLIDATED!I:I,0,0,1)
B16: EBIT | E16: =IFERROR(SUM(E14:E15),0) | F16: =IFERROR(SUM(F14:F15),0) | G16: =IFERROR(SUM(G14:G15),0) | H16: =IFERROR(SUM(H14:H15),0) | I16: =IFERROR(SUM(I14:I15),0) | J16: =IFERROR(SUM(J14:J15),0)
C17: Total finance costs | E17: =-_xlfn.XLOOKUP("FinanceCosts",LTI_HS_CONSOLIDATED!$C:$C,LTI_HS_CONSOLIDATED!D:D,0,0,1) | F17: =-_xlfn.XLOOKUP("FinanceCosts",LTI_HS_CONSOLIDATED!$C:$C,LTI_HS_CONSOLIDATED!E:E,0,0,1) | G17: =-_xlfn.XLOOKUP("FinanceCosts",LTI_HS_CONSOLIDATED!$C:$C,LTI_HS_CONSOLIDATED!F:F,0,0,1) | H17: =-_xlfn.XLOOKUP("FinanceCosts",LTI_HS_CONSOLIDATED!$C:$C,LTI_HS_CONSOLIDATED!G:G,0,0,1) | I17: =-_xlfn.XLOOKUP("FinanceCosts",LTI_HS_CONSOLIDATED!$C:$C,LTI_HS_CONSOLIDATED!H:H,0,0,1) | J17: =-_xlfn.XLOOKUP("FinanceCosts",LTI_HS_CONSOLIDATED!$C:$C,LTI_HS_CONSOLIDATED!I:I,0,0,1)
B18: EBT | E18: =IFERROR(SUM(E16:E17),0) | F18: =IFERROR(SUM(F16:F17),0) | G18: =IFERROR(SUM(G16:G17),0) | H18: =IFERROR(SUM(H16:H17),0) | I18: =IFERROR(SUM(I16:I17),0) | J18: =IFERROR(SUM(J16:J17),0)
C19: Total current tax | E19: =-_xlfn.XLOOKUP("CurrentTax",LTI_HS_CONSOLIDATED!$C:$C,LTI_HS_CONSOLIDATED!D:D,0,0,1) | F19: =-_xlfn.XLOOKUP("CurrentTax",LTI_HS_CONSOLIDATED!$C:$C,LTI_HS_CONSOLIDATED!E:E,0,0,1) | G19: =-_xlfn.XLOOKUP("CurrentTax",LTI_HS_CONSOLIDATED!$C:$C,LTI_HS_CONSOLIDATED!F:F,0,0,1) | H19: =-_xlfn.XLOOKUP("CurrentTax",LTI_HS_CONSOLIDATED!$C:$C,LTI_HS_CONSOLIDATED!G:G,0,0,1) | I19: =-_xlfn.XLOOKUP("CurrentTax",LTI_HS_CONSOLIDATED!$C:$C,LTI_HS_CONSOLIDATED!H:H,0,0,1) | J19: =-_xlfn.XLOOKUP("CurrentTax",LTI_HS_CONSOLIDATED!$C:$C,LTI_HS_CONSOLIDATED!I:I,0,0,1)
C20: Deferred tax | E20: =-_xlfn.XLOOKUP("DeferredTax",LTI_HS_CONSOLIDATED!$C:$C,LTI_HS_CONSOLIDATED!D:D,0,0,1) | F20: =-_xlfn.XLOOKUP("DeferredTax",LTI_HS_CONSOLIDATED!$C:$C,LTI_HS_CONSOLIDATED!E:E,0,0,1) | G20: =-_xlfn.XLOOKUP("DeferredTax",LTI_HS_CONSOLIDATED!$C:$C,LTI_HS_CONSOLIDATED!F:F,0,0,1) | H20: =-_xlfn.XLOOKUP("DeferredTax",LTI_HS_CONSOLIDATED!$C:$C,LTI_HS_CONSOLIDATED!G:G,0,0,1) | I20: =-_xlfn.XLOOKUP("DeferredTax",LTI_HS_CONSOLIDATED!$C:$C,LTI_HS_CONSOLIDATED!H:H,0,0,1) | J20: =-_xlfn.XLOOKUP("DeferredTax",LTI_HS_CONSOLIDATED!$C:$C,LTI_HS_CONSOLIDATED!I:I,0,0,1)
C21: Total tax expense | E21: =IFERROR(SUM(E19:E20),0) | F21: =IFERROR(SUM(F19:F20),0) | G21: =IFERROR(SUM(G19:G20),0) | H21: =IFERROR(SUM(H19:H20),0) | I21: =IFERROR(SUM(I19:I20),0) | J21: =IFERROR(SUM(J19:J20),0)
B22: NETINCOME | E22: =IFERROR(E21+E18,0) | F22: =IFERROR(F21+F18,0) | G22: =IFERROR(G21+G18,0) | H22: =IFERROR(H21+H18,0) | I22: =IFERROR(I21+I18,0) | J22: =IFERROR(J21+J18,0)
A23: # | B23: Balance Sheet
B24: Assets [Abstract]
B25: Non-current assets [Abstract]
C26: Operating
D27: Property, plant and equipment at end of period | E27: =_xlfn.XLOOKUP("PropertyPlantAndEquipment",LTI_HS_CONSOLIDATED!$C:$C,LTI_HS_CONSOLIDATED!D:D,0,0,1) | F27: =_xlfn.XLOOKUP("PropertyPlantAndEquipment",LTI_HS_CONSOLIDATED!$C:$C,LTI_HS_CONSOLIDATED!E:E,0,0,1) | G27: =_xlfn.XLOOKUP("PropertyPlantAndEquipment",LTI_HS_CONSOLIDATED!$C:$C,LTI_HS_CONSOLIDATED!F:F,0,0,1) | H27: =_xlfn.XLOOKUP("PropertyPlantAndEquipment",LTI_HS_CONSOLIDATED!$C:$C,LTI_HS_CONSOLIDATED!G:G,0,0,1) | I27: =_xlfn.XLOOKUP("PropertyPlantAndEquipment",LTI_HS_CONSOLIDATED!$C:$C,LTI_HS_CONSOLIDATED!H:H,0,0,1) | J27: =_xlfn.XLOOKUP("PropertyPlantAndEquipment",LTI_HS_CONSOLIDATED!$C:$C,LTI_HS_CONSOLIDATED!I:I,0,0,1)
D28: Capital work-in-progress | E28: =_xlfn.XLOOKUP("CapitalWorkInProgress",LTI_HS_CONSOLIDATED!$C:$C,LTI_HS_CONSOLIDATED!D:D,0,0,1) | F28: =_xlfn.XLOOKUP("CapitalWorkInProgress",LTI_HS_CONSOLIDATED!$C:$C,LTI_HS_CONSOLIDATED!E:E,0,0,1) | G28: =_xlfn.XLOOKUP("CapitalWorkInProgress",LTI_HS_CONSOLIDATED!$C:$C,LTI_HS_CONSOLIDATED!F:F,0,0,1) | H28: =_xlfn.XLOOKUP("CapitalWorkInProgress",LTI_HS_CONSOLIDATED!$C:$C,LTI_HS_CONSOLIDATED!G:G,0,0,1) | I28: =_xlfn.XLOOKUP("CapitalWorkInProgress",LTI_HS_CONSOLIDATED!$C:$C,LTI_HS_CONSOLIDATED!H:H,0,0,1) | J28: =_xlfn.XLOOKUP("CapitalWorkInProgress",LTI_HS_CONSOLIDATED!$C:$C,LTI_HS_CONSOLIDATED!I:I,0,0,1)
D29: Goodwill at end of period | E29: =_xlfn.XLOOKUP("Goodwill",LTI_HS_CONSOLIDATED!$C:$C,LTI_HS_CONSOLIDATED!D:D,0,0,1) | F29: =_xlfn.XLOOKUP("Goodwill",LTI_HS_CONSOLIDATED!$C:$C,LTI_HS_CONSOLIDATED!E:E,0,0,1) | G29: =_xlfn.XLOOKUP("Goodwill",LTI_HS_CONSOLIDATED!$C:$C,LTI_HS_CONSOLIDATED!F:F,0,0,1) | H29: =_xlfn.XLOOKUP("Goodwill",LTI_HS_CONSOLIDATED!$C:$C,LTI_HS_CONSOLIDATED!G:G,0,0,1) | I29: =_xlfn.XLOOKUP("Goodwill",LTI_HS_CONSOLIDATED!$C:$C,LTI_HS_CONSOLIDATED!H:H,0,0,1) | J29: =_xlfn.XLOOKUP("Goodwill",LTI_HS_CONSOLIDATED!$C:$C,LTI_HS_CONSOLIDATED!I:I,0,0,1)
D30: Other intangible assets at end of period | E30: =_xlfn.XLOOKUP("OtherIntangibleAssets",LTI_HS_CONSOLIDATED!$C:$C,LTI_HS_CONSOLIDATED!D:D,0,0,1) | F30: =_xlfn.XLOOKUP("OtherIntangibleAssets",LTI_HS_CONSOLIDATED!$C:$C,LTI_HS_CONSOLIDATED!E:E,0,0,1) | G30: =_xlfn.XLOOKUP("OtherIntangibleAssets",LTI_HS_CONSOLIDATED!$C:$C,LTI_HS_CONSOLIDATED!F:F,0,0,1) | H30: =_xlfn.XLOOKUP("OtherIntangibleAssets",LTI_HS_CONSOLIDATED!$C:$C,LTI_HS_CONSOLIDATED!G:G,0,0,1) | I30: =_xlfn.XLOOKUP("OtherIntangibleAssets",LTI_HS_CONSOLIDATED!$C:$C,LTI_HS_CONSOLIDATED!H:H,0,0,1) | J30: =_xlfn.XLOOKUP("OtherIntangibleAssets",LTI_HS_CONSOLIDATED!$C:$C,LTI_HS_CONSOLIDATED!I:I,0,0,1)
D31: Intangible assets under development | E31: =_xlfn.XLOOKUP("IntangibleAssetsUnderDevelopment",LTI_HS_CONSOLIDATED!$C:$C,LTI_HS_CONSOLIDATED!D:D,0,0,1) | F31: =_xlfn.XLOOKUP("IntangibleAssetsUnderDevelopment",LTI_HS_CONSOLIDATED!$C:$C,LTI_HS_CONSOLIDATED!E:E,0,0,1) | G31: =_xlfn.XLOOKUP("IntangibleAssetsUnderDevelopment",LTI_HS_CONSOLIDATED!$C:$C,LTI_HS_CONSOLIDATED!F:F,0,0,1) | H31: =_xlfn.XLOOKUP("IntangibleAssetsUnderDevelopment",LTI_HS_CONSOLIDATED!$C:$C,LTI_HS_CONSOLIDATED!G:G,0,0,1) | I31: =_xlfn.XLOOKUP("IntangibleAssetsUnderDevelopment",LTI_HS_CONSOLIDATED!$C:$C,LTI_HS_CONSOLIDATED!H:H,0,0,1) | J31: =_xlfn.XLOOKUP("IntangibleAssetsUnderDevelopment",LTI_HS_CONSOLIDATED!$C:$C,LTI_HS_CONSOLIDATED!I:I,0,0,1)
D32: Total other non-current assets | E32: =_xlfn.XLOOKUP("OtherNoncurrentAssets",LTI_HS_CONSOLIDATED!$C:$C,LTI_HS_CONSOLIDATED!D:D,0,0,1) | F32: =_xlfn.XLOOKUP("OtherNoncurrentAssets",LTI_HS_CONSOLIDATED!$C:$C,LTI_HS_CONSOLIDATED!E:E,0,0,1) | G32: =_xlfn.XLOOKUP("OtherNoncurrentAssets",LTI_HS_CONSOLIDATED!$C:$C,LTI_HS_CONSOLIDATED!F:F,0,0,1) | H32: =_xlfn.XLOOKUP("OtherNoncurrentAssets",LTI_HS_CONSOLIDATED!$C:$C,LTI_HS_CONSOLIDATED!G:G,0,0,1) | I32: =_xlfn.XLOOKUP("OtherNoncurrentAssets",LTI_HS_CONSOLIDATED!$C:$C,LTI_HS_CONSOLIDATED!H:H,0,0,1) | J32: =_xlfn.XLOOKUP("OtherNoncurrentAssets",LTI_HS_CONSOLIDATED!$C:$C,LTI_HS_CONSOLIDATED!I:I,0,0,1)
C33: Total Operating | E33: =IFERROR(SUM(E27:E32),0) | F33: =IFERROR(SUM(F27:F32),0) | G33: =IFERROR(SUM(G27:G32),0) | H33: =IFERROR(SUM(H27:H32),0) | I33: =IFERROR(SUM(I27:I32),0) | J33: =IFERROR(SUM(J27:J32),0)
C34: Non-Operating
D35: Non-current investments | E35: =_xlfn.XLOOKUP("NoncurrentInvestments",LTI_HS_CONSOLIDATED!$C:$C,LTI_HS_CONSOLIDATED!D:D,0,0,1) | F35: =_xlfn.XLOOKUP("NoncurrentInvestments",LTI_HS_CONSOLIDATED!$C:$C,LTI_HS_CONSOLIDATED!E:E,0,0,1) | G35: =_xlfn.XLOOKUP("NoncurrentInvestments",LTI_HS_CONSOLIDATED!$C:$C,LTI_HS_CONSOLIDATED!F:F,0,0,1) | H35: =_xlfn.XLOOKUP("NoncurrentInvestments",LTI_HS_CONSOLIDATED!$C:$C,LTI_HS_CONSOLIDATED!G:G,0,0,1) | I35: =_xlfn.XLOOKUP("NoncurrentInvestments",LTI_HS_CONSOLIDATED!$C:$C,LTI_HS_CONSOLIDATED!H:H,0,0,1) | J35: =_xlfn.XLOOKUP("NoncurrentInvestments",LTI_HS_CONSOLIDATED!$C:$C,LTI_HS_CONSOLIDATED!I:I,0,0,1)
D36: Loans, non-current | E36: =_xlfn.XLOOKUP("LoansNoncurrent",LTI_HS_CONSOLIDATED!$C:$C,LTI_HS_CONSOLIDATED!D:D,0,0,1) | F36: =_xlfn.XLOOKUP("LoansNoncurrent",LTI_HS_CONSOLIDATED!$C:$C,LTI_HS_CONSOLIDATED!E:E,0,0,1) | G36: =_xlfn.XLOOKUP("LoansNoncurrent",LTI_HS_CONSOLIDATED!$C:$C,LTI_HS_CONSOLIDATED!F:F,0,0,1) | H36: =_xlfn.XLOOKUP("LoansNoncurrent",LTI_HS_CONSOLIDATED!$C:$C,LTI_HS_CONSOLIDATED!G:G,0,0,1) | I36: =_xlfn.XLOOKUP("LoansNoncurrent",LTI_HS_CONSOLIDATED!$C:$C,LTI_HS_CONSOLIDATED!H:H,0,0,1) | J36: =_xlfn.XLOOKUP("LoansNoncurrent",LTI_HS_CONSOLIDATED!$C:$C,LTI_HS_CONSOLIDATED!I:I,0,0,1)
D37: Total other non-current financial assets | E37: =_xlfn.XLOOKUP("OtherNoncurrentFinancialAssets",LTI_HS_CONSOLIDATED!$C:$C,LTI_HS_CONSOLIDATED!D:D,0,0,1) | F37: =_xlfn.XLOOKUP("OtherNoncurrentFinancialAssets",LTI_HS_CONSOLIDATED!$C:$C,LTI_HS_CONSOLIDATED!E:E,0,0,1) | G37: =_xlfn.XLOOKUP("OtherNoncurrentFinancialAssets",LTI_HS_CONSOLIDATED!$C:$C,LTI_HS_CONSOLIDATED!F:F,0,0,1) | H37: =_xlfn.XLOOKUP("OtherNoncurrentFinancialAssets",LTI_HS_CONSOLIDATED!$C:$C,LTI_HS_CONSOLIDATED!G:G,0,0,1) | I37: =_xlfn.XLOOKUP("OtherNoncurrentFinancialAssets",LTI_HS_CONSOLIDATED!$C:$C,LTI_HS_CONSOLIDATED!H:H,0,0,1) | J37: =_xlfn.XLOOKUP("OtherNoncurrentFinancialAssets",LTI_HS_CONSOLIDATED!$C:$C,LTI_HS_CONSOLIDATED!I:I,0,0,1)
D38: Deferred tax assets (net) | E38: =_xlfn.XLOOKUP("DeferredTaxAssetsNet",LTI_HS_CONSOLIDATED!$C:$C,LTI_HS_CONSOLIDATED!D:D,0,0,1) | F38: =_xlfn.XLOOKUP("DeferredTaxAssetsNet",LTI_HS_CONSOLIDATED!$C:$C,LTI_HS_CONSOLIDATED!E:E,0,0,1) | G38: =_xlfn.XLOOKUP("DeferredTaxAssetsNet",LTI_HS_CONSOLIDATED!$C:$C,LTI_HS_CONSOLIDATED!F:F,0,0,1) | H38: =_xlfn.XLOOKUP("DeferredTaxAssetsNet",LTI_HS_CONSOLIDATED!$C:$C,LTI_HS_CONSOLIDATED!G:G,0,0,1) | I38: =_xlfn.XLOOKUP("DeferredTaxAssetsNet",LTI_HS_CONSOLIDATED!$C:$C,LTI_HS_CONSOLIDATED!H:H,0,0,1) | J38: =_xlfn.XLOOKUP("DeferredTaxAssetsNet",LTI_HS_CONSOLIDATED!$C:$C,LTI_HS_CONSOLIDATED!I:I,0,0,1)
C39: Total Non-Operating | E39: =IFERROR(SUM(E35:E38),0) | F39: =IFERROR(SUM(F35:F38),0) | G39: =IFERROR(SUM(G35:G38),0) | H39: =IFERROR(SUM(H35:H38),0) | I39: =IFERROR(SUM(I35:I38),0) | J39: =IFERROR(SUM(J35:J38),0)
C40: Total non-current financial assets | E40: =_xlfn.XLOOKUP("NoncurrentFinancialAssets",LTI_HS_CONSOLIDATED!$C:$C,LTI_HS_CONSOLIDATED!D:D,0,0,1) | F40: =_xlfn.XLOOKUP("NoncurrentFinancialAssets",LTI_HS_CONSOLIDATED!$C:$C,LTI_HS_CONSOLIDATED!E:E,0,0,1) | G40: =_xlfn.XLOOKUP("NoncurrentFinancialAssets",LTI_HS_CONSOLIDATED!$C:$C,LTI_HS_CONSOLIDATED!F:F,0,0,1) | H40: =_xlfn.XLOOKUP("NoncurrentFinancialAssets",LTI_HS_CONSOLIDATED!$C:$C,LTI_HS_CONSOLIDATED!G:G,0,0,1) | I40: =_xlfn.XLOOKUP("NoncurrentFinancialAssets",LTI_HS_CONSOLIDATED!$C:$C,LTI_HS_CONSOLIDATED!H:H,0,0,1) | J40: =_xlfn.XLOOKUP("NoncurrentFinancialAssets",LTI_HS_CONSOLIDATED!$C:$C,LTI_HS_CONSOLIDATED!I:I,0,0,1)
B41: Total Non-Current Assets | E41: =IFERROR(E39+E33,0) | F41: =IFERROR(F39+F33,0) | G41: =IFERROR(G39+G33,0) | H41: =IFERROR(H39+H33,0) | I41: =IFERROR(I39+I33,0) | J41: =IFERROR(J39+J33,0)
B42: Current Assets
C43: Operating
D44: Trade receivables, current | E44: =_xlfn.XLOOKUP("TradeReceivablesCurrent",LTI_HS_CONSOLIDATED!$C:$C,LTI_HS_CONSOLIDATED!D:D,0,0,1) | F44: =_xlfn.XLOOKUP("TradeReceivablesCurrent",LTI_HS_CONSOLIDATED!$C:$C,LTI_HS_CONSOLIDATED!E:E,0,0,1) | G44: =_xlfn.XLOOKUP("TradeReceivablesCurrent",LTI_HS_CONSOLIDATED!$C:$C,LTI_HS_CONSOLIDATED!F:F,0,0,1) | H44: =_xlfn.XLOOKUP("TradeReceivablesCurrent",LTI_HS_CONSOLIDATED!$C:$C,LTI_HS_CONSOLIDATED!G:G,0,0,1) | I44: =_xlfn.XLOOKUP("TradeReceivablesCurrent",LTI_HS_CONSOLIDATED!$C:$C,LTI_HS_CONSOLIDATED!H:H,0,0,1) | J44: =_xlfn.XLOOKUP("TradeReceivablesCurrent",LTI_HS_CONSOLIDATED!$C:$C,LTI_HS_CONSOLIDATED!I:I,0,0,1)
D45: Total other current assets | E45: =_xlfn.XLOOKUP("OtherCurrentAssets",LTI_HS_CONSOLIDATED!$C:$C,LTI_HS_CONSOLIDATED!D:D,0,0,1) | F45: =_xlfn.XLOOKUP("OtherCurrentAssets",LTI_HS_CONSOLIDATED!$C:$C,LTI_HS_CONSOLIDATED!E:E,0,0,1) | G45: =_xlfn.XLOOKUP("OtherCurrentAssets",LTI_HS_CONSOLIDATED!$C:$C,LTI_HS_CONSOLIDATED!F:F,0,0,1) | H45: =_xlfn.XLOOKUP("OtherCurrentAssets",LTI_HS_CONSOLIDATED!$C:$C,LTI_HS_CONSOLIDATED!G:G,0,0,1) | I45: =_xlfn.XLOOKUP("OtherCurrentAssets",LTI_HS_CONSOLIDATED!$C:$C,LTI_HS_CONSOLIDATED!H:H,0,0,1) | J45: =_xlfn.XLOOKUP("OtherCurrentAssets",LTI_HS_CONSOLIDATED!$C:$C,LTI_HS_CONSOLIDATED!I:I,0,0,1)
C46: Total Operating | E46: =IFERROR(SUM(E44:E45),0) | F46: =IFERROR(SUM(F44:F45),0) | G46: =IFERROR(SUM(G44:G45),0) | H46: =IFERROR(SUM(H44:H45),0) | I46: =IFERROR(SUM(I44:I45),0) | J46: =IFERROR(SUM(J44:J45),0)
C47: Non-Operating
D48: Current investments | E48: =_xlfn.XLOOKUP("CurrentInvestments",LTI_HS_CONSOLIDATED!$C:$C,LTI_HS_CONSOLIDATED!D:D,0,0,1) | F48: =_xlfn.XLOOKUP("CurrentInvestments",LTI_HS_CONSOLIDATED!$C:$C,LTI_HS_CONSOLIDATED!E:E,0,0,1) | G48: =_xlfn.XLOOKUP("CurrentInvestments",LTI_HS_CONSOLIDATED!$C:$C,LTI_HS_CONSOLIDATED!F:F,0,0,1) | H48: =_xlfn.XLOOKUP("CurrentInvestments",LTI_HS_CONSOLIDATED!$C:$C,LTI_HS_CONSOLIDATED!G:G,0,0,1) | I48: =_xlfn.XLOOKUP("CurrentInvestments",LTI_HS_CONSOLIDATED!$C:$C,LTI_HS_CONSOLIDATED!H:H,0,0,1) | J48: =_xlfn.XLOOKUP("CurrentInvestments",LTI_HS_CONSOLIDATED!$C:$C,LTI_HS_CONSOLIDATED!I:I,0,0,1)
D49: Cash and cash equivalents at end of period | E49: =_xlfn.XLOOKUP("CashAndCashEquivalents",LTI_HS_CONSOLIDATED!$C:$C,LTI_HS_CONSOLIDATED!D:D,0,0,1) | F49: =_xlfn.XLOOKUP("CashAndCashEquivalents",LTI_HS_CONSOLIDATED!$C:$C,LTI_HS_CONSOLIDATED!E:E,0,0,1) | G49: =_xlfn.XLOOKUP("CashAndCashEquivalents",LTI_HS_CONSOLIDATED!$C:$C,LTI_HS_CONSOLIDATED!F:F,0,0,1) | H49: =_xlfn.XLOOKUP("CashAndCashEquivalents",LTI_HS_CONSOLIDATED!$C:$C,LTI_HS_CONSOLIDATED!G:G,0,0,1) | I49: =_xlfn.XLOOKUP("CashAndCashEquivalents",LTI_HS_CONSOLIDATED!$C:$C,LTI_HS_CONSOLIDATED!H:H,0,0,1) | J49: =_xlfn.XLOOKUP("CashAndCashEquivalents",LTI_HS_CONSOLIDATED!$C:$C,LTI_HS_CONSOLIDATED!I:I,0,0,1)
D50: Bank balance other than cash and cash equivalents | E50: =_xlfn.XLOOKUP("BankBalanceOtherThanCashAndCashEquivalents",LTI_HS_CONSOLIDATED!$C:$C,LTI_HS_CONSOLIDATED!D:D,0,0,1) | F50: =_xlfn.XLOOKUP("BankBalanceOtherThanCashAndCashEquivalents",LTI_HS_CONSOLIDATED!$C:$C,LTI_HS_CONSOLIDATED!E:E,0,0,1) | G50: =_xlfn.XLOOKUP("BankBalanceOtherThanCashAndCashEquivalents",LTI_HS_CONSOLIDATED!$C:$C,LTI_HS_CONSOLIDATED!F:F,0,0,1) | H50: =_xlfn.XLOOKUP("BankBalanceOtherThanCashAndCashEquivalents",LTI_HS_CONSOLIDATED!$C:$C,LTI_HS_CONSOLIDATED!G:G,0,0,1) | I50: =_xlfn.XLOOKUP("BankBalanceOtherThanCashAndCashEquivalents",LTI_HS_CONSOLIDATED!$C:$C,LTI_HS_CONSOLIDATED!H:H,0,0,1) | J50: =_xlfn.XLOOKUP("BankBalanceOtherThanCashAndCashEquivalents",LTI_HS_CONSOLIDATED!$C:$C,LTI_HS_CONSOLIDATED!I:I,0,0,1)
D51: Loans, current | E51: =_xlfn.XLOOKUP("LoansCurrent",LTI_HS_CONSOLIDATED!$C:$C,LTI_HS_CONSOLIDATED!D:D,0,0,1) | F51: =_xlfn.XLOOKUP("LoansCurrent",LTI_HS_CONSOLIDATED!$C:$C,LTI_HS_CONSOLIDATED!E:E,0,0,1) | G51: =_xlfn.XLOOKUP("LoansCurrent",LTI_HS_CONSOLIDATED!$C:$C,LTI_HS_CONSOLIDATED!F:F,0,0,1) | H51: =_xlfn.XLOOKUP("LoansCurrent",LTI_HS_CONSOLIDATED!$C:$C,LTI_HS_CONSOLIDATED!G:G,0,0,1) | I51: =_xlfn.XLOOKUP("LoansCurrent",LTI_HS_CONSOLIDATED!$C:$C,LTI_HS_CONSOLIDATED!H:H,0,0,1) | J51: =_xlfn.XLOOKUP("LoansCurrent",LTI_HS_CONSOLIDATED!$C:$C,LTI_HS_CONSOLIDATED!I:I,0,0,1)
D52: Total other current financial assets | E52: =_xlfn.XLOOKUP("OtherCurrentFinancialAssets",LTI_HS_CONSOLIDATED!$C:$C,LTI_HS_CONSOLIDATED!D:D,0,0,1) | F52: =_xlfn.XLOOKUP("OtherCurrentFinancialAssets",LTI_HS_CONSOLIDATED!$C:$C,LTI_HS_CONSOLIDATED!E:E,0,0,1) | G52: =_xlfn.XLOOKUP("OtherCurrentFinancialAssets",LTI_HS_CONSOLIDATED!$C:$C,LTI_HS_CONSOLIDATED!F:F,0,0,1) | H52: =_xlfn.XLOOKUP("OtherCurrentFinancialAssets",LTI_HS_CONSOLIDATED!$C:$C,LTI_HS_CONSOLIDATED!G:G,0,0,1) | I52: =_xlfn.XLOOKUP("OtherCurrentFinancialAssets",LTI_HS_CONSOLIDATED!$C:$C,LTI_HS_CONSOLIDATED!H:H,0,0,1) | J52: =_xlfn.XLOOKUP("OtherCurrentFinancialAssets",LTI_HS_CONSOLIDATED!$C:$C,LTI_HS_CONSOLIDATED!I:I,0,0,1)
D53: Current tax assets, Current | E53: =_xlfn.XLOOKUP("CurrentTaxAssetsCurrent",LTI_HS_CONSOLIDATED!$C:$C,LTI_HS_CONSOLIDATED!D:D,0,0,1) | F53: =_xlfn.XLOOKUP("CurrentTaxAssetsCurrent",LTI_HS_CONSOLIDATED!$C:$C,LTI_HS_CONSOLIDATED!E:E,0,0,1) | G53: =_xlfn.XLOOKUP("CurrentTaxAssetsCurrent",LTI_HS_CONSOLIDATED!$C:$C,LTI_HS_CONSOLIDATED!F:F,0,0,1) | H53: =_xlfn.XLOOKUP("CurrentTaxAssetsCurrent",LTI_HS_CONSOLIDATED!$C:$C,LTI_HS_CONSOLIDATED!G:G,0,0,1) | I53: =_xlfn.XLOOKUP("CurrentTaxAssetsCurrent",LTI_HS_CONSOLIDATED!$C:$C,LTI_HS_CONSOLIDATED!H:H,0,0,1) | J53: =_xlfn.XLOOKUP("CurrentTaxAssetsCurrent",LTI_HS_CONSOLIDATED!$C:$C,LTI_HS_CONSOLIDATED!I:I,0,0,1)
C54: Total Non-Operating | E54: =IFERROR(SUM(E48:E53),0) | F54: =IFERROR(SUM(F48:F53),0) | G54: =IFERROR(SUM(G48:G53),0) | H54: =IFERROR(SUM(H48:H53),0) | I54: =IFERROR(SUM(I48:I53),0) | J54: =IFERROR(SUM(J48:J53),0)
C55: Total current financial assets | E55: =_xlfn.XLOOKUP("CurrentFinancialAssets",LTI_HS_CONSOLIDATED!$C:$C,LTI_HS_CONSOLIDATED!D:D,0,0,1) | F55: =_xlfn.XLOOKUP("CurrentFinancialAssets",LTI_HS_CONSOLIDATED!$C:$C,LTI_HS_CONSOLIDATED!E:E,0,0,1) | G55: =_xlfn.XLOOKUP("CurrentFinancialAssets",LTI_HS_CONSOLIDATED!$C:$C,LTI_HS_CONSOLIDATED!F:F,0,0,1) | H55: =_xlfn.XLOOKUP("CurrentFinancialAssets",LTI_HS_CONSOLIDATED!$C:$C,LTI_HS_CONSOLIDATED!G:G,0,0,1) | I55: =_xlfn.XLOOKUP("CurrentFinancialAssets",LTI_HS_CONSOLIDATED!$C:$C,LTI_HS_CONSOLIDATED!H:H,0,0,1) | J55: =_xlfn.XLOOKUP("CurrentFinancialAssets",LTI_HS_CONSOLIDATED!$C:$C,LTI_HS_CONSOLIDATED!I:I,0,0,1)
B56: Total Current Assets | E56: =IFERROR(E54+E46,0) | F56: =IFERROR(F54+F46,0) | G56: =IFERROR(G54+G46,0) | H56: =IFERROR(H54+H46,0) | I56: =IFERROR(I54+I46,0) | J56: =IFERROR(J54+J46,0)
B57: Total Assets | E57: =IFERROR(SUM(E56:E56)+E41,0) | F57: =IFERROR(SUM(F56:F56)+F41,0) | G57: =IFERROR(SUM(G56:G56)+G41,0) | H57: =IFERROR(SUM(H56:H56)+H41,0) | I57: =IFERROR(SUM(I56:I56)+I41,0) | J57: =IFERROR(SUM(J56:J56)+J41,0)
B58: Equity and Liabilities
B59: Equity attributable to owners of parent
C60: Equity share capital at end of period | E60: =_xlfn.XLOOKUP("EquityShareCapital",LTI_HS_CONSOLIDATED!$C:$C,LTI_HS_CONSOLIDATED!D:D,0,0,1) | F60: =_xlfn.XLOOKUP("EquityShareCapital",LTI_HS_CONSOLIDATED!$C:$C,LTI_HS_CONSOLIDATED!E:E,0,0,1) | G60: =_xlfn.XLOOKUP("EquityShareCapital",LTI_HS_CONSOLIDATED!$C:$C,LTI_HS_CONSOLIDATED!F:F,0,0,1) | H60: =_xlfn.XLOOKUP("EquityShareCapital",LTI_HS_CONSOLIDATED!$C:$C,LTI_HS_CONSOLIDATED!G:G,0,0,1) | I60: =_xlfn.XLOOKUP("EquityShareCapital",LTI_HS_CONSOLIDATED!$C:$C,LTI_HS_CONSOLIDATED!H:H,0,0,1) | J60: =_xlfn.XLOOKUP("EquityShareCapital",LTI_HS_CONSOLIDATED!$C:$C,LTI_HS_CONSOLIDATED!I:I,0,0,1)
C61: Other equity | E61: =_xlfn.XLOOKUP("OtherEquity",LTI_HS_CONSOLIDATED!$C:$C,LTI_HS_CONSOLIDATED!D:D,0,0,1) | F61: =_xlfn.XLOOKUP("OtherEquity",LTI_HS_CONSOLIDATED!$C:$C,LTI_HS_CONSOLIDATED!E:E,0,0,1) | G61: =_xlfn.XLOOKUP("OtherEquity",LTI_HS_CONSOLIDATED!$C:$C,LTI_HS_CONSOLIDATED!F:F,0,0,1) | H61: =_xlfn.XLOOKUP("OtherEquity",LTI_HS_CONSOLIDATED!$C:$C,LTI_HS_CONSOLIDATED!G:G,0,0,1) | I61: =_xlfn.XLOOKUP("OtherEquity",LTI_HS_CONSOLIDATED!$C:$C,LTI_HS_CONSOLIDATED!H:H,0,0,1) | J61: =_xlfn.XLOOKUP("OtherEquity",LTI_HS_CONSOLIDATED!$C:$C,LTI_HS_CONSOLIDATED!I:I,0,0,1)
B62: Total equity attributable to owners of parent | E62: =IFERROR(SUM(E60:E61),0) | F62: =IFERROR(SUM(F60:F61),0) | G62: =IFERROR(SUM(G60:G61),0) | H62: =IFERROR(SUM(H60:H61),0) | I62: =IFERROR(SUM(I60:I61),0) | J62: =IFERROR(SUM(J60:J61),0)
C63: Non controlling interest | E63: =_xlfn.XLOOKUP("NonControllingInterest",LTI_HS_CONSOLIDATED!$C:$C,LTI_HS_CONSOLIDATED!D:D,0,0,1) | F63: =_xlfn.XLOOKUP("NonControllingInterest",LTI_HS_CONSOLIDATED!$C:$C,LTI_HS_CONSOLIDATED!E:E,0,0,1) | G63: =_xlfn.XLOOKUP("NonControllingInterest",LTI_HS_CONSOLIDATED!$C:$C,LTI_HS_CONSOLIDATED!F:F,0,0,1) | H63: =_xlfn.XLOOKUP("NonControllingInterest",LTI_HS_CONSOLIDATED!$C:$C,LTI_HS_CONSOLIDATED!G:G,0,0,1) | I63: =_xlfn.XLOOKUP("NonControllingInterest",LTI_HS_CONSOLIDATED!$C:$C,LTI_HS_CONSOLIDATED!H:H,0,0,1) | J63: =_xlfn.XLOOKUP("NonControllingInterest",LTI_HS_CONSOLIDATED!$C:$C,LTI_HS_CONSOLIDATED!I:I,0,0,1)
B64: Equity at end of period | E64: =IFERROR(SUM(E62:E63),0) | F64: =IFERROR(SUM(F62:F63),0) | G64: =IFERROR(SUM(G62:G63),0) | H64: =IFERROR(SUM(H62:H63),0) | I64: =IFERROR(SUM(I62:I63),0) | J64: =IFERROR(SUM(J62:J63),0)
B65: Liabilities
B66: Non-current liabilities
B67: Non-current financial liabilities
C68: Trade payables, non-current
C69: Total other non-current financial liabilities | E69: =_xlfn.XLOOKUP("OtherNoncurrentFinancialLiabilities",LTI_HS_CONSOLIDATED!$C:$C,LTI_HS_CONSOLIDATED!D:D,0,0,1) | F69: =_xlfn.XLOOKUP("OtherNoncurrentFinancialLiabilities",LTI_HS_CONSOLIDATED!$C:$C,LTI_HS_CONSOLIDATED!E:E,0,0,1) | G69: =_xlfn.XLOOKUP("OtherNoncurrentFinancialLiabilities",LTI_HS_CONSOLIDATED!$C:$C,LTI_HS_CONSOLIDATED!F:F,0,0,1) | H69: =_xlfn.XLOOKUP("OtherNoncurrentFinancialLiabilities",LTI_HS_CONSOLIDATED!$C:$C,LTI_HS_CONSOLIDATED!G:G,0,0,1) | I69: =_xlfn.XLOOKUP("OtherNoncurrentFinancialLiabilities",LTI_HS_CONSOLIDATED!$C:$C,LTI_HS_CONSOLIDATED!H:H,0,0,1) | J69: =_xlfn.XLOOKUP("OtherNoncurrentFinancialLiabilities",LTI_HS_CONSOLIDATED!$C:$C,LTI_HS_CONSOLIDATED!I:I,0,0,1)
C70: Total non-current financial liabilities | E70: =_xlfn.XLOOKUP("NoncurrentFinancialLiabilities",LTI_HS_CONSOLIDATED!$C:$C,LTI_HS_CONSOLIDATED!D:D,0,0,1) | F70: =_xlfn.XLOOKUP("NoncurrentFinancialLiabilities",LTI_HS_CONSOLIDATED!$C:$C,LTI_HS_CONSOLIDATED!E:E,0,0,1) | G70: =_xlfn.XLOOKUP("NoncurrentFinancialLiabilities",LTI_HS_CONSOLIDATED!$C:$C,LTI_HS_CONSOLIDATED!F:F,0,0,1) | H70: =_xlfn.XLOOKUP("NoncurrentFinancialLiabilities",LTI_HS_CONSOLIDATED!$C:$C,LTI_HS_CONSOLIDATED!G:G,0,0,1) | I70: =_xlfn.XLOOKUP("NoncurrentFinancialLiabilities",LTI_HS_CONSOLIDATED!$C:$C,LTI_HS_CONSOLIDATED!H:H,0,0,1) | J70: =_xlfn.XLOOKUP("NoncurrentFinancialLiabilities",LTI_HS_CONSOLIDATED!$C:$C,LTI_HS_CONSOLIDATED!I:I,0,0,1)
D71: Provisions, non-current | E71: =_xlfn.XLOOKUP("ProvisionsNoncurrent",LTI_HS_CONSOLIDATED!$C:$C,LTI_HS_CONSOLIDATED!D:D,0,0,1) | F71: =_xlfn.XLOOKUP("ProvisionsNoncurrent",LTI_HS_CONSOLIDATED!$C:$C,LTI_HS_CONSOLIDATED!E:E,0,0,1) | G71: =_xlfn.XLOOKUP("ProvisionsNoncurrent",LTI_HS_CONSOLIDATED!$C:$C,LTI_HS_CONSOLIDATED!F:F,0,0,1) | H71: =_xlfn.XLOOKUP("ProvisionsNoncurrent",LTI_HS_CONSOLIDATED!$C:$C,LTI_HS_CONSOLIDATED!G:G,0,0,1) | I71: =_xlfn.XLOOKUP("ProvisionsNoncurrent",LTI_HS_CONSOLIDATED!$C:$C,LTI_HS_CONSOLIDATED!H:H,0,0,1) | J71: =_xlfn.XLOOKUP("ProvisionsNoncurrent",LTI_HS_CONSOLIDATED!$C:$C,LTI_HS_CONSOLIDATED!I:I,0,0,1)
D72: Deferred tax liabilities (net) | E72: =_xlfn.XLOOKUP("DeferredTaxLiabilitiesNet",LTI_HS_CONSOLIDATED!$C:$C,LTI_HS_CONSOLIDATED!D:D,0,0,1) | F72: =_xlfn.XLOOKUP("DeferredTaxLiabilitiesNet",LTI_HS_CONSOLIDATED!$C:$C,LTI_HS_CONSOLIDATED!E:E,0,0,1) | G72: =_xlfn.XLOOKUP("DeferredTaxLiabilitiesNet",LTI_HS_CONSOLIDATED!$C:$C,LTI_HS_CONSOLIDATED!F:F,0,0,1) | H72: =_xlfn.XLOOKUP("DeferredTaxLiabilitiesNet",LTI_HS_CONSOLIDATED!$C:$C,LTI_HS_CONSOLIDATED!G:G,0,0,1) | I72: =_xlfn.XLOOKUP("DeferredTaxLiabilitiesNet",LTI_HS_CONSOLIDATED!$C:$C,LTI_HS_CONSOLIDATED!H:H,0,0,1) | J72: =_xlfn.XLOOKUP("DeferredTaxLiabilitiesNet",LTI_HS_CONSOLIDATED!$C:$C,LTI_HS_CONSOLIDATED!I:I,0,0,1)
D73: Total other non-current liabilities | E73: =_xlfn.XLOOKUP("OtherNoncurrentLiabilities",LTI_HS_CONSOLIDATED!$C:$C,LTI_HS_CONSOLIDATED!D:D,0,0,1) | F73: =_xlfn.XLOOKUP("OtherNoncurrentLiabilities",LTI_HS_CONSOLIDATED!$C:$C,LTI_HS_CONSOLIDATED!E:E,0,0,1) | G73: =_xlfn.XLOOKUP("OtherNoncurrentLiabilities",LTI_HS_CONSOLIDATED!$C:$C,LTI_HS_CONSOLIDATED!F:F,0,0,1) | H73: =_xlfn.XLOOKUP("OtherNoncurrentLiabilities",LTI_HS_CONSOLIDATED!$C:$C,LTI_HS_CONSOLIDATED!G:G,0,0,1) | I73: =_xlfn.XLOOKUP("OtherNoncurrentLiabilities",LTI_HS_CONSOLIDATED!$C:$C,LTI_HS_CONSOLIDATED!H:H,0,0,1) | J73: =_xlfn.XLOOKUP("OtherNoncurrentLiabilities",LTI_HS_CONSOLIDATED!$C:$C,LTI_HS_CONSOLIDATED!I:I,0,0,1)
B74: Total non-current liabilities | E74: =IFERROR(SUM(E69:E69)+SUM(E71:E73),0) | F74: =IFERROR(SUM(F69:F69)+SUM(F71:F73),0) | G74: =IFERROR(SUM(G69:G69)+SUM(G71:G73),0) | H74: =IFERROR(SUM(H69:H69)+SUM(H71:H73),0) | I74: =IFERROR(SUM(I69:I69)+SUM(I71:I73),0) | J74: =IFERROR(SUM(J69:J69)+SUM(J71:J73),0)
B75: Current liabilities
B76: Current financial liabilities
C77: Borrowings, current | E77: =_xlfn.XLOOKUP("BorrowingsCurrent",LTI_HS_CONSOLIDATED!$C:$C,LTI_HS_CONSOLIDATED!D:D,0,0,1) | F77: =_xlfn.XLOOKUP("BorrowingsCurrent",LTI_HS_CONSOLIDATED!$C:$C,LTI_HS_CONSOLIDATED!E:E,0,0,1) | G77: =_xlfn.XLOOKUP("BorrowingsCurrent",LTI_HS_CONSOLIDATED!$C:$C,LTI_HS_CONSOLIDATED!F:F,0,0,1) | H77: =_xlfn.XLOOKUP("BorrowingsCurrent",LTI_HS_CONSOLIDATED!$C:$C,LTI_HS_CONSOLIDATED!G:G,0,0,1) | I77: =_xlfn.XLOOKUP("BorrowingsCurrent",LTI_HS_CONSOLIDATED!$C:$C,LTI_HS_CONSOLIDATED!H:H,0,0,1) | J77: =_xlfn.XLOOKUP("BorrowingsCurrent",LTI_HS_CONSOLIDATED!$C:$C,LTI_HS_CONSOLIDATED!I:I,0,0,1)
C78: Trade payables, current
D79: Total trade payables, current | E79: =_xlfn.XLOOKUP("TradePayablesCurrent",LTI_HS_CONSOLIDATED!$C:$C,LTI_HS_CONSOLIDATED!D:D,0,0,1) | F79: =_xlfn.XLOOKUP("TradePayablesCurrent",LTI_HS_CONSOLIDATED!$C:$C,LTI_HS_CONSOLIDATED!E:E,0,0,1) | G79: =_xlfn.XLOOKUP("TradePayablesCurrent",LTI_HS_CONSOLIDATED!$C:$C,LTI_HS_CONSOLIDATED!F:F,0,0,1) | H79: =_xlfn.XLOOKUP("TradePayablesCurrent",LTI_HS_CONSOLIDATED!$C:$C,LTI_HS_CONSOLIDATED!G:G,0,0,1) | I79: =_xlfn.XLOOKUP("TradePayablesCurrent",LTI_HS_CONSOLIDATED!$C:$C,LTI_HS_CONSOLIDATED!H:H,0,0,1) | J79: =_xlfn.XLOOKUP("TradePayablesCurrent",LTI_HS_CONSOLIDATED!$C:$C,LTI_HS_CONSOLIDATED!I:I,0,0,1)
C80: Total other current financial liabilities | E80: =_xlfn.XLOOKUP("OtherCurrentFinancialLiabilities",LTI_HS_CONSOLIDATED!$C:$C,LTI_HS_CONSOLIDATED!D:D,0,0,1) | F80: =_xlfn.XLOOKUP("OtherCurrentFinancialLiabilities",LTI_HS_CONSOLIDATED!$C:$C,LTI_HS_CONSOLIDATED!E:E,0,0,1) | G80: =_xlfn.XLOOKUP("OtherCurrentFinancialLiabilities",LTI_HS_CONSOLIDATED!$C:$C,LTI_HS_CONSOLIDATED!F:F,0,0,1) | H80: =_xlfn.XLOOKUP("OtherCurrentFinancialLiabilities",LTI_HS_CONSOLIDATED!$C:$C,LTI_HS_CONSOLIDATED!G:G,0,0,1) | I80: =_xlfn.XLOOKUP("OtherCurrentFinancialLiabilities",LTI_HS_CONSOLIDATED!$C:$C,LTI_HS_CONSOLIDATED!H:H,0,0,1) | J80: =_xlfn.XLOOKUP("OtherCurrentFinancialLiabilities",LTI_HS_CONSOLIDATED!$C:$C,LTI_HS_CONSOLIDATED!I:I,0,0,1)
B81: Total current financial liabilities | E81: =_xlfn.XLOOKUP("CurrentFinancialLiabilities",LTI_HS_CONSOLIDATED!$C:$C,LTI_HS_CONSOLIDATED!D:D,0,0,1) | F81: =_xlfn.XLOOKUP("CurrentFinancialLiabilities",LTI_HS_CONSOLIDATED!$C:$C,LTI_HS_CONSOLIDATED!E:E,0,0,1) | G81: =_xlfn.XLOOKUP("CurrentFinancialLiabilities",LTI_HS_CONSOLIDATED!$C:$C,LTI_HS_CONSOLIDATED!F:F,0,0,1) | H81: =_xlfn.XLOOKUP("CurrentFinancialLiabilities",LTI_HS_CONSOLIDATED!$C:$C,LTI_HS_CONSOLIDATED!G:G,0,0,1) | I81: =_xlfn.XLOOKUP("CurrentFinancialLiabilities",LTI_HS_CONSOLIDATED!$C:$C,LTI_HS_CONSOLIDATED!H:H,0,0,1) | J81: =_xlfn.XLOOKUP("CurrentFinancialLiabilities",LTI_HS_CONSOLIDATED!$C:$C,LTI_HS_CONSOLIDATED!I:I,0,0,1)
C82: Total other current liabilities | E82: =_xlfn.XLOOKUP("OtherCurrentLiabilities",LTI_HS_CONSOLIDATED!$C:$C,LTI_HS_CONSOLIDATED!D:D,0,0,1) | F82: =_xlfn.XLOOKUP("OtherCurrentLiabilities",LTI_HS_CONSOLIDATED!$C:$C,LTI_HS_CONSOLIDATED!E:E,0,0,1) | G82: =_xlfn.XLOOKUP("OtherCurrentLiabilities",LTI_HS_CONSOLIDATED!$C:$C,LTI_HS_CONSOLIDATED!F:F,0,0,1) | H82: =_xlfn.XLOOKUP("OtherCurrentLiabilities",LTI_HS_CONSOLIDATED!$C:$C,LTI_HS_CONSOLIDATED!G:G,0,0,1) | I82: =_xlfn.XLOOKUP("OtherCurrentLiabilities",LTI_HS_CONSOLIDATED!$C:$C,LTI_HS_CONSOLIDATED!H:H,0,0,1) | J82: =_xlfn.XLOOKUP("OtherCurrentLiabilities",LTI_HS_CONSOLIDATED!$C:$C,LTI_HS_CONSOLIDATED!I:I,0,0,1)
C83: Provisions, current | E83: =_xlfn.XLOOKUP("ProvisionsCurrent",LTI_HS_CONSOLIDATED!$C:$C,LTI_HS_CONSOLIDATED!D:D,0,0,1) | F83: =_xlfn.XLOOKUP("ProvisionsCurrent",LTI_HS_CONSOLIDATED!$C:$C,LTI_HS_CONSOLIDATED!E:E,0,0,1) | G83: =_xlfn.XLOOKUP("ProvisionsCurrent",LTI_HS_CONSOLIDATED!$C:$C,LTI_HS_CONSOLIDATED!F:F,0,0,1) | H83: =_xlfn.XLOOKUP("ProvisionsCurrent",LTI_HS_CONSOLIDATED!$C:$C,LTI_HS_CONSOLIDATED!G:G,0,0,1) | I83: =_xlfn.XLOOKUP("ProvisionsCurrent",LTI_HS_CONSOLIDATED!$C:$C,LTI_HS_CONSOLIDATED!H:H,0,0,1) | J83: =_xlfn.XLOOKUP("ProvisionsCurrent",LTI_HS_CONSOLIDATED!$C:$C,LTI_HS_CONSOLIDATED!I:I,0,0,1)
C84: Current tax liabilities | E84: =_xlfn.XLOOKUP("CurrentTaxLiabilities",LTI_HS_CONSOLIDATED!$C:$C,LTI_HS_CONSOLIDATED!D:D,0,0,1) | F84: =_xlfn.XLOOKUP("CurrentTaxLiabilities",LTI_HS_CONSOLIDATED!$C:$C,LTI_HS_CONSOLIDATED!E:E,0,0,1) | G84: =_xlfn.XLOOKUP("CurrentTaxLiabilities",LTI_HS_CONSOLIDATED!$C:$C,LTI_HS_CONSOLIDATED!F:F,0,0,1) | H84: =_xlfn.XLOOKUP("CurrentTaxLiabilities",LTI_HS_CONSOLIDATED!$C:$C,LTI_HS_CONSOLIDATED!G:G,0,0,1) | I84: =_xlfn.XLOOKUP("CurrentTaxLiabilities",LTI_HS_CONSOLIDATED!$C:$C,LTI_HS_CONSOLIDATED!H:H,0,0,1) | J84: =_xlfn.XLOOKUP("CurrentTaxLiabilities",LTI_HS_CONSOLIDATED!$C:$C,LTI_HS_CONSOLIDATED!I:I,0,0,1)
B85: Total current liabilities | E85: =IFERROR(SUM(E77:E77)+SUM(E79:E80)+SUM(E82:E84),0) | F85: =IFERROR(SUM(F77:F77)+SUM(F79:F80)+SUM(F82:F84),0) | G85: =IFERROR(SUM(G77:G77)+SUM(G79:G80)+SUM(G82:G84),0) | H85: =IFERROR(SUM(H77:H77)+SUM(H79:H80)+SUM(H82:H84),0) | I85: =IFERROR(SUM(I77:I77)+SUM(I79:I80)+SUM(I82:I84),0) | J85: =IFERROR(SUM(J77:J77)+SUM(J79:J80)+SUM(J82:J84),0)
B86: Liabilities | E86: =IFERROR(SUM(E85:E85)+E74,0) | F86: =IFERROR(SUM(F85:F85)+F74,0) | G86: =IFERROR(SUM(G85:G85)+G74,0) | H86: =IFERROR(SUM(H85:H85)+H74,0) | I86: =IFERROR(SUM(I85:I85)+I74,0) | J86: =IFERROR(SUM(J85:J85)+J74,0)
B87: Total equity and liabilities | E87: =IFERROR(E64+E86,0) | F87: =IFERROR(F64+F86,0) | G87: =IFERROR(G64+G86,0) | H87: =IFERROR(H64+H86,0) | I87: =IFERROR(I64+I86,0) | J87: =IFERROR(J64+J86,0)
B88: BALANCE CHECK (Total Assets − Total Equity & Liabilities) | E88: =E57-E87 | F88: =F57-F87 | G88: =G57-G87 | H88: =H57-H87 | I88: =I57-I87 | J88: =J57-J87
A89: # | B89: Statement of Cash Flows
B90: Cash flows from used in operating activities
C91: Total profit before tax | E91: =_xlfn.XLOOKUP("ProfitBeforeTax",LTI_HS_CONSOLIDATED!$C:$C,LTI_HS_CONSOLIDATED!D:D,0,0,1) | F91: =_xlfn.XLOOKUP("ProfitBeforeTax",LTI_HS_CONSOLIDATED!$C:$C,LTI_HS_CONSOLIDATED!E:E,0,0,1) | G91: =_xlfn.XLOOKUP("ProfitBeforeTax",LTI_HS_CONSOLIDATED!$C:$C,LTI_HS_CONSOLIDATED!F:F,0,0,1) | H91: =_xlfn.XLOOKUP("ProfitBeforeTax",LTI_HS_CONSOLIDATED!$C:$C,LTI_HS_CONSOLIDATED!G:G,0,0,1) | I91: =_xlfn.XLOOKUP("ProfitBeforeTax",LTI_HS_CONSOLIDATED!$C:$C,LTI_HS_CONSOLIDATED!H:H,0,0,1) | J91: =_xlfn.XLOOKUP("ProfitBeforeTax",LTI_HS_CONSOLIDATED!$C:$C,LTI_HS_CONSOLIDATED!I:I,0,0,1)
C92: Adjustments for reconcile profit (loss)
D93: Adjustments for finance costs | E93: =_xlfn.XLOOKUP("AdjustmentsForFinanceCosts",LTI_HS_CONSOLIDATED!$C:$C,LTI_HS_CONSOLIDATED!D:D,0,0,1) | F93: =_xlfn.XLOOKUP("AdjustmentsForFinanceCosts",LTI_HS_CONSOLIDATED!$C:$C,LTI_HS_CONSOLIDATED!E:E,0,0,1) | G93: =_xlfn.XLOOKUP("AdjustmentsForFinanceCosts",LTI_HS_CONSOLIDATED!$C:$C,LTI_HS_CONSOLIDATED!F:F,0,0,1) | H93: =_xlfn.XLOOKUP("AdjustmentsForFinanceCosts",LTI_HS_CONSOLIDATED!$C:$C,LTI_HS_CONSOLIDATED!G:G,0,0,1) | I93: =_xlfn.XLOOKUP("AdjustmentsForFinanceCosts",LTI_HS_CONSOLIDATED!$C:$C,LTI_HS_CONSOLIDATED!H:H,0,0,1) | J93: =_xlfn.XLOOKUP("AdjustmentsForFinanceCosts",LTI_HS_CONSOLIDATED!$C:$C,LTI_HS_CONSOLIDATED!I:I,0,0,1)
D94: Adjustments for decrease (increase) in trade receivables, current | E94: =_xlfn.XLOOKUP("AdjustmentsForDecreaseIncreaseInTradeReceivablesCurrent",LTI_HS_CONSOLIDATED!$C:$C,LTI_HS_CONSOLIDATED!D:D,0,0,1) | F94: =_xlfn.XLOOKUP("AdjustmentsForDecreaseIncreaseInTradeReceivablesCurrent",LTI_HS_CONSOLIDATED!$C:$C,LTI_HS_CONSOLIDATED!E:E,0,0,1) | G94: =_xlfn.XLOOKUP("AdjustmentsForDecreaseIncreaseInTradeReceivablesCurrent",LTI_HS_CONSOLIDATED!$C:$C,LTI_HS_CONSOLIDATED!F:F,0,0,1) | H94: =_xlfn.XLOOKUP("AdjustmentsForDecreaseIncreaseInTradeReceivablesCurrent",LTI_HS_CONSOLIDATED!$C:$C,LTI_HS_CONSOLIDATED!G:G,0,0,1) | I94: =_xlfn.XLOOKUP("AdjustmentsForDecreaseIncreaseInTradeReceivablesCurrent",LTI_HS_CONSOLIDATED!$C:$C,LTI_HS_CONSOLIDATED!H:H,0,0,1) | J94: =_xlfn.XLOOKUP("AdjustmentsForDecreaseIncreaseInTradeReceivablesCurrent",LTI_HS_CONSOLIDATED!$C:$C,LTI_HS_CONSOLIDATED!I:I,0,0,1)
D95: Adjustments for decrease (increase) in other current assets | E95: =_xlfn.XLOOKUP("AdjustmentsForDecreaseIncreaseInOtherCurrentAssets",LTI_HS_CONSOLIDATED!$C:$C,LTI_HS_CONSOLIDATED!D:D,0,0,1) | F95: =_xlfn.XLOOKUP("AdjustmentsForDecreaseIncreaseInOtherCurrentAssets",LTI_HS_CONSOLIDATED!$C:$C,LTI_HS_CONSOLIDATED!E:E,0,0,1) | G95: =_xlfn.XLOOKUP("AdjustmentsForDecreaseIncreaseInOtherCurrentAssets",LTI_HS_CONSOLIDATED!$C:$C,LTI_HS_CONSOLIDATED!F:F,0,0,1) | H95: =_xlfn.XLOOKUP("AdjustmentsForDecreaseIncreaseInOtherCurrentAssets",LTI_HS_CONSOLIDATED!$C:$C,LTI_HS_CONSOLIDATED!G:G,0,0,1) | I95: =_xlfn.XLOOKUP("AdjustmentsForDecreaseIncreaseInOtherCurrentAssets",LTI_HS_CONSOLIDATED!$C:$C,LTI_HS_CONSOLIDATED!H:H,0,0,1) | J95: =_xlfn.XLOOKUP("AdjustmentsForDecreaseIncreaseInOtherCurrentAssets",LTI_HS_CONSOLIDATED!$C:$C,LTI_HS_CONSOLIDATED!I:I,0,0,1)
D96: Adjustments for decrease (increase) in other non-current assets | E96: =_xlfn.XLOOKUP("AdjustmentsForDecreaseIncreaseInOtherNoncurrentAssets",LTI_HS_CONSOLIDATED!$C:$C,LTI_HS_CONSOLIDATED!D:D,0,0,1) | F96: =_xlfn.XLOOKUP("AdjustmentsForDecreaseIncreaseInOtherNoncurrentAssets",LTI_HS_CONSOLIDATED!$C:$C,LTI_HS_CONSOLIDATED!E:E,0,0,1) | G96: =_xlfn.XLOOKUP("AdjustmentsForDecreaseIncreaseInOtherNoncurrentAssets",LTI_HS_CONSOLIDATED!$C:$C,LTI_HS_CONSOLIDATED!F:F,0,0,1) | H96: =_xlfn.XLOOKUP("AdjustmentsForDecreaseIncreaseInOtherNoncurrentAssets",LTI_HS_CONSOLIDATED!$C:$C,LTI_HS_CONSOLIDATED!G:G,0,0,1) | I96: =_xlfn.XLOOKUP("AdjustmentsForDecreaseIncreaseInOtherNoncurrentAssets",LTI_HS_CONSOLIDATED!$C:$C,LTI_HS_CONSOLIDATED!H:H,0,0,1) | J96: =_xlfn.XLOOKUP("AdjustmentsForDecreaseIncreaseInOtherNoncurrentAssets",LTI_HS_CONSOLIDATED!$C:$C,LTI_HS_CONSOLIDATED!I:I,0,0,1)
D97: Adjustments for increase (decrease) in trade payables, current | E97: =_xlfn.XLOOKUP("AdjustmentsForIncreaseDecreaseInTradePayablesCurrent",LTI_HS_CONSOLIDATED!$C:$C,LTI_HS_CONSOLIDATED!D:D,0,0,1) | F97: =_xlfn.XLOOKUP("AdjustmentsForIncreaseDecreaseInTradePayablesCurrent",LTI_HS_CONSOLIDATED!$C:$C,LTI_HS_CONSOLIDATED!E:E,0,0,1) | G97: =_xlfn.XLOOKUP("AdjustmentsForIncreaseDecreaseInTradePayablesCurrent",LTI_HS_CONSOLIDATED!$C:$C,LTI_HS_CONSOLIDATED!F:F,0,0,1) | H97: =_xlfn.XLOOKUP("AdjustmentsForIncreaseDecreaseInTradePayablesCurrent",LTI_HS_CONSOLIDATED!$C:$C,LTI_HS_CONSOLIDATED!G:G,0,0,1) | I97: =_xlfn.XLOOKUP("AdjustmentsForIncreaseDecreaseInTradePayablesCurrent",LTI_HS_CONSOLIDATED!$C:$C,LTI_HS_CONSOLIDATED!H:H,0,0,1) | J97: =_xlfn.XLOOKUP("AdjustmentsForIncreaseDecreaseInTradePayablesCurrent",LTI_HS_CONSOLIDATED!$C:$C,LTI_HS_CONSOLIDATED!I:I,0,0,1)
D98: Adjustments for depreciation and amortisation expense | E98: =_xlfn.XLOOKUP("AdjustmentsForDepreciationAndAmortisationExpense",LTI_HS_CONSOLIDATED!$C:$C,LTI_HS_CONSOLIDATED!D:D,0,0,1) | F98: =_xlfn.XLOOKUP("AdjustmentsForDepreciationAndAmortisationExpense",LTI_HS_CONSOLIDATED!$C:$C,LTI_HS_CONSOLIDATED!E:E,0,0,1) | G98: =_xlfn.XLOOKUP("AdjustmentsForDepreciationAndAmortisationExpense",LTI_HS_CONSOLIDATED!$C:$C,LTI_HS_CONSOLIDATED!F:F,0,0,1) | H98: =_xlfn.XLOOKUP("AdjustmentsForDepreciationAndAmortisationExpense",LTI_HS_CONSOLIDATED!$C:$C,LTI_HS_CONSOLIDATED!G:G,0,0,1) | I98: =_xlfn.XLOOKUP("AdjustmentsForDepreciationAndAmortisationExpense",LTI_HS_CONSOLIDATED!$C:$C,LTI_HS_CONSOLIDATED!H:H,0,0,1) | J98: =_xlfn.XLOOKUP("AdjustmentsForDepreciationAndAmortisationExpense",LTI_HS_CONSOLIDATED!$C:$C,LTI_HS_CONSOLIDATED!I:I,0,0,1)
D99: Adjustments for unrealised foreign exchange losses gains | E99: =_xlfn.XLOOKUP("AdjustmentsForUnrealisedForeignExchangeLossesGains",LTI_HS_CONSOLIDATED!$C:$C,LTI_HS_CONSOLIDATED!D:D,0,0,1) | F99: =_xlfn.XLOOKUP("AdjustmentsForUnrealisedForeignExchangeLossesGains",LTI_HS_CONSOLIDATED!$C:$C,LTI_HS_CONSOLIDATED!E:E,0,0,1) | G99: =_xlfn.XLOOKUP("AdjustmentsForUnrealisedForeignExchangeLossesGains",LTI_HS_CONSOLIDATED!$C:$C,LTI_HS_CONSOLIDATED!F:F,0,0,1) | H99: =_xlfn.XLOOKUP("AdjustmentsForUnrealisedForeignExchangeLossesGains",LTI_HS_CONSOLIDATED!$C:$C,LTI_HS_CONSOLIDATED!G:G,0,0,1) | I99: =_xlfn.XLOOKUP("AdjustmentsForUnrealisedForeignExchangeLossesGains",LTI_HS_CONSOLIDATED!$C:$C,LTI_HS_CONSOLIDATED!H:H,0,0,1) | J99: =_xlfn.XLOOKUP("AdjustmentsForUnrealisedForeignExchangeLossesGains",LTI_HS_CONSOLIDATED!$C:$C,LTI_HS_CONSOLIDATED!I:I,0,0,1)
D100: Adjustments for interest income | E100: =_xlfn.XLOOKUP("AdjustmentsForInterestIncome",LTI_HS_CONSOLIDATED!$C:$C,LTI_HS_CONSOLIDATED!D:D,0,0,1) | F100: =_xlfn.XLOOKUP("AdjustmentsForInterestIncome",LTI_HS_CONSOLIDATED!$C:$C,LTI_HS_CONSOLIDATED!E:E,0,0,1) | G100: =_xlfn.XLOOKUP("AdjustmentsForInterestIncome",LTI_HS_CONSOLIDATED!$C:$C,LTI_HS_CONSOLIDATED!F:F,0,0,1) | H100: =_xlfn.XLOOKUP("AdjustmentsForInterestIncome",LTI_HS_CONSOLIDATED!$C:$C,LTI_HS_CONSOLIDATED!G:G,0,0,1) | I100: =_xlfn.XLOOKUP("AdjustmentsForInterestIncome",LTI_HS_CONSOLIDATED!$C:$C,LTI_HS_CONSOLIDATED!H:H,0,0,1) | J100: =_xlfn.XLOOKUP("AdjustmentsForInterestIncome",LTI_HS_CONSOLIDATED!$C:$C,LTI_HS_CONSOLIDATED!I:I,0,0,1)
D101: Adjustments for share-based payments | E101: =_xlfn.XLOOKUP("AdjustmentsForSharebasedPayments",LTI_HS_CONSOLIDATED!$C:$C,LTI_HS_CONSOLIDATED!D:D,0,0,1) | F101: =_xlfn.XLOOKUP("AdjustmentsForSharebasedPayments",LTI_HS_CONSOLIDATED!$C:$C,LTI_HS_CONSOLIDATED!E:E,0,0,1) | G101: =_xlfn.XLOOKUP("AdjustmentsForSharebasedPayments",LTI_HS_CONSOLIDATED!$C:$C,LTI_HS_CONSOLIDATED!F:F,0,0,1) | H101: =_xlfn.XLOOKUP("AdjustmentsForSharebasedPayments",LTI_HS_CONSOLIDATED!$C:$C,LTI_HS_CONSOLIDATED!G:G,0,0,1) | I101: =_xlfn.XLOOKUP("AdjustmentsForSharebasedPayments",LTI_HS_CONSOLIDATED!$C:$C,LTI_HS_CONSOLIDATED!H:H,0,0,1) | J101: =_xlfn.XLOOKUP("AdjustmentsForSharebasedPayments",LTI_HS_CONSOLIDATED!$C:$C,LTI_HS_CONSOLIDATED!I:I,0,0,1)
D102: Other adjustments for which cash effects are investing or financing cash flow | E102: =_xlfn.XLOOKUP("OtherAdjustmentsForWhichCashEffectsAreInvestingOrFinancingCashFlow",LTI_HS_CONSOLIDATED!$C:$C,LTI_HS_CONSOLIDATED!D:D,0,0,1) | F102: =_xlfn.XLOOKUP("OtherAdjustmentsForWhichCashEffectsAreInvestingOrFinancingCashFlow",LTI_HS_CONSOLIDATED!$C:$C,LTI_HS_CONSOLIDATED!E:E,0,0,1) | G102: =_xlfn.XLOOKUP("OtherAdjustmentsForWhichCashEffectsAreInvestingOrFinancingCashFlow",LTI_HS_CONSOLIDATED!$C:$C,LTI_HS_CONSOLIDATED!F:F,0,0,1) | H102: =_xlfn.XLOOKUP("OtherAdjustmentsForWhichCashEffectsAreInvestingOrFinancingCashFlow",LTI_HS_CONSOLIDATED!$C:$C,LTI_HS_CONSOLIDATED!G:G,0,0,1) | I102: =_xlfn.XLOOKUP("OtherAdjustmentsForWhichCashEffectsAreInvestingOrFinancingCashFlow",LTI_HS_CONSOLIDATED!$C:$C,LTI_HS_CONSOLIDATED!H:H,0,0,1) | J102: =_xlfn.XLOOKUP("OtherAdjustmentsForWhichCashEffectsAreInvestingOrFinancingCashFlow",LTI_HS_CONSOLIDATED!$C:$C,LTI_HS_CONSOLIDATED!I:I,0,0,1)
...

Sheet LTI_HIST_STAND
A1: LTIMindtree — Derived Financial Model
A2: Green = cross-sheet formula (XLOOKUP against raw data) | Black = same-sheet formula (subtotal/total)
A5: # | B5: Statement of Profit and Loss | E5: FY2017 | F5: FY2018 | G5: FY2019 | H5: FY2020 | I5: FY2021 | J5: FY2022
B6: Income [Abstract]
C7: Total revenue from operations | E7: =_xlfn.XLOOKUP("RevenueFromOperations",LTI_HS_STANDALONE!$C:$C,LTI_HS_STANDALONE!D:D,0,0,1) | F7: =_xlfn.XLOOKUP("RevenueFromOperations",LTI_HS_STANDALONE!$C:$C,LTI_HS_STANDALONE!E:E,0,0,1) | G7: =_xlfn.XLOOKUP("RevenueFromOperations",LTI_HS_STANDALONE!$C:$C,LTI_HS_STANDALONE!F:F,0,0,1) | H7: =_xlfn.XLOOKUP("RevenueFromOperations",LTI_HS_STANDALONE!$C:$C,LTI_HS_STANDALONE!G:G,0,0,1) | I7: =_xlfn.XLOOKUP("RevenueFromOperations",LTI_HS_STANDALONE!$C:$C,LTI_HS_STANDALONE!H:H,0,0,1) | J7: =_xlfn.XLOOKUP("RevenueFromOperations",LTI_HS_STANDALONE!$C:$C,LTI_HS_STANDALONE!I:I,0,0,1)
C8: Total other income | E8: =_xlfn.XLOOKUP("OtherIncome",LTI_HS_STANDALONE!$C:$C,LTI_HS_STANDALONE!D:D,0,0,1) | F8: =_xlfn.XLOOKUP("OtherIncome",LTI_HS_STANDALONE!$C:$C,LTI_HS_STANDALONE!E:E,0,0,1) | G8: =_xlfn.XLOOKUP("OtherIncome",LTI_HS_STANDALONE!$C:$C,LTI_HS_STANDALONE!F:F,0,0,1) | H8: =_xlfn.XLOOKUP("OtherIncome",LTI_HS_STANDALONE!$C:$C,LTI_HS_STANDALONE!G:G,0,0,1) | I8: =_xlfn.XLOOKUP("OtherIncome",LTI_HS_STANDALONE!$C:$C,LTI_HS_STANDALONE!H:H,0,0,1) | J8: =_xlfn.XLOOKUP("OtherIncome",LTI_HS_STANDALONE!$C:$C,LTI_HS_STANDALONE!I:I,0,0,1)
C9: Total income | E9: =IFERROR(SUM(E7:E8),0) | F9: =IFERROR(SUM(F7:F8),0) | G9: =IFERROR(SUM(G7:G8),0) | H9: =IFERROR(SUM(H7:H8),0) | I9: =IFERROR(SUM(I7:I8),0) | J9: =IFERROR(SUM(J7:J8),0)
B10: COGS
B11: Gross Profit | E11: =IFERROR(E9,0) | F11: =IFERROR(F9,0) | G11: =IFERROR(G9,0) | H11: =IFERROR(H9,0) | I11: =IFERROR(I9,0) | J11: =IFERROR(J9,0)
C12: SG&A | E12: =-_xlfn.XLOOKUP("EmployeeBenefitExpense",LTI_HS_STANDALONE!$C:$C,LTI_HS_STANDALONE!D:D,0,0,1)-_xlfn.XLOOKUP("ExpenditureOnProductionTransportationAndOtherExpenditurePertainingToExplorationAndProductionActivities",LTI_HS_STANDALONE!$C:$C,LTI_HS_STANDALONE!D:D,0,0,1) | F12: =-_xlfn.XLOOKUP("EmployeeBenefitExpense",LTI_HS_STANDALONE!$C:$C,LTI_HS_STANDALONE!E:E,0,0,1)-_xlfn.XLOOKUP("ExpenditureOnProductionTransportationAndOtherExpenditurePertainingToExplorationAndProductionActivities",LTI_HS_STANDALONE!$C:$C,LTI_HS_STANDALONE!E:E,0,0,1) | G12: =-_xlfn.XLOOKUP("EmployeeBenefitExpense",LTI_HS_STANDALONE!$C:$C,LTI_HS_STANDALONE!F:F,0,0,1)-_xlfn.XLOOKUP("ExpenditureOnProductionTransportationAndOtherExpenditurePertainingToExplorationAndProductionActivities",LTI_HS_STANDALONE!$C:$C,LTI_HS_STANDALONE!F:F,0,0,1) | H12: =-_xlfn.XLOOKUP("EmployeeBenefitExpense",LTI_HS_STANDALONE!$C:$C,LTI_HS_STANDALONE!G:G,0,0,1)-_xlfn.XLOOKUP("ExpenditureOnProductionTransportationAndOtherExpenditurePertainingToExplorationAndProductionActivities",LTI_HS_STANDALONE!$C:$C,LTI_HS_STANDALONE!G:G,0,0,1) | I12: =-_xlfn.XLOOKUP("EmployeeBenefitExpense",LTI_HS_STANDALONE!$C:$C,LTI_HS_STANDALONE!H:H,0,0,1)-_xlfn.XLOOKUP("ExpenditureOnProductionTransportationAndOtherExpenditurePertainingToExplorationAndProductionActivities",LTI_HS_STANDALONE!$C:$C,LTI_HS_STANDALONE!H:H,0,0,1) | J12: =-_xlfn.XLOOKUP("EmployeeBenefitExpense",LTI_HS_STANDALONE!$C:$C,LTI_HS_STANDALONE!I:I,0,0,1)-_xlfn.XLOOKUP("ExpenditureOnProductionTransportationAndOtherExpenditurePertainingToExplorationAndProductionActivities",LTI_HS_STANDALONE!$C:$C,LTI_HS_STANDALONE!I:I,0,0,1)
C13: Total other expenses | E13: =-_xlfn.XLOOKUP("OtherExpenses",LTI_HS_STANDALONE!$C:$C,LTI_HS_STANDALONE!D:D,0,0,1) | F13: =-_xlfn.XLOOKUP("OtherExpenses",LTI_HS_STANDALONE!$C:$C,LTI_HS_STANDALONE!E:E,0,0,1) | G13: =-_xlfn.XLOOKUP("OtherExpenses",LTI_HS_STANDALONE!$C:$C,LTI_HS_STANDALONE!F:F,0,0,1) | H13: =-_xlfn.XLOOKUP("OtherExpenses",LTI_HS_STANDALONE!$C:$C,LTI_HS_STANDALONE!G:G,0,0,1) | I13: =-_xlfn.XLOOKUP("OtherExpenses",LTI_HS_STANDALONE!$C:$C,LTI_HS_STANDALONE!H:H,0,0,1) | J13: =-_xlfn.XLOOKUP("OtherExpenses",LTI_HS_STANDALONE!$C:$C,LTI_HS_STANDALONE!I:I,0,0,1)
B14: EBITDA | E14: =IFERROR(SUM(E11:E13),0) | F14: =IFERROR(SUM(F11:F13),0) | G14: =IFERROR(SUM(G11:G13),0) | H14: =IFERROR(SUM(H11:H13),0) | I14: =IFERROR(SUM(I11:I13),0) | J14: =IFERROR(SUM(J11:J13),0)
C15: D&A | E15: =-_xlfn.XLOOKUP("DepreciationDepletionAndAmortisationExpense",LTI_HS_STANDALONE!$C:$C,LTI_HS_STANDALONE!D:D,0,0,1) | F15: =-_xlfn.XLOOKUP("DepreciationDepletionAndAmortisationExpense",LTI_HS_STANDALONE!$C:$C,LTI_HS_STANDALONE!E:E,0,0,1) | G15: =-_xlfn.XLOOKUP("DepreciationDepletionAndAmortisationExpense",LTI_HS_STANDALONE!$C:$C,LTI_HS_STANDALONE!F:F,0,0,1) | H15: =-_xlfn.XLOOKUP("DepreciationDepletionAndAmortisationExpense",LTI_HS_STANDALONE!$C:$C,LTI_HS_STANDALONE!G:G,0,0,1) | I15: =-_xlfn.XLOOKUP("DepreciationDepletionAndAmortisationExpense",LTI_HS_STANDALONE!$C:$C,LTI_HS_STANDALONE!H:H,0,0,1) | J15: =-_xlfn.XLOOKUP("DepreciationDepletionAndAmortisationExpense",LTI_HS_STANDALONE!$C:$C,LTI_HS_STANDALONE!I:I,0,0,1)
B16: EBIT | E16: =IFERROR(SUM(E14:E15),0) | F16: =IFERROR(SUM(F14:F15),0) | G16: =IFERROR(SUM(G14:G15),0) | H16: =IFERROR(SUM(H14:H15),0) | I16: =IFERROR(SUM(I14:I15),0) | J16: =IFERROR(SUM(J14:J15),0)
C17: Total finance costs | E17: =-_xlfn.XLOOKUP("FinanceCosts",LTI_HS_STANDALONE!$C:$C,LTI_HS_STANDALONE!D:D,0,0,1) | F17: =-_xlfn.XLOOKUP("FinanceCosts",LTI_HS_STANDALONE!$C:$C,LTI_HS_STANDALONE!E:E,0,0,1) | G17: =-_xlfn.XLOOKUP("FinanceCosts",LTI_HS_STANDALONE!$C:$C,LTI_HS_STANDALONE!F:F,0,0,1) | H17: =-_xlfn.XLOOKUP("FinanceCosts",LTI_HS_STANDALONE!$C:$C,LTI_HS_STANDALONE!G:G,0,0,1) | I17: =-_xlfn.XLOOKUP("FinanceCosts",LTI_HS_STANDALONE!$C:$C,LTI_HS_STANDALONE!H:H,0,0,1) | J17: =-_xlfn.XLOOKUP("FinanceCosts",LTI_HS_STANDALONE!$C:$C,LTI_HS_STANDALONE!I:I,0,0,1)
B18: EBT | E18: =IFERROR(SUM(E16:E17),0) | F18: =IFERROR(SUM(F16:F17),0) | G18: =IFERROR(SUM(G16:G17),0) | H18: =IFERROR(SUM(H16:H17),0) | I18: =IFERROR(SUM(I16:I17),0) | J18: =IFERROR(SUM(J16:J17),0)
C19: Total current tax | E19: =-_xlfn.XLOOKUP("CurrentTax",LTI_HS_STANDALONE!$C:$C,LTI_HS_STANDALONE!D:D,0,0,1) | F19: =-_xlfn.XLOOKUP("CurrentTax",LTI_HS_STANDALONE!$C:$C,LTI_HS_STANDALONE!E:E,0,0,1) | G19: =-_xlfn.XLOOKUP("CurrentTax",LTI_HS_STANDALONE!$C:$C,LTI_HS_STANDALONE!F:F,0,0,1) | H19: =-_xlfn.XLOOKUP("CurrentTax",LTI_HS_STANDALONE!$C:$C,LTI_HS_STANDALONE!G:G,0,0,1) | I19: =-_xlfn.XLOOKUP("CurrentTax",LTI_HS_STANDALONE!$C:$C,LTI_HS_STANDALONE!H:H,0,0,1) | J19: =-_xlfn.XLOOKUP("CurrentTax",LTI_HS_STANDALONE!$C:$C,LTI_HS_STANDALONE!I:I,0,0,1)
C20: Deferred tax | E20: =-_xlfn.XLOOKUP("DeferredTax",LTI_HS_STANDALONE!$C:$C,LTI_HS_STANDALONE!D:D,0,0,1) | F20: =-_xlfn.XLOOKUP("DeferredTax",LTI_HS_STANDALONE!$C:$C,LTI_HS_STANDALONE!E:E,0,0,1) | G20: =-_xlfn.XLOOKUP("DeferredTax",LTI_HS_STANDALONE!$C:$C,LTI_HS_STANDALONE!F:F,0,0,1) | H20: =-_xlfn.XLOOKUP("DeferredTax",LTI_HS_STANDALONE!$C:$C,LTI_HS_STANDALONE!G:G,0,0,1) | I20: =-_xlfn.XLOOKUP("DeferredTax",LTI_HS_STANDALONE!$C:$C,LTI_HS_STANDALONE!H:H,0,0,1) | J20: =-_xlfn.XLOOKUP("DeferredTax",LTI_HS_STANDALONE!$C:$C,LTI_HS_STANDALONE!I:I,0,0,1)
C21: Total tax expense | E21: =IFERROR(SUM(E19:E20),0) | F21: =IFERROR(SUM(F19:F20),0) | G21: =IFERROR(SUM(G19:G20),0) | H21: =IFERROR(SUM(H19:H20),0) | I21: =IFERROR(SUM(I19:I20),0) | J21: =IFERROR(SUM(J19:J20),0)
B22: NETINCOME | E22: =IFERROR(E21+E18,0) | F22: =IFERROR(F21+F18,0) | G22: =IFERROR(G21+G18,0) | H22: =IFERROR(H21+H18,0) | I22: =IFERROR(I21+I18,0) | J22: =IFERROR(J21+J18,0)
A23: # | B23: Balance Sheet
B24: Assets [Abstract]
B25: Non-current assets [Abstract]
C26: Operating
D27: Property, plant and equipment at end of period | E27: =_xlfn.XLOOKUP("PropertyPlantAndEquipment",LTI_HS_STANDALONE!$C:$C,LTI_HS_STANDALONE!D:D,0,0,1) | F27: =_xlfn.XLOOKUP("PropertyPlantAndEquipment",LTI_HS_STANDALONE!$C:$C,LTI_HS_STANDALONE!E:E,0,0,1) | G27: =_xlfn.XLOOKUP("PropertyPlantAndEquipment",LTI_HS_STANDALONE!$C:$C,LTI_HS_STANDALONE!F:F,0,0,1) | H27: =_xlfn.XLOOKUP("PropertyPlantAndEquipment",LTI_HS_STANDALONE!$C:$C,LTI_HS_STANDALONE!G:G,0,0,1) | I27: =_xlfn.XLOOKUP("PropertyPlantAndEquipment",LTI_HS_STANDALONE!$C:$C,LTI_HS_STANDALONE!H:H,0,0,1) | J27: =_xlfn.XLOOKUP("PropertyPlantAndEquipment",LTI_HS_STANDALONE!$C:$C,LTI_HS_STANDALONE!I:I,0,0,1)
D28: Capital work-in-progress | E28: =_xlfn.XLOOKUP("CapitalWorkInProgress",LTI_HS_STANDALONE!$C:$C,LTI_HS_STANDALONE!D:D,0,0,1) | F28: =_xlfn.XLOOKUP("CapitalWorkInProgress",LTI_HS_STANDALONE!$C:$C,LTI_HS_STANDALONE!E:E,0,0,1) | G28: =_xlfn.XLOOKUP("CapitalWorkInProgress",LTI_HS_STANDALONE!$C:$C,LTI_HS_STANDALONE!F:F,0,0,1) | H28: =_xlfn.XLOOKUP("CapitalWorkInProgress",LTI_HS_STANDALONE!$C:$C,LTI_HS_STANDALONE!G:G,0,0,1) | I28: =_xlfn.XLOOKUP("CapitalWorkInProgress",LTI_HS_STANDALONE!$C:$C,LTI_HS_STANDALONE!H:H,0,0,1) | J28: =_xlfn.XLOOKUP("CapitalWorkInProgress",LTI_HS_STANDALONE!$C:$C,LTI_HS_STANDALONE!I:I,0,0,1)
D29: Goodwill at end of period | E29: =_xlfn.XLOOKUP("Goodwill",LTI_HS_STANDALONE!$C:$C,LTI_HS_STANDALONE!D:D,0,0,1) | F29: =_xlfn.XLOOKUP("Goodwill",LTI_HS_STANDALONE!$C:$C,LTI_HS_STANDALONE!E:E,0,0,1) | G29: =_xlfn.XLOOKUP("Goodwill",LTI_HS_STANDALONE!$C:$C,LTI_HS_STANDALONE!F:F,0,0,1) | H29: =_xlfn.XLOOKUP("Goodwill",LTI_HS_STANDALONE!$C:$C,LTI_HS_STANDALONE!G:G,0,0,1) | I29: =_xlfn.XLOOKUP("Goodwill",LTI_HS_STANDALONE!$C:$C,LTI_HS_STANDALONE!H:H,0,0,1) | J29: =_xlfn.XLOOKUP("Goodwill",LTI_HS_STANDALONE!$C:$C,LTI_HS_STANDALONE!I:I,0,0,1)
D30: Other intangible assets at end of period | E30: =_xlfn.XLOOKUP("OtherIntangibleAssets",LTI_HS_STANDALONE!$C:$C,LTI_HS_STANDALONE!D:D,0,0,1) | F30: =_xlfn.XLOOKUP("OtherIntangibleAssets",LTI_HS_STANDALONE!$C:$C,LTI_HS_STANDALONE!E:E,0,0,1) | G30: =_xlfn.XLOOKUP("OtherIntangibleAssets",LTI_HS_STANDALONE!$C:$C,LTI_HS_STANDALONE!F:F,0,0,1) | H30: =_xlfn.XLOOKUP("OtherIntangibleAssets",LTI_HS_STANDALONE!$C:$C,LTI_HS_STANDALONE!G:G,0,0,1) | I30: =_xlfn.XLOOKUP("OtherIntangibleAssets",LTI_HS_STANDALONE!$C:$C,LTI_HS_STANDALONE!H:H,0,0,1) | J30: =_xlfn.XLOOKUP("OtherIntangibleAssets",LTI_HS_STANDALONE!$C:$C,LTI_HS_STANDALONE!I:I,0,0,1)
D31: Intangible assets under development | E31: =_xlfn.XLOOKUP("IntangibleAssetsUnderDevelopment",LTI_HS_STANDALONE!$C:$C,LTI_HS_STANDALONE!D:D,0,0,1) | F31: =_xlfn.XLOOKUP("IntangibleAssetsUnderDevelopment",LTI_HS_STANDALONE!$C:$C,LTI_HS_STANDALONE!E:E,0,0,1) | G31: =_xlfn.XLOOKUP("IntangibleAssetsUnderDevelopment",LTI_HS_STANDALONE!$C:$C,LTI_HS_STANDALONE!F:F,0,0,1) | H31: =_xlfn.XLOOKUP("IntangibleAssetsUnderDevelopment",LTI_HS_STANDALONE!$C:$C,LTI_HS_STANDALONE!G:G,0,0,1) | I31: =_xlfn.XLOOKUP("IntangibleAssetsUnderDevelopment",LTI_HS_STANDALONE!$C:$C,LTI_HS_STANDALONE!H:H,0,0,1) | J31: =_xlfn.XLOOKUP("IntangibleAssetsUnderDevelopment",LTI_HS_STANDALONE!$C:$C,LTI_HS_STANDALONE!I:I,0,0,1)
D32: Total other non-current assets | E32: =_xlfn.XLOOKUP("OtherNoncurrentAssets",LTI_HS_STANDALONE!$C:$C,LTI_HS_STANDALONE!D:D,0,0,1) | F32: =_xlfn.XLOOKUP("OtherNoncurrentAssets",LTI_HS_STANDALONE!$C:$C,LTI_HS_STANDALONE!E:E,0,0,1) | G32: =_xlfn.XLOOKUP("OtherNoncurrentAssets",LTI_HS_STANDALONE!$C:$C,LTI_HS_STANDALONE!F:F,0,0,1) | H32: =_xlfn.XLOOKUP("OtherNoncurrentAssets",LTI_HS_STANDALONE!$C:$C,LTI_HS_STANDALONE!G:G,0,0,1) | I32: =_xlfn.XLOOKUP("OtherNoncurrentAssets",LTI_HS_STANDALONE!$C:$C,LTI_HS_STANDALONE!H:H,0,0,1) | J32: =_xlfn.XLOOKUP("OtherNoncurrentAssets",LTI_HS_STANDALONE!$C:$C,LTI_HS_STANDALONE!I:I,0,0,1)
C33: Total Operating | E33: =IFERROR(SUM(E27:E32),0) | F33: =IFERROR(SUM(F27:F32),0) | G33: =IFERROR(SUM(G27:G32),0) | H33: =IFERROR(SUM(H27:H32),0) | I33: =IFERROR(SUM(I27:I32),0) | J33: =IFERROR(SUM(J27:J32),0)
C34: Non-Operating
D35: Non-current investments | E35: =_xlfn.XLOOKUP("NoncurrentInvestments",LTI_HS_STANDALONE!$C:$C,LTI_HS_STANDALONE!D:D,0,0,1) | F35: =_xlfn.XLOOKUP("NoncurrentInvestments",LTI_HS_STANDALONE!$C:$C,LTI_HS_STANDALONE!E:E,0,0,1) | G35: =_xlfn.XLOOKUP("NoncurrentInvestments",LTI_HS_STANDALONE!$C:$C,LTI_HS_STANDALONE!F:F,0,0,1) | H35: =_xlfn.XLOOKUP("NoncurrentInvestments",LTI_HS_STANDALONE!$C:$C,LTI_HS_STANDALONE!G:G,0,0,1) | I35: =_xlfn.XLOOKUP("NoncurrentInvestments",LTI_HS_STANDALONE!$C:$C,LTI_HS_STANDALONE!H:H,0,0,1) | J35: =_xlfn.XLOOKUP("NoncurrentInvestments",LTI_HS_STANDALONE!$C:$C,LTI_HS_STANDALONE!I:I,0,0,1)
D36: Loans, non-current | E36: =_xlfn.XLOOKUP("LoansNoncurrent",LTI_HS_STANDALONE!$C:$C,LTI_HS_STANDALONE!D:D,0,0,1) | F36: =_xlfn.XLOOKUP("LoansNoncurrent",LTI_HS_STANDALONE!$C:$C,LTI_HS_STANDALONE!E:E,0,0,1) | G36: =_xlfn.XLOOKUP("LoansNoncurrent",LTI_HS_STANDALONE!$C:$C,LTI_HS_STANDALONE!F:F,0,0,1) | H36: =_xlfn.XLOOKUP("LoansNoncurrent",LTI_HS_STANDALONE!$C:$C,LTI_HS_STANDALONE!G:G,0,0,1) | I36: =_xlfn.XLOOKUP("LoansNoncurrent",LTI_HS_STANDALONE!$C:$C,LTI_HS_STANDALONE!H:H,0,0,1) | J36: =_xlfn.XLOOKUP("LoansNoncurrent",LTI_HS_STANDALONE!$C:$C,LTI_HS_STANDALONE!I:I,0,0,1)
D37: Total other non-current financial assets | E37: =_xlfn.XLOOKUP("OtherNoncurrentFinancialAssets",LTI_HS_STANDALONE!$C:$C,LTI_HS_STANDALONE!D:D,0,0,1) | F37: =_xlfn.XLOOKUP("OtherNoncurrentFinancialAssets",LTI_HS_STANDALONE!$C:$C,LTI_HS_STANDALONE!E:E,0,0,1) | G37: =_xlfn.XLOOKUP("OtherNoncurrentFinancialAssets",LTI_HS_STANDALONE!$C:$C,LTI_HS_STANDALONE!F:F,0,0,1) | H37: =_xlfn.XLOOKUP("OtherNoncurrentFinancialAssets",LTI_HS_STANDALONE!$C:$C,LTI_HS_STANDALONE!G:G,0,0,1) | I37: =_xlfn.XLOOKUP("OtherNoncurrentFinancialAssets",LTI_HS_STANDALONE!$C:$C,LTI_HS_STANDALONE!H:H,0,0,1) | J37: =_xlfn.XLOOKUP("OtherNoncurrentFinancialAssets",LTI_HS_STANDALONE!$C:$C,LTI_HS_STANDALONE!I:I,0,0,1)
D38: Deferred tax assets (net) | E38: =_xlfn.XLOOKUP("DeferredTaxAssetsNet",LTI_HS_STANDALONE!$C:$C,LTI_HS_STANDALONE!D:D,0,0,1) | F38: =_xlfn.XLOOKUP("DeferredTaxAssetsNet",LTI_HS_STANDALONE!$C:$C,LTI_HS_STANDALONE!E:E,0,0,1) | G38: =_xlfn.XLOOKUP("DeferredTaxAssetsNet",LTI_HS_STANDALONE!$C:$C,LTI_HS_STANDALONE!F:F,0,0,1) | H38: =_xlfn.XLOOKUP("DeferredTaxAssetsNet",LTI_HS_STANDALONE!$C:$C,LTI_HS_STANDALONE!G:G,0,0,1) | I38: =_xlfn.XLOOKUP("DeferredTaxAssetsNet",LTI_HS_STANDALONE!$C:$C,LTI_HS_STANDALONE!H:H,0,0,1) | J38: =_xlfn.XLOOKUP("DeferredTaxAssetsNet",LTI_HS_STANDALONE!$C:$C,LTI_HS_STANDALONE!I:I,0,0,1)
C39: Total Non-Operating | E39: =IFERROR(SUM(E35:E38),0) | F39: =IFERROR(SUM(F35:F38),0) | G39: =IFERROR(SUM(G35:G38),0) | H39: =IFERROR(SUM(H35:H38),0) | I39: =IFERROR(SUM(I35:I38),0) | J39: =IFERROR(SUM(J35:J38),0)
C40: Total non-current financial assets | E40: =_xlfn.XLOOKUP("NoncurrentFinancialAssets",LTI_HS_STANDALONE!$C:$C,LTI_HS_STANDALONE!D:D,0,0,1) | F40: =_xlfn.XLOOKUP("NoncurrentFinancialAssets",LTI_HS_STANDALONE!$C:$C,LTI_HS_STANDALONE!E:E,0,0,1) | G40: =_xlfn.XLOOKUP("NoncurrentFinancialAssets",LTI_HS_STANDALONE!$C:$C,LTI_HS_STANDALONE!F:F,0,0,1) | H40: =_xlfn.XLOOKUP("NoncurrentFinancialAssets",LTI_HS_STANDALONE!$C:$C,LTI_HS_STANDALONE!G:G,0,0,1) | I40: =_xlfn.XLOOKUP("NoncurrentFinancialAssets",LTI_HS_STANDALONE!$C:$C,LTI_HS_STANDALONE!H:H,0,0,1) | J40: =_xlfn.XLOOKUP("NoncurrentFinancialAssets",LTI_HS_STANDALONE!$C:$C,LTI_HS_STANDALONE!I:I,0,0,1)
B41: Total Non-Current Assets | E41: =IFERROR(E39+E33,0) | F41: =IFERROR(F39+F33,0) | G41: =IFERROR(G39+G33,0) | H41: =IFERROR(H39+H33,0) | I41: =IFERROR(I39+I33,0) | J41: =IFERROR(J39+J33,0)
B42: Current Assets
C43: Operating
D44: Trade receivables, current | E44: =_xlfn.XLOOKUP("TradeReceivablesCurrent",LTI_HS_STANDALONE!$C:$C,LTI_HS_STANDALONE!D:D,0,0,1) | F44: =_xlfn.XLOOKUP("TradeReceivablesCurrent",LTI_HS_STANDALONE!$C:$C,LTI_HS_STANDALONE!E:E,0,0,1) | G44: =_xlfn.XLOOKUP("TradeReceivablesCurrent",LTI_HS_STANDALONE!$C:$C,LTI_HS_STANDALONE!F:F,0,0,1) | H44: =_xlfn.XLOOKUP("TradeReceivablesCurrent",LTI_HS_STANDALONE!$C:$C,LTI_HS_STANDALONE!G:G,0,0,1) | I44: =_xlfn.XLOOKUP("TradeReceivablesCurrent",LTI_HS_STANDALONE!$C:$C,LTI_HS_STANDALONE!H:H,0,0,1) | J44: =_xlfn.XLOOKUP("TradeReceivablesCurrent",LTI_HS_STANDALONE!$C:$C,LTI_HS_STANDALONE!I:I,0,0,1)
D45: Total other current assets | E45: =_xlfn.XLOOKUP("OtherCurrentAssets",LTI_HS_STANDALONE!$C:$C,LTI_HS_STANDALONE!D:D,0,0,1) | F45: =_xlfn.XLOOKUP("OtherCurrentAssets",LTI_HS_STANDALONE!$C:$C,LTI_HS_STANDALONE!E:E,0,0,1) | G45: =_xlfn.XLOOKUP("OtherCurrentAssets",LTI_HS_STANDALONE!$C:$C,LTI_HS_STANDALONE!F:F,0,0,1) | H45: =_xlfn.XLOOKUP("OtherCurrentAssets",LTI_HS_STANDALONE!$C:$C,LTI_HS_STANDALONE!G:G,0,0,1) | I45: =_xlfn.XLOOKUP("OtherCurrentAssets",LTI_HS_STANDALONE!$C:$C,LTI_HS_STANDALONE!H:H,0,0,1) | J45: =_xlfn.XLOOKUP("OtherCurrentAssets",LTI_HS_STANDALONE!$C:$C,LTI_HS_STANDALONE!I:I,0,0,1)
C46: Total Operating | E46: =IFERROR(SUM(E44:E45),0) | F46: =IFERROR(SUM(F44:F45),0) | G46: =IFERROR(SUM(G44:G45),0) | H46: =IFERROR(SUM(H44:H45),0) | I46: =IFERROR(SUM(I44:I45),0) | J46: =IFERROR(SUM(J44:J45),0)
C47: Non-Operating
D48: Current investments | E48: =_xlfn.XLOOKUP("CurrentInvestments",LTI_HS_STANDALONE!$C:$C,LTI_HS_STANDALONE!D:D,0,0,1) | F48: =_xlfn.XLOOKUP("CurrentInvestments",LTI_HS_STANDALONE!$C:$C,LTI_HS_STANDALONE!E:E,0,0,1) | G48: =_xlfn.XLOOKUP("CurrentInvestments",LTI_HS_STANDALONE!$C:$C,LTI_HS_STANDALONE!F:F,0,0,1) | H48: =_xlfn.XLOOKUP("CurrentInvestments",LTI_HS_STANDALONE!$C:$C,LTI_HS_STANDALONE!G:G,0,0,1) | I48: =_xlfn.XLOOKUP("CurrentInvestments",LTI_HS_STANDALONE!$C:$C,LTI_HS_STANDALONE!H:H,0,0,1) | J48: =_xlfn.XLOOKUP("CurrentInvestments",LTI_HS_STANDALONE!$C:$C,LTI_HS_STANDALONE!I:I,0,0,1)
D49: Cash and cash equivalents at end of period | E49: =_xlfn.XLOOKUP("CashAndCashEquivalents",LTI_HS_STANDALONE!$C:$C,LTI_HS_STANDALONE!D:D,0,0,1) | F49: =_xlfn.XLOOKUP("CashAndCashEquivalents",LTI_HS_STANDALONE!$C:$C,LTI_HS_STANDALONE!E:E,0,0,1) | G49: =_xlfn.XLOOKUP("CashAndCashEquivalents",LTI_HS_STANDALONE!$C:$C,LTI_HS_STANDALONE!F:F,0,0,1) | H49: =_xlfn.XLOOKUP("CashAndCashEquivalents",LTI_HS_STANDALONE!$C:$C,LTI_HS_STANDALONE!G:G,0,0,1) | I49: =_xlfn.XLOOKUP("CashAndCashEquivalents",LTI_HS_STANDALONE!$C:$C,LTI_HS_STANDALONE!H:H,0,0,1) | J49: =_xlfn.XLOOKUP("CashAndCashEquivalents",LTI_HS_STANDALONE!$C:$C,LTI_HS_STANDALONE!I:I,0,0,1)
D50: Bank balance other than cash and cash equivalents | E50: =_xlfn.XLOOKUP("BankBalanceOtherThanCashAndCashEquivalents",LTI_HS_STANDALONE!$C:$C,LTI_HS_STANDALONE!D:D,0,0,1) | F50: =_xlfn.XLOOKUP("BankBalanceOtherThanCashAndCashEquivalents",LTI_HS_STANDALONE!$C:$C,LTI_HS_STANDALONE!E:E,0,0,1) | G50: =_xlfn.XLOOKUP("BankBalanceOtherThanCashAndCashEquivalents",LTI_HS_STANDALONE!$C:$C,LTI_HS_STANDALONE!F:F,0,0,1) | H50: =_xlfn.XLOOKUP("BankBalanceOtherThanCashAndCashEquivalents",LTI_HS_STANDALONE!$C:$C,LTI_HS_STANDALONE!G:G,0,0,1) | I50: =_xlfn.XLOOKUP("BankBalanceOtherThanCashAndCashEquivalents",LTI_HS_STANDALONE!$C:$C,LTI_HS_STANDALONE!H:H,0,0,1) | J50: =_xlfn.XLOOKUP("BankBalanceOtherThanCashAndCashEquivalents",LTI_HS_STANDALONE!$C:$C,LTI_HS_STANDALONE!I:I,0,0,1)
D51: Loans, current | E51: =_xlfn.XLOOKUP("LoansCurrent",LTI_HS_STANDALONE!$C:$C,LTI_HS_STANDALONE!D:D,0,0,1) | F51: =_xlfn.XLOOKUP("LoansCurrent",LTI_HS_STANDALONE!$C:$C,LTI_HS_STANDALONE!E:E,0,0,1) | G51: =_xlfn.XLOOKUP("LoansCurrent",LTI_HS_STANDALONE!$C:$C,LTI_HS_STANDALONE!F:F,0,0,1) | H51: =_xlfn.XLOOKUP("LoansCurrent",LTI_HS_STANDALONE!$C:$C,LTI_HS_STANDALONE!G:G,0,0,1) | I51: =_xlfn.XLOOKUP("LoansCurrent",LTI_HS_STANDALONE!$C:$C,LTI_HS_STANDALONE!H:H,0,0,1) | J51: =_xlfn.XLOOKUP("LoansCurrent",LTI_HS_STANDALONE!$C:$C,LTI_HS_STANDALONE!I:I,0,0,1)
D52: Total other current financial assets | E52: =_xlfn.XLOOKUP("OtherCurrentFinancialAssets",LTI_HS_STANDALONE!$C:$C,LTI_HS_STANDALONE!D:D,0,0,1) | F52: =_xlfn.XLOOKUP("OtherCurrentFinancialAssets",LTI_HS_STANDALONE!$C:$C,LTI_HS_STANDALONE!E:E,0,0,1) | G52: =_xlfn.XLOOKUP("OtherCurrentFinancialAssets",LTI_HS_STANDALONE!$C:$C,LTI_HS_STANDALONE!F:F,0,0,1) | H52: =_xlfn.XLOOKUP("OtherCurrentFinancialAssets",LTI_HS_STANDALONE!$C:$C,LTI_HS_STANDALONE!G:G,0,0,1) | I52: =_xlfn.XLOOKUP("OtherCurrentFinancialAssets",LTI_HS_STANDALONE!$C:$C,LTI_HS_STANDALONE!H:H,0,0,1) | J52: =_xlfn.XLOOKUP("OtherCurrentFinancialAssets",LTI_HS_STANDALONE!$C:$C,LTI_HS_STANDALONE!I:I,0,0,1)
D53: Current tax assets, Current | E53: =_xlfn.XLOOKUP("CurrentTaxAssetsCurrent",LTI_HS_STANDALONE!$C:$C,LTI_HS_STANDALONE!D:D,0,0,1) | F53: =_xlfn.XLOOKUP("CurrentTaxAssetsCurrent",LTI_HS_STANDALONE!$C:$C,LTI_HS_STANDALONE!E:E,0,0,1) | G53: =_xlfn.XLOOKUP("CurrentTaxAssetsCurrent",LTI_HS_STANDALONE!$C:$C,LTI_HS_STANDALONE!F:F,0,0,1) | H53: =_xlfn.XLOOKUP("CurrentTaxAssetsCurrent",LTI_HS_STANDALONE!$C:$C,LTI_HS_STANDALONE!G:G,0,0,1) | I53: =_xlfn.XLOOKUP("CurrentTaxAssetsCurrent",LTI_HS_STANDALONE!$C:$C,LTI_HS_STANDALONE!H:H,0,0,1) | J53: =_xlfn.XLOOKUP("CurrentTaxAssetsCurrent",LTI_HS_STANDALONE!$C:$C,LTI_HS_STANDALONE!I:I,0,0,1)
C54: Total Non-Operating | E54: =IFERROR(SUM(E48:E53),0) | F54: =IFERROR(SUM(F48:F53),0) | G54: =IFERROR(SUM(G48:G53),0) | H54: =IFERROR(SUM(H48:H53),0) | I54: =IFERROR(SUM(I48:I53),0) | J54: =IFERROR(SUM(J48:J53),0)
C55: Total current financial assets | E55: =_xlfn.XLOOKUP("CurrentFinancialAssets",LTI_HS_STANDALONE!$C:$C,LTI_HS_STANDALONE!D:D,0,0,1) | F55: =_xlfn.XLOOKUP("CurrentFinancialAssets",LTI_HS_STANDALONE!$C:$C,LTI_HS_STANDALONE!E:E,0,0,1) | G55: =_xlfn.XLOOKUP("CurrentFinancialAssets",LTI_HS_STANDALONE!$C:$C,LTI_HS_STANDALONE!F:F,0,0,1) | H55: =_xlfn.XLOOKUP("CurrentFinancialAssets",LTI_HS_STANDALONE!$C:$C,LTI_HS_STANDALONE!G:G,0,0,1) | I55: =_xlfn.XLOOKUP("CurrentFinancialAssets",LTI_HS_STANDALONE!$C:$C,LTI_HS_STANDALONE!H:H,0,0,1) | J55: =_xlfn.XLOOKUP("CurrentFinancialAssets",LTI_HS_STANDALONE!$C:$C,LTI_HS_STANDALONE!I:I,0,0,1)
B56: Total Current Assets | E56: =IFERROR(E54+E46,0) | F56: =IFERROR(F54+F46,0) | G56: =IFERROR(G54+G46,0) | H56: =IFERROR(H54+H46,0) | I56: =IFERROR(I54+I46,0) | J56: =IFERROR(J54+J46,0)
B57: Total Assets | E57: =IFERROR(SUM(E56:E56)+E41,0) | F57: =IFERROR(SUM(F56:F56)+F41,0) | G57: =IFERROR(SUM(G56:G56)+G41,0) | H57: =IFERROR(SUM(H56:H56)+H41,0) | I57: =IFERROR(SUM(I56:I56)+I41,0) | J57: =IFERROR(SUM(J56:J56)+J41,0)
B58: Equity and Liabilities
B59: Equity attributable to owners of parent
C60: Equity share capital at end of period | E60: =_xlfn.XLOOKUP("EquityShareCapital",LTI_HS_STANDALONE!$C:$C,LTI_HS_STANDALONE!D:D,0,0,1) | F60: =_xlfn.XLOOKUP("EquityShareCapital",LTI_HS_STANDALONE!$C:$C,LTI_HS_STANDALONE!E:E,0,0,1) | G60: =_xlfn.XLOOKUP("EquityShareCapital",LTI_HS_STANDALONE!$C:$C,LTI_HS_STANDALONE!F:F,0,0,1) | H60: =_xlfn.XLOOKUP("EquityShareCapital",LTI_HS_STANDALONE!$C:$C,LTI_HS_STANDALONE!G:G,0,0,1) | I60: =_xlfn.XLOOKUP("EquityShareCapital",LTI_HS_STANDALONE!$C:$C,LTI_HS_STANDALONE!H:H,0,0,1) | J60: =_xlfn.XLOOKUP("EquityShareCapital",LTI_HS_STANDALONE!$C:$C,LTI_HS_STANDALONE!I:I,0,0,1)
C61: Other equity | E61: =_xlfn.XLOOKUP("OtherEquity",LTI_HS_STANDALONE!$C:$C,LTI_HS_STANDALONE!D:D,0,0,1) | F61: =_xlfn.XLOOKUP("OtherEquity",LTI_HS_STANDALONE!$C:$C,LTI_HS_STANDALONE!E:E,0,0,1) | G61: =_xlfn.XLOOKUP("OtherEquity",LTI_HS_STANDALONE!$C:$C,LTI_HS_STANDALONE!F:F,0,0,1) | H61: =_xlfn.XLOOKUP("OtherEquity",LTI_HS_STANDALONE!$C:$C,LTI_HS_STANDALONE!G:G,0,0,1) | I61: =_xlfn.XLOOKUP("OtherEquity",LTI_HS_STANDALONE!$C:$C,LTI_HS_STANDALONE!H:H,0,0,1) | J61: =_xlfn.XLOOKUP("OtherEquity",LTI_HS_STANDALONE!$C:$C,LTI_HS_STANDALONE!I:I,0,0,1)
B62: Total equity attributable to owners of parent | E62: =IFERROR(SUM(E60:E61),0) | F62: =IFERROR(SUM(F60:F61),0) | G62: =IFERROR(SUM(G60:G61),0) | H62: =IFERROR(SUM(H60:H61),0) | I62: =IFERROR(SUM(I60:I61),0) | J62: =IFERROR(SUM(J60:J61),0)
B63: Equity at end of period | E63: =IFERROR(SUM(E62:E62),0) | F63: =IFERROR(SUM(F62:F62),0) | G63: =IFERROR(SUM(G62:G62),0) | H63: =IFERROR(SUM(H62:H62),0) | I63: =IFERROR(SUM(I62:I62),0) | J63: =IFERROR(SUM(J62:J62),0)
B64: Liabilities
B65: Non-current liabilities
B66: Non-current financial liabilities
C67: Trade payables, non-current
C68: Total other non-current financial liabilities | E68: =_xlfn.XLOOKUP("OtherNoncurrentFinancialLiabilities",LTI_HS_STANDALONE!$C:$C,LTI_HS_STANDALONE!D:D,0,0,1) | F68: =_xlfn.XLOOKUP("OtherNoncurrentFinancialLiabilities",LTI_HS_STANDALONE!$C:$C,LTI_HS_STANDALONE!E:E,0,0,1) | G68: =_xlfn.XLOOKUP("OtherNoncurrentFinancialLiabilities",LTI_HS_STANDALONE!$C:$C,LTI_HS_STANDALONE!F:F,0,0,1) | H68: =_xlfn.XLOOKUP("OtherNoncurrentFinancialLiabilities",LTI_HS_STANDALONE!$C:$C,LTI_HS_STANDALONE!G:G,0,0,1) | I68: =_xlfn.XLOOKUP("OtherNoncurrentFinancialLiabilities",LTI_HS_STANDALONE!$C:$C,LTI_HS_STANDALONE!H:H,0,0,1) | J68: =_xlfn.XLOOKUP("OtherNoncurrentFinancialLiabilities",LTI_HS_STANDALONE!$C:$C,LTI_HS_STANDALONE!I:I,0,0,1)
C69: Total non-current financial liabilities | E69: =_xlfn.XLOOKUP("NoncurrentFinancialLiabilities",LTI_HS_STANDALONE!$C:$C,LTI_HS_STANDALONE!D:D,0,0,1) | F69: =_xlfn.XLOOKUP("NoncurrentFinancialLiabilities",LTI_HS_STANDALONE!$C:$C,LTI_HS_STANDALONE!E:E,0,0,1) | G69: =_xlfn.XLOOKUP("NoncurrentFinancialLiabilities",LTI_HS_STANDALONE!$C:$C,LTI_HS_STANDALONE!F:F,0,0,1) | H69: =_xlfn.XLOOKUP("NoncurrentFinancialLiabilities",LTI_HS_STANDALONE!$C:$C,LTI_HS_STANDALONE!G:G,0,0,1) | I69: =_xlfn.XLOOKUP("NoncurrentFinancialLiabilities",LTI_HS_STANDALONE!$C:$C,LTI_HS_STANDALONE!H:H,0,0,1) | J69: =_xlfn.XLOOKUP("NoncurrentFinancialLiabilities",LTI_HS_STANDALONE!$C:$C,LTI_HS_STANDALONE!I:I,0,0,1)
D70: Provisions, non-current | E70: =_xlfn.XLOOKUP("ProvisionsNoncurrent",LTI_HS_STANDALONE!$C:$C,LTI_HS_STANDALONE!D:D,0,0,1) | F70: =_xlfn.XLOOKUP("ProvisionsNoncurrent",LTI_HS_STANDALONE!$C:$C,LTI_HS_STANDALONE!E:E,0,0,1) | G70: =_xlfn.XLOOKUP("ProvisionsNoncurrent",LTI_HS_STANDALONE!$C:$C,LTI_HS_STANDALONE!F:F,0,0,1) | H70: =_xlfn.XLOOKUP("ProvisionsNoncurrent",LTI_HS_STANDALONE!$C:$C,LTI_HS_STANDALONE!G:G,0,0,1) | I70: =_xlfn.XLOOKUP("ProvisionsNoncurrent",LTI_HS_STANDALONE!$C:$C,LTI_HS_STANDALONE!H:H,0,0,1) | J70: =_xlfn.XLOOKUP("ProvisionsNoncurrent",LTI_HS_STANDALONE!$C:$C,LTI_HS_STANDALONE!I:I,0,0,1)
D71: Total other non-current liabilities | E71: =_xlfn.XLOOKUP("OtherNoncurrentLiabilities",LTI_HS_STANDALONE!$C:$C,LTI_HS_STANDALONE!D:D,0,0,1) | F71: =_xlfn.XLOOKUP("OtherNoncurrentLiabilities",LTI_HS_STANDALONE!$C:$C,LTI_HS_STANDALONE!E:E,0,0,1) | G71: =_xlfn.XLOOKUP("OtherNoncurrentLiabilities",LTI_HS_STANDALONE!$C:$C,LTI_HS_STANDALONE!F:F,0,0,1) | H71: =_xlfn.XLOOKUP("OtherNoncurrentLiabilities",LTI_HS_STANDALONE!$C:$C,LTI_HS_STANDALONE!G:G,0,0,1) | I71: =_xlfn.XLOOKUP("OtherNoncurrentLiabilities",LTI_HS_STANDALONE!$C:$C,LTI_HS_STANDALONE!H:H,0,0,1) | J71: =_xlfn.XLOOKUP("OtherNoncurrentLiabilities",LTI_HS_STANDALONE!$C:$C,LTI_HS_STANDALONE!I:I,0,0,1)
B72: Total non-current liabilities | E72: =IFERROR(SUM(E68:E68)+SUM(E70:E71),0) | F72: =IFERROR(SUM(F68:F68)+SUM(F70:F71),0) | G72: =IFERROR(SUM(G68:G68)+SUM(G70:G71),0) | H72: =IFERROR(SUM(H68:H68)+SUM(H70:H71),0) | I72: =IFERROR(SUM(I68:I68)+SUM(I70:I71),0) | J72: =IFERROR(SUM(J68:J68)+SUM(J70:J71),0)
B73: Current liabilities
B74: Current financial liabilities
C75: Trade payables, current
D76: Total trade payables, current | E76: =_xlfn.XLOOKUP("TradePayablesCurrent",LTI_HS_STANDALONE!$C:$C,LTI_HS_STANDALONE!D:D,0,0,1) | F76: =_xlfn.XLOOKUP("TradePayablesCurrent",LTI_HS_STANDALONE!$C:$C,LTI_HS_STANDALONE!E:E,0,0,1) | G76: =_xlfn.XLOOKUP("TradePayablesCurrent",LTI_HS_STANDALONE!$C:$C,LTI_HS_STANDALONE!F:F,0,0,1) | H76: =_xlfn.XLOOKUP("TradePayablesCurrent",LTI_HS_STANDALONE!$C:$C,LTI_HS_STANDALONE!G:G,0,0,1) | I76: =_xlfn.XLOOKUP("TradePayablesCurrent",LTI_HS_STANDALONE!$C:$C,LTI_HS_STANDALONE!H:H,0,0,1) | J76: =_xlfn.XLOOKUP("TradePayablesCurrent",LTI_HS_STANDALONE!$C:$C,LTI_HS_STANDALONE!I:I,0,0,1)
C77: Total other current financial liabilities | E77: =_xlfn.XLOOKUP("OtherCurrentFinancialLiabilities",LTI_HS_STANDALONE!$C:$C,LTI_HS_STANDALONE!D:D,0,0,1) | F77: =_xlfn.XLOOKUP("OtherCurrentFinancialLiabilities",LTI_HS_STANDALONE!$C:$C,LTI_HS_STANDALONE!E:E,0,0,1) | G77: =_xlfn.XLOOKUP("OtherCurrentFinancialLiabilities",LTI_HS_STANDALONE!$C:$C,LTI_HS_STANDALONE!F:F,0,0,1) | H77: =_xlfn.XLOOKUP("OtherCurrentFinancialLiabilities",LTI_HS_STANDALONE!$C:$C,LTI_HS_STANDALONE!G:G,0,0,1) | I77: =_xlfn.XLOOKUP("OtherCurrentFinancialLiabilities",LTI_HS_STANDALONE!$C:$C,LTI_HS_STANDALONE!H:H,0,0,1) | J77: =_xlfn.XLOOKUP("OtherCurrentFinancialLiabilities",LTI_HS_STANDALONE!$C:$C,LTI_HS_STANDALONE!I:I,0,0,1)
B78: Total current financial liabilities | E78: =_xlfn.XLOOKUP("CurrentFinancialLiabilities",LTI_HS_STANDALONE!$C:$C,LTI_HS_STANDALONE!D:D,0,0,1) | F78: =_xlfn.XLOOKUP("CurrentFinancialLiabilities",LTI_HS_STANDALONE!$C:$C,LTI_HS_STANDALONE!E:E,0,0,1) | G78: =_xlfn.XLOOKUP("CurrentFinancialLiabilities",LTI_HS_STANDALONE!$C:$C,LTI_HS_STANDALONE!F:F,0,0,1) | H78: =_xlfn.XLOOKUP("CurrentFinancialLiabilities",LTI_HS_STANDALONE!$C:$C,LTI_HS_STANDALONE!G:G,0,0,1) | I78: =_xlfn.XLOOKUP("CurrentFinancialLiabilities",LTI_HS_STANDALONE!$C:$C,LTI_HS_STANDALONE!H:H,0,0,1) | J78: =_xlfn.XLOOKUP("CurrentFinancialLiabilities",LTI_HS_STANDALONE!$C:$C,LTI_HS_STANDALONE!I:I,0,0,1)
C79: Total other current liabilities | E79: =_xlfn.XLOOKUP("OtherCurrentLiabilities",LTI_HS_STANDALONE!$C:$C,LTI_HS_STANDALONE!D:D,0,0,1) | F79: =_xlfn.XLOOKUP("OtherCurrentLiabilities",LTI_HS_STANDALONE!$C:$C,LTI_HS_STANDALONE!E:E,0,0,1) | G79: =_xlfn.XLOOKUP("OtherCurrentLiabilities",LTI_HS_STANDALONE!$C:$C,LTI_HS_STANDALONE!F:F,0,0,1) | H79: =_xlfn.XLOOKUP("OtherCurrentLiabilities",LTI_HS_STANDALONE!$C:$C,LTI_HS_STANDALONE!G:G,0,0,1) | I79: =_xlfn.XLOOKUP("OtherCurrentLiabilities",LTI_HS_STANDALONE!$C:$C,LTI_HS_STANDALONE!H:H,0,0,1) | J79: =_xlfn.XLOOKUP("OtherCurrentLiabilities",LTI_HS_STANDALONE!$C:$C,LTI_HS_STANDALONE!I:I,0,0,1)
C80: Provisions, current | E80: =_xlfn.XLOOKUP("ProvisionsCurrent",LTI_HS_STANDALONE!$C:$C,LTI_HS_STANDALONE!D:D,0,0,1) | F80: =_xlfn.XLOOKUP("ProvisionsCurrent",LTI_HS_STANDALONE!$C:$C,LTI_HS_STANDALONE!E:E,0,0,1) | G80: =_xlfn.XLOOKUP("ProvisionsCurrent",LTI_HS_STANDALONE!$C:$C,LTI_HS_STANDALONE!F:F,0,0,1) | H80: =_xlfn.XLOOKUP("ProvisionsCurrent",LTI_HS_STANDALONE!$C:$C,LTI_HS_STANDALONE!G:G,0,0,1) | I80: =_xlfn.XLOOKUP("ProvisionsCurrent",LTI_HS_STANDALONE!$C:$C,LTI_HS_STANDALONE!H:H,0,0,1) | J80: =_xlfn.XLOOKUP("ProvisionsCurrent",LTI_HS_STANDALONE!$C:$C,LTI_HS_STANDALONE!I:I,0,0,1)
C81: Current tax liabilities | E81: =_xlfn.XLOOKUP("CurrentTaxLiabilities",LTI_HS_STANDALONE!$C:$C,LTI_HS_STANDALONE!D:D,0,0,1) | F81: =_xlfn.XLOOKUP("CurrentTaxLiabilities",LTI_HS_STANDALONE!$C:$C,LTI_HS_STANDALONE!E:E,0,0,1) | G81: =_xlfn.XLOOKUP("CurrentTaxLiabilities",LTI_HS_STANDALONE!$C:$C,LTI_HS_STANDALONE!F:F,0,0,1) | H81: =_xlfn.XLOOKUP("CurrentTaxLiabilities",LTI_HS_STANDALONE!$C:$C,LTI_HS_STANDALONE!G:G,0,0,1) | I81: =_xlfn.XLOOKUP("CurrentTaxLiabilities",LTI_HS_STANDALONE!$C:$C,LTI_HS_STANDALONE!H:H,0,0,1) | J81: =_xlfn.XLOOKUP("CurrentTaxLiabilities",LTI_HS_STANDALONE!$C:$C,LTI_HS_STANDALONE!I:I,0,0,1)
B82: Total current liabilities | E82: =IFERROR(SUM(E76:E77)+SUM(E79:E81),0) | F82: =IFERROR(SUM(F76:F77)+SUM(F79:F81),0) | G82: =IFERROR(SUM(G76:G77)+SUM(G79:G81),0) | H82: =IFERROR(SUM(H76:H77)+SUM(H79:H81),0) | I82: =IFERROR(SUM(I76:I77)+SUM(I79:I81),0) | J82: =IFERROR(SUM(J76:J77)+SUM(J79:J81),0)
B83: Liabilities | E83: =IFERROR(SUM(E82:E82)+E72,0) | F83: =IFERROR(SUM(F82:F82)+F72,0) | G83: =IFERROR(SUM(G82:G82)+G72,0) | H83: =IFERROR(SUM(H82:H82)+H72,0) | I83: =IFERROR(SUM(I82:I82)+I72,0) | J83: =IFERROR(SUM(J82:J82)+J72,0)
B84: Total equity and liabilities | E84: =IFERROR(E63+E83,0) | F84: =IFERROR(F63+F83,0) | G84: =IFERROR(G63+G83,0) | H84: =IFERROR(H63+H83,0) | I84: =IFERROR(I63+I83,0) | J84: =IFERROR(J63+J83,0)
B85: BALANCE CHECK (Total Assets − Total Equity & Liabilities) | E85: =E57-E84 | F85: =F57-F84 | G85: =G57-G84 | H85: =H57-H84 | I85: =I57-I84 | J85: =J57-J84
A86: # | B86: Statement of Cash Flows
B87: Cash flows from used in operating activities
C88: Total profit before tax | E88: =_xlfn.XLOOKUP("ProfitBeforeTax",LTI_HS_STANDALONE!$C:$C,LTI_HS_STANDALONE!D:D,0,0,1) | F88: =_xlfn.XLOOKUP("ProfitBeforeTax",LTI_HS_STANDALONE!$C:$C,LTI_HS_STANDALONE!E:E,0,0,1) | G88: =_xlfn.XLOOKUP("ProfitBeforeTax",LTI_HS_STANDALONE!$C:$C,LTI_HS_STANDALONE!F:F,0,0,1) | H88: =_xlfn.XLOOKUP("ProfitBeforeTax",LTI_HS_STANDALONE!$C:$C,LTI_HS_STANDALONE!G:G,0,0,1) | I88: =_xlfn.XLOOKUP("ProfitBeforeTax",LTI_HS_STANDALONE!$C:$C,LTI_HS_STANDALONE!H:H,0,0,1) | J88: =_xlfn.XLOOKUP("ProfitBeforeTax",LTI_HS_STANDALONE!$C:$C,LTI_HS_STANDALONE!I:I,0,0,1)
C89: Adjustments for reconcile profit (loss)
D90: Adjustments for finance costs | E90: =_xlfn.XLOOKUP("AdjustmentsForFinanceCosts",LTI_HS_STANDALONE!$C:$C,LTI_HS_STANDALONE!D:D,0,0,1) | F90: =_xlfn.XLOOKUP("AdjustmentsForFinanceCosts",LTI_HS_STANDALONE!$C:$C,LTI_HS_STANDALONE!E:E,0,0,1) | G90: =_xlfn.XLOOKUP("AdjustmentsForFinanceCosts",LTI_HS_STANDALONE!$C:$C,LTI_HS_STANDALONE!F:F,0,0,1) | H90: =_xlfn.XLOOKUP("AdjustmentsForFinanceCosts",LTI_HS_STANDALONE!$C:$C,LTI_HS_STANDALONE!G:G,0,0,1) | I90: =_xlfn.XLOOKUP("AdjustmentsForFinanceCosts",LTI_HS_STANDALONE!$C:$C,LTI_HS_STANDALONE!H:H,0,0,1) | J90: =_xlfn.XLOOKUP("AdjustmentsForFinanceCosts",LTI_HS_STANDALONE!$C:$C,LTI_HS_STANDALONE!I:I,0,0,1)
D91: Adjustments for decrease (increase) in trade receivables, current | E91: =_xlfn.XLOOKUP("AdjustmentsForDecreaseIncreaseInTradeReceivablesCurrent",LTI_HS_STANDALONE!$C:$C,LTI_HS_STANDALONE!D:D,0,0,1) | F91: =_xlfn.XLOOKUP("AdjustmentsForDecreaseIncreaseInTradeReceivablesCurrent",LTI_HS_STANDALONE!$C:$C,LTI_HS_STANDALONE!E:E,0,0,1) | G91: =_xlfn.XLOOKUP("AdjustmentsForDecreaseIncreaseInTradeReceivablesCurrent",LTI_HS_STANDALONE!$C:$C,LTI_HS_STANDALONE!F:F,0,0,1) | H91: =_xlfn.XLOOKUP("AdjustmentsForDecreaseIncreaseInTradeReceivablesCurrent",LTI_HS_STANDALONE!$C:$C,LTI_HS_STANDALONE!G:G,0,0,1) | I91: =_xlfn.XLOOKUP("AdjustmentsForDecreaseIncreaseInTradeReceivablesCurrent",LTI_HS_STANDALONE!$C:$C,LTI_HS_STANDALONE!H:H,0,0,1) | J91: =_xlfn.XLOOKUP("AdjustmentsForDecreaseIncreaseInTradeReceivablesCurrent",LTI_HS_STANDALONE!$C:$C,LTI_HS_STANDALONE!I:I,0,0,1)
D92: Adjustments for decrease (increase) in other current assets | E92: =_xlfn.XLOOKUP("AdjustmentsForDecreaseIncreaseInOtherCurrentAssets",LTI_HS_STANDALONE!$C:$C,LTI_HS_STANDALONE!D:D,0,0,1) | F92: =_xlfn.XLOOKUP("AdjustmentsForDecreaseIncreaseInOtherCurrentAssets",LTI_HS_STANDALONE!$C:$C,LTI_HS_STANDALONE!E:E,0,0,1) | G92: =_xlfn.XLOOKUP("AdjustmentsForDecreaseIncreaseInOtherCurrentAssets",LTI_HS_STANDALONE!$C:$C,LTI_HS_STANDALONE!F:F,0,0,1) | H92: =_xlfn.XLOOKUP("AdjustmentsForDecreaseIncreaseInOtherCurrentAssets",LTI_HS_STANDALONE!$C:$C,LTI_HS_STANDALONE!G:G,0,0,1) | I92: =_xlfn.XLOOKUP("AdjustmentsForDecreaseIncreaseInOtherCurrentAssets",LTI_HS_STANDALONE!$C:$C,LTI_HS_STANDALONE!H:H,0,0,1) | J92: =_xlfn.XLOOKUP("AdjustmentsForDecreaseIncreaseInOtherCurrentAssets",LTI_HS_STANDALONE!$C:$C,LTI_HS_STANDALONE!I:I,0,0,1)
D93: Adjustments for decrease (increase) in other non-current assets | E93: =_xlfn.XLOOKUP("AdjustmentsForDecreaseIncreaseInOtherNoncurrentAssets",LTI_HS_STANDALONE!$C:$C,LTI_HS_STANDALONE!D:D,0,0,1) | F93: =_xlfn.XLOOKUP("AdjustmentsForDecreaseIncreaseInOtherNoncurrentAssets",LTI_HS_STANDALONE!$C:$C,LTI_HS_STANDALONE!E:E,0,0,1) | G93: =_xlfn.XLOOKUP("AdjustmentsForDecreaseIncreaseInOtherNoncurrentAssets",LTI_HS_STANDALONE!$C:$C,LTI_HS_STANDALONE!F:F,0,0,1) | H93: =_xlfn.XLOOKUP("AdjustmentsForDecreaseIncreaseInOtherNoncurrentAssets",LTI_HS_STANDALONE!$C:$C,LTI_HS_STANDALONE!G:G,0,0,1) | I93: =_xlfn.XLOOKUP("AdjustmentsForDecreaseIncreaseInOtherNoncurrentAssets",LTI_HS_STANDALONE!$C:$C,LTI_HS_STANDALONE!H:H,0,0,1) | J93: =_xlfn.XLOOKUP("AdjustmentsForDecreaseIncreaseInOtherNoncurrentAssets",LTI_HS_STANDALONE!$C:$C,LTI_HS_STANDALONE!I:I,0,0,1)
D94: Adjustments for increase (decrease) in trade payables, current | E94: =_xlfn.XLOOKUP("AdjustmentsForIncreaseDecreaseInTradePayablesCurrent",LTI_HS_STANDALONE!$C:$C,LTI_HS_STANDALONE!D:D,0,0,1) | F94: =_xlfn.XLOOKUP("AdjustmentsForIncreaseDecreaseInTradePayablesCurrent",LTI_HS_STANDALONE!$C:$C,LTI_HS_STANDALONE!E:E,0,0,1) | G94: =_xlfn.XLOOKUP("AdjustmentsForIncreaseDecreaseInTradePayablesCurrent",LTI_HS_STANDALONE!$C:$C,LTI_HS_STANDALONE!F:F,0,0,1) | H94: =_xlfn.XLOOKUP("AdjustmentsForIncreaseDecreaseInTradePayablesCurrent",LTI_HS_STANDALONE!$C:$C,LTI_HS_STANDALONE!G:G,0,0,1) | I94: =_xlfn.XLOOKUP("AdjustmentsForIncreaseDecreaseInTradePayablesCurrent",LTI_HS_STANDALONE!$C:$C,LTI_HS_STANDALONE!H:H,0,0,1) | J94: =_xlfn.XLOOKUP("AdjustmentsForIncreaseDecreaseInTradePayablesCurrent",LTI_HS_STANDALONE!$C:$C,LTI_HS_STANDALONE!I:I,0,0,1)
D95: Adjustments for depreciation and amortisation expense | E95: =_xlfn.XLOOKUP("AdjustmentsForDepreciationAndAmortisationExpense",LTI_HS_STANDALONE!$C:$C,LTI_HS_STANDALONE!D:D,0,0,1) | F95: =_xlfn.XLOOKUP("AdjustmentsForDepreciationAndAmortisationExpense",LTI_HS_STANDALONE!$C:$C,LTI_HS_STANDALONE!E:E,0,0,1) | G95: =_xlfn.XLOOKUP("AdjustmentsForDepreciationAndAmortisationExpense",LTI_HS_STANDALONE!$C:$C,LTI_HS_STANDALONE!F:F,0,0,1) | H95: =_xlfn.XLOOKUP("AdjustmentsForDepreciationAndAmortisationExpense",LTI_HS_STANDALONE!$C:$C,LTI_HS_STANDALONE!G:G,0,0,1) | I95: =_xlfn.XLOOKUP("AdjustmentsForDepreciationAndAmortisationExpense",LTI_HS_STANDALONE!$C:$C,LTI_HS_STANDALONE!H:H,0,0,1) | J95: =_xlfn.XLOOKUP("AdjustmentsForDepreciationAndAmortisationExpense",LTI_HS_STANDALONE!$C:$C,LTI_HS_STANDALONE!I:I,0,0,1)
D96: Adjustments for unrealised foreign exchange losses gains | E96: =_xlfn.XLOOKUP("AdjustmentsForUnrealisedForeignExchangeLossesGains",LTI_HS_STANDALONE!$C:$C,LTI_HS_STANDALONE!D:D,0,0,1) | F96: =_xlfn.XLOOKUP("AdjustmentsForUnrealisedForeignExchangeLossesGains",LTI_HS_STANDALONE!$C:$C,LTI_HS_STANDALONE!E:E,0,0,1) | G96: =_xlfn.XLOOKUP("AdjustmentsForUnrealisedForeignExchangeLossesGains",LTI_HS_STANDALONE!$C:$C,LTI_HS_STANDALONE!F:F,0,0,1) | H96: =_xlfn.XLOOKUP("AdjustmentsForUnrealisedForeignExchangeLossesGains",LTI_HS_STANDALONE!$C:$C,LTI_HS_STANDALONE!G:G,0,0,1) | I96: =_xlfn.XLOOKUP("AdjustmentsForUnrealisedForeignExchangeLossesGains",LTI_HS_STANDALONE!$C:$C,LTI_HS_STANDALONE!H:H,0,0,1) | J96: =_xlfn.XLOOKUP("AdjustmentsForUnrealisedForeignExchangeLossesGains",LTI_HS_STANDALONE!$C:$C,LTI_HS_STANDALONE!I:I,0,0,1)
D97: Adjustments for dividend income | E97: =_xlfn.XLOOKUP("AdjustmentsForDividendIncome",LTI_HS_STANDALONE!$C:$C,LTI_HS_STANDALONE!D:D,0,0,1) | F97: =_xlfn.XLOOKUP("AdjustmentsForDividendIncome",LTI_HS_STANDALONE!$C:$C,LTI_HS_STANDALONE!E:E,0,0,1) | G97: =_xlfn.XLOOKUP("AdjustmentsForDividendIncome",LTI_HS_STANDALONE!$C:$C,LTI_HS_STANDALONE!F:F,0,0,1) | H97: =_xlfn.XLOOKUP("AdjustmentsForDividendIncome",LTI_HS_STANDALONE!$C:$C,LTI_HS_STANDALONE!G:G,0,0,1) | I97: =_xlfn.XLOOKUP("AdjustmentsForDividendIncome",LTI_HS_STANDALONE!$C:$C,LTI_HS_STANDALONE!H:H,0,0,1) | J97: =_xlfn.XLOOKUP("AdjustmentsForDividendIncome",LTI_HS_STANDALONE!$C:$C,LTI_HS_STANDALONE!I:I,0,0,1)
D98: Adjustments for interest income | E98: =_xlfn.XLOOKUP("AdjustmentsForInterestIncome",LTI_HS_STANDALONE!$C:$C,LTI_HS_STANDALONE!D:D,0,0,1) | F98: =_xlfn.XLOOKUP("AdjustmentsForInterestIncome",LTI_HS_STANDALONE!$C:$C,LTI_HS_STANDALONE!E:E,0,0,1) | G98: =_xlfn.XLOOKUP("AdjustmentsForInterestIncome",LTI_HS_STANDALONE!$C:$C,LTI_HS_STANDALONE!F:F,0,0,1) | H98: =_xlfn.XLOOKUP("AdjustmentsForInterestIncome",LTI_HS_STANDALONE!$C:$C,LTI_HS_STANDALONE!G:G,0,0,1) | I98: =_xlfn.XLOOKUP("AdjustmentsForInterestIncome",LTI_HS_STANDALONE!$C:$C,LTI_HS_STANDALONE!H:H,0,0,1) | J98: =_xlfn.XLOOKUP("AdjustmentsForInterestIncome",LTI_HS_STANDALONE!$C:$C,LTI_HS_STANDALONE!I:I,0,0,1)
D99: Adjustments for share-based payments | E99: =_xlfn.XLOOKUP("AdjustmentsForSharebasedPayments",LTI_HS_STANDALONE!$C:$C,LTI_HS_STANDALONE!D:D,0,0,1) | F99: =_xlfn.XLOOKUP("AdjustmentsForSharebasedPayments",LTI_HS_STANDALONE!$C:$C,LTI_HS_STANDALONE!E:E,0,0,1) | G99: =_xlfn.XLOOKUP("AdjustmentsForSharebasedPayments",LTI_HS_STANDALONE!$C:$C,LTI_HS_STANDALONE!F:F,0,0,1) | H99: =_xlfn.XLOOKUP("AdjustmentsForSharebasedPayments",LTI_HS_STANDALONE!$C:$C,LTI_HS_STANDALONE!G:G,0,0,1) | I99: =_xlfn.XLOOKUP("AdjustmentsForSharebasedPayments",LTI_HS_STANDALONE!$C:$C,LTI_HS_STANDALONE!H:H,0,0,1) | J99: =_xlfn.XLOOKUP("AdjustmentsForSharebasedPayments",LTI_HS_STANDALONE!$C:$C,LTI_HS_STANDALONE!I:I,0,0,1)
D100: Other adjustments for which cash effects are investing or financing cash flow | E100: =_xlfn.XLOOKUP("OtherAdjustmentsForWhichCashEffectsAreInvestingOrFinancingCashFlow",LTI_HS_STANDALONE!$C:$C,LTI_HS_STANDALONE!D:D,0,0,1) | F100: =_xlfn.XLOOKUP("OtherAdjustmentsForWhichCashEffectsAreInvestingOrFinancingCashFlow",LTI_HS_STANDALONE!$C:$C,LTI_HS_STANDALONE!E:E,0,0,1) | G100: =_xlfn.XLOOKUP("OtherAdjustmentsForWhichCashEffectsAreInvestingOrFinancingCashFlow",LTI_HS_STANDALONE!$C:$C,LTI_HS_STANDALONE!F:F,0,0,1) | H100: =_xlfn.XLOOKUP("OtherAdjustmentsForWhichCashEffectsAreInvestingOrFinancingCashFlow",LTI_HS_STANDALONE!$C:$C,LTI_HS_STANDALONE!G:G,0,0,1) | I100: =_xlfn.XLOOKUP("OtherAdjustmentsForWhichCashEffectsAreInvestingOrFinancingCashFlow",LTI_HS_STANDALONE!$C:$C,LTI_HS_STANDALONE!H:H,0,0,1) | J100: =_xlfn.XLOOKUP("OtherAdjustmentsForWhichCashEffectsAreInvestingOrFinancingCashFlow",LTI_HS_STANDALONE!$C:$C,LTI_HS_STANDALONE!I:I,0,0,1)
D101: Other adjustments to reconcile profit (loss) | E101: =_xlfn.XLOOKUP("OtherAdjustmentsToReconcileProfitLoss",LTI_HS_STANDALONE!$C:$C,LTI_HS_STANDALONE!D:D,0,0,1) | F101: =_xlfn.XLOOKUP("OtherAdjustmentsToReconcileProfitLoss",LTI_HS_STANDALONE!$C:$C,LTI_HS_STANDALONE!E:E,0,0,1) | G101: =_xlfn.XLOOKUP("OtherAdjustmentsToReconcileProfitLoss",LTI_HS_STANDALONE!$C:$C,LTI_HS_STANDALONE!F:F,0,0,1) | H101: =_xlfn.XLOOKUP("OtherAdjustmentsToReconcileProfitLoss",LTI_HS_STANDALONE!$C:$C,LTI_HS_STANDALONE!G:G,0,0,1) | I101: =_xlfn.XLOOKUP("OtherAdjustmentsToReconcileProfitLoss",LTI_HS_STANDALONE!$C:$C,LTI_HS_STANDALONE!H:H,0,0,1) | J101: =_xlfn.XLOOKUP("OtherAdjustmentsToReconcileProfitLoss",LTI_HS_STANDALONE!$C:$C,LTI_HS_STANDALONE!I:I,0,0,1)
D102: Other adjustments for non-cash items | E102: =_xlfn.XLOOKUP("OtherAdjustmentsForNoncashItems",LTI_HS_STANDALONE!$C:$C,LTI_HS_STANDALONE!D:D,0,0,1) | F102: =_xlfn.XLOOKUP("OtherAdjustmentsForNoncashItems",LTI_HS_STANDALONE!$C:$C,LTI_HS_STANDALONE!E:E,0,0,1) | G102: =_xlfn.XLOOKUP("OtherAdjustmentsForNoncashItems",LTI_HS_STANDALONE!$C:$C,LTI_HS_STANDALONE!F:F,0,0,1) | H102: =_xlfn.XLOOKUP("OtherAdjustmentsForNoncashItems",LTI_HS_STANDALONE!$C:$C,LTI_HS_STANDALONE!G:G,0,0,1) | I102: =_xlfn.XLOOKUP("OtherAdjustmentsForNoncashItems",LTI_HS_STANDALONE!$C:$C,LTI_HS_STANDALONE!H:H,0,0,1) | J102: =_xlfn.XLOOKUP("OtherAdjustmentsForNoncashItems",LTI_HS_STANDALONE!$C:$C,LTI_HS_STANDALONE!I:I,0,0,1)
...

Sheet LTI_RATIO_ANALYSIS
A1: LTIMindtree — Ratio Analysis (Consolidated)
A2: Each ratio shown as Name = Numerator / Denominator, values computed once and reused (Green = first pull/computation from Derived Sheet, Black = same-sheet reuse) | Result appears on the right | Single-year figures (no opening/closing average)
A5: # | F5: FY2017 | G5: FY2018 | H5: FY2019 | I5: FY2020 | J5: FY2021 | K5: FY2022 | M5: FY2017 | N5: FY2018 | O5: FY2019 | P5: FY2020 | Q5: FY2021 | R5: FY2022
A6: # | B6: Profitability and Return Ratios
B7: Return on Equity | C7: = | D7: Net Income | E7: = | F7: =LTI_HIST_CON!E22 | G7: =LTI_HIST_CON!F22 | H7: =LTI_HIST_CON!G22 | I7: =LTI_HIST_CON!H22 | J7: =LTI_HIST_CON!I22 | K7: =LTI_HIST_CON!J22 | L7: = | M7: =IFERROR(IF(F8=0,"",F7/F8),"") | N7: =IFERROR(IF(G8=0,"",G7/G8),"") | O7: =IFERROR(IF(H8=0,"",H7/H8),"") | P7: =IFERROR(IF(I8=0,"",I7/I8),"") | Q7: =IFERROR(IF(J8=0,"",J7/J8),"") | R7: =IFERROR(IF(K8=0,"",K7/K8),"")
D8: Equity | F8: =LTI_HIST_CON!E64 | G8: =LTI_HIST_CON!F64 | H8: =LTI_HIST_CON!G64 | I8: =LTI_HIST_CON!H64 | J8: =LTI_HIST_CON!I64 | K8: =LTI_HIST_CON!J64
B10: Return on Assets | C10: = | D10: Net Income | E10: = | F10: =+F7 | G10: =+G7 | H10: =+H7 | I10: =+I7 | J10: =+J7 | K10: =+K7 | L10: = | M10: =IFERROR(IF(F11=0,"",F10/F11),"") | N10: =IFERROR(IF(G11=0,"",G10/G11),"") | O10: =IFERROR(IF(H11=0,"",H10/H11),"") | P10: =IFERROR(IF(I11=0,"",I10/I11),"") | Q10: =IFERROR(IF(J11=0,"",J10/J11),"") | R10: =IFERROR(IF(K11=0,"",K10/K11),"")
D11: Total Assets | F11: =LTI_HIST_CON!E57 | G11: =LTI_HIST_CON!F57 | H11: =LTI_HIST_CON!G57 | I11: =LTI_HIST_CON!H57 | J11: =LTI_HIST_CON!I57 | K11: =LTI_HIST_CON!J57
B13: Return on Net Assets | C13: = | D13: Net Income | E13: = | F13: =+F7 | G13: =+G7 | H13: =+H7 | I13: =+I7 | J13: =+J7 | K13: =+K7 | L13: = | M13: =IFERROR(IF(F14=0,"",F13/F14),"") | N13: =IFERROR(IF(G14=0,"",G13/G14),"") | O13: =IFERROR(IF(H14=0,"",H13/H14),"") | P13: =IFERROR(IF(I14=0,"",I13/I14),"") | Q13: =IFERROR(IF(J14=0,"",J13/J14),"") | R13: =IFERROR(IF(K14=0,"",K13/K14),"")
D14: Net PP&E + Net Working Capital | F14: =LTI_HIST_CON!E27+(LTI_HIST_CON!E56-LTI_HIST_CON!E85) | G14: =LTI_HIST_CON!F27+(LTI_HIST_CON!F56-LTI_HIST_CON!F85) | H14: =LTI_HIST_CON!G27+(LTI_HIST_CON!G56-LTI_HIST_CON!G85) | I14: =LTI_HIST_CON!H27+(LTI_HIST_CON!H56-LTI_HIST_CON!H85) | J14: =LTI_HIST_CON!I27+(LTI_HIST_CON!I56-LTI_HIST_CON!I85) | K14: =LTI_HIST_CON!J27+(LTI_HIST_CON!J56-LTI_HIST_CON!J85)
B16: Return on Invested Capital | C16: = | D16: NOPAT (= EBIT × (1 − Tax Expense / EBT)) | E16: = | F16: =LTI_HIST_CON!E16*(1-(-LTI_HIST_CON!E21/LTI_HIST_CON!E18)) | G16: =LTI_HIST_CON!F16*(1-(-LTI_HIST_CON!F21/LTI_HIST_CON!F18)) | H16: =LTI_HIST_CON!G16*(1-(-LTI_HIST_CON!G21/LTI_HIST_CON!G18)) | I16: =LTI_HIST_CON!H16*(1-(-LTI_HIST_CON!H21/LTI_HIST_CON!H18)) | J16: =LTI_HIST_CON!I16*(1-(-LTI_HIST_CON!I21/LTI_HIST_CON!I18)) | K16: =LTI_HIST_CON!J16*(1-(-LTI_HIST_CON!J21/LTI_HIST_CON!J18)) | L16: = | M16: =IFERROR(IF(F17=0,"",F16/F17),"") | N16: =IFERROR(IF(G17=0,"",G16/G17),"") | O16: =IFERROR(IF(H17=0,"",H16/H17),"") | P16: =IFERROR(IF(I17=0,"",I16/I17),"") | Q16: =IFERROR(IF(J17=0,"",J16/J17),"") | R16: =IFERROR(IF(K17=0,"",K16/K17),"")
D17: Invested Capital (= Debt + Equity − Cash) | F17: =(0+LTI_HIST_CON!E77+0+0)+LTI_HIST_CON!E64-LTI_HIST_CON!E49 | G17: =(0+LTI_HIST_CON!F77+0+0)+LTI_HIST_CON!F64-LTI_HIST_CON!F49 | H17: =(0+LTI_HIST_CON!G77+0+0)+LTI_HIST_CON!G64-LTI_HIST_CON!G49 | I17: =(0+LTI_HIST_CON!H77+0+0)+LTI_HIST_CON!H64-LTI_HIST_CON!H49 | J17: =(0+LTI_HIST_CON!I77+0+0)+LTI_HIST_CON!I64-LTI_HIST_CON!I49 | K17: =(0+LTI_HIST_CON!J77+0+0)+LTI_HIST_CON!J64-LTI_HIST_CON!J49
B19: Gross Margin | C19: = | D19: Gross Profit | E19: = | F19: =LTI_HIST_CON!E11 | G19: =LTI_HIST_CON!F11 | H19: =LTI_HIST_CON!G11 | I19: =LTI_HIST_CON!H11 | J19: =LTI_HIST_CON!I11 | K19: =LTI_HIST_CON!J11 | L19: = | M19: =IFERROR(IF(F20=0,"",F19/F20),"") | N19: =IFERROR(IF(G20=0,"",G19/G20),"") | O19: =IFERROR(IF(H20=0,"",H19/H20),"") | P19: =IFERROR(IF(I20=0,"",I19/I20),"") | Q19: =IFERROR(IF(J20=0,"",J19/J20),"") | R19: =IFERROR(IF(K20=0,"",K19/K20),"")
D20: Revenue | F20: =LTI_HIST_CON!E7 | G20: =LTI_HIST_CON!F7 | H20: =LTI_HIST_CON!G7 | I20: =LTI_HIST_CON!H7 | J20: =LTI_HIST_CON!I7 | K20: =LTI_HIST_CON!J7
B22: SG&A % of Revenue | C22: = | D22: SG&A | E22: = | F22: =-LTI_HIST_CON!E12 | G22: =-LTI_HIST_CON!F12 | H22: =-LTI_HIST_CON!G12 | I22: =-LTI_HIST_CON!H12 | J22: =-LTI_HIST_CON!I12 | K22: =-LTI_HIST_CON!J12 | L22: = | M22: =IFERROR(IF(F23=0,"",F22/F23),"") | N22: =IFERROR(IF(G23=0,"",G22/G23),"") | O22: =IFERROR(IF(H23=0,"",H22/H23),"") | P22: =IFERROR(IF(I23=0,"",I22/I23),"") | Q22: =IFERROR(IF(J23=0,"",J22/J23),"") | R22: =IFERROR(IF(K23=0,"",K22/K23),"")
D23: Revenue | F23: =+F20 | G23: =+G20 | H23: =+H20 | I23: =+I20 | J23: =+J20 | K23: =+K20
B25: Other Operating Expenses % of Revenue | C25: = | D25: Other Operating Expenses | E25: = | F25: =-LTI_HIST_CON!E13 | G25: =-LTI_HIST_CON!F13 | H25: =-LTI_HIST_CON!G13 | I25: =-LTI_HIST_CON!H13 | J25: =-LTI_HIST_CON!I13 | K25: =-LTI_HIST_CON!J13 | L25: = | M25: =IFERROR(IF(F26=0,"",F25/F26),"") | N25: =IFERROR(IF(G26=0,"",G25/G26),"") | O25: =IFERROR(IF(H26=0,"",H25/H26),"") | P25: =IFERROR(IF(I26=0,"",I25/I26),"") | Q25: =IFERROR(IF(J26=0,"",J25/J26),"") | R25: =IFERROR(IF(K26=0,"",K25/K26),"")
D26: Revenue | F26: =+F20 | G26: =+G20 | H26: =+H20 | I26: =+I20 | J26: =+J20 | K26: =+K20
B28: EBITDA Margin | C28: = | D28: EBITDA | E28: = | F28: =LTI_HIST_CON!E14 | G28: =LTI_HIST_CON!F14 | H28: =LTI_HIST_CON!G14 | I28: =LTI_HIST_CON!H14 | J28: =LTI_HIST_CON!I14 | K28: =LTI_HIST_CON!J14 | L28: = | M28: =IFERROR(IF(F29=0,"",F28/F29),"") | N28: =IFERROR(IF(G29=0,"",G28/G29),"") | O28: =IFERROR(IF(H29=0,"",H28/H29),"") | P28: =IFERROR(IF(I29=0,"",I28/I29),"") | Q28: =IFERROR(IF(J29=0,"",J28/J29),"") | R28: =IFERROR(IF(K29=0,"",K28/K29),"")
D29: Revenue | F29: =+F20 | G29: =+G20 | H29: =+H20 | I29: =+I20 | J29: =+J20 | K29: =+K20
B31: Check | M31: =IF(ABS(M19-M22-M25-M28)<0.0001,"OK","Error") | N31: =IF(ABS(N19-N22-N25-N28)<0.0001,"OK","Error") | O31: =IF(ABS(O19-O22-O25-O28)<0.0001,"OK","Error") | P31: =IF(ABS(P19-P22-P25-P28)<0.0001,"OK","Error") | Q31: =IF(ABS(Q19-Q22-Q25-Q28)<0.0001,"OK","Error") | R31: =IF(ABS(R19-R22-R25-R28)<0.0001,"OK","Error")
B33: Depreciation % of Revenue | C33: = | D33: Depreciation & Amortisation | E33: = | F33: =-LTI_HIST_CON!E15 | G33: =-LTI_HIST_CON!F15 | H33: =-LTI_HIST_CON!G15 | I33: =-LTI_HIST_CON!H15 | J33: =-LTI_HIST_CON!I15 | K33: =-LTI_HIST_CON!J15 | L33: = | M33: =IFERROR(IF(F34=0,"",F33/F34),"") | N33: =IFERROR(IF(G34=0,"",G33/G34),"") | O33: =IFERROR(IF(H34=0,"",H33/H34),"") | P33: =IFERROR(IF(I34=0,"",I33/I34),"") | Q33: =IFERROR(IF(J34=0,"",J33/J34),"") | R33: =IFERROR(IF(K34=0,"",K33/K34),"")
D34: Revenue | F34: =+F20 | G34: =+G20 | H34: =+H20 | I34: =+I20 | J34: =+J20 | K34: =+K20
B36: EBIT Margin | C36: = | D36: EBIT | E36: = | F36: =LTI_HIST_CON!E16 | G36: =LTI_HIST_CON!F16 | H36: =LTI_HIST_CON!G16 | I36: =LTI_HIST_CON!H16 | J36: =LTI_HIST_CON!I16 | K36: =LTI_HIST_CON!J16 | L36: = | M36: =IFERROR(IF(F37=0,"",F36/F37),"") | N36: =IFERROR(IF(G37=0,"",G36/G37),"") | O36: =IFERROR(IF(H37=0,"",H36/H37),"") | P36: =IFERROR(IF(I37=0,"",I36/I37),"") | Q36: =IFERROR(IF(J37=0,"",J36/J37),"") | R36: =IFERROR(IF(K37=0,"",K36/K37),"")
D37: Revenue | F37: =+F20 | G37: =+G20 | H37: =+H20 | I37: =+I20 | J37: =+J20 | K37: =+K20
B39: Check | M39: =IF(ABS(M28-M33-M36)<0.0001,"OK","Error") | N39: =IF(ABS(N28-N33-N36)<0.0001,"OK","Error") | O39: =IF(ABS(O28-O33-O36)<0.0001,"OK","Error") | P39: =IF(ABS(P28-P33-P36)<0.0001,"OK","Error") | Q39: =IF(ABS(Q28-Q33-Q36)<0.0001,"OK","Error") | R39: =IF(ABS(R28-R33-R36)<0.0001,"OK","Error")
B41: Other Non-Operating Expense % of Revenue | C41: = | D41: Finance Costs + Exceptional Items (net) | E41: = | F41: =-(LTI_HIST_CON!E17+0) | G41: =-(LTI_HIST_CON!F17+0) | H41: =-(LTI_HIST_CON!G17+0) | I41: =-(LTI_HIST_CON!H17+0) | J41: =-(LTI_HIST_CON!I17+0) | K41: =-(LTI_HIST_CON!J17+0) | L41: = | M41: =IFERROR(IF(F42=0,"",F41/F42),"") | N41: =IFERROR(IF(G42=0,"",G41/G42),"") | O41: =IFERROR(IF(H42=0,"",H41/H42),"") | P41: =IFERROR(IF(I42=0,"",I41/I42),"") | Q41: =IFERROR(IF(J42=0,"",J41/J42),"") | R41: =IFERROR(IF(K42=0,"",K41/K42),"")
D42: Revenue | F42: =+F20 | G42: =+G20 | H42: =+H20 | I42: =+I20 | J42: =+J20 | K42: =+K20
B44: EBT Margin | C44: = | D44: EBT (Pre-Tax Income) | E44: = | F44: =LTI_HIST_CON!E18 | G44: =LTI_HIST_CON!F18 | H44: =LTI_HIST_CON!G18 | I44: =LTI_HIST_CON!H18 | J44: =LTI_HIST_CON!I18 | K44: =LTI_HIST_CON!J18 | L44: = | M44: =IFERROR(IF(F45=0,"",F44/F45),"") | N44: =IFERROR(IF(G45=0,"",G44/G45),"") | O44: =IFERROR(IF(H45=0,"",H44/H45),"") | P44: =IFERROR(IF(I45=0,"",I44/I45),"") | Q44: =IFERROR(IF(J45=0,"",J44/J45),"") | R44: =IFERROR(IF(K45=0,"",K44/K45),"")
D45: Revenue | F45: =+F20 | G45: =+G20 | H45: =+H20 | I45: =+I20 | J45: =+J20 | K45: =+K20
B47: Check | M47: =IF(ABS(M36-M41-M44)<0.0001,"OK","Error") | N47: =IF(ABS(N36-N41-N44)<0.0001,"OK","Error") | O47: =IF(ABS(O36-O41-O44)<0.0001,"OK","Error") | P47: =IF(ABS(P36-P41-P44)<0.0001,"OK","Error") | Q47: =IF(ABS(Q36-Q41-Q44)<0.0001,"OK","Error") | R47: =IF(ABS(R36-R41-R44)<0.0001,"OK","Error")
B49: Tax % of Revenue | C49: = | D49: Total Tax Expense | E49: = | F49: =-LTI_HIST_CON!E21 | G49: =-LTI_HIST_CON!F21 | H49: =-LTI_HIST_CON!G21 | I49: =-LTI_HIST_CON!H21 | J49: =-LTI_HIST_CON!I21 | K49: =-LTI_HIST_CON!J21 | L49: = | M49: =IFERROR(IF(F50=0,"",F49/F50),"") | N49: =IFERROR(IF(G50=0,"",G49/G50),"") | O49: =IFERROR(IF(H50=0,"",H49/H50),"") | P49: =IFERROR(IF(I50=0,"",I49/I50),"") | Q49: =IFERROR(IF(J50=0,"",J49/J50),"") | R49: =IFERROR(IF(K50=0,"",K49/K50),"")
D50: Revenue | F50: =+F20 | G50: =+G20 | H50: =+H20 | I50: =+I20 | J50: =+J20 | K50: =+K20
B52: Net Profit Margin | C52: = | D52: Net Income | E52: = | F52: =+F7 | G52: =+G7 | H52: =+H7 | I52: =+I7 | J52: =+J7 | K52: =+K7 | L52: = | M52: =IFERROR(IF(F53=0,"",F52/F53),"") | N52: =IFERROR(IF(G53=0,"",G52/G53),"") | O52: =IFERROR(IF(H53=0,"",H52/H53),"") | P52: =IFERROR(IF(I53=0,"",I52/I53),"") | Q52: =IFERROR(IF(J53=0,"",J52/J53),"") | R52: =IFERROR(IF(K53=0,"",K52/K53),"")
D53: Revenue | F53: =+F20 | G53: =+G20 | H53: =+H20 | I53: =+I20 | J53: =+J20 | K53: =+K20
B55: Check | M55: =IF(ABS(M44-M49-M52)<0.0001,"OK","Error") | N55: =IF(ABS(N44-N49-N52)<0.0001,"OK","Error") | O55: =IF(ABS(O44-O49-O52)<0.0001,"OK","Error") | P55: =IF(ABS(P44-P49-P52)<0.0001,"OK","Error") | Q55: =IF(ABS(Q44-Q49-Q52)<0.0001,"OK","Error") | R55: =IF(ABS(R44-R49-R52)<0.0001,"OK","Error")
B57: Effective Tax Rate | C57: = | D57: Total Tax Expense | E57: = | F57: =+F49 | G57: =+G49 | H57: =+H49 | I57: =+I49 | J57: =+J49 | K57: =+K49 | L57: = | M57: =IFERROR(IF(F58=0,"",F57/F58),"") | N57: =IFERROR(IF(G58=0,"",G57/G58),"") | O57: =IFERROR(IF(H58=0,"",H57/H58),"") | P57: =IFERROR(IF(I58=0,"",I57/I58),"") | Q57: =IFERROR(IF(J58=0,"",J57/J58),"") | R57: =IFERROR(IF(K58=0,"",K57/K58),"")
D58: EBT (Pre-Tax Income) | F58: =+F44 | G58: =+G44 | H58: =+H44 | I58: =+I44 | J58: =+J44 | K58: =+K44
B60: Tax Burden | C60: = | D60: Net Income | E60: = | F60: =+F7 | G60: =+G7 | H60: =+H7 | I60: =+I7 | J60: =+J7 | K60: =+K7 | L60: = | M60: =IFERROR(IF(F61=0,"",F60/F61),"") | N60: =IFERROR(IF(G61=0,"",G60/G61),"") | O60: =IFERROR(IF(H61=0,"",H60/H61),"") | P60: =IFERROR(IF(I61=0,"",I60/I61),"") | Q60: =IFERROR(IF(J61=0,"",J60/J61),"") | R60: =IFERROR(IF(K61=0,"",K60/K61),"")
D61: EBT (Pre-Tax Income) | F61: =+F44 | G61: =+G44 | H61: =+H44 | I61: =+I44 | J61: =+J44 | K61: =+K44
B63: Effective Interest Rate | C63: = | D63: Finance Costs (absolute) | E63: = | F63: =ABS(LTI_HIST_CON!E17) | G63: =ABS(LTI_HIST_CON!F17) | H63: =ABS(LTI_HIST_CON!G17) | I63: =ABS(LTI_HIST_CON!H17) | J63: =ABS(LTI_HIST_CON!I17) | K63: =ABS(LTI_HIST_CON!J17) | L63: = | M63: =IFERROR(IF(F64=0,"",F63/F64),"") | N63: =IFERROR(IF(G64=0,"",G63/G64),"") | O63: =IFERROR(IF(H64=0,"",H63/H64),"") | P63: =IFERROR(IF(I64=0,"",I63/I64),"") | Q63: =IFERROR(IF(J64=0,"",J63/J64),"") | R63: =IFERROR(IF(K64=0,"",K63/K64),"")
D64: Total Debt (= Borrowings + Lease Liabilities) | F64: =(0+LTI_HIST_CON!E77+0+0) | G64: =(0+LTI_HIST_CON!F77+0+0) | H64: =(0+LTI_HIST_CON!G77+0+0) | I64: =(0+LTI_HIST_CON!H77+0+0) | J64: =(0+LTI_HIST_CON!I77+0+0) | K64: =(0+LTI_HIST_CON!J77+0+0)
B66: Interest Burden | C66: = | D66: EBT (Pre-Tax Income) | E66: = | F66: =+F44 | G66: =+G44 | H66: =+H44 | I66: =+I44 | J66: =+J44 | K66: =+K44 | L66: = | M66: =IFERROR(IF(F67=0,"",F66/F67),"") | N66: =IFERROR(IF(G67=0,"",G66/G67),"") | O66: =IFERROR(IF(H67=0,"",H66/H67),"") | P66: =IFERROR(IF(I67=0,"",I66/I67),"") | Q66: =IFERROR(IF(J67=0,"",J66/J67),"") | R66: =IFERROR(IF(K67=0,"",K66/K67),"")
D67: EBIT | F67: =+F36 | G67: =+G36 | H67: =+H36 | I67: =+I36 | J67: =+J36 | K67: =+K36
A69: # | B69: Asset Utilization Ratios
B70: Asset Turnover | C70: = | D70: Revenue | E70: = | F70: =+F20 | G70: =+G20 | H70: =+H20 | I70: =+I20 | J70: =+J20 | K70: =+K20 | L70: = | M70: =IFERROR(IF(F71=0,"",F70/F71),"") | N70: =IFERROR(IF(G71=0,"",G70/G71),"") | O70: =IFERROR(IF(H71=0,"",H70/H71),"") | P70: =IFERROR(IF(I71=0,"",I70/I71),"") | Q70: =IFERROR(IF(J71=0,"",J70/J71),"") | R70: =IFERROR(IF(K71=0,"",K70/K71),"")
D71: Total Assets | F71: =+F11 | G71: =+G11 | H71: =+H11 | I71: =+I11 | J71: =+J11 | K71: =+K11
B73: PPE Turnover | C73: = | D73: Revenue | E73: = | F73: =+F20 | G73: =+G20 | H73: =+H20 | I73: =+I20 | J73: =+J20 | K73: =+K20 | L73: = | M73: =IFERROR(IF(F74=0,"",F73/F74),"") | N73: =IFERROR(IF(G74=0,"",G73/G74),"") | O73: =IFERROR(IF(H74=0,"",H73/H74),"") | P73: =IFERROR(IF(I74=0,"",I73/I74),"") | Q73: =IFERROR(IF(J74=0,"",J73/J74),"") | R73: =IFERROR(IF(K74=0,"",K73/K74),"")
D74: Net PP&E | F74: =LTI_HIST_CON!E27 | G74: =LTI_HIST_CON!F27 | H74: =LTI_HIST_CON!G27 | I74: =LTI_HIST_CON!H27 | J74: =LTI_HIST_CON!I27 | K74: =LTI_HIST_CON!J27
B76: Cash Turnover | C76: = | D76: Revenue | E76: = | F76: =+F20 | G76: =+G20 | H76: =+H20 | I76: =+I20 | J76: =+J20 | K76: =+K20 | L76: = | M76: =IFERROR(IF(F77=0,"",F76/F77),"") | N76: =IFERROR(IF(G77=0,"",G76/G77),"") | O76: =IFERROR(IF(H77=0,"",H76/H77),"") | P76: =IFERROR(IF(I77=0,"",I76/I77),"") | Q76: =IFERROR(IF(J77=0,"",J76/J77),"") | R76: =IFERROR(IF(K77=0,"",K76/K77),"")
D77: Cash & Cash Equivalents | F77: =LTI_HIST_CON!E49 | G77: =LTI_HIST_CON!F49 | H77: =LTI_HIST_CON!G49 | I77: =LTI_HIST_CON!H49 | J77: =LTI_HIST_CON!I49 | K77: =LTI_HIST_CON!J49
B79: Cash Days | C79: = | D79: 365 (days) | E79: = | F79: 365 | G79: 365 | H79: 365 | I79: 365 | J79: 365 | K79: 365 | L79: = | M79: =IFERROR(IF(F80=0,"",F79/F80),"") | N79: =IFERROR(IF(G80=0,"",G79/G80),"") | O79: =IFERROR(IF(H80=0,"",H79/H80),"") | P79: =IFERROR(IF(I80=0,"",I79/I80),"") | Q79: =IFERROR(IF(J80=0,"",J79/J80),"") | R79: =IFERROR(IF(K80=0,"",K79/K80),"")
D80: Turnover (above) | F80: =+M76 | G80: =+N76 | H80: =+O76 | I80: =+P76 | J80: =+Q76 | K80: =+R76
B82: A/R Turnover | C82: = | D82: Revenue | E82: = | F82: =+F20 | G82: =+G20 | H82: =+H20 | I82: =+I20 | J82: =+J20 | K82: =+K20 | L82: = | M82: =IFERROR(IF(F83=0,"",F82/F83),"") | N82: =IFERROR(IF(G83=0,"",G82/G83),"") | O82: =IFERROR(IF(H83=0,"",H82/H83),"") | P82: =IFERROR(IF(I83=0,"",I82/I83),"") | Q82: =IFERROR(IF(J83=0,"",J82/J83),"") | R82: =IFERROR(IF(K83=0,"",K82/K83),"")
D83: Trade Receivables, Current | F83: =LTI_HIST_CON!E44 | G83: =LTI_HIST_CON!F44 | H83: =LTI_HIST_CON!G44 | I83: =LTI_HIST_CON!H44 | J83: =LTI_HIST_CON!I44 | K83: =LTI_HIST_CON!J44
B85: A/R Days | C85: = | D85: 365 (days) | E85: = | F85: 365 | G85: 365 | H85: 365 | I85: 365 | J85: 365 | K85: 365 | L85: = | M85: =IFERROR(IF(F86=0,"",F85/F86),"") | N85: =IFERROR(IF(G86=0,"",G85/G86),"") | O85: =IFERROR(IF(H86=0,"",H85/H86),"") | P85: =IFERROR(IF(I86=0,"",I85/I86),"") | Q85: =IFERROR(IF(J86=0,"",J85/J86),"") | R85: =IFERROR(IF(K86=0,"",K85/K86),"")
D86: Turnover (above) | F86: =+M82 | G86: =+N82 | H86: =+O82 | I86: =+P82 | J86: =+Q82 | K86: =+R82
B88: Inventory Turnover | C88: = | D88: COGS (= Revenue − Gross Profit) | E88: = | F88: =LTI_HIST_CON!E7-LTI_HIST_CON!E11 | G88: =LTI_HIST_CON!F7-LTI_HIST_CON!F11 | H88: =LTI_HIST_CON!G7-LTI_HIST_CON!G11 | I88: =LTI_HIST_CON!H7-LTI_HIST_CON!H11 | J88: =LTI_HIST_CON!I7-LTI_HIST_CON!I11 | K88: =LTI_HIST_CON!J7-LTI_HIST_CON!J11 | L88: = | M88: =IFERROR(IF(F89=0,"",F88/F89),"") | N88: =IFERROR(IF(G89=0,"",G88/G89),"") | O88: =IFERROR(IF(H89=0,"",H88/H89),"") | P88: =IFERROR(IF(I89=0,"",I88/I89),"") | Q88: =IFERROR(IF(J89=0,"",J88/J89),"") | R88: =IFERROR(IF(K89=0,"",K88/K89),"")
D89: Inventory | F89: =0 | G89: =0 | H89: =0 | I89: =0 | J89: =0 | K89: =0
B91: Inventory Days | C91: = | D91: 365 (days) | E91: = | F91: 365 | G91: 365 | H91: 365 | I91: 365 | J91: 365 | K91: 365 | L91: = | M91: =IFERROR(IF(F92=0,"",F91/F92),"") | N91: =IFERROR(IF(G92=0,"",G91/G92),"") | O91: =IFERROR(IF(H92=0,"",H91/H92),"") | P91: =IFERROR(IF(I92=0,"",I91/I92),"") | Q91: =IFERROR(IF(J92=0,"",J91/J92),"") | R91: =IFERROR(IF(K92=0,"",K91/K92),"")
D92: Turnover (above) | F92: =+M88 | G92: =+N88 | H92: =+O88 | I92: =+P88 | J92: =+Q88 | K92: =+R88
B94: A/P Turnover | C94: = | D94: COGS (= Revenue − Gross Profit) | E94: = | F94: =+F88 | G94: =+G88 | H94: =+H88 | I94: =+I88 | J94: =+J88 | K94: =+K88 | L94: = | M94: =IFERROR(IF(F95=0,"",F94/F95),"") | N94: =IFERROR(IF(G95=0,"",G94/G95),"") | O94: =IFERROR(IF(H95=0,"",H94/H95),"") | P94: =IFERROR(IF(I95=0,"",I94/I95),"") | Q94: =IFERROR(IF(J95=0,"",J94/J95),"") | R94: =IFERROR(IF(K95=0,"",K94/K95),"")
D95: Trade Payables, Current | F95: =LTI_HIST_CON!E79 | G95: =LTI_HIST_CON!F79 | H95: =LTI_HIST_CON!G79 | I95: =LTI_HIST_CON!H79 | J95: =LTI_HIST_CON!I79 | K95: =LTI_HIST_CON!J79
B97: A/P Days | C97: = | D97: 365 (days) | E97: = | F97: 365 | G97: 365 | H97: 365 | I97: 365 | J97: 365 | K97: 365 | L97: = | M97: =IFERROR(IF(F98=0,"",F97/F98),"") | N97: =IFERROR(IF(G98=0,"",G97/G98),"") | O97: =IFERROR(IF(H98=0,"",H97/H98),"") | P97: =IFERROR(IF(I98=0,"",I97/I98),"") | Q97: =IFERROR(IF(J98=0,"",J97/J98),"") | R97: =IFERROR(IF(K98=0,"",K97/K98),"")
D98: Turnover (above) | F98: =+M94 | G98: =+N94 | H98: =+O94 | I98: =+P94 | J98: =+Q94 | K98: =+R94
B100: Cash Conversion Cycle | D100: (A/R Days + Inventory Days − A/P Days) | L100: = | M100: =N(M85)+N(M91)-N(M97) | N100: =N(N85)+N(N91)-N(N97) | O100: =N(O85)+N(O91)-N(O97) | P100: =N(P85)+N(P91)-N(P97) | Q100: =N(Q85)+N(Q91)-N(Q97) | R100: =N(R85)+N(R91)-N(R97)
A102: # | B102: Leverage Ratios
B103: Total Asset to Equity | C103: = | D103: Total Assets | E103: = | F103: =+F11 | G103: =+G11 | H103: =+H11 | I103: =+I11 | J103: =+J11 | K103: =+K11 | L103: = | M103: =IFERROR(IF(F104=0,"",F103/F104),"") | N103: =IFERROR(IF(G104=0,"",G103/G104),"") | O103: =IFERROR(IF(H104=0,"",H103/H104),"") | P103: =IFERROR(IF(I104=0,"",I103/I104),"") | Q103: =IFERROR(IF(J104=0,"",J103/J104),"") | R103: =IFERROR(IF(K104=0,"",K103/K104),"")
D104: Equity | F104: =+F8 | G104: =+G8 | H104: =+H8 | I104: =+I8 | J104: =+J8 | K104: =+K8
B106: Total Liabilities to Equity | C106: = | D106: Total Liabilities (= Total Assets − Equity) | E106: = | F106: =LTI_HIST_CON!E57-LTI_HIST_CON!E64 | G106: =LTI_HIST_CON!F57-LTI_HIST_CON!F64 | H106: =LTI_HIST_CON!G57-LTI_HIST_CON!G64 | I106: =LTI_HIST_CON!H57-LTI_HIST_CON!H64 | J106: =LTI_HIST_CON!I57-LTI_HIST_CON!I64 | K106: =LTI_HIST_CON!J57-LTI_HIST_CON!J64 | L106: = | M106: =IFERROR(IF(F107=0,"",F106/F107),"") | N106: =IFERROR(IF(G107=0,"",G106/G107),"") | O106: =IFERROR(IF(H107=0,"",H106/H107),"") | P106: =IFERROR(IF(I107=0,"",I106/I107),"") | Q106: =IFERROR(IF(J107=0,"",J106/J107),"") | R106: =IFERROR(IF(K107=0,"",K106/K107),"")
D107: Equity | F107: =+F8 | G107: =+G8 | H107: =+H8 | I107: =+I8 | J107: =+J8 | K107: =+K8
B109: Debt to Equity | C109: = | D109: Total Debt (= Borrowings + Lease Liabilities) | E109: = | F109: =+F64 | G109: =+G64 | H109: =+H64 | I109: =+I64 | J109: =+J64 | K109: =+K64 | L109: = | M109: =IFERROR(IF(F110=0,"",F109/F110),"") | N109: =IFERROR(IF(G110=0,"",G109/G110),"") | O109: =IFERROR(IF(H110=0,"",H109/H110),"") | P109: =IFERROR(IF(I110=0,"",I109/I110),"") | Q109: =IFERROR(IF(J110=0,"",J109/J110),"") | R109: =IFERROR(IF(K110=0,"",K109/K110),"")
D110: Equity | F110: =+F8 | G110: =+G8 | H110: =+H8 | I110: =+I8 | J110: =+J8 | K110: =+K8
B112: Debt to EBITDA | C112: = | D112: Total Debt (= Borrowings + Lease Liabilities) | E112: = | F112: =+F64 | G112: =+G64 | H112: =+H64 | I112: =+I64 | J112: =+J64 | K112: =+K64 | L112: = | M112: =IFERROR(IF(F113=0,"",F112/F113),"") | N112: =IFERROR(IF(G113=0,"",G112/G113),"") | O112: =IFERROR(IF(H113=0,"",H112/H113),"") | P112: =IFERROR(IF(I113=0,"",I112/I113),"") | Q112: =IFERROR(IF(J113=0,"",J112/J113),"") | R112: =IFERROR(IF(K113=0,"",K112/K113),"")
D113: EBITDA | F113: =+F28 | G113: =+G28 | H113: =+H28 | I113: =+I28 | J113: =+J28 | K113: =+K28
