Workbook

Sheet Cover Page
B2: Suzlon Energy Limited
B3: NSE: SUZLON | Discounted Cash Flow Valuation
B4: Valuation date: 26-Sep-2025
B7: Key Outputs
B8: Implied Value / Share | C8: =DCF!C33 -> 56.048728
B9: Actual Market Price | C9: ='WACC Schedule'!$C6 -> 56.04
B10: WACC | C10: ='WACC Schedule'!$C39 -> 0.078867218
B11: Terminal Growth Rate | C11: =DCF!C22 -> 0.0501
B12: Explicit Forecast Horizon | C12: ="10 years ("&DCF!C5&"-"&DCF!L5&")" -> 10 years (FY2026E-FY2035E)
B15: Contents
B16: Inputs & Assumptions
B17: HIST_CON
B18: HIST_STAND
B19: RATIO_ANALYSIS
B20: DUPONT_ANALYSIS
B21: Schedules
B22: WC_SCHEDULE
B23: P&L Schedule
B24: WACC Schedule
B25: DCF
B26: Sensitivity Tables
... B34: Academic valuation project -- not investment advice. Every figure on this page is a live formula referencing the schedules that follow; nothing here is a pasted value.

Sheet Inputs & Assumptions
A1: # | B1: Inputs & Assumptions -- forecast years only
B3: Driver | C3: FY? | D3: FY2017 | E3: FY2018 | F3: FY2019 | G3: FY2020 | H3: FY2021 | I3: FY2022 | J3: FY2023 | K3: FY2024 | L3: FY2025 | M3: FY2026E | N3: FY2027E | O3: FY2028E | P3: FY2029E | Q3: FY2030E | R3: FY2031E | S3: FY2032E | T3: FY2033E | U3: FY2034E | V3: FY2035E
A5: # | B5: Outlier Filter -- excludes statistically anomalous years (IQR fence on YoY growth) from the Terminal Growth Rate and PP&E Additions Growth trend regressions
B7: Suggested: Outlier Filter Enabled (1=on, 0=off) -- default 1 (>=5yr history, enough points for a meaningful IQR fence) | C7: 1
B8: INPUT: Outlier Filter Enabled (1=on, 0=off)
A10: # | B10: Terminal / Fade-Target Growth Rate (computed from this company's own full history)
B12: Suggested: Terminal Growth Rate -- MIN(this company's own full-history log-linear trend on Total Revenue, with statistically anomalous years excluded per the Outlier Filter above, the Risk-Free Rate). No company grows faster than the risk-free rate forever -- caps a fast-growing company's own historical trend (seen on AdaniPorts: ~16.5%/yr, which broke the Value-Driver TV formula outright) without hardcoding an external macro number; slow-growth companies (e.g. Suzlon, ~0.75%/yr) are unaffected since their own trend already sits below the cap. | C12: =MIN(SLOPE(Schedules!C18:L18,Schedules!C12:L12),'WACC Schedule'!$C$21) -> 0.047222046 | D12: =$C$12 -> 0.047222046 | E12: =$C$12 -> 0.047222046 | F12: =$C$12 -> 0.047222046 | G12: =$C$12 -> 0.047222046 | H12: =$C$12 -> 0.047222046 | I12: =$C$12 -> 0.047222046 | J12: =$C$12 -> 0.047222046 | K12: =$C$12 -> 0.047222046 | L12: =$C$12 -> 0.047222046
B13: INPUT: Terminal Growth Rate (used by the fade) | C13: 0.0501
B15: Suggested: Growth Fade Half-Life, years -- default 6yr | C15: 6
B16: INPUT: Growth Fade Half-Life, years
B18: Suggested: Products Revenue Growth % -- log-linear, last 3yr, half-life decay to terminal | C18: =IFERROR(IF('Inputs & Assumptions'!$C$13="",'Inputs & Assumptions'!$C$12,'Inputs & Assumptions'!$C$13)+(IF('Inputs & Assumptions'!$C$19="",SLOPE(Schedules!J13:L13,Schedules!J12:L12),'Inputs & Assumptions'!$C$19)-(IF('Inputs & Assumptions'!$C$13="",'Inputs & Assumptions'!$C$12,'Inputs & Assumptions'!$C$13)))*0.5^(1/(IF('Inputs & Assumptions'!$C$16="",'Inputs & Assumptions'!$C$15,'Inputs & Assumptions'!$C$16))),IF('Inputs & Assumptions'!$C$13="",'Inputs & Assumptions'!$C$12,'Inputs & Assumptions'!$C$13)) -> 0.33402942 | D18: =IFERROR(IF('Inputs & Assumptions'!$C$13="",'Inputs & Assumptions'!$C$12,'Inputs & Assumptions'!$C$13)+(IF('Inputs & Assumptions'!$C$19="",SLOPE(Schedules!J13:L13,Schedules!J12:L12),'Inputs & Assumptions'!$C$19)-(IF('Inputs & Assumptions'!$C$13="",'Inputs & Assumptions'!$C$12,'Inputs & Assumptions'!$C$13)))*0.5^(2/(IF('Inputs & Assumptions'!$C$16="",'Inputs & Assumptions'!$C$15,'Inputs & Assumptions'!$C$16))),IF('Inputs & Assumptions'!$C$13="",'Inputs & Assumptions'!$C$12,'Inputs & Assumptions'!$C$13)) -> 0.30305236 | E18: =IFERROR(IF('Inputs & Assumptions'!$C$13="",'Inputs & Assumptions'!$C$12,'Inputs & Assumptions'!$C$13)+(IF('Inputs & Assumptions'!$C$19="",SLOPE(Schedules!J13:L13,Schedules!J12:L12),'Inputs & Assumptions'!$C$19)-(IF('Inputs & Assumptions'!$C$13="",'Inputs & Assumptions'!$C$12,'Inputs & Assumptions'!$C$13)))*0.5^(3/(IF('Inputs & Assumptions'!$C$16="",'Inputs & Assumptions'!$C$15,'Inputs & Assumptions'!$C$16))),IF('Inputs & Assumptions'!$C$13="",'Inputs & Assumptions'!$C$12,'Inputs & Assumptions'!$C$13)) -> 0.27545493 | F18: =IFERROR(IF('Inputs & Assumptions'!$C$13="",'Inputs & Assumptions'!$C$12,'Inputs & Assumptions'!$C$13)+(IF('Inputs & Assumptions'!$C$19="",SLOPE(Schedules!J13:L13,Schedules!J12:L12),'Inputs & Assumptions'!$C$19)-(IF('Inputs & Assumptions'!$C$13="",'Inputs & Assumptions'!$C$12,'Inputs & Assumptions'!$C$13)))*0.5^(4/(IF('Inputs & Assumptions'!$C$16="",'Inputs & Assumptions'!$C$15,'Inputs & Assumptions'!$C$16))),IF('Inputs & Assumptions'!$C$13="",'Inputs & Assumptions'!$C$12,'Inputs & Assumptions'!$C$13)) -> 0.25086842 | G18: =IFERROR(IF('Inputs & Assumptions'!$C$13="",'Inputs & Assumptions'!$C$12,'Inputs & Assumptions'!$C$13)+(IF('Inputs & Assumptions'!$C$19="",SLOPE(Schedules!J13:L13,Schedules!J12:L12),'Inputs & Assumptions'!$C$19)-(IF('Inputs & Assumptions'!$C$13="",'Inputs & Assumptions'!$C$12,'Inputs & Assumptions'!$C$13)))*0.5^(5/(IF('Inputs & Assumptions'!$C$16="",'Inputs & Assumptions'!$C$15,'Inputs & Assumptions'!$C$16))),IF('Inputs & Assumptions'!$C$13="",'Inputs & Assumptions'!$C$12,'Inputs & Assumptions'!$C$13)) -> 0.22896433 | H18: =IFERROR(IF('Inputs & Assumptions'!$C$13="",'Inputs & Assumptions'!$C$12,'Inputs & Assumptions'!$C$13)+(IF('Inputs & Assumptions'!$C$19="",SLOPE(Schedules!J13:L13,Schedules!J12:L12),'Inputs & Assumptions'!$C$19)-(IF('Inputs & Assumptions'!$C$13="",'Inputs & Assumptions'!$C$12,'Inputs & Assumptions'!$C$13)))*0.5^(6/(IF('Inputs & Assumptions'!$C$16="",'Inputs & Assumptions'!$C$15,'Inputs & Assumptions'!$C$16))),IF('Inputs & Assumptions'!$C$13="",'Inputs & Assumptions'!$C$12,'Inputs & Assumptions'!$C$13)) -> 0.20945 | I18: =IFERROR(IF('Inputs & Assumptions'!$C$13="",'Inputs & Assumptions'!$C$12,'Inputs & Assumptions'!$C$13)+(IF('Inputs & Assumptions'!$C$19="",SLOPE(Schedules!J13:L13,Schedules!J12:L12),'Inputs & Assumptions'!$C$19)-(IF('Inputs & Assumptions'!$C$13="",'Inputs & Assumptions'!$C$12,'Inputs & Assumptions'!$C$13)))*0.5^(7/(IF('Inputs & Assumptions'!$C$16="",'Inputs & Assumptions'!$C$15,'Inputs & Assumptions'!$C$16))),IF('Inputs & Assumptions'!$C$13="",'Inputs & Assumptions'!$C$12,'Inputs & Assumptions'!$C$13)) -> 0.19206471 | J18: =IFERROR(IF('Inputs & Assumptions'!$C$13="",'Inputs & Assumptions'!$C$12,'Inputs & Assumptions'!$C$13)+(IF('Inputs & Assumptions'!$C$19="",SLOPE(Schedules!J13:L13,Schedules!J12:L12),'Inputs & Assumptions'!$C$19)-(IF('Inputs & Assumptions'!$C$13="",'Inputs & Assumptions'!$C$12,'Inputs & Assumptions'!$C$13)))*0.5^(8/(IF('Inputs & Assumptions'!$C$16="",'Inputs & Assumptions'!$C$15,'Inputs & Assumptions'!$C$16))),IF('Inputs & Assumptions'!$C$13="",'Inputs & Assumptions'!$C$12,'Inputs & Assumptions'!$C$13)) -> 0.17657618 | K18: =IFERROR(IF('Inputs & Assumptions'!$C$13="",'Inputs & Assumptions'!$C$12,'Inputs & Assumptions'!$C$13)+(IF('Inputs & Assumptions'!$C$19="",SLOPE(Schedules!J13:L13,Schedules!J12:L12),'Inputs & Assumptions'!$C$19)-(IF('Inputs & Assumptions'!$C$13="",'Inputs & Assumptions'!$C$12,'Inputs & Assumptions'!$C$13)))*0.5^(9/(IF('Inputs & Assumptions'!$C$16="",'Inputs & Assumptions'!$C$15,'Inputs & Assumptions'!$C$16))),IF('Inputs & Assumptions'!$C$13="",'Inputs & Assumptions'!$C$12,'Inputs & Assumptions'!$C$13)) -> 0.16277747 | L18: =IFERROR(IF('Inputs & Assumptions'!$C$13="",'Inputs & Assumptions'!$C$12,'Inputs & Assumptions'!$C$13)+(IF('Inputs & Assumptions'!$C$19="",SLOPE(Schedules!J13:L13,Schedules!J12:L12),'Inputs & Assumptions'!$C$19)-(IF('Inputs & Assumptions'!$C$13="",'Inputs & Assumptions'!$C$12,'Inputs & Assumptions'!$C$13)))*0.5^(10/(IF('Inputs & Assumptions'!$C$16="",'Inputs & Assumptions'!$C$15,'Inputs & Assumptions'!$C$16))),IF('Inputs & Assumptions'!$C$13="",'Inputs & Assumptions'!$C$12,'Inputs & Assumptions'!$C$13)) -> 0.15048421
B19: INPUT: Products Revenue Growth % (overrides the trend/fade) | C19: 0.3688
A21: # | B21: Misc. Revenue / WC Schedule Drivers
B23: Suggested: Misc. Other Operating Revenue % of Total Revenue, last 3yr avg | C23: =AVERAGE(Schedules!J24:L24) -> 0.0041451154 | D23: =$C$23 -> 0.0041451154 | E23: =$C$23 -> 0.0041451154 | F23: =$C$23 -> 0.0041451154 | G23: =$C$23 -> 0.0041451154 | H23: =$C$23 -> 0.0041451154 | I23: =$C$23 -> 0.0041451154 | J23: =$C$23 -> 0.0041451154 | K23: =$C$23 -> 0.0041451154 | L23: =$C$23 -> 0.0041451154
B24: INPUT: Misc. Other Operating Revenue % of Total Revenue
B26: Suggested: Services Revenue Growth % -- log-linear, last 3yr, half-life decay to terminal (simplified vs. an installed-base driver) | C26: =IFERROR(IF('Inputs & Assumptions'!$C$13="",'Inputs & Assumptions'!$C$12,'Inputs & Assumptions'!$C$13)+(IF('Inputs & Assumptions'!$C$27="",SLOPE(Schedules!J25:L25,Schedules!J12:L12),'Inputs & Assumptions'!$C$27)-(IF('Inputs & Assumptions'!$C$13="",'Inputs & Assumptions'!$C$12,'Inputs & Assumptions'!$C$13)))*0.5^(1/(IF('Inputs & Assumptions'!$C$16="",'Inputs & Assumptions'!$C$15,'Inputs & Assumptions'!$C$16))),IF('Inputs & Assumptions'!$C$13="",'Inputs & Assumptions'!$C$12,'Inputs & Assumptions'!$C$13)) -> 0.33402942 | D26: =IFERROR(IF('Inputs & Assumptions'!$C$13="",'Inputs & Assumptions'!$C$12,'Inputs & Assumptions'!$C$13)+(IF('Inputs & Assumptions'!$C$27="",SLOPE(Schedules!J25:L25,Schedules!J12:L12),'Inputs & Assumptions'!$C$27)-(IF('Inputs & Assumptions'!$C$13="",'Inputs & Assumptions'!$C$12,'Inputs & Assumptions'!$C$13)))*0.5^(2/(IF('Inputs & Assumptions'!$C$16="",'Inputs & Assumptions'!$C$15,'Inputs & Assumptions'!$C$16))),IF('Inputs & Assumptions'!$C$13="",'Inputs & Assumptions'!$C$12,'Inputs & Assumptions'!$C$13)) -> 0.30305236 | E26: =IFERROR(IF('Inputs & Assumptions'!$C$13="",'Inputs & Assumptions'!$C$12,'Inputs & Assumptions'!$C$13)+(IF('Inputs & Assumptions'!$C$27="",SLOPE(Schedules!J25:L25,Schedules!J12:L12),'Inputs & Assumptions'!$C$27)-(IF('Inputs & Assumptions'!$C$13="",'Inputs & Assumptions'!$C$12,'Inputs & Assumptions'!$C$13)))*0.5^(3/(IF('Inputs & Assumptions'!$C$16="",'Inputs & Assumptions'!$C$15,'Inputs & Assumptions'!$C$16))),IF('Inputs & Assumptions'!$C$13="",'Inputs & Assumptions'!$C$12,'Inputs & Assumptions'!$C$13)) -> 0.27545493 | F26: =IFERROR(IF('Inputs & Assumptions'!$C$13="",'Inputs & Assumptions'!$C$12,'Inputs & Assumptions'!$C$13)+(IF('Inputs & Assumptions'!$C$27="",SLOPE(Schedules!J25:L25,Schedules!J12:L12),'Inputs & Assumptions'!$C$27)-(IF('Inputs & Assumptions'!$C$13="",'Inputs & Assumptions'!$C$12,'Inputs & Assumptions'!$C$13)))*0.5^(4/(IF('Inputs & Assumptions'!$C$16="",'Inputs & Assumptions'!$C$15,'Inputs & Assumptions'!$C$16))),IF('Inputs & Assumptions'!$C$13="",'Inputs & Assumptions'!$C$12,'Inputs & Assumptions'!$C$13)) -> 0.25086842 | G26: =IFERROR(IF('Inputs & Assumptions'!$C$13="",'Inputs & Assumptions'!$C$12,'Inputs & Assumptions'!$C$13)+(IF('Inputs & Assumptions'!$C$27="",SLOPE(Schedules!J25:L25,Schedules!J12:L12),'Inputs & Assumptions'!$C$27)-(IF('Inputs & Assumptions'!$C$13="",'Inputs & Assumptions'!$C$12,'Inputs & Assumptions'!$C$13)))*0.5^(5/(IF('Inputs & Assumptions'!$C$16="",'Inputs & Assumptions'!$C$15,'Inputs & Assumptions'!$C$16))),IF('Inputs & Assumptions'!$C$13="",'Inputs & Assumptions'!$C$12,'Inputs & Assumptions'!$C$13)) -> 0.22896433 | H26: =IFERROR(IF('Inputs & Assumptions'!$C$13="",'Inputs & Assumptions'!$C$12,'Inputs & Assumptions'!$C$13)+(IF('Inputs & Assumptions'!$C$27="",SLOPE(Schedules!J25:L25,Schedules!J12:L12),'Inputs & Assumptions'!$C$27)-(IF('Inputs & Assumptions'!$C$13="",'Inputs & Assumptions'!$C$12,'Inputs & Assumptions'!$C$13)))*0.5^(6/(IF('Inputs & Assumptions'!$C$16="",'Inputs & Assumptions'!$C$15,'Inputs & Assumptions'!$C$16))),IF('Inputs & Assumptions'!$C$13="",'Inputs & Assumptions'!$C$12,'Inputs & Assumptions'!$C$13)) -> 0.20945 | I26: =IFERROR(IF('Inputs & Assumptions'!$C$13="",'Inputs & Assumptions'!$C$12,'Inputs & Assumptions'!$C$13)+(IF('Inputs & Assumptions'!$C$27="",SLOPE(Schedules!J25:L25,Schedules!J12:L12),'Inputs & Assumptions'!$C$27)-(IF('Inputs & Assumptions'!$C$13="",'Inputs & Assumptions'!$C$12,'Inputs & Assumptions'!$C$13)))*0.5^(7/(IF('Inputs & Assumptions'!$C$16="",'Inputs & Assumptions'!$C$15,'Inputs & Assumptions'!$C$16))),IF('Inputs & Assumptions'!$C$13="",'Inputs & Assumptions'!$C$12,'Inputs & Assumptions'!$C$13)) -> 0.19206471 | J26: =IFERROR(IF('Inputs & Assumptions'!$C$13="",'Inputs & Assumptions'!$C$12,'Inputs & Assumptions'!$C$13)+(IF('Inputs & Assumptions'!$C$27="",SLOPE(Schedules!J25:L25,Schedules!J12:L12),'Inputs & Assumptions'!$C$27)-(IF('Inputs & Assumptions'!$C$13="",'Inputs & Assumptions'!$C$12,'Inputs & Assumptions'!$C$13)))*0.5^(8/(IF('Inputs & Assumptions'!$C$16="",'Inputs & Assumptions'!$C$15,'Inputs & Assumptions'!$C$16))),IF('Inputs & Assumptions'!$C$13="",'Inputs & Assumptions'!$C$12,'Inputs & Assumptions'!$C$13)) -> 0.17657618 | K26: =IFERROR(IF('Inputs & Assumptions'!$C$13="",'Inputs & Assumptions'!$C$12,'Inputs & Assumptions'!$C$13)+(IF('Inputs & Assumptions'!$C$27="",SLOPE(Schedules!J25:L25,Schedules!J12:L12),'Inputs & Assumptions'!$C$27)-(IF('Inputs & Assumptions'!$C$13="",'Inputs & Assumptions'!$C$12,'Inputs & Assumptions'!$C$13)))*0.5^(9/(IF('Inputs & Assumptions'!$C$16="",'Inputs & Assumptions'!$C$15,'Inputs & Assumptions'!$C$16))),IF('Inputs & Assumptions'!$C$13="",'Inputs & Assumptions'!$C$12,'Inputs & Assumptions'!$C$13)) -> 0.16277747 | L26: =IFERROR(IF('Inputs & Assumptions'!$C$13="",'Inputs & Assumptions'!$C$12,'Inputs & Assumptions'!$C$13)+(IF('Inputs & Assumptions'!$C$27="",SLOPE(Schedules!J25:L25,Schedules!J12:L12),'Inputs & Assumptions'!$C$27)-(IF('Inputs & Assumptions'!$C$13="",'Inputs & Assumptions'!$C$12,'Inputs & Assumptions'!$C$13)))*0.5^(10/(IF('Inputs & Assumptions'!$C$16="",'Inputs & Assumptions'!$C$15,'Inputs & Assumptions'!$C$16))),IF('Inputs & Assumptions'!$C$13="",'Inputs & Assumptions'!$C$12,'Inputs & Assumptions'!$C$13)) -> 0.15048421
B27: INPUT: Services Revenue Growth % (overrides the trend/fade) | C27: 0.3688
A29: # | B29: Working Capital Schedule Drivers
B31: Suggested: COGS % of Revenue, last 3yr avg | C31: =AVERAGE(Schedules!J33:L33) -> -0.6252848 | D31: =$C$31 -> -0.6252848 | E31: =$C$31 -> -0.6252848 | F31: =$C$31 -> -0.6252848 | G31: =$C$31 -> -0.6252848 | H31: =$C$31 -> -0.6252848 | I31: =$C$31 -> -0.6252848 | J31: =$C$31 -> -0.6252848 | K31: =$C$31 -> -0.6252848 | L31: =$C$31 -> -0.6252848
B32: INPUT: COGS % of Revenue
B34: Suggested: Days Sales Outstanding, last 3yr avg | C34: =AVERAGE(Schedules!J40:L40) -> 101.14164 | D34: =$C$34 -> 101.14164 | E34: =$C$34 -> 101.14164 | F34: =$C$34 -> 101.14164 | G34: =$C$34 -> 101.14164 | H34: =$C$34 -> 101.14164 | I34: =$C$34 -> 101.14164 | J34: =$C$34 -> 101.14164 | K34: =$C$34 -> 101.14164 | L34: =$C$34 -> 101.14164
B35: INPUT: Days Sales Outstanding
B37: Suggested: Days Inventory Outstanding, last 3yr avg | C37: =AVERAGE(Schedules!J41:L41) -> 185.93274 | D37: =$C$37 -> 185.93274 | E37: =$C$37 -> 185.93274 | F37: =$C$37 -> 185.93274 | G37: =$C$37 -> 185.93274 | H37: =$C$37 -> 185.93274 | I37: =$C$37 -> 185.93274 | J37: =$C$37 -> 185.93274 | K37: =$C$37 -> 185.93274 | L37: =$C$37 -> 185.93274
B38: INPUT: Days Inventory Outstanding
B40: Suggested: Days Payable Outstanding, last 3yr avg | C40: =AVERAGE(Schedules!J42:L42) -> 135.49783 | D40: =$C$40 -> 135.49783 | E40: =$C$40 -> 135.49783 | F40: =$C$40 -> 135.49783 | G40: =$C$40 -> 135.49783 | H40: =$C$40 -> 135.49783 | I40: =$C$40 -> 135.49783 | J40: =$C$40 -> 135.49783 | K40: =$C$40 -> 135.49783 | L40: =$C$40 -> 135.49783
B41: INPUT: Days Payable Outstanding
A43: # | B43: PP&E Schedule Drivers
B45: Suggested: Additions Growth % -- log-linear, last 3yr, half-life decay to terminal | C45: =(IF('Inputs & Assumptions'!$C$13="",'Inputs & Assumptions'!$C$12,'Inputs & Assumptions'!$C$13)+(IF('Inputs & Assumptions'!$C$46="",MIN(SLOPE(Schedules!J74:L74,Schedules!J70:L70),'WACC Schedule'!$C$21),'Inputs & Assumptions'!$C$46)-(IF('Inputs & Assumptions'!$C$13="",'Inputs & Assumptions'!$C$12,'Inputs & Assumptions'!$C$13)))*0.5^(1/(IF('Inputs & Assumptions'!$C$16="",'Inputs & Assumptions'!$C$15,'Inputs & Assumptions'!$C$16)))) -> 0.047536034 | D45: =(IF('Inputs & Assumptions'!$C$13="",'Inputs & Assumptions'!$C$12,'Inputs & Assumptions'!$C$13)+(IF('Inputs & Assumptions'!$C$46="",MIN(SLOPE(Schedules!J74:L74,Schedules!J70:L70),'WACC Schedule'!$C$21),'Inputs & Assumptions'!$C$46)-(IF('Inputs & Assumptions'!$C$13="",'Inputs & Assumptions'!$C$12,'Inputs & Assumptions'!$C$13)))*0.5^(2/(IF('Inputs & Assumptions'!$C$16="",'Inputs & Assumptions'!$C$15,'Inputs & Assumptions'!$C$16)))) -> 0.047815766 | E45: =(IF('Inputs & Assumptions'!$C$13="",'Inputs & Assumptions'!$C$12,'Inputs & Assumptions'!$C$13)+(IF('Inputs & Assumptions'!$C$46="",MIN(SLOPE(Schedules!J74:L74,Schedules!J70:L70),'WACC Schedule'!$C$21),'Inputs & Assumptions'!$C$46)-(IF('Inputs & Assumptions'!$C$13="",'Inputs & Assumptions'!$C$12,'Inputs & Assumptions'!$C$13)))*0.5^(3/(IF('Inputs & Assumptions'!$C$16="",'Inputs & Assumptions'!$C$15,'Inputs & Assumptions'!$C$16)))) -> 0.048064979 | F45: =(IF('Inputs & Assumptions'!$C$13="",'Inputs & Assumptions'!$C$12,'Inputs & Assumptions'!$C$13)+(IF('Inputs & Assumptions'!$C$46="",MIN(SLOPE(Schedules!J74:L74,Schedules!J70:L70),'WACC Schedule'!$C$21),'Inputs & Assumptions'!$C$46)-(IF('Inputs & Assumptions'!$C$13="",'Inputs & Assumptions'!$C$12,'Inputs & Assumptions'!$C$13)))*0.5^(4/(IF('Inputs & Assumptions'!$C$16="",'Inputs & Assumptions'!$C$15,'Inputs & Assumptions'!$C$16)))) -> 0.048287003 | G45: =(IF('Inputs & Assumptions'!$C$13="",'Inputs & Assumptions'!$C$12,'Inputs & Assumptions'!$C$13)+(IF('Inputs & Assumptions'!$C$46="",MIN(SLOPE(Schedules!J74:L74,Schedules!J70:L70),'WACC Schedule'!$C$21),'Inputs & Assumptions'!$C$46)-(IF('Inputs & Assumptions'!$C$13="",'Inputs & Assumptions'!$C$12,'Inputs & Assumptions'!$C$13)))*0.5^(5/(IF('Inputs & Assumptions'!$C$16="",'Inputs & Assumptions'!$C$15,'Inputs & Assumptions'!$C$16)))) -> 0.048484803 | H45: =(IF('Inputs & Assumptions'!$C$13="",'Inputs & Assumptions'!$C$12,'Inputs & Assumptions'!$C$13)+(IF('Inputs & Assumptions'!$C$46="",MIN(SLOPE(Schedules!J74:L74,Schedules!J70:L70),'WACC Schedule'!$C$21),'Inputs & Assumptions'!$C$46)-(IF('Inputs & Assumptions'!$C$13="",'Inputs & Assumptions'!$C$12,'Inputs & Assumptions'!$C$13)))*0.5^(6/(IF('Inputs & Assumptions'!$C$16="",'Inputs & Assumptions'!$C$15,'Inputs & Assumptions'!$C$16)))) -> 0.048661023 | I45: =(IF('Inputs & Assumptions'!$C$13="",'Inputs & Assumptions'!$C$12,'Inputs & Assumptions'!$C$13)+(IF('Inputs & Assumptions'!$C$46="",MIN(SLOPE(Schedules!J74:L74,Schedules!J70:L70),'WACC Schedule'!$C$21),'Inputs & Assumptions'!$C$46)-(IF('Inputs & Assumptions'!$C$13="",'Inputs & Assumptions'!$C$12,'Inputs & Assumptions'!$C$13)))*0.5^(7/(IF('Inputs & Assumptions'!$C$16="",'Inputs & Assumptions'!$C$15,'Inputs & Assumptions'!$C$16)))) -> 0.048818017 | J45: =(IF('Inputs & Assumptions'!$C$13="",'Inputs & Assumptions'!$C$12,'Inputs & Assumptions'!$C$13)+(IF('Inputs & Assumptions'!$C$46="",MIN(SLOPE(Schedules!J74:L74,Schedules!J70:L70),'WACC Schedule'!$C$21),'Inputs & Assumptions'!$C$46)-(IF('Inputs & Assumptions'!$C$13="",'Inputs & Assumptions'!$C$12,'Inputs & Assumptions'!$C$13)))*0.5^(8/(IF('Inputs & Assumptions'!$C$16="",'Inputs & Assumptions'!$C$15,'Inputs & Assumptions'!$C$16)))) -> 0.048957883 | K45: =(IF('Inputs & Assumptions'!$C$13="",'Inputs & Assumptions'!$C$12,'Inputs & Assumptions'!$C$13)+(IF('Inputs & Assumptions'!$C$46="",MIN(SLOPE(Schedules!J74:L74,Schedules!J70:L70),'WACC Schedule'!$C$21),'Inputs & Assumptions'!$C$46)-(IF('Inputs & Assumptions'!$C$13="",'Inputs & Assumptions'!$C$12,'Inputs & Assumptions'!$C$13)))*0.5^(9/(IF('Inputs & Assumptions'!$C$16="",'Inputs & Assumptions'!$C$15,'Inputs & Assumptions'!$C$16)))) -> 0.04908249 | L45: =(IF('Inputs & Assumptions'!$C$13="",'Inputs & Assumptions'!$C$12,'Inputs & Assumptions'!$C$13)+(IF('Inputs & Assumptions'!$C$46="",MIN(SLOPE(Schedules!J74:L74,Schedules!J70:L70),'WACC Schedule'!$C$21),'Inputs & Assumptions'!$C$46)-(IF('Inputs & Assumptions'!$C$13="",'Inputs & Assumptions'!$C$12,'Inputs & Assumptions'!$C$13)))*0.5^(10/(IF('Inputs & Assumptions'!$C$16="",'Inputs & Assumptions'!$C$15,'Inputs & Assumptions'!$C$16)))) -> 0.049193501
B46: INPUT: Additions Growth % (overrides the trend/fade)
B48: Suggested: New Asset Useful Life, years -- Ind AS Schedule II general Plant & Machinery default (15yr, generic regulatory constant) | C48: 15
B49: INPUT: New Asset Useful Life, years
B51: Suggested: Impairment, % of Opening PP&E, last 3yr avg | C51: =AVERAGE(Schedules!J77:L77) -> 0 | D51: =$C$51 -> 0 | E51: =$C$51 -> 0 | F51: =$C$51 -> 0 | G51: =$C$51 -> 0 | H51: =$C$51 -> 0 | I51: =$C$51 -> 0 | J51: =$C$51 -> 0 | K51: =$C$51 -> 0 | L51: =$C$51 -> 0
B52: INPUT: Impairment % of Opening PP&E
B54: Suggested: Other Changes, % of Opening PP&E, last 3yr avg | C54: =AVERAGE(Schedules!J78:L78) -> 0 | D54: =$C$54 -> 0 | E54: =$C$54 -> 0 | F54: =$C$54 -> 0 | G54: =$C$54 -> 0 | H54: =$C$54 -> 0 | I54: =$C$54 -> 0 | J54: =$C$54 -> 0 | K54: =$C$54 -> 0 | L54: =$C$54 -> 0
B55: INPUT: Other Changes % of Opening PP&E
B57: Suggested: Disposals, % of Opening PP&E, last 3yr avg | C57: =AVERAGE(Schedules!J79:L79) -> 0 | D57: =$C$57 -> 0 | E57: =$C$57 -> 0 | F57: =$C$57 -> 0 | G57: =$C$57 -> 0 | H57: =$C$57 -> 0 | I57: =$C$57 -> 0 | J57: =$C$57 -> 0 | K57: =$C$57 -> 0 | L57: =$C$57 -> 0
B58: INPUT: Disposals % of Opening PP&E
A60: # | B60: Debt Schedule Drivers
B62: Suggested: Include Lease Liabilities as Quasi-Debt (1=yes, 0=no) -- default 0 (Borrowings only) | C62: 0
B63: INPUT: Include Lease Liabilities as Quasi-Debt (1=yes, 0=no)
B65: Suggested: Effective Interest Rate % -- weighted avg (SUM Interest/SUM Avg Debt), last 3yr | C65: =SUM(Schedules!J98:L98)/SUM(Schedules!J96:L96) -> 0.11104727 | D65: =$C$65 -> 0.11104727 | E65: =$C$65 -> 0.11104727 | F65: =$C$65 -> 0.11104727 | G65: =$C$65 -> 0.11104727 | H65: =$C$65 -> 0.11104727 | I65: =$C$65 -> 0.11104727 | J65: =$C$65 -> 0.11104727 | K65: =$C$65 -> 0.11104727 | L65: =$C$65 -> 0.11104727
B66: INPUT: Effective Interest Rate %
B68: Suggested: Target Debt/Capitalization Ratio -- last actual year (no fade by default, generic) | C68: =MAX(0,MIN(0.95,(Schedules!L93/(Schedules!L93+(Schedules!L132+Schedules!L140))))) -> 0.044346186 | D68: =$C$68 -> 0.044346186 | E68: =$C$68 -> 0.044346186 | F68: =$C$68 -> 0.044346186 | G68: =$C$68 -> 0.044346186 | H68: =$C$68 -> 0.044346186 | I68: =$C$68 -> 0.044346186 | J68: =$C$68 -> 0.044346186 | K68: =$C$68 -> 0.044346186 | L68: =$C$68 -> 0.044346186
B69: INPUT: Target Debt/Capitalization Ratio
A71: # | B71: Tax Schedule Drivers
B73: Suggested: Statutory Corporate Tax Rate -- 25.17% (India Section 115BAA default; override for a different jurisdiction) | C73: 0.2517
B74: INPUT: Statutory Corporate Tax Rate
B76: Suggested: Current Tax (MAT-floor) Rate -- materiality/plausibility-filtered avg, last 3yr, widening to full history if none qualify | C76: =IFERROR(AVERAGEIFS(Schedules!J120:L120,Schedules!J119:L119,1),IFERROR(AVERAGEIFS(Schedules!C120:L120,Schedules!C119:L119,1),0)) -> 0.0053198481 | D76: =$C$76 -> 0.0053198481 | E76: =$C$76 -> 0.0053198481 | F76: =$C$76 -> 0.0053198481 | G76: =$C$76 -> 0.0053198481 | H76: =$C$76 -> 0.0053198481 | I76: =$C$76 -> 0.0053198481 | J76: =$C$76 -> 0.0053198481 | K76: =$C$76 -> 0.0053198481 | L76: =$C$76 -> 0.0053198481
B77: INPUT: Current Tax (MAT-floor) Rate
A79: # | B79: Equity Schedule Drivers
B81: Suggested: Dividend Payout %, last 3yr avg | C81: =AVERAGE(Schedules!J142:L142) -> 0 | D81: =$C$81 -> 0 | E81: =$C$81 -> 0 | F81: =$C$81 -> 0 | G81: =$C$81 -> 0 | H81: =$C$81 -> 0 | I81: =$C$81 -> 0 | J81: =$C$81 -> 0 | K81: =$C$81 -> 0 | L81: =$C$81 -> 0
B82: INPUT: Dividend Payout %
A84: # | B84: P&L Schedule Drivers
B86: Suggested: Employee Benefit Expense, % of Revenue, last 3yr avg | C86: =-AVERAGE('P&L Schedule'!J9:L9)/AVERAGE('P&L Schedule'!J7:L7) -> 0.096353641 | D86: =$C$86 -> 0.096353641 | E86: =$C$86 -> 0.096353641 | F86: =$C$86 -> 0.096353641 | G86: =$C$86 -> 0.096353641 | H86: =$C$86 -> 0.096353641 | I86: =$C$86 -> 0.096353641 | J86: =$C$86 -> 0.096353641 | K86: =$C$86 -> 0.096353641 | L86: =$C$86 -> 0.096353641
B87: INPUT: Employee Benefit Expense, % of Revenue
B89: Suggested: Other Expenses, % of Revenue, last 3yr avg | C89: =-AVERAGE('P&L Schedule'!J10:L10)/AVERAGE('P&L Schedule'!J7:L7) -> 0.1182713 | D89: =$C$89 -> 0.1182713 | E89: =$C$89 -> 0.1182713 | F89: =$C$89 -> 0.1182713 | G89: =$C$89 -> 0.1182713 | H89: =$C$89 -> 0.1182713 | I89: =$C$89 -> 0.1182713 | J89: =$C$89 -> 0.1182713 | K89: =$C$89 -> 0.1182713 | L89: =$C$89 -> 0.1182713
B90: INPUT: Other Expenses, % of Revenue
B92: Suggested: Other Income, % of Revenue, last 3yr avg | C92: =AVERAGE('P&L Schedule'!J16:L16)/AVERAGE('P&L Schedule'!J7:L7) -> 0.0069022838 | D92: =$C$92 -> 0.0069022838 | E92: =$C$92 -> 0.0069022838 | F92: =$C$92 -> 0.0069022838 | G92: =$C$92 -> 0.0069022838 | H92: =$C$92 -> 0.0069022838 | I92: =$C$92 -> 0.0069022838 | J92: =$C$92 -> 0.0069022838 | K92: =$C$92 -> 0.0069022838 | L92: =$C$92 -> 0.0069022838
B93: INPUT: Other Income, % of Revenue
B95: Suggested: D&A Uplift Ratio, last 3yr avg | C95: =AVERAGE('P&L Schedule'!J30:L30) -> 1.5247755 | D95: =$C$95 -> 1.5247755 | E95: =$C$95 -> 1.5247755 | F95: =$C$95 -> 1.5247755 | G95: =$C$95 -> 1.5247755 | H95: =$C$95 -> 1.5247755 | I95: =$C$95 -> 1.5247755 | J95: =$C$95 -> 1.5247755 | K95: =$C$95 -> 1.5247755 | L95: =$C$95 -> 1.5247755
B96: INPUT: D&A Uplift Ratio
B98: Suggested: Finance Cost Uplift Ratio, last 3yr avg | C98: =AVERAGE('P&L Schedule'!J32:L32) -> 1.6883509 | D98: =$C$98 -> 1.6883509 | E98: =$C$98 -> 1.6883509 | F98: =$C$98 -> 1.6883509 | G98: =$C$98 -> 1.6883509 | H98: =$C$98 -> 1.6883509 | I98: =$C$98 -> 1.6883509 | J98: =$C$98 -> 1.6883509 | K98: =$C$98 -> 1.6883509 | L98: =$C$98 -> 1.6883509
B99: INPUT: Finance Cost Uplift Ratio

Sheet HIST_CON
A1: Suzlon — Derived Financial Model
A2: Green = cross-sheet formula (XLOOKUP against raw data) | Black = same-sheet formula (subtotal/total)
A5: # | B5: Statement of Profit and Loss | E5: FY? | F5: FY2017 | G5: FY2018 | H5: FY2019 | I5: FY2020 | J5: FY2021 | K5: FY2022 | L5: FY2023 | M5: FY2024 | N5: FY2025
B6: Income [Abstract]
C7: Total revenue from operations | E7: =_xlfn.XLOOKUP("RevenueFromOperations",HS_CONSOLIDATED!$C:$C,HS_CONSOLIDATED!D:D,0,0,1) -> 0 | F7: =_xlfn.XLOOKUP("RevenueFromOperations",HS_CONSOLIDATED!$C:$C,HS_CONSOLIDATED!E:E,0,0,1) -> 127143700000 | G7: =_xlfn.XLOOKUP("RevenueFromOperations",HS_CONSOLIDATED!$C:$C,HS_CONSOLIDATED!F:F,0,0,1) -> 83338400000 | H7: =_xlfn.XLOOKUP("RevenueFromOperations",HS_CONSOLIDATED!$C:$C,HS_CONSOLIDATED!G:G,0,0,1) -> 50246900000 | I7: =_xlfn.XLOOKUP("RevenueFromOperations",HS_CONSOLIDATED!$C:$C,HS_CONSOLIDATED!H:H,0,0,1) -> 29728500000 | J7: =_xlfn.XLOOKUP("RevenueFromOperations",HS_CONSOLIDATED!$C:$C,HS_CONSOLIDATED!I:I,0,0,1) -> 33457200000 | K7: =_xlfn.XLOOKUP("RevenueFromOperations",HS_CONSOLIDATED!$C:$C,HS_CONSOLIDATED!J:J,0,0,1) -> 65817800000 | L7: =_xlfn.XLOOKUP("RevenueFromOperations",HS_CONSOLIDATED!$C:$C,HS_CONSOLIDATED!K:K,0,0,1) -> 59705300000 | M7: =_xlfn.XLOOKUP("RevenueFromOperations",HS_CONSOLIDATED!$C:$C,HS_CONSOLIDATED!L:L,0,0,1) -> 65290900000 | N7: =_xlfn.XLOOKUP("RevenueFromOperations",HS_CONSOLIDATED!$C:$C,HS_CONSOLIDATED!M:M,0,0,1) -> 108897400000
C8: Total other income | E8: =_xlfn.XLOOKUP("OtherIncome",HS_CONSOLIDATED!$C:$C,HS_CONSOLIDATED!D:D,0,0,1) -> 0 | F8: =_xlfn.XLOOKUP("OtherIncome",HS_CONSOLIDATED!$C:$C,HS_CONSOLIDATED!E:E,0,0,1) -> 888200000 | G8: =_xlfn.XLOOKUP("OtherIncome",HS_CONSOLIDATED!$C:$C,HS_CONSOLIDATED!F:F,0,0,1) -> 791700000 | H8: =_xlfn.XLOOKUP("OtherIncome",HS_CONSOLIDATED!$C:$C,HS_CONSOLIDATED!G:G,0,0,1) -> 499500000 | I8: =_xlfn.XLOOKUP("OtherIncome",HS_CONSOLIDATED!$C:$C,HS_CONSOLIDATED!H:H,0,0,1) -> 275700000 | J8: =_xlfn.XLOOKUP("OtherIncome",HS_CONSOLIDATED!$C:$C,HS_CONSOLIDATED!I:I,0,0,1) -> 198700000 | K8: =_xlfn.XLOOKUP("OtherIncome",HS_CONSOLIDATED!$C:$C,HS_CONSOLIDATED!J:J,0,0,1) -> 221900000 | L8: =_xlfn.XLOOKUP("OtherIncome",HS_CONSOLIDATED!$C:$C,HS_CONSOLIDATED!K:K,0,0,1) -> 196300000 | M8: =_xlfn.XLOOKUP("OtherIncome",HS_CONSOLIDATED!$C:$C,HS_CONSOLIDATED!L:L,0,0,1) -> 384200000 | N8: =_xlfn.XLOOKUP("OtherIncome",HS_CONSOLIDATED!$C:$C,HS_CONSOLIDATED!M:M,0,0,1) -> 1033900000
C9: Total income | E9: =IFERROR(SUM(E7:E8),0) -> 0 | F9: =IFERROR(SUM(F7:F8),0) -> 128031900000 | G9: =IFERROR(SUM(G7:G8),0) -> 84130100000 | H9: =IFERROR(SUM(H7:H8),0) -> 50746400000 | I9: =IFERROR(SUM(I7:I8),0) -> 30004200000 | J9: =IFERROR(SUM(J7:J8),0) -> 33655900000 | K9: =IFERROR(SUM(K7:K8),0) -> 66039700000 | L9: =IFERROR(SUM(L7:L8),0) -> 59901600000 | ... N9: =IFERROR(SUM(N7:N8),0) -> 109931300000
B10: COGS
C11: Cost of materials consumed | E11: =-_xlfn.XLOOKUP("CostOfMaterialsConsumed",HS_CONSOLIDATED!$C:$C,HS_CONSOLIDATED!D:D,0,0,1) -> 0 | F11: =-_xlfn.XLOOKUP("CostOfMaterialsConsumed",HS_CONSOLIDATED!$C:$C,HS_CONSOLIDATED!E:E,0,0,1) -> -82914400000 | G11: =-_xlfn.XLOOKUP("CostOfMaterialsConsumed",HS_CONSOLIDATED!$C:$C,HS_CONSOLIDATED!F:F,0,0,1) -> -40319900000 | H11: =-_xlfn.XLOOKUP("CostOfMaterialsConsumed",HS_CONSOLIDATED!$C:$C,HS_CONSOLIDATED!G:G,0,0,1) -> -29565000000 | I11: =-_xlfn.XLOOKUP("CostOfMaterialsConsumed",HS_CONSOLIDATED!$C:$C,HS_CONSOLIDATED!H:H,0,0,1) -> -14044100000 | J11: =-_xlfn.XLOOKUP("CostOfMaterialsConsumed",HS_CONSOLIDATED!$C:$C,HS_CONSOLIDATED!I:I,0,0,1) -> -16107500000 | K11: =-_xlfn.XLOOKUP("CostOfMaterialsConsumed",HS_CONSOLIDATED!$C:$C,HS_CONSOLIDATED!J:J,0,0,1) -> -40919500000 | L11: =-_xlfn.XLOOKUP("CostOfMaterialsConsumed",HS_CONSOLIDATED!$C:$C,HS_CONSOLIDATED!K:K,0,0,1) -> -36267600000 | M11: =-_xlfn.XLOOKUP("CostOfMaterialsConsumed",HS_CONSOLIDATED!$C:$C,HS_CONSOLIDATED!L:L,0,0,1) -> -40186500000 | N11: =-_xlfn.XLOOKUP("CostOfMaterialsConsumed",HS_CONSOLIDATED!$C:$C,HS_CONSOLIDATED!M:M,0,0,1) -> -71391700000
C12: Purchases of stock-in-trade | E12: =-_xlfn.XLOOKUP("PurchasesOfStockInTrade",HS_CONSOLIDATED!$C:$C,HS_CONSOLIDATED!D:D,0,0,1) -> 0 | F12: =-_xlfn.XLOOKUP("PurchasesOfStockInTrade",HS_CONSOLIDATED!$C:$C,HS_CONSOLIDATED!E:E,0,0,1) -> 0 | G12: =-_xlfn.XLOOKUP("PurchasesOfStockInTrade",HS_CONSOLIDATED!$C:$C,HS_CONSOLIDATED!F:F,0,0,1) -> -9879500000 | H12: =-_xlfn.XLOOKUP("PurchasesOfStockInTrade",HS_CONSOLIDATED!$C:$C,HS_CONSOLIDATED!G:G,0,0,1) -> 0 | I12: =-_xlfn.XLOOKUP("PurchasesOfStockInTrade",HS_CONSOLIDATED!$C:$C,HS_CONSOLIDATED!H:H,0,0,1) -> 0 | J12: =-_xlfn.XLOOKUP("PurchasesOfStockInTrade",HS_CONSOLIDATED!$C:$C,HS_CONSOLIDATED!I:I,0,0,1) -> 0 | K12: =-_xlfn.XLOOKUP("PurchasesOfStockInTrade",HS_CONSOLIDATED!$C:$C,HS_CONSOLIDATED!J:J,0,0,1) -> 0 | L12: =-_xlfn.XLOOKUP("PurchasesOfStockInTrade",HS_CONSOLIDATED!$C:$C,HS_CONSOLIDATED!K:K,0,0,1) -> 0 | M12: =-_xlfn.XLOOKUP("PurchasesOfStockInTrade",HS_CONSOLIDATED!$C:$C,HS_CONSOLIDATED!L:L,0,0,1) -> 0 | N12: =-_xlfn.XLOOKUP("PurchasesOfStockInTrade",HS_CONSOLIDATED!$C:$C,HS_CONSOLIDATED!M:M,0,0,1) -> 0
C13: Total changes in inventories of finished goods, work-in-progress and stock-in-trade | E13: =-_xlfn.XLOOKUP("ChangesInInventoriesOfFinishedGoodsWorkInProgressAndStockInTrade",HS_CONSOLIDATED!$C:$C,HS_CONSOLIDATED!D:D,0,0,1) -> 0 | F13: =-_xlfn.XLOOKUP("ChangesInInventoriesOfFinishedGoodsWorkInProgressAndStockInTrade",HS_CONSOLIDATED!$C:$C,HS_CONSOLIDATED!E:E,0,0,1) -> 7485500000 | G13: =-_xlfn.XLOOKUP("ChangesInInventoriesOfFinishedGoodsWorkInProgressAndStockInTrade",HS_CONSOLIDATED!$C:$C,HS_CONSOLIDATED!F:F,0,0,1) -> -957700000 | H13: =-_xlfn.XLOOKUP("ChangesInInventoriesOfFinishedGoodsWorkInProgressAndStockInTrade",HS_CONSOLIDATED!$C:$C,HS_CONSOLIDATED!G:G,0,0,1) -> -418500000 | I13: =-_xlfn.XLOOKUP("ChangesInInventoriesOfFinishedGoodsWorkInProgressAndStockInTrade",HS_CONSOLIDATED!$C:$C,HS_CONSOLIDATED!H:H,0,0,1) -> -4691000000 | J13: =-_xlfn.XLOOKUP("ChangesInInventoriesOfFinishedGoodsWorkInProgressAndStockInTrade",HS_CONSOLIDATED!$C:$C,HS_CONSOLIDATED!I:I,0,0,1) -> 334800000 | K13: =-_xlfn.XLOOKUP("ChangesInInventoriesOfFinishedGoodsWorkInProgressAndStockInTrade",HS_CONSOLIDATED!$C:$C,HS_CONSOLIDATED!J:J,0,0,1) -> -2396100000 | L13: =-_xlfn.XLOOKUP("ChangesInInventoriesOfFinishedGoodsWorkInProgressAndStockInTrade",HS_CONSOLIDATED!$C:$C,HS_CONSOLIDATED!K:K,0,0,1) -> -1559000000 | M13: =-_xlfn.XLOOKUP("ChangesInInventoriesOfFinishedGoodsWorkInProgressAndStockInTrade",HS_CONSOLIDATED!$C:$C,HS_CONSOLIDATED!L:L,0,0,1) -> 365200000 | N13: =-_xlfn.XLOOKUP("ChangesInInventoriesOfFinishedGoodsWorkInProgressAndStockInTrade",HS_CONSOLIDATED!$C:$C,HS_CONSOLIDATED!M:M,0,0,1) -> 2525700000
B14: Gross Profit | E14: =IFERROR(E9+SUM(E11:E13),0) -> 0 | F14: =IFERROR(F9+SUM(F11:F13),0) -> 52603000000 | G14: =IFERROR(G9+SUM(G11:G13),0) -> 32973000000 | H14: =IFERROR(H9+SUM(H11:H13),0) -> 20762900000 | I14: =IFERROR(I9+SUM(I11:I13),0) -> 11269100000 | J14: =IFERROR(J9+SUM(J11:J13),0) -> 17883200000 | K14: =IFERROR(K9+SUM(K11:K13),0) -> 22724100000 | L14: =IFERROR(L9+SUM(L11:L13),0) -> 22075000000 | ... N14: =IFERROR(N9+SUM(N11:N13),0) -> 41065300000
C15: SG&A | E15: =-_xlfn.XLOOKUP("EmployeeBenefitExpense",HS_CONSOLIDATED!$C:$C,HS_CONSOLIDATED!D:D,0,0,1)-_xlfn.XLOOKUP("ExpenditureOnProductionTransportationAndOtherExpenditurePertainingToExplorationAndProductionActivities",HS_CONSOLIDATED!$C:$C,HS_CONSOLIDATED!D:D,0,0,1) -> 0 | F15: =-_xlfn.XLOOKUP("EmployeeBenefitExpense",HS_CONSOLIDATED!$C:$C,HS_CONSOLIDATED!E:E,0,0,1)-_xlfn.XLOOKUP("ExpenditureOnProductionTransportationAndOtherExpenditurePertainingToExplorationAndProductionActivities",HS_CONSOLIDATED!$C:$C,HS_CONSOLIDATED!E:E,0,0,1) -> -10464800000 | G15: =-_xlfn.XLOOKUP("EmployeeBenefitExpense",HS_CONSOLIDATED!$C:$C,HS_CONSOLIDATED!F:F,0,0,1)-_xlfn.XLOOKUP("ExpenditureOnProductionTransportationAndOtherExpenditurePertainingToExplorationAndProductionActivities",HS_CONSOLIDATED!$C:$C,HS_CONSOLIDATED!F:F,0,0,1) -> -8046800000 | H15: =-_xlfn.XLOOKUP("EmployeeBenefitExpense",HS_CONSOLIDATED!$C:$C,HS_CONSOLIDATED!G:G,0,0,1)-_xlfn.XLOOKUP("ExpenditureOnProductionTransportationAndOtherExpenditurePertainingToExplorationAndProductionActivities",HS_CONSOLIDATED!$C:$C,HS_CONSOLIDATED!G:G,0,0,1) -> -8741600000 | I15: =-_xlfn.XLOOKUP("EmployeeBenefitExpense",HS_CONSOLIDATED!$C:$C,HS_CONSOLIDATED!H:H,0,0,1)-_xlfn.XLOOKUP("ExpenditureOnProductionTransportationAndOtherExpenditurePertainingToExplorationAndProductionActivities",HS_CONSOLIDATED!$C:$C,HS_CONSOLIDATED!H:H,0,0,1) -> -7962500000 | J15: =-_xlfn.XLOOKUP("EmployeeBenefitExpense",HS_CONSOLIDATED!$C:$C,HS_CONSOLIDATED!I:I,0,0,1)-_xlfn.XLOOKUP("ExpenditureOnProductionTransportationAndOtherExpenditurePertainingToExplorationAndProductionActivities",HS_CONSOLIDATED!$C:$C,HS_CONSOLIDATED!I:I,0,0,1) -> -5532100000 | K15: =-_xlfn.XLOOKUP("EmployeeBenefitExpense",HS_CONSOLIDATED!$C:$C,HS_CONSOLIDATED!J:J,0,0,1)-_xlfn.XLOOKUP("ExpenditureOnProductionTransportationAndOtherExpenditurePertainingToExplorationAndProductionActivities",HS_CONSOLIDATED!$C:$C,HS_CONSOLIDATED!J:J,0,0,1) -> -5453600000 | L15: =-_xlfn.XLOOKUP("EmployeeBenefitExpense",HS_CONSOLIDATED!$C:$C,HS_CONSOLIDATED!K:K,0,0,1)-_xlfn.XLOOKUP("ExpenditureOnProductionTransportationAndOtherExpenditurePertainingToExplorationAndProductionActivities",HS_CONSOLIDATED!$C:$C,HS_CONSOLIDATED!K:K,0,0,1) -> -6092200000 | M15: =-_xlfn.XLOOKUP("EmployeeBenefitExpense",HS_CONSOLIDATED!$C:$C,HS_CONSOLIDATED!L:L,0,0,1)-_xlfn.XLOOKUP("ExpenditureOnProductionTransportationAndOtherExpenditurePertainingToExplorationAndProductionActivities",HS_CONSOLIDATED!$C:$C,HS_CONSOLIDATED!L:L,0,0,1) -> -7029000000 | N15: =-_xlfn.XLOOKUP("EmployeeBenefitExpense",HS_CONSOLIDATED!$C:$C,HS_CONSOLIDATED!M:M,0,0,1)-_xlfn.XLOOKUP("ExpenditureOnProductionTransportationAndOtherExpenditurePertainingToExplorationAndProductionActivities",HS_CONSOLIDATED!$C:$C,HS_CONSOLIDATED!M:M,0,0,1) -> -9415300000
C16: Total other expenses | E16: =-_xlfn.XLOOKUP("OtherExpenses",HS_CONSOLIDATED!$C:$C,HS_CONSOLIDATED!D:D,0,0,1) -> 0 | F16: =-_xlfn.XLOOKUP("OtherExpenses",HS_CONSOLIDATED!$C:$C,HS_CONSOLIDATED!E:E,0,0,1) -> -16256100000 | G16: =-_xlfn.XLOOKUP("OtherExpenses",HS_CONSOLIDATED!$C:$C,HS_CONSOLIDATED!F:F,0,0,1) -> -14103900000 | H16: =-_xlfn.XLOOKUP("OtherExpenses",HS_CONSOLIDATED!$C:$C,HS_CONSOLIDATED!G:G,0,0,1) -> -11609300000 | I16: =-_xlfn.XLOOKUP("OtherExpenses",HS_CONSOLIDATED!$C:$C,HS_CONSOLIDATED!H:H,0,0,1) -> -11628200000 | J16: =-_xlfn.XLOOKUP("OtherExpenses",HS_CONSOLIDATED!$C:$C,HS_CONSOLIDATED!I:I,0,0,1) -> -6809600000 | K16: =-_xlfn.XLOOKUP("OtherExpenses",HS_CONSOLIDATED!$C:$C,HS_CONSOLIDATED!J:J,0,0,1) -> -8154100000 | L16: =-_xlfn.XLOOKUP("OtherExpenses",HS_CONSOLIDATED!$C:$C,HS_CONSOLIDATED!K:K,0,0,1) -> -7467300000 | M16: =-_xlfn.XLOOKUP("OtherExpenses",HS_CONSOLIDATED!$C:$C,HS_CONSOLIDATED!L:L,0,0,1) -> -8151800000 | N16: =-_xlfn.XLOOKUP("OtherExpenses",HS_CONSOLIDATED!$C:$C,HS_CONSOLIDATED!M:M,0,0,1) -> -12043800000
B17: EBITDA | E17: =IFERROR(SUM(E14:E16),0) -> 0 | F17: =IFERROR(SUM(F14:F16),0) -> 25882100000 | G17: =IFERROR(SUM(G14:G16),0) -> 10822300000 | H17: =IFERROR(SUM(H14:H16),0) -> 412000000 | I17: =IFERROR(SUM(I14:I16),0) -> -8321600000 | J17: =IFERROR(SUM(J14:J16),0) -> 5541500000 | K17: =IFERROR(SUM(K14:K16),0) -> 9116400000 | L17: =IFERROR(SUM(L14:L16),0) -> 8515500000 | ... N17: =IFERROR(SUM(N14:N16),0) -> 19606200000
C18: D&A | E18: =-_xlfn.XLOOKUP("DepreciationDepletionAndAmortisationExpense",HS_CONSOLIDATED!$C:$C,HS_CONSOLIDATED!D:D,0,0,1) -> 0 | F18: =-_xlfn.XLOOKUP("DepreciationDepletionAndAmortisationExpense",HS_CONSOLIDATED!$C:$C,HS_CONSOLIDATED!E:E,0,0,1) -> -3890300000 | G18: =-_xlfn.XLOOKUP("DepreciationDepletionAndAmortisationExpense",HS_CONSOLIDATED!$C:$C,HS_CONSOLIDATED!F:F,0,0,1) -> -3416100000 | H18: =-_xlfn.XLOOKUP("DepreciationDepletionAndAmortisationExpense",HS_CONSOLIDATED!$C:$C,HS_CONSOLIDATED!G:G,0,0,1) -> -3418500000 | I18: =-_xlfn.XLOOKUP("DepreciationDepletionAndAmortisationExpense",HS_CONSOLIDATED!$C:$C,HS_CONSOLIDATED!H:H,0,0,1) -> -4186100000 | J18: =-_xlfn.XLOOKUP("DepreciationDepletionAndAmortisationExpense",HS_CONSOLIDATED!$C:$C,HS_CONSOLIDATED!I:I,0,0,1) -> -2583800000 | K18: =-_xlfn.XLOOKUP("DepreciationDepletionAndAmortisationExpense",HS_CONSOLIDATED!$C:$C,HS_CONSOLIDATED!J:J,0,0,1) -> -2598400000 | L18: =-_xlfn.XLOOKUP("DepreciationDepletionAndAmortisationExpense",HS_CONSOLIDATED!$C:$C,HS_CONSOLIDATED!K:K,0,0,1) -> -2596800000 | M18: =-_xlfn.XLOOKUP("DepreciationDepletionAndAmortisationExpense",HS_CONSOLIDATED!$C:$C,HS_CONSOLIDATED!L:L,0,0,1) -> -1896000000 | N18: =-_xlfn.XLOOKUP("DepreciationDepletionAndAmortisationExpense",HS_CONSOLIDATED!$C:$C,HS_CONSOLIDATED!M:M,0,0,1) -> -2591900000
B19: EBIT | E19: =IFERROR(SUM(E17:E18),0) -> 0 | F19: =IFERROR(SUM(F17:F18),0) -> 21991800000 | G19: =IFERROR(SUM(G17:G18),0) -> 7406200000 | H19: =IFERROR(SUM(H17:H18),0) -> -3006500000 | I19: =IFERROR(SUM(I17:I18),0) -> -12507700000 | J19: =IFERROR(SUM(J17:J18),0) -> 2957700000 | K19: =IFERROR(SUM(K17:K18),0) -> 6518000000 | L19: =IFERROR(SUM(L17:L18),0) -> 5918700000 | ... N19: =IFERROR(SUM(N17:N18),0) -> 17014300000
C20: Total finance costs | E20: =-_xlfn.XLOOKUP("FinanceCosts",HS_CONSOLIDATED!$C:$C,HS_CONSOLIDATED!D:D,0,0,1) -> 0 | F20: =-_xlfn.XLOOKUP("FinanceCosts",HS_CONSOLIDATED!$C:$C,HS_CONSOLIDATED!E:E,0,0,1) -> -12875900000 | G20: =-_xlfn.XLOOKUP("FinanceCosts",HS_CONSOLIDATED!$C:$C,HS_CONSOLIDATED!F:F,0,0,1) -> -15809800000 | H20: =-_xlfn.XLOOKUP("FinanceCosts",HS_CONSOLIDATED!$C:$C,HS_CONSOLIDATED!G:G,0,0,1) -> -12699100000 | I20: =-_xlfn.XLOOKUP("FinanceCosts",HS_CONSOLIDATED!$C:$C,HS_CONSOLIDATED!H:H,0,0,1) -> -13672900000 | J20: =-_xlfn.XLOOKUP("FinanceCosts",HS_CONSOLIDATED!$C:$C,HS_CONSOLIDATED!I:I,0,0,1) -> -9962600000 | K20: =-_xlfn.XLOOKUP("FinanceCosts",HS_CONSOLIDATED!$C:$C,HS_CONSOLIDATED!J:J,0,0,1) -> -7345200000 | L20: =-_xlfn.XLOOKUP("FinanceCosts",HS_CONSOLIDATED!$C:$C,HS_CONSOLIDATED!K:K,0,0,1) -> -4207600000 | M20: =-_xlfn.XLOOKUP("FinanceCosts",HS_CONSOLIDATED!$C:$C,HS_CONSOLIDATED!L:L,0,0,1) -> -1643200000 | N20: =-_xlfn.XLOOKUP("FinanceCosts",HS_CONSOLIDATED!$C:$C,HS_CONSOLIDATED!M:M,0,0,1) -> -2548000000
C21: Exceptional items before tax | E21: =_xlfn.XLOOKUP("ExceptionalItemsBeforeTax",HS_CONSOLIDATED!$C:$C,HS_CONSOLIDATED!D:D,0,0,1) -> 0 | F21: =_xlfn.XLOOKUP("ExceptionalItemsBeforeTax",HS_CONSOLIDATED!$C:$C,HS_CONSOLIDATED!E:E,0,0,1) -> 0 | G21: =_xlfn.XLOOKUP("ExceptionalItemsBeforeTax",HS_CONSOLIDATED!$C:$C,HS_CONSOLIDATED!F:F,0,0,1) -> 4496200000 | H21: =_xlfn.XLOOKUP("ExceptionalItemsBeforeTax",HS_CONSOLIDATED!$C:$C,HS_CONSOLIDATED!G:G,0,0,1) -> 275700000 | I21: =_xlfn.XLOOKUP("ExceptionalItemsBeforeTax",HS_CONSOLIDATED!$C:$C,HS_CONSOLIDATED!H:H,0,0,1) -> -658900000 | J21: =_xlfn.XLOOKUP("ExceptionalItemsBeforeTax",HS_CONSOLIDATED!$C:$C,HS_CONSOLIDATED!I:I,0,0,1) -> 8054600000 | K21: =_xlfn.XLOOKUP("ExceptionalItemsBeforeTax",HS_CONSOLIDATED!$C:$C,HS_CONSOLIDATED!J:J,0,0,1) -> 831200000 | L21: =_xlfn.XLOOKUP("ExceptionalItemsBeforeTax",HS_CONSOLIDATED!$C:$C,HS_CONSOLIDATED!K:K,0,0,1) -> 27206000000 | M21: =_xlfn.XLOOKUP("ExceptionalItemsBeforeTax",HS_CONSOLIDATED!$C:$C,HS_CONSOLIDATED!L:L,0,0,1) -> -538900000 | N21: =_xlfn.XLOOKUP("ExceptionalItemsBeforeTax",HS_CONSOLIDATED!$C:$C,HS_CONSOLIDATED!M:M,0,0,1) -> 0
B22: EBT | E22: =IFERROR(SUM(E19:E21),0) -> 0 | F22: =IFERROR(SUM(F19:F21),0) -> 9115900000 | G22: =IFERROR(SUM(G19:G21),0) -> -3907400000 | H22: =IFERROR(SUM(H19:H21),0) -> -15429900000 | I22: =IFERROR(SUM(I19:I21),0) -> -26839500000 | J22: =IFERROR(SUM(J19:J21),0) -> 1049700000 | K22: =IFERROR(SUM(K19:K21),0) -> 4000000 | L22: =IFERROR(SUM(L19:L21),0) -> 28917100000 | ... N22: =IFERROR(SUM(N19:N21),0) -> 14466300000
C23: Total current tax | E23: =-_xlfn.XLOOKUP("CurrentTax",HS_CONSOLIDATED!$C:$C,HS_CONSOLIDATED!D:D,0,0,1) -> 0 | F23: =-_xlfn.XLOOKUP("CurrentTax",HS_CONSOLIDATED!$C:$C,HS_CONSOLIDATED!E:E,0,0,1) -> -117000000 | G23: =-_xlfn.XLOOKUP("CurrentTax",HS_CONSOLIDATED!$C:$C,HS_CONSOLIDATED!F:F,0,0,1) -> 15600000 | H23: =-_xlfn.XLOOKUP("CurrentTax",HS_CONSOLIDATED!$C:$C,HS_CONSOLIDATED!G:G,0,0,1) -> -30900000 | I23: =-_xlfn.XLOOKUP("CurrentTax",HS_CONSOLIDATED!$C:$C,HS_CONSOLIDATED!H:H,0,0,1) -> -74400000 | J23: =-_xlfn.XLOOKUP("CurrentTax",HS_CONSOLIDATED!$C:$C,HS_CONSOLIDATED!I:I,0,0,1) -> -46300000 | K23: =-_xlfn.XLOOKUP("CurrentTax",HS_CONSOLIDATED!$C:$C,HS_CONSOLIDATED!J:J,0,0,1) -> -1840700000 | L23: =-_xlfn.XLOOKUP("CurrentTax",HS_CONSOLIDATED!$C:$C,HS_CONSOLIDATED!K:K,0,0,1) -> -46100000 | M23: =-_xlfn.XLOOKUP("CurrentTax",HS_CONSOLIDATED!$C:$C,HS_CONSOLIDATED!L:L,0,0,1) -> -29000000 | N23: =-_xlfn.XLOOKUP("CurrentTax",HS_CONSOLIDATED!$C:$C,HS_CONSOLIDATED!M:M,0,0,1) -> -144200000
C24: Deferred tax | E24: =-_xlfn.XLOOKUP("DeferredTax",HS_CONSOLIDATED!$C:$C,HS_CONSOLIDATED!D:D,0,0,1) -> 0 | F24: =-_xlfn.XLOOKUP("DeferredTax",HS_CONSOLIDATED!$C:$C,HS_CONSOLIDATED!E:E,0,0,1) -> 0 | G24: =-_xlfn.XLOOKUP("DeferredTax",HS_CONSOLIDATED!$C:$C,HS_CONSOLIDATED!F:F,0,0,1) -> 0 | H24: =-_xlfn.XLOOKUP("DeferredTax",HS_CONSOLIDATED!$C:$C,HS_CONSOLIDATED!G:G,0,0,1) -> 149900000 | I24: =-_xlfn.XLOOKUP("DeferredTax",HS_CONSOLIDATED!$C:$C,HS_CONSOLIDATED!H:H,0,0,1) -> 0 | J24: =-_xlfn.XLOOKUP("DeferredTax",HS_CONSOLIDATED!$C:$C,HS_CONSOLIDATED!I:I,0,0,1) -> 0 | K24: =-_xlfn.XLOOKUP("DeferredTax",HS_CONSOLIDATED!$C:$C,HS_CONSOLIDATED!J:J,0,0,1) -> 174800000 | L24: =-_xlfn.XLOOKUP("DeferredTax",HS_CONSOLIDATED!$C:$C,HS_CONSOLIDATED!K:K,0,0,1) -> 1900000 | M24: =-_xlfn.XLOOKUP("DeferredTax",HS_CONSOLIDATED!$C:$C,HS_CONSOLIDATED!L:L,0,0,1) -> 37600000 | N24: =-_xlfn.XLOOKUP("DeferredTax",HS_CONSOLIDATED!$C:$C,HS_CONSOLIDATED!M:M,0,0,1) -> 6394200000
C25: Total tax expense | E25: =IFERROR(SUM(E23:E24),0) -> 0 | F25: =IFERROR(SUM(F23:F24),0) -> -117000000 | G25: =IFERROR(SUM(G23:G24),0) -> 15600000 | H25: =IFERROR(SUM(H23:H24),0) -> 119000000 | I25: =IFERROR(SUM(I23:I24),0) -> -74400000 | J25: =IFERROR(SUM(J23:J24),0) -> -46300000 | K25: =IFERROR(SUM(K23:K24),0) -> -1665900000 | L25: =IFERROR(SUM(L23:L24),0) -> -44200000 | ... N25: =IFERROR(SUM(N23:N24),0) -> 6250000000
B26: NETINCOME | E26: =IFERROR(E25+E22,0) -> 0 | F26: =IFERROR(F25+F22,0) -> 8998900000 | G26: =IFERROR(G25+G22,0) -> -3891800000 | H26: =IFERROR(H25+H22,0) -> -15310900000 | I26: =IFERROR(I25+I22,0) -> -26913900000 | J26: =IFERROR(J25+J22,0) -> 1003400000 | K26: =IFERROR(K25+K22,0) -> -1661900000 | L26: =IFERROR(L25+L22,0) -> 28872900000 | ... N26: =IFERROR(N25+N22,0) -> 20716300000
A27: # | B27: Balance Sheet
B28: Assets [Abstract]
B29: Non-current assets [Abstract]
C30: Operating
D31: Property, plant and equipment at end of period | E31: =_xlfn.XLOOKUP("PropertyPlantAndEquipment",HS_CONSOLIDATED!$C:$C,HS_CONSOLIDATED!D:D,0,0,1) -> 0 | F31: =_xlfn.XLOOKUP("PropertyPlantAndEquipment",HS_CONSOLIDATED!$C:$C,HS_CONSOLIDATED!E:E,0,0,1) -> 14201800000 | G31: =_xlfn.XLOOKUP("PropertyPlantAndEquipment",HS_CONSOLIDATED!$C:$C,HS_CONSOLIDATED!F:F,0,0,1) -> 12673200000 | H31: =_xlfn.XLOOKUP("PropertyPlantAndEquipment",HS_CONSOLIDATED!$C:$C,HS_CONSOLIDATED!G:G,0,0,1) -> 11473200000 | I31: =_xlfn.XLOOKUP("PropertyPlantAndEquipment",HS_CONSOLIDATED!$C:$C,HS_CONSOLIDATED!H:H,0,0,1) -> 10484300000 | J31: =_xlfn.XLOOKUP("PropertyPlantAndEquipment",HS_CONSOLIDATED!$C:$C,HS_CONSOLIDATED!I:I,0,0,1) -> 9353100000 | K31: =_xlfn.XLOOKUP("PropertyPlantAndEquipment",HS_CONSOLIDATED!$C:$C,HS_CONSOLIDATED!J:J,0,0,1) -> 9073300000 | L31: =_xlfn.XLOOKUP("PropertyPlantAndEquipment",HS_CONSOLIDATED!$C:$C,HS_CONSOLIDATED!K:K,0,0,1) -> 7784500000 | M31: =_xlfn.XLOOKUP("PropertyPlantAndEquipment",HS_CONSOLIDATED!$C:$C,HS_CONSOLIDATED!L:L,0,0,1) -> 8095100000 | N31: =_xlfn.XLOOKUP("PropertyPlantAndEquipment",HS_CONSOLIDATED!$C:$C,HS_CONSOLIDATED!M:M,0,0,1) -> 8220600000
D32: Capital work-in-progress | E32: =_xlfn.XLOOKUP("CapitalWorkInProgress",HS_CONSOLIDATED!$C:$C,HS_CONSOLIDATED!D:D,0,0,1) -> 0 | F32: =_xlfn.XLOOKUP("CapitalWorkInProgress",HS_CONSOLIDATED!$C:$C,HS_CONSOLIDATED!E:E,0,0,1) -> 1185600000 | G32: =_xlfn.XLOOKUP("CapitalWorkInProgress",HS_CONSOLIDATED!$C:$C,HS_CONSOLIDATED!F:F,0,0,1) -> 1734200000 | H32: =_xlfn.XLOOKUP("CapitalWorkInProgress",HS_CONSOLIDATED!$C:$C,HS_CONSOLIDATED!G:G,0,0,1) -> 2183300000 | I32: =_xlfn.XLOOKUP("CapitalWorkInProgress",HS_CONSOLIDATED!$C:$C,HS_CONSOLIDATED!H:H,0,0,1) -> 1100800000 | J32: =_xlfn.XLOOKUP("CapitalWorkInProgress",HS_CONSOLIDATED!$C:$C,HS_CONSOLIDATED!I:I,0,0,1) -> 1039300000 | K32: =_xlfn.XLOOKUP("CapitalWorkInProgress",HS_CONSOLIDATED!$C:$C,HS_CONSOLIDATED!J:J,0,0,1) -> 152100000 | L32: =_xlfn.XLOOKUP("CapitalWorkInProgress",HS_CONSOLIDATED!$C:$C,HS_CONSOLIDATED!K:K,0,0,1) -> 25700000 | M32: =_xlfn.XLOOKUP("CapitalWorkInProgress",HS_CONSOLIDATED!$C:$C,HS_CONSOLIDATED!L:L,0,0,1) -> 162100000 | N32: =_xlfn.XLOOKUP("CapitalWorkInProgress",HS_CONSOLIDATED!$C:$C,HS_CONSOLIDATED!M:M,0,0,1) -> 886700000
D33: Goodwill at end of period | E33: =_xlfn.XLOOKUP("Goodwill",HS_CONSOLIDATED!$C:$C,HS_CONSOLIDATED!D:D,0,0,1) -> 0 | F33: =_xlfn.XLOOKUP("Goodwill",HS_CONSOLIDATED!$C:$C,HS_CONSOLIDATED!E:E,0,0,1) -> 76200000 | G33: =_xlfn.XLOOKUP("Goodwill",HS_CONSOLIDATED!$C:$C,HS_CONSOLIDATED!F:F,0,0,1) -> 76300000 | H33: =_xlfn.XLOOKUP("Goodwill",HS_CONSOLIDATED!$C:$C,HS_CONSOLIDATED!G:G,0,0,1) -> 76300000 | I33: =_xlfn.XLOOKUP("Goodwill",HS_CONSOLIDATED!$C:$C,HS_CONSOLIDATED!H:H,0,0,1) -> 76300000 | J33: =_xlfn.XLOOKUP("Goodwill",HS_CONSOLIDATED!$C:$C,HS_CONSOLIDATED!I:I,0,0,1) -> 76300000 | K33: =_xlfn.XLOOKUP("Goodwill",HS_CONSOLIDATED!$C:$C,HS_CONSOLIDATED!J:J,0,0,1) -> 0 | L33: =_xlfn.XLOOKUP("Goodwill",HS_CONSOLIDATED!$C:$C,HS_CONSOLIDATED!K:K,0,0,1) -> 0 | M33: =_xlfn.XLOOKUP("Goodwill",HS_CONSOLIDATED!$C:$C,HS_CONSOLIDATED!L:L,0,0,1) -> 0 | N33: =_xlfn.XLOOKUP("Goodwill",HS_CONSOLIDATED!$C:$C,HS_CONSOLIDATED!M:M,0,0,1) -> 4798300000
D34: Other intangible assets at end of period | E34: =_xlfn.XLOOKUP("OtherIntangibleAssets",HS_CONSOLIDATED!$C:$C,HS_CONSOLIDATED!D:D,0,0,1) -> 0 | F34: =_xlfn.XLOOKUP("OtherIntangibleAssets",HS_CONSOLIDATED!$C:$C,HS_CONSOLIDATED!E:E,0,0,1) -> 2033500000 | G34: =_xlfn.XLOOKUP("OtherIntangibleAssets",HS_CONSOLIDATED!$C:$C,HS_CONSOLIDATED!F:F,0,0,1) -> 1471200000 | H34: =_xlfn.XLOOKUP("OtherIntangibleAssets",HS_CONSOLIDATED!$C:$C,HS_CONSOLIDATED!G:G,0,0,1) -> 3274400000 | I34: =_xlfn.XLOOKUP("OtherIntangibleAssets",HS_CONSOLIDATED!$C:$C,HS_CONSOLIDATED!H:H,0,0,1) -> 2675000000 | J34: =_xlfn.XLOOKUP("OtherIntangibleAssets",HS_CONSOLIDATED!$C:$C,HS_CONSOLIDATED!I:I,0,0,1) -> 1904600000 | K34: =_xlfn.XLOOKUP("OtherIntangibleAssets",HS_CONSOLIDATED!$C:$C,HS_CONSOLIDATED!J:J,0,0,1) -> 1211100000 | L34: =_xlfn.XLOOKUP("OtherIntangibleAssets",HS_CONSOLIDATED!$C:$C,HS_CONSOLIDATED!K:K,0,0,1) -> 584800000 | M34: =_xlfn.XLOOKUP("OtherIntangibleAssets",HS_CONSOLIDATED!$C:$C,HS_CONSOLIDATED!L:L,0,0,1) -> 499400000 | N34: =_xlfn.XLOOKUP("OtherIntangibleAssets",HS_CONSOLIDATED!$C:$C,HS_CONSOLIDATED!M:M,0,0,1) -> 4519200000
D35: Intangible assets under development | E35: =_xlfn.XLOOKUP("IntangibleAssetsUnderDevelopment",HS_CONSOLIDATED!$C:$C,HS_CONSOLIDATED!D:D,0,0,1) -> 0 | F35: =_xlfn.XLOOKUP("IntangibleAssetsUnderDevelopment",HS_CONSOLIDATED!$C:$C,HS_CONSOLIDATED!E:E,0,0,1) -> 874300000 | G35: =_xlfn.XLOOKUP("IntangibleAssetsUnderDevelopment",HS_CONSOLIDATED!$C:$C,HS_CONSOLIDATED!F:F,0,0,1) -> 1798200000 | H35: =_xlfn.XLOOKUP("IntangibleAssetsUnderDevelopment",HS_CONSOLIDATED!$C:$C,HS_CONSOLIDATED!G:G,0,0,1) -> 104100000 | I35: =_xlfn.XLOOKUP("IntangibleAssetsUnderDevelopment",HS_CONSOLIDATED!$C:$C,HS_CONSOLIDATED!H:H,0,0,1) -> 123000000 | J35: =_xlfn.XLOOKUP("IntangibleAssetsUnderDevelopment",HS_CONSOLIDATED!$C:$C,HS_CONSOLIDATED!I:I,0,0,1) -> 35200000 | K35: =_xlfn.XLOOKUP("IntangibleAssetsUnderDevelopment",HS_CONSOLIDATED!$C:$C,HS_CONSOLIDATED!J:J,0,0,1) -> 44200000 | L35: =_xlfn.XLOOKUP("IntangibleAssetsUnderDevelopment",HS_CONSOLIDATED!$C:$C,HS_CONSOLIDATED!K:K,0,0,1) -> 34300000 | M35: =_xlfn.XLOOKUP("IntangibleAssetsUnderDevelopment",HS_CONSOLIDATED!$C:$C,HS_CONSOLIDATED!L:L,0,0,1) -> 35100000 | N35: =_xlfn.XLOOKUP("IntangibleAssetsUnderDevelopment",HS_CONSOLIDATED!$C:$C,HS_CONSOLIDATED!M:M,0,0,1) -> 164300000
D36: Trade receivables, non-current | E36: =_xlfn.XLOOKUP("TradeReceivablesNoncurrent",HS_CONSOLIDATED!$C:$C,HS_CONSOLIDATED!D:D,0,0,1) -> 0 | F36: =_xlfn.XLOOKUP("TradeReceivablesNoncurrent",HS_CONSOLIDATED!$C:$C,HS_CONSOLIDATED!E:E,0,0,1) -> 457700000 | G36: =_xlfn.XLOOKUP("TradeReceivablesNoncurrent",HS_CONSOLIDATED!$C:$C,HS_CONSOLIDATED!F:F,0,0,1) -> 48400000 | H36: =_xlfn.XLOOKUP("TradeReceivablesNoncurrent",HS_CONSOLIDATED!$C:$C,HS_CONSOLIDATED!G:G,0,0,1) -> 0 | I36: =_xlfn.XLOOKUP("TradeReceivablesNoncurrent",HS_CONSOLIDATED!$C:$C,HS_CONSOLIDATED!H:H,0,0,1) -> 0 | J36: =_xlfn.XLOOKUP("TradeReceivablesNoncurrent",HS_CONSOLIDATED!$C:$C,HS_CONSOLIDATED!I:I,0,0,1) -> 0 | K36: =_xlfn.XLOOKUP("TradeReceivablesNoncurrent",HS_CONSOLIDATED!$C:$C,HS_CONSOLIDATED!J:J,0,0,1) -> 0 | L36: =_xlfn.XLOOKUP("TradeReceivablesNoncurrent",HS_CONSOLIDATED!$C:$C,HS_CONSOLIDATED!K:K,0,0,1) -> 0 | M36: =_xlfn.XLOOKUP("TradeReceivablesNoncurrent",HS_CONSOLIDATED!$C:$C,HS_CONSOLIDATED!L:L,0,0,1) -> 0 | N36: =_xlfn.XLOOKUP("TradeReceivablesNoncurrent",HS_CONSOLIDATED!$C:$C,HS_CONSOLIDATED!M:M,0,0,1) -> 0
D37: Total other non-current assets | E37: =_xlfn.XLOOKUP("OtherNoncurrentAssets",HS_CONSOLIDATED!$C:$C,HS_CONSOLIDATED!D:D,0,0,1) -> 0 | F37: =_xlfn.XLOOKUP("OtherNoncurrentAssets",HS_CONSOLIDATED!$C:$C,HS_CONSOLIDATED!E:E,0,0,1) -> 1661600000 | G37: =_xlfn.XLOOKUP("OtherNoncurrentAssets",HS_CONSOLIDATED!$C:$C,HS_CONSOLIDATED!F:F,0,0,1) -> 1393800000 | H37: =_xlfn.XLOOKUP("OtherNoncurrentAssets",HS_CONSOLIDATED!$C:$C,HS_CONSOLIDATED!G:G,0,0,1) -> 1038400000 | I37: =_xlfn.XLOOKUP("OtherNoncurrentAssets",HS_CONSOLIDATED!$C:$C,HS_CONSOLIDATED!H:H,0,0,1) -> 510500000 | J37: =_xlfn.XLOOKUP("OtherNoncurrentAssets",HS_CONSOLIDATED!$C:$C,HS_CONSOLIDATED!I:I,0,0,1) -> 544600000 | K37: =_xlfn.XLOOKUP("OtherNoncurrentAssets",HS_CONSOLIDATED!$C:$C,HS_CONSOLIDATED!J:J,0,0,1) -> 292400000 | L37: =_xlfn.XLOOKUP("OtherNoncurrentAssets",HS_CONSOLIDATED!$C:$C,HS_CONSOLIDATED!K:K,0,0,1) -> 402200000 | M37: =_xlfn.XLOOKUP("OtherNoncurrentAssets",HS_CONSOLIDATED!$C:$C,HS_CONSOLIDATED!L:L,0,0,1) -> 784300000 | N37: =_xlfn.XLOOKUP("OtherNoncurrentAssets",HS_CONSOLIDATED!$C:$C,HS_CONSOLIDATED!M:M,0,0,1) -> 751400000
C38: Total Operating | E38: =IFERROR(SUM(E31:E37),0) -> 0 | F38: =IFERROR(SUM(F31:F37),0) -> 20490700000 | G38: =IFERROR(SUM(G31:G37),0) -> 19195300000 | H38: =IFERROR(SUM(H31:H37),0) -> 18149700000 | I38: =IFERROR(SUM(I31:I37),0) -> 14969900000 | J38: =IFERROR(SUM(J31:J37),0) -> 12953100000 | K38: =IFERROR(SUM(K31:K37),0) -> 10773100000 | L38: =IFERROR(SUM(L31:L37),0) -> 8831500000 | ... N38: =IFERROR(SUM(N31:N37),0) -> 19340500000
C39: Non-Operating
D40: Investment property at end of period | E40: =_xlfn.XLOOKUP("InvestmentProperty",HS_CONSOLIDATED!$C:$C,HS_CONSOLIDATED!D:D,0,0,1) -> 0 | F40: =_xlfn.XLOOKUP("InvestmentProperty",HS_CONSOLIDATED!$C:$C,HS_CONSOLIDATED!E:E,0,0,1) -> 341400000 | G40: =_xlfn.XLOOKUP("InvestmentProperty",HS_CONSOLIDATED!$C:$C,HS_CONSOLIDATED!F:F,0,0,1) -> 407900000 | H40: =_xlfn.XLOOKUP("InvestmentProperty",HS_CONSOLIDATED!$C:$C,HS_CONSOLIDATED!G:G,0,0,1) -> 373600000 | I40: =_xlfn.XLOOKUP("InvestmentProperty",HS_CONSOLIDATED!$C:$C,HS_CONSOLIDATED!H:H,0,0,1) -> 346700000 | J40: =_xlfn.XLOOKUP("InvestmentProperty",HS_CONSOLIDATED!$C:$C,HS_CONSOLIDATED!I:I,0,0,1) -> 326400000 | K40: =_xlfn.XLOOKUP("InvestmentProperty",HS_CONSOLIDATED!$C:$C,HS_CONSOLIDATED!J:J,0,0,1) -> 308600000 | L40: =_xlfn.XLOOKUP("InvestmentProperty",HS_CONSOLIDATED!$C:$C,HS_CONSOLIDATED!K:K,0,0,1) -> 292100000 | M40: =_xlfn.XLOOKUP("InvestmentProperty",HS_CONSOLIDATED!$C:$C,HS_CONSOLIDATED!L:L,0,0,1) -> 270100000 | N40: =_xlfn.XLOOKUP("InvestmentProperty",HS_CONSOLIDATED!$C:$C,HS_CONSOLIDATED!M:M,0,0,1) -> 257500000
D41: Investments accounted for using equity method | E41: =_xlfn.XLOOKUP("InvestmentsAccountedForUsingEquityMethod",HS_CONSOLIDATED!$C:$C,HS_CONSOLIDATED!D:D,0,0,1) -> 0 | F41: =_xlfn.XLOOKUP("InvestmentsAccountedForUsingEquityMethod",HS_CONSOLIDATED!$C:$C,HS_CONSOLIDATED!E:E,0,0,1) -> 0 | G41: =_xlfn.XLOOKUP("InvestmentsAccountedForUsingEquityMethod",HS_CONSOLIDATED!$C:$C,HS_CONSOLIDATED!F:F,0,0,1) -> 668600000 | H41: =_xlfn.XLOOKUP("InvestmentsAccountedForUsingEquityMethod",HS_CONSOLIDATED!$C:$C,HS_CONSOLIDATED!G:G,0,0,1) -> 203000000 | I41: =_xlfn.XLOOKUP("InvestmentsAccountedForUsingEquityMethod",HS_CONSOLIDATED!$C:$C,HS_CONSOLIDATED!H:H,0,0,1) -> 197100000 | J41: =_xlfn.XLOOKUP("InvestmentsAccountedForUsingEquityMethod",HS_CONSOLIDATED!$C:$C,HS_CONSOLIDATED!I:I,0,0,1) -> 229700000 | K41: =_xlfn.XLOOKUP("InvestmentsAccountedForUsingEquityMethod",HS_CONSOLIDATED!$C:$C,HS_CONSOLIDATED!J:J,0,0,1) -> 0 | L41: =_xlfn.XLOOKUP("InvestmentsAccountedForUsingEquityMethod",HS_CONSOLIDATED!$C:$C,HS_CONSOLIDATED!K:K,0,0,1) -> 0 | M41: =_xlfn.XLOOKUP("InvestmentsAccountedForUsingEquityMethod",HS_CONSOLIDATED!$C:$C,HS_CONSOLIDATED!L:L,0,0,1) -> 0 | N41: =_xlfn.XLOOKUP("InvestmentsAccountedForUsingEquityMethod",HS_CONSOLIDATED!$C:$C,HS_CONSOLIDATED!M:M,0,0,1) -> 0
D42: Non-current investments | E42: =_xlfn.XLOOKUP("NoncurrentInvestments",HS_CONSOLIDATED!$C:$C,HS_CONSOLIDATED!D:D,0,0,1) -> 0 | F42: =_xlfn.XLOOKUP("NoncurrentInvestments",HS_CONSOLIDATED!$C:$C,HS_CONSOLIDATED!E:E,0,0,1) -> 1885500000 | G42: =_xlfn.XLOOKUP("NoncurrentInvestments",HS_CONSOLIDATED!$C:$C,HS_CONSOLIDATED!F:F,0,0,1) -> 1300000 | H42: =_xlfn.XLOOKUP("NoncurrentInvestments",HS_CONSOLIDATED!$C:$C,HS_CONSOLIDATED!G:G,0,0,1) -> 1300000 | I42: =_xlfn.XLOOKUP("NoncurrentInvestments",HS_CONSOLIDATED!$C:$C,HS_CONSOLIDATED!H:H,0,0,1) -> 300000 | J42: =_xlfn.XLOOKUP("NoncurrentInvestments",HS_CONSOLIDATED!$C:$C,HS_CONSOLIDATED!I:I,0,0,1) -> 300000 | K42: =_xlfn.XLOOKUP("NoncurrentInvestments",HS_CONSOLIDATED!$C:$C,HS_CONSOLIDATED!J:J,0,0,1) -> 300000 | L42: =_xlfn.XLOOKUP("NoncurrentInvestments",HS_CONSOLIDATED!$C:$C,HS_CONSOLIDATED!K:K,0,0,1) -> 300000 | M42: =_xlfn.XLOOKUP("NoncurrentInvestments",HS_CONSOLIDATED!$C:$C,HS_CONSOLIDATED!L:L,0,0,1) -> 300000 | N42: =_xlfn.XLOOKUP("NoncurrentInvestments",HS_CONSOLIDATED!$C:$C,HS_CONSOLIDATED!M:M,0,0,1) -> 300000
D43: Loans, non-current | E43: =_xlfn.XLOOKUP("LoansNoncurrent",HS_CONSOLIDATED!$C:$C,HS_CONSOLIDATED!D:D,0,0,1) -> 0 | F43: =_xlfn.XLOOKUP("LoansNoncurrent",HS_CONSOLIDATED!$C:$C,HS_CONSOLIDATED!E:E,0,0,1) -> 59600000 | G43: =_xlfn.XLOOKUP("LoansNoncurrent",HS_CONSOLIDATED!$C:$C,HS_CONSOLIDATED!F:F,0,0,1) -> 11200000 | H43: =_xlfn.XLOOKUP("LoansNoncurrent",HS_CONSOLIDATED!$C:$C,HS_CONSOLIDATED!G:G,0,0,1) -> 0 | I43: =_xlfn.XLOOKUP("LoansNoncurrent",HS_CONSOLIDATED!$C:$C,HS_CONSOLIDATED!H:H,0,0,1) -> 0 | J43: =_xlfn.XLOOKUP("LoansNoncurrent",HS_CONSOLIDATED!$C:$C,HS_CONSOLIDATED!I:I,0,0,1) -> 0 | K43: =_xlfn.XLOOKUP("LoansNoncurrent",HS_CONSOLIDATED!$C:$C,HS_CONSOLIDATED!J:J,0,0,1) -> 0 | L43: =_xlfn.XLOOKUP("LoansNoncurrent",HS_CONSOLIDATED!$C:$C,HS_CONSOLIDATED!K:K,0,0,1) -> 0 | M43: =_xlfn.XLOOKUP("LoansNoncurrent",HS_CONSOLIDATED!$C:$C,HS_CONSOLIDATED!L:L,0,0,1) -> 0 | N43: =_xlfn.XLOOKUP("LoansNoncurrent",HS_CONSOLIDATED!$C:$C,HS_CONSOLIDATED!M:M,0,0,1) -> 0
D44: Total other non-current financial assets | E44: =_xlfn.XLOOKUP("OtherNoncurrentFinancialAssets",HS_CONSOLIDATED!$C:$C,HS_CONSOLIDATED!D:D,0,0,1) -> 0 | F44: =_xlfn.XLOOKUP("OtherNoncurrentFinancialAssets",HS_CONSOLIDATED!$C:$C,HS_CONSOLIDATED!E:E,0,0,1) -> 7118400000 | G44: =_xlfn.XLOOKUP("OtherNoncurrentFinancialAssets",HS_CONSOLIDATED!$C:$C,HS_CONSOLIDATED!F:F,0,0,1) -> 5811500000 | H44: =_xlfn.XLOOKUP("OtherNoncurrentFinancialAssets",HS_CONSOLIDATED!$C:$C,HS_CONSOLIDATED!G:G,0,0,1) -> 4838100000 | I44: =_xlfn.XLOOKUP("OtherNoncurrentFinancialAssets",HS_CONSOLIDATED!$C:$C,HS_CONSOLIDATED!H:H,0,0,1) -> 2844000000 | J44: =_xlfn.XLOOKUP("OtherNoncurrentFinancialAssets",HS_CONSOLIDATED!$C:$C,HS_CONSOLIDATED!I:I,0,0,1) -> 4026300000 | K44: =_xlfn.XLOOKUP("OtherNoncurrentFinancialAssets",HS_CONSOLIDATED!$C:$C,HS_CONSOLIDATED!J:J,0,0,1) -> 2643100000 | L44: =_xlfn.XLOOKUP("OtherNoncurrentFinancialAssets",HS_CONSOLIDATED!$C:$C,HS_CONSOLIDATED!K:K,0,0,1) -> 4331400000 | M44: =_xlfn.XLOOKUP("OtherNoncurrentFinancialAssets",HS_CONSOLIDATED!$C:$C,HS_CONSOLIDATED!L:L,0,0,1) -> 9029200000 | N44: =_xlfn.XLOOKUP("OtherNoncurrentFinancialAssets",HS_CONSOLIDATED!$C:$C,HS_CONSOLIDATED!M:M,0,0,1) -> 11035000000
D45: Deferred tax assets (net) | E45: =_xlfn.XLOOKUP("DeferredTaxAssetsNet",HS_CONSOLIDATED!$C:$C,HS_CONSOLIDATED!D:D,0,0,1) -> 0 | F45: =_xlfn.XLOOKUP("DeferredTaxAssetsNet",HS_CONSOLIDATED!$C:$C,HS_CONSOLIDATED!E:E,0,0,1) -> 0 | G45: =_xlfn.XLOOKUP("DeferredTaxAssetsNet",HS_CONSOLIDATED!$C:$C,HS_CONSOLIDATED!F:F,0,0,1) -> 0 | H45: =_xlfn.XLOOKUP("DeferredTaxAssetsNet",HS_CONSOLIDATED!$C:$C,HS_CONSOLIDATED!G:G,0,0,1) -> 0 | I45: =_xlfn.XLOOKUP("DeferredTaxAssetsNet",HS_CONSOLIDATED!$C:$C,HS_CONSOLIDATED!H:H,0,0,1) -> 0 | J45: =_xlfn.XLOOKUP("DeferredTaxAssetsNet",HS_CONSOLIDATED!$C:$C,HS_CONSOLIDATED!I:I,0,0,1) -> 0 | K45: =_xlfn.XLOOKUP("DeferredTaxAssetsNet",HS_CONSOLIDATED!$C:$C,HS_CONSOLIDATED!J:J,0,0,1) -> 174800000 | L45: =_xlfn.XLOOKUP("DeferredTaxAssetsNet",HS_CONSOLIDATED!$C:$C,HS_CONSOLIDATED!K:K,0,0,1) -> 2000000 | M45: =_xlfn.XLOOKUP("DeferredTaxAssetsNet",HS_CONSOLIDATED!$C:$C,HS_CONSOLIDATED!L:L,0,0,1) -> 37700000 | N45: =_xlfn.XLOOKUP("DeferredTaxAssetsNet",HS_CONSOLIDATED!$C:$C,HS_CONSOLIDATED!M:M,0,0,1) -> 6445500000
C46: Total Non-Operating | E46: =IFERROR(SUM(E40:E45),0) -> 0 | F46: =IFERROR(SUM(F40:F45),0) -> 9404900000 | G46: =IFERROR(SUM(G40:G45),0) -> 6900500000 | H46: =IFERROR(SUM(H40:H45),0) -> 5416000000 | I46: =IFERROR(SUM(I40:I45),0) -> 3388100000 | J46: =IFERROR(SUM(J40:J45),0) -> 4582700000 | K46: =IFERROR(SUM(K40:K45),0) -> 3126800000 | L46: =IFERROR(SUM(L40:L45),0) -> 4625800000 | ... N46: =IFERROR(SUM(N40:N45),0) -> 17738300000
C47: Total non-current financial assets | E47: =_xlfn.XLOOKUP("NoncurrentFinancialAssets",HS_CONSOLIDATED!$C:$C,HS_CONSOLIDATED!D:D,0,0,1) -> 0 | F47: =_xlfn.XLOOKUP("NoncurrentFinancialAssets",HS_CONSOLIDATED!$C:$C,HS_CONSOLIDATED!E:E,0,0,1) -> 9521200000 | G47: =_xlfn.XLOOKUP("NoncurrentFinancialAssets",HS_CONSOLIDATED!$C:$C,HS_CONSOLIDATED!F:F,0,0,1) -> 5872400000 | H47: =_xlfn.XLOOKUP("NoncurrentFinancialAssets",HS_CONSOLIDATED!$C:$C,HS_CONSOLIDATED!G:G,0,0,1) -> 4839400000 | I47: =_xlfn.XLOOKUP("NoncurrentFinancialAssets",HS_CONSOLIDATED!$C:$C,HS_CONSOLIDATED!H:H,0,0,1) -> 2844300000 | J47: =_xlfn.XLOOKUP("NoncurrentFinancialAssets",HS_CONSOLIDATED!$C:$C,HS_CONSOLIDATED!I:I,0,0,1) -> 4026600000 | K47: =_xlfn.XLOOKUP("NoncurrentFinancialAssets",HS_CONSOLIDATED!$C:$C,HS_CONSOLIDATED!J:J,0,0,1) -> 2643400000 | L47: =_xlfn.XLOOKUP("NoncurrentFinancialAssets",HS_CONSOLIDATED!$C:$C,HS_CONSOLIDATED!K:K,0,0,1) -> 4331700000 | M47: =_xlfn.XLOOKUP("NoncurrentFinancialAssets",HS_CONSOLIDATED!$C:$C,HS_CONSOLIDATED!L:L,0,0,1) -> 9029500000 | N47: =_xlfn.XLOOKUP("NoncurrentFinancialAssets",HS_CONSOLIDATED!$C:$C,HS_CONSOLIDATED!M:M,0,0,1) -> 11035300000
B48: Total Non-Current Assets | E48: =IFERROR(E46+E38,0) -> 0 | F48: =IFERROR(F46+F38,0) -> 29895600000 | G48: =IFERROR(G46+G38,0) -> 26095800000 | H48: =IFERROR(H46+H38,0) -> 23565700000 | I48: =IFERROR(I46+I38,0) -> 18358000000 | J48: =IFERROR(J46+J38,0) -> 17535800000 | K48: =IFERROR(K46+K38,0) -> 13899900000 | L48: =IFERROR(L46+L38,0) -> 13457300000 | ... N48: =IFERROR(N46+N38,0) -> 37078800000
B49: Current Assets
C50: Operating
D51: Inventories | E51: =_xlfn.XLOOKUP("Inventories",HS_CONSOLIDATED!$C:$C,HS_CONSOLIDATED!D:D,0,0,1) -> 0 | F51: =_xlfn.XLOOKUP("Inventories",HS_CONSOLIDATED!$C:$C,HS_CONSOLIDATED!E:E,0,0,1) -> 34688400000 | G51: =_xlfn.XLOOKUP("Inventories",HS_CONSOLIDATED!$C:$C,HS_CONSOLIDATED!F:F,0,0,1) -> 30263700000 | H51: =_xlfn.XLOOKUP("Inventories",HS_CONSOLIDATED!$C:$C,HS_CONSOLIDATED!G:G,0,0,1) -> 29139300000 | I51: =_xlfn.XLOOKUP("Inventories",HS_CONSOLIDATED!$C:$C,HS_CONSOLIDATED!H:H,0,0,1) -> 20555900000 | J51: =_xlfn.XLOOKUP("Inventories",HS_CONSOLIDATED!$C:$C,HS_CONSOLIDATED!I:I,0,0,1) -> 21727600000 | K51: =_xlfn.XLOOKUP("Inventories",HS_CONSOLIDATED!$C:$C,HS_CONSOLIDATED!J:J,0,0,1) -> 22079000000 | L51: =_xlfn.XLOOKUP("Inventories",HS_CONSOLIDATED!$C:$C,HS_CONSOLIDATED!K:K,0,0,1) -> 18271300000 | M51: =_xlfn.XLOOKUP("Inventories",HS_CONSOLIDATED!$C:$C,HS_CONSOLIDATED!L:L,0,0,1) -> 22922900000 | N51: =_xlfn.XLOOKUP("Inventories",HS_CONSOLIDATED!$C:$C,HS_CONSOLIDATED!M:M,0,0,1) -> 32335500000
D52: Trade receivables, current | E52: =_xlfn.XLOOKUP("TradeReceivablesCurrent",HS_CONSOLIDATED!$C:$C,HS_CONSOLIDATED!D:D,0,0,1) -> 0 | F52: =_xlfn.XLOOKUP("TradeReceivablesCurrent",HS_CONSOLIDATED!$C:$C,HS_CONSOLIDATED!E:E,0,0,1) -> 36275300000 | G52: =_xlfn.XLOOKUP("TradeReceivablesCurrent",HS_CONSOLIDATED!$C:$C,HS_CONSOLIDATED!F:F,0,0,1) -> 29851500000 | H52: =_xlfn.XLOOKUP("TradeReceivablesCurrent",HS_CONSOLIDATED!$C:$C,HS_CONSOLIDATED!G:G,0,0,1) -> 18805900000 | I52: =_xlfn.XLOOKUP("TradeReceivablesCurrent",HS_CONSOLIDATED!$C:$C,HS_CONSOLIDATED!H:H,0,0,1) -> 13645400000 | J52: =_xlfn.XLOOKUP("TradeReceivablesCurrent",HS_CONSOLIDATED!$C:$C,HS_CONSOLIDATED!I:I,0,0,1) -> 11897200000 | K52: =_xlfn.XLOOKUP("TradeReceivablesCurrent",HS_CONSOLIDATED!$C:$C,HS_CONSOLIDATED!J:J,0,0,1) -> 13769500000 | L52: =_xlfn.XLOOKUP("TradeReceivablesCurrent",HS_CONSOLIDATED!$C:$C,HS_CONSOLIDATED!K:K,0,0,1) -> 11704400000 | M52: =_xlfn.XLOOKUP("TradeReceivablesCurrent",HS_CONSOLIDATED!$C:$C,HS_CONSOLIDATED!L:L,0,0,1) -> 18295800000 | N52: =_xlfn.XLOOKUP("TradeReceivablesCurrent",HS_CONSOLIDATED!$C:$C,HS_CONSOLIDATED!M:M,0,0,1) -> 38663500000
D53: Total other current assets | E53: =_xlfn.XLOOKUP("OtherCurrentAssets",HS_CONSOLIDATED!$C:$C,HS_CONSOLIDATED!D:D,0,0,1) -> 0 | F53: =_xlfn.XLOOKUP("OtherCurrentAssets",HS_CONSOLIDATED!$C:$C,HS_CONSOLIDATED!E:E,0,0,1) -> 10137600000 | G53: =_xlfn.XLOOKUP("OtherCurrentAssets",HS_CONSOLIDATED!$C:$C,HS_CONSOLIDATED!F:F,0,0,1) -> 9306100000 | H53: =_xlfn.XLOOKUP("OtherCurrentAssets",HS_CONSOLIDATED!$C:$C,HS_CONSOLIDATED!G:G,0,0,1) -> 12119300000 | I53: =_xlfn.XLOOKUP("OtherCurrentAssets",HS_CONSOLIDATED!$C:$C,HS_CONSOLIDATED!H:H,0,0,1) -> 9894700000 | J53: =_xlfn.XLOOKUP("OtherCurrentAssets",HS_CONSOLIDATED!$C:$C,HS_CONSOLIDATED!I:I,0,0,1) -> 9695800000 | K53: =_xlfn.XLOOKUP("OtherCurrentAssets",HS_CONSOLIDATED!$C:$C,HS_CONSOLIDATED!J:J,0,0,1) -> 8112600000 | L53: =_xlfn.XLOOKUP("OtherCurrentAssets",HS_CONSOLIDATED!$C:$C,HS_CONSOLIDATED!K:K,0,0,1) -> 6271000000 | M53: =_xlfn.XLOOKUP("OtherCurrentAssets",HS_CONSOLIDATED!$C:$C,HS_CONSOLIDATED!L:L,0,0,1) -> 5942400000 | N53: =_xlfn.XLOOKUP("OtherCurrentAssets",HS_CONSOLIDATED!$C:$C,HS_CONSOLIDATED!M:M,0,0,1) -> 7570400000
C54: Total Operating | E54: =IFERROR(SUM(E51:E53),0) -> 0 | F54: =IFERROR(SUM(F51:F53),0) -> 81101300000 | G54: =IFERROR(SUM(G51:G53),0) -> 69421300000 | H54: =IFERROR(SUM(H51:H53),0) -> 60064500000 | I54: =IFERROR(SUM(I51:I53),0) -> 44096000000 | J54: =IFERROR(SUM(J51:J53),0) -> 43320600000 | K54: =IFERROR(SUM(K51:K53),0) -> 43961100000 | L54: =IFERROR(SUM(L51:L53),0) -> 36246700000 | ... N54: =IFERROR(SUM(N51:N53),0) -> 78569400000
C55: Non-Operating
D56: Current investments | E56: =_xlfn.XLOOKUP("CurrentInvestments",HS_CONSOLIDATED!$C:$C,HS_CONSOLIDATED!D:D,0,0,1) -> 0 | F56: =_xlfn.XLOOKUP("CurrentInvestments",HS_CONSOLIDATED!$C:$C,HS_CONSOLIDATED!E:E,0,0,1) -> 4811000000 | G56: =_xlfn.XLOOKUP("CurrentInvestments",HS_CONSOLIDATED!$C:$C,HS_CONSOLIDATED!F:F,0,0,1) -> 0 | H56: =_xlfn.XLOOKUP("CurrentInvestments",HS_CONSOLIDATED!$C:$C,HS_CONSOLIDATED!G:G,0,0,1) -> 0 | I56: =_xlfn.XLOOKUP("CurrentInvestments",HS_CONSOLIDATED!$C:$C,HS_CONSOLIDATED!H:H,0,0,1) -> 0 | J56: =_xlfn.XLOOKUP("CurrentInvestments",HS_CONSOLIDATED!$C:$C,HS_CONSOLIDATED!I:I,0,0,1) -> 0 | K56: =_xlfn.XLOOKUP("CurrentInvestments",HS_CONSOLIDATED!$C:$C,HS_CONSOLIDATED!J:J,0,0,1) -> 0 | L56: =_xlfn.XLOOKUP("CurrentInvestments",HS_CONSOLIDATED!$C:$C,HS_CONSOLIDATED!K:K,0,0,1) -> 0 | M56: =_xlfn.XLOOKUP("CurrentInvestments",HS_CONSOLIDATED!$C:$C,HS_CONSOLIDATED!L:L,0,0,1) -> 83500000 | N56: =_xlfn.XLOOKUP("CurrentInvestments",HS_CONSOLIDATED!$C:$C,HS_CONSOLIDATED!M:M,0,0,1) -> 429100000
D57: Cash and cash equivalents at end of period | E57: =_xlfn.XLOOKUP("CashAndCashEquivalents",HS_CONSOLIDATED!$C:$C,HS_CONSOLIDATED!D:D,0,0,1) -> 0 | F57: =_xlfn.XLOOKUP("CashAndCashEquivalents",HS_CONSOLIDATED!$C:$C,HS_CONSOLIDATED!E:E,0,0,1) -> 3361200000 | G57: =_xlfn.XLOOKUP("CashAndCashEquivalents",HS_CONSOLIDATED!$C:$C,HS_CONSOLIDATED!F:F,0,0,1) -> 5810700000 | H57: =_xlfn.XLOOKUP("CashAndCashEquivalents",HS_CONSOLIDATED!$C:$C,HS_CONSOLIDATED!G:G,0,0,1) -> 746200000 | I57: =_xlfn.XLOOKUP("CashAndCashEquivalents",HS_CONSOLIDATED!$C:$C,HS_CONSOLIDATED!H:H,0,0,1) -> 823300000 | J57: =_xlfn.XLOOKUP("CashAndCashEquivalents",HS_CONSOLIDATED!$C:$C,HS_CONSOLIDATED!I:I,0,0,1) -> 2625000000 | K57: =_xlfn.XLOOKUP("CashAndCashEquivalents",HS_CONSOLIDATED!$C:$C,HS_CONSOLIDATED!J:J,0,0,1) -> 5004300000 | L57: =_xlfn.XLOOKUP("CashAndCashEquivalents",HS_CONSOLIDATED!$C:$C,HS_CONSOLIDATED!K:K,0,0,1) -> 3673100000 | M57: =_xlfn.XLOOKUP("CashAndCashEquivalents",HS_CONSOLIDATED!$C:$C,HS_CONSOLIDATED!L:L,0,0,1) -> 4268400000 | N57: =_xlfn.XLOOKUP("CashAndCashEquivalents",HS_CONSOLIDATED!$C:$C,HS_CONSOLIDATED!M:M,0,0,1) -> 11128300000
D58: Loans, current | E58: =_xlfn.XLOOKUP("LoansCurrent",HS_CONSOLIDATED!$C:$C,HS_CONSOLIDATED!D:D,0,0,1) -> 0 | F58: =_xlfn.XLOOKUP("LoansCurrent",HS_CONSOLIDATED!$C:$C,HS_CONSOLIDATED!E:E,0,0,1) -> 494000000 | G58: =_xlfn.XLOOKUP("LoansCurrent",HS_CONSOLIDATED!$C:$C,HS_CONSOLIDATED!F:F,0,0,1) -> 499300000 | H58: =_xlfn.XLOOKUP("LoansCurrent",HS_CONSOLIDATED!$C:$C,HS_CONSOLIDATED!G:G,0,0,1) -> 115200000 | I58: =_xlfn.XLOOKUP("LoansCurrent",HS_CONSOLIDATED!$C:$C,HS_CONSOLIDATED!H:H,0,0,1) -> 224500000 | J58: =_xlfn.XLOOKUP("LoansCurrent",HS_CONSOLIDATED!$C:$C,HS_CONSOLIDATED!I:I,0,0,1) -> 212700000 | K58: =_xlfn.XLOOKUP("LoansCurrent",HS_CONSOLIDATED!$C:$C,HS_CONSOLIDATED!J:J,0,0,1) -> 9600000 | L58: =_xlfn.XLOOKUP("LoansCurrent",HS_CONSOLIDATED!$C:$C,HS_CONSOLIDATED!K:K,0,0,1) -> 6100000 | M58: =_xlfn.XLOOKUP("LoansCurrent",HS_CONSOLIDATED!$C:$C,HS_CONSOLIDATED!L:L,0,0,1) -> 2600000 | N58: =_xlfn.XLOOKUP("LoansCurrent",HS_CONSOLIDATED!$C:$C,HS_CONSOLIDATED!M:M,0,0,1) -> 2700000
D59: Total other current financial assets | E59: =_xlfn.XLOOKUP("OtherCurrentFinancialAssets",HS_CONSOLIDATED!$C:$C,HS_CONSOLIDATED!D:D,0,0,1) -> 0 | F59: =_xlfn.XLOOKUP("OtherCurrentFinancialAssets",HS_CONSOLIDATED!$C:$C,HS_CONSOLIDATED!E:E,0,0,1) -> 1486000000 | G59: =_xlfn.XLOOKUP("OtherCurrentFinancialAssets",HS_CONSOLIDATED!$C:$C,HS_CONSOLIDATED!F:F,0,0,1) -> 2663600000 | H59: =_xlfn.XLOOKUP("OtherCurrentFinancialAssets",HS_CONSOLIDATED!$C:$C,HS_CONSOLIDATED!G:G,0,0,1) -> 3163100000 | I59: =_xlfn.XLOOKUP("OtherCurrentFinancialAssets",HS_CONSOLIDATED!$C:$C,HS_CONSOLIDATED!H:H,0,0,1) -> 1087100000 | J59: =_xlfn.XLOOKUP("OtherCurrentFinancialAssets",HS_CONSOLIDATED!$C:$C,HS_CONSOLIDATED!I:I,0,0,1) -> 1759700000 | K59: =_xlfn.XLOOKUP("OtherCurrentFinancialAssets",HS_CONSOLIDATED!$C:$C,HS_CONSOLIDATED!J:J,0,0,1) -> 1205000000 | L59: =_xlfn.XLOOKUP("OtherCurrentFinancialAssets",HS_CONSOLIDATED!$C:$C,HS_CONSOLIDATED!K:K,0,0,1) -> 1490500000 | M59: =_xlfn.XLOOKUP("OtherCurrentFinancialAssets",HS_CONSOLIDATED!$C:$C,HS_CONSOLIDATED!L:L,0,0,1) -> 1349800000 | N59: =_xlfn.XLOOKUP("OtherCurrentFinancialAssets",HS_CONSOLIDATED!$C:$C,HS_CONSOLIDATED!M:M,0,0,1) -> 1883800000
D60: Current tax assets, Current | E60: =_xlfn.XLOOKUP("CurrentTaxAssetsCurrent",HS_CONSOLIDATED!$C:$C,HS_CONSOLIDATED!D:D,0,0,1) -> 0 | F60: =_xlfn.XLOOKUP("CurrentTaxAssetsCurrent",HS_CONSOLIDATED!$C:$C,HS_CONSOLIDATED!E:E,0,0,1) -> 451900000 | G60: =_xlfn.XLOOKUP("CurrentTaxAssetsCurrent",HS_CONSOLIDATED!$C:$C,HS_CONSOLIDATED!F:F,0,0,1) -> 93300000 | H60: =_xlfn.XLOOKUP("CurrentTaxAssetsCurrent",HS_CONSOLIDATED!$C:$C,HS_CONSOLIDATED!G:G,0,0,1) -> 160800000 | I60: =_xlfn.XLOOKUP("CurrentTaxAssetsCurrent",HS_CONSOLIDATED!$C:$C,HS_CONSOLIDATED!H:H,0,0,1) -> 204600000 | J60: =_xlfn.XLOOKUP("CurrentTaxAssetsCurrent",HS_CONSOLIDATED!$C:$C,HS_CONSOLIDATED!I:I,0,0,1) -> 61200000 | K60: =_xlfn.XLOOKUP("CurrentTaxAssetsCurrent",HS_CONSOLIDATED!$C:$C,HS_CONSOLIDATED!J:J,0,0,1) -> 11100000 | L60: =_xlfn.XLOOKUP("CurrentTaxAssetsCurrent",HS_CONSOLIDATED!$C:$C,HS_CONSOLIDATED!K:K,0,0,1) -> 5400000 | M60: =_xlfn.XLOOKUP("CurrentTaxAssetsCurrent",HS_CONSOLIDATED!$C:$C,HS_CONSOLIDATED!L:L,0,0,1) -> 11500000 | N60: =_xlfn.XLOOKUP("CurrentTaxAssetsCurrent",HS_CONSOLIDATED!$C:$C,HS_CONSOLIDATED!M:M,0,0,1) -> 503800000
C61: Total Non-Operating | E61: =IFERROR(SUM(E56:E60),0) -> 0 | F61: =IFERROR(SUM(F56:F60),0) -> 10604100000 | G61: =IFERROR(SUM(G56:G60),0) -> 9066900000 | H61: =IFERROR(SUM(H56:H60),0) -> 4185300000 | I61: =IFERROR(SUM(I56:I60),0) -> 2339500000 | J61: =IFERROR(SUM(J56:J60),0) -> 4658600000 | K61: =IFERROR(SUM(K56:K60),0) -> 6230000000 | L61: =IFERROR(SUM(L56:L60),0) -> 5175100000 | ... N61: =IFERROR(SUM(N56:N60),0) -> 13947700000
C62: Total current financial assets | E62: =_xlfn.XLOOKUP("CurrentFinancialAssets",HS_CONSOLIDATED!$C:$C,HS_CONSOLIDATED!D:D,0,0,1) -> 0 | F62: =_xlfn.XLOOKUP("CurrentFinancialAssets",HS_CONSOLIDATED!$C:$C,HS_CONSOLIDATED!E:E,0,0,1) -> 46427500000 | G62: =_xlfn.XLOOKUP("CurrentFinancialAssets",HS_CONSOLIDATED!$C:$C,HS_CONSOLIDATED!F:F,0,0,1) -> 38825100000 | H62: =_xlfn.XLOOKUP("CurrentFinancialAssets",HS_CONSOLIDATED!$C:$C,HS_CONSOLIDATED!G:G,0,0,1) -> 22830400000 | I62: =_xlfn.XLOOKUP("CurrentFinancialAssets",HS_CONSOLIDATED!$C:$C,HS_CONSOLIDATED!H:H,0,0,1) -> 15780300000 | J62: =_xlfn.XLOOKUP("CurrentFinancialAssets",HS_CONSOLIDATED!$C:$C,HS_CONSOLIDATED!I:I,0,0,1) -> 16494600000 | K62: =_xlfn.XLOOKUP("CurrentFinancialAssets",HS_CONSOLIDATED!$C:$C,HS_CONSOLIDATED!J:J,0,0,1) -> 19988400000 | L62: =_xlfn.XLOOKUP("CurrentFinancialAssets",HS_CONSOLIDATED!$C:$C,HS_CONSOLIDATED!K:K,0,0,1) -> 16874100000 | M62: =_xlfn.XLOOKUP("CurrentFinancialAssets",HS_CONSOLIDATED!$C:$C,HS_CONSOLIDATED!L:L,0,0,1) -> 24000100000 | N62: =_xlfn.XLOOKUP("CurrentFinancialAssets",HS_CONSOLIDATED!$C:$C,HS_CONSOLIDATED!M:M,0,0,1) -> 52107400000
B63: Total Current Assets | E63: =IFERROR(E61+E54,0) -> 0 | F63: =IFERROR(F61+F54,0) -> 91705400000 | G63: =IFERROR(G61+G54,0) -> 78488200000 | H63: =IFERROR(H61+H54,0) -> 64249800000 | I63: =IFERROR(I61+I54,0) -> 46435500000 | J63: =IFERROR(J61+J54,0) -> 47979200000 | K63: =IFERROR(K61+K54,0) -> 50191100000 | L63: =IFERROR(L61+L54,0) -> 41421800000 | ... N63: =IFERROR(N61+N54,0) -> 92517100000
C64: Non-current assets classified as held for sale | E64: =_xlfn.XLOOKUP("NoncurrentAssetsOrDisposalGroupsClassifiedAsHeldForSaleOrAsHeldForDistributionToOwners",HS_CONSOLIDATED!$C:$C,HS_CONSOLIDATED!D:D,0,0,1) -> 0 | F64: =_xlfn.XLOOKUP("NoncurrentAssetsOrDisposalGroupsClassifiedAsHeldForSaleOrAsHeldForDistributionToOwners",HS_CONSOLIDATED!$C:$C,HS_CONSOLIDATED!E:E,0,0,1) -> 0 | G64: =_xlfn.XLOOKUP("NoncurrentAssetsOrDisposalGroupsClassifiedAsHeldForSaleOrAsHeldForDistributionToOwners",HS_CONSOLIDATED!$C:$C,HS_CONSOLIDATED!F:F,0,0,1) -> 6621700000 | H64: =_xlfn.XLOOKUP("NoncurrentAssetsOrDisposalGroupsClassifiedAsHeldForSaleOrAsHeldForDistributionToOwners",HS_CONSOLIDATED!$C:$C,HS_CONSOLIDATED!G:G,0,0,1) -> 893600000 | I64: =_xlfn.XLOOKUP("NoncurrentAssetsOrDisposalGroupsClassifiedAsHeldForSaleOrAsHeldForDistributionToOwners",HS_CONSOLIDATED!$C:$C,HS_CONSOLIDATED!H:H,0,0,1) -> 510000000 | J64: =_xlfn.XLOOKUP("NoncurrentAssetsOrDisposalGroupsClassifiedAsHeldForSaleOrAsHeldForDistributionToOwners",HS_CONSOLIDATED!$C:$C,HS_CONSOLIDATED!I:I,0,0,1) -> 495900000 | K64: =_xlfn.XLOOKUP("NoncurrentAssetsOrDisposalGroupsClassifiedAsHeldForSaleOrAsHeldForDistributionToOwners",HS_CONSOLIDATED!$C:$C,HS_CONSOLIDATED!J:J,0,0,1) -> 657600000 | L64: =_xlfn.XLOOKUP("NoncurrentAssetsOrDisposalGroupsClassifiedAsHeldForSaleOrAsHeldForDistributionToOwners",HS_CONSOLIDATED!$C:$C,HS_CONSOLIDATED!K:K,0,0,1) -> 354700000 | M64: =_xlfn.XLOOKUP("NoncurrentAssetsOrDisposalGroupsClassifiedAsHeldForSaleOrAsHeldForDistributionToOwners",HS_CONSOLIDATED!$C:$C,HS_CONSOLIDATED!L:L,0,0,1) -> 0 | N64: =_xlfn.XLOOKUP("NoncurrentAssetsOrDisposalGroupsClassifiedAsHeldForSaleOrAsHeldForDistributionToOwners",HS_CONSOLIDATED!$C:$C,HS_CONSOLIDATED!M:M,0,0,1) -> 0
B65: Total Assets | E65: =IFERROR(SUM(E63:E64)+E48,0) -> 0 | F65: =IFERROR(SUM(F63:F64)+F48,0) -> 121601000000 | G65: =IFERROR(SUM(G63:G64)+G48,0) -> 111205700000 | H65: =IFERROR(SUM(H63:H64)+H48,0) -> 88709100000 | I65: =IFERROR(SUM(I63:I64)+I48,0) -> 65303500000 | J65: =IFERROR(SUM(J63:J64)+J48,0) -> 66010900000 | K65: =IFERROR(SUM(K63:K64)+K48,0) -> 64748600000 | L65: =IFERROR(SUM(L63:L64)+L48,0) -> 55233800000 | ... N65: =IFERROR(SUM(N63:N64)+N48,0) -> 129595900000
B66: Equity and Liabilities
B67: Equity attributable to owners of parent
C68: Equity share capital at end of period | E68: =_xlfn.XLOOKUP("EquityShareCapital",HS_CONSOLIDATED!$C:$C,HS_CONSOLIDATED!D:D,0,0,1) -> 0 | F68: =_xlfn.XLOOKUP("EquityShareCapital",HS_CONSOLIDATED!$C:$C,HS_CONSOLIDATED!E:E,0,0,1) -> 10048800000 | G68: =_xlfn.XLOOKUP("EquityShareCapital",HS_CONSOLIDATED!$C:$C,HS_CONSOLIDATED!F:F,0,0,1) -> 10639500000 | H68: =_xlfn.XLOOKUP("EquityShareCapital",HS_CONSOLIDATED!$C:$C,HS_CONSOLIDATED!G:G,0,0,1) -> 10639500000 | I68: =_xlfn.XLOOKUP("EquityShareCapital",HS_CONSOLIDATED!$C:$C,HS_CONSOLIDATED!H:H,0,0,1) -> 10639500000 | J68: =_xlfn.XLOOKUP("EquityShareCapital",HS_CONSOLIDATED!$C:$C,HS_CONSOLIDATED!I:I,0,0,1) -> 17016000000 | K68: =_xlfn.XLOOKUP("EquityShareCapital",HS_CONSOLIDATED!$C:$C,HS_CONSOLIDATED!J:J,0,0,1) -> 18434900000 | L68: =_xlfn.XLOOKUP("EquityShareCapital",HS_CONSOLIDATED!$C:$C,HS_CONSOLIDATED!K:K,0,0,1) -> 24544000000 | M68: =_xlfn.XLOOKUP("EquityShareCapital",HS_CONSOLIDATED!$C:$C,HS_CONSOLIDATED!L:L,0,0,1) -> 27217200000 | N68: =_xlfn.XLOOKUP("EquityShareCapital",HS_CONSOLIDATED!$C:$C,HS_CONSOLIDATED!M:M,0,0,1) -> 27317900000
C69: Other equity | E69: =_xlfn.XLOOKUP("OtherEquity",HS_CONSOLIDATED!$C:$C,HS_CONSOLIDATED!D:D,0,0,1) -> 0 | F69: =_xlfn.XLOOKUP("OtherEquity",HS_CONSOLIDATED!$C:$C,HS_CONSOLIDATED!E:E,0,0,1) -> -78462100000 | G69: =_xlfn.XLOOKUP("OtherEquity",HS_CONSOLIDATED!$C:$C,HS_CONSOLIDATED!F:F,0,0,1) -> -80308000000 | H69: =_xlfn.XLOOKUP("OtherEquity",HS_CONSOLIDATED!$C:$C,HS_CONSOLIDATED!G:G,0,0,1) -> -95615600000 | I69: =_xlfn.XLOOKUP("OtherEquity",HS_CONSOLIDATED!$C:$C,HS_CONSOLIDATED!H:H,0,0,1) -> -120468900000 | J69: =_xlfn.XLOOKUP("OtherEquity",HS_CONSOLIDATED!$C:$C,HS_CONSOLIDATED!I:I,0,0,1) -> -50446300000 | K69: =_xlfn.XLOOKUP("OtherEquity",HS_CONSOLIDATED!$C:$C,HS_CONSOLIDATED!J:J,0,0,1) -> -53692200000 | L69: =_xlfn.XLOOKUP("OtherEquity",HS_CONSOLIDATED!$C:$C,HS_CONSOLIDATED!K:K,0,0,1) -> -13552600000 | M69: =_xlfn.XLOOKUP("OtherEquity",HS_CONSOLIDATED!$C:$C,HS_CONSOLIDATED!L:L,0,0,1) -> 11985900000 | N69: =_xlfn.XLOOKUP("OtherEquity",HS_CONSOLIDATED!$C:$C,HS_CONSOLIDATED!M:M,0,0,1) -> 33739300000
B70: Total equity attributable to owners of parent | E70: =IFERROR(SUM(E68:E69),0) -> 0 | F70: =IFERROR(SUM(F68:F69),0) -> -68413300000 | G70: =IFERROR(SUM(G68:G69),0) -> -69668500000 | H70: =IFERROR(SUM(H68:H69),0) -> -84976100000 | I70: =IFERROR(SUM(I68:I69),0) -> -109829400000 | J70: =IFERROR(SUM(J68:J69),0) -> -33430300000 | K70: =IFERROR(SUM(K68:K69),0) -> -35257300000 | L70: =IFERROR(SUM(L68:L69),0) -> 10991400000 | ... N70: =IFERROR(SUM(N68:N69),0) -> 61057200000
C71: Non controlling interest | E71: =_xlfn.XLOOKUP("NonControllingInterest",HS_CONSOLIDATED!$C:$C,HS_CONSOLIDATED!D:D,0,0,1) -> 0 | F71: =_xlfn.XLOOKUP("NonControllingInterest",HS_CONSOLIDATED!$C:$C,HS_CONSOLIDATED!E:E,0,0,1) -> 86800000 | G71: =_xlfn.XLOOKUP("NonControllingInterest",HS_CONSOLIDATED!$C:$C,HS_CONSOLIDATED!F:F,0,0,1) -> 101900000 | H71: =_xlfn.XLOOKUP("NonControllingInterest",HS_CONSOLIDATED!$C:$C,HS_CONSOLIDATED!G:G,0,0,1) -> -54800000 | I71: =_xlfn.XLOOKUP("NonControllingInterest",HS_CONSOLIDATED!$C:$C,HS_CONSOLIDATED!H:H,0,0,1) -> -589000000 | J71: =_xlfn.XLOOKUP("NonControllingInterest",HS_CONSOLIDATED!$C:$C,HS_CONSOLIDATED!I:I,0,0,1) -> -576800000 | K71: =_xlfn.XLOOKUP("NonControllingInterest",HS_CONSOLIDATED!$C:$C,HS_CONSOLIDATED!J:J,0,0,1) -> -360800000 | L71: =_xlfn.XLOOKUP("NonControllingInterest",HS_CONSOLIDATED!$C:$C,HS_CONSOLIDATED!K:K,0,0,1) -> 0 | M71: =_xlfn.XLOOKUP("NonControllingInterest",HS_CONSOLIDATED!$C:$C,HS_CONSOLIDATED!L:L,0,0,1) -> 0 | N71: =_xlfn.XLOOKUP("NonControllingInterest",HS_CONSOLIDATED!$C:$C,HS_CONSOLIDATED!M:M,0,0,1) -> 0
B72: Equity at end of period | E72: =IFERROR(SUM(E70:E71),0) -> 0 | F72: =IFERROR(SUM(F70:F71),0) -> -68326500000 | G72: =IFERROR(SUM(G70:G71),0) -> -69566600000 | H72: =IFERROR(SUM(H70:H71),0) -> -85030900000 | I72: =IFERROR(SUM(I70:I71),0) -> -110418400000 | J72: =IFERROR(SUM(J70:J71),0) -> -34007100000 | K72: =IFERROR(SUM(K70:K71),0) -> -35618100000 | L72: =IFERROR(SUM(L70:L71),0) -> 10991400000 | ... N72: =IFERROR(SUM(N70:N71),0) -> 61057200000
B73: Liabilities
B74: Non-current liabilities
B75: Non-current financial liabilities
C76: Borrowings, non-current | E76: =_xlfn.XLOOKUP("BorrowingsNoncurrent",HS_CONSOLIDATED!$C:$C,HS_CONSOLIDATED!D:D,0,0,1) -> 0 | F76: =_xlfn.XLOOKUP("BorrowingsNoncurrent",HS_CONSOLIDATED!$C:$C,HS_CONSOLIDATED!E:E,0,0,1) -> 48409800000 | G76: =_xlfn.XLOOKUP("BorrowingsNoncurrent",HS_CONSOLIDATED!$C:$C,HS_CONSOLIDATED!F:F,0,0,1) -> 77157100000 | H76: =_xlfn.XLOOKUP("BorrowingsNoncurrent",HS_CONSOLIDATED!$C:$C,HS_CONSOLIDATED!G:G,0,0,1) -> 62441400000 | I76: =_xlfn.XLOOKUP("BorrowingsNoncurrent",HS_CONSOLIDATED!$C:$C,HS_CONSOLIDATED!H:H,0,0,1) -> 8417700000 | J76: =_xlfn.XLOOKUP("BorrowingsNoncurrent",HS_CONSOLIDATED!$C:$C,HS_CONSOLIDATED!I:I,0,0,1) -> 60272000000 | K76: =_xlfn.XLOOKUP("BorrowingsNoncurrent",HS_CONSOLIDATED!$C:$C,HS_CONSOLIDATED!J:J,0,0,1) -> 55924400000 | L76: =_xlfn.XLOOKUP("BorrowingsNoncurrent",HS_CONSOLIDATED!$C:$C,HS_CONSOLIDATED!K:K,0,0,1) -> 15172700000 | M76: =_xlfn.XLOOKUP("BorrowingsNoncurrent",HS_CONSOLIDATED!$C:$C,HS_CONSOLIDATED!L:L,0,0,1) -> 498700000 | N76: =_xlfn.XLOOKUP("BorrowingsNoncurrent",HS_CONSOLIDATED!$C:$C,HS_CONSOLIDATED!M:M,0,0,1) -> 1291900000
C77: Trade payables, non-current
C78: Total other non-current financial liabilities | E78: =_xlfn.XLOOKUP("OtherNoncurrentFinancialLiabilities",HS_CONSOLIDATED!$C:$C,HS_CONSOLIDATED!D:D,0,0,1) -> 0 | F78: =_xlfn.XLOOKUP("OtherNoncurrentFinancialLiabilities",HS_CONSOLIDATED!$C:$C,HS_CONSOLIDATED!E:E,0,0,1) -> 2254600000 | G78: =_xlfn.XLOOKUP("OtherNoncurrentFinancialLiabilities",HS_CONSOLIDATED!$C:$C,HS_CONSOLIDATED!F:F,0,0,1) -> 553300000 | H78: =_xlfn.XLOOKUP("OtherNoncurrentFinancialLiabilities",HS_CONSOLIDATED!$C:$C,HS_CONSOLIDATED!G:G,0,0,1) -> 504900000 | I78: =_xlfn.XLOOKUP("OtherNoncurrentFinancialLiabilities",HS_CONSOLIDATED!$C:$C,HS_CONSOLIDATED!H:H,0,0,1) -> 910900000 | J78: =_xlfn.XLOOKUP("OtherNoncurrentFinancialLiabilities",HS_CONSOLIDATED!$C:$C,HS_CONSOLIDATED!I:I,0,0,1) -> 775400000 | K78: =_xlfn.XLOOKUP("OtherNoncurrentFinancialLiabilities",HS_CONSOLIDATED!$C:$C,HS_CONSOLIDATED!J:J,0,0,1) -> 792100000 | L78: =_xlfn.XLOOKUP("OtherNoncurrentFinancialLiabilities",HS_CONSOLIDATED!$C:$C,HS_CONSOLIDATED!K:K,0,0,1) -> 375200000 | M78: =_xlfn.XLOOKUP("OtherNoncurrentFinancialLiabilities",HS_CONSOLIDATED!$C:$C,HS_CONSOLIDATED!L:L,0,0,1) -> 341300000 | N78: =_xlfn.XLOOKUP("OtherNoncurrentFinancialLiabilities",HS_CONSOLIDATED!$C:$C,HS_CONSOLIDATED!M:M,0,0,1) -> 6546100000
C79: Total non-current financial liabilities | E79: =_xlfn.XLOOKUP("NoncurrentFinancialLiabilities",HS_CONSOLIDATED!$C:$C,HS_CONSOLIDATED!D:D,0,0,1) -> 0 | F79: =_xlfn.XLOOKUP("NoncurrentFinancialLiabilities",HS_CONSOLIDATED!$C:$C,HS_CONSOLIDATED!E:E,0,0,1) -> 50664400000 | G79: =_xlfn.XLOOKUP("NoncurrentFinancialLiabilities",HS_CONSOLIDATED!$C:$C,HS_CONSOLIDATED!F:F,0,0,1) -> 77710400000 | H79: =_xlfn.XLOOKUP("NoncurrentFinancialLiabilities",HS_CONSOLIDATED!$C:$C,HS_CONSOLIDATED!G:G,0,0,1) -> 62946300000 | I79: =_xlfn.XLOOKUP("NoncurrentFinancialLiabilities",HS_CONSOLIDATED!$C:$C,HS_CONSOLIDATED!H:H,0,0,1) -> 9328600000 | J79: =_xlfn.XLOOKUP("NoncurrentFinancialLiabilities",HS_CONSOLIDATED!$C:$C,HS_CONSOLIDATED!I:I,0,0,1) -> 61047400000 | K79: =_xlfn.XLOOKUP("NoncurrentFinancialLiabilities",HS_CONSOLIDATED!$C:$C,HS_CONSOLIDATED!J:J,0,0,1) -> 56716500000 | L79: =_xlfn.XLOOKUP("NoncurrentFinancialLiabilities",HS_CONSOLIDATED!$C:$C,HS_CONSOLIDATED!K:K,0,0,1) -> 15547900000 | M79: =_xlfn.XLOOKUP("NoncurrentFinancialLiabilities",HS_CONSOLIDATED!$C:$C,HS_CONSOLIDATED!L:L,0,0,1) -> 840000000 | N79: =_xlfn.XLOOKUP("NoncurrentFinancialLiabilities",HS_CONSOLIDATED!$C:$C,HS_CONSOLIDATED!M:M,0,0,1) -> 7838000000
D80: Provisions, non-current | E80: =_xlfn.XLOOKUP("ProvisionsNoncurrent",HS_CONSOLIDATED!$C:$C,HS_CONSOLIDATED!D:D,0,0,1) -> 0 | F80: =_xlfn.XLOOKUP("ProvisionsNoncurrent",HS_CONSOLIDATED!$C:$C,HS_CONSOLIDATED!E:E,0,0,1) -> 1272000000 | G80: =_xlfn.XLOOKUP("ProvisionsNoncurrent",HS_CONSOLIDATED!$C:$C,HS_CONSOLIDATED!F:F,0,0,1) -> 1204300000 | H80: =_xlfn.XLOOKUP("ProvisionsNoncurrent",HS_CONSOLIDATED!$C:$C,HS_CONSOLIDATED!G:G,0,0,1) -> 1184600000 | I80: =_xlfn.XLOOKUP("ProvisionsNoncurrent",HS_CONSOLIDATED!$C:$C,HS_CONSOLIDATED!H:H,0,0,1) -> 932700000 | J80: =_xlfn.XLOOKUP("ProvisionsNoncurrent",HS_CONSOLIDATED!$C:$C,HS_CONSOLIDATED!I:I,0,0,1) -> 825100000 | K80: =_xlfn.XLOOKUP("ProvisionsNoncurrent",HS_CONSOLIDATED!$C:$C,HS_CONSOLIDATED!J:J,0,0,1) -> 1304300000 | L80: =_xlfn.XLOOKUP("ProvisionsNoncurrent",HS_CONSOLIDATED!$C:$C,HS_CONSOLIDATED!K:K,0,0,1) -> 1681800000 | M80: =_xlfn.XLOOKUP("ProvisionsNoncurrent",HS_CONSOLIDATED!$C:$C,HS_CONSOLIDATED!L:L,0,0,1) -> 1653800000 | N80: =_xlfn.XLOOKUP("ProvisionsNoncurrent",HS_CONSOLIDATED!$C:$C,HS_CONSOLIDATED!M:M,0,0,1) -> 1549800000
D81: Total other non-current liabilities | E81: =_xlfn.XLOOKUP("OtherNoncurrentLiabilities",HS_CONSOLIDATED!$C:$C,HS_CONSOLIDATED!D:D,0,0,1) -> 0 | F81: =_xlfn.XLOOKUP("OtherNoncurrentLiabilities",HS_CONSOLIDATED!$C:$C,HS_CONSOLIDATED!E:E,0,0,1) -> 400200000 | G81: =_xlfn.XLOOKUP("OtherNoncurrentLiabilities",HS_CONSOLIDATED!$C:$C,HS_CONSOLIDATED!F:F,0,0,1) -> 299800000 | H81: =_xlfn.XLOOKUP("OtherNoncurrentLiabilities",HS_CONSOLIDATED!$C:$C,HS_CONSOLIDATED!G:G,0,0,1) -> 117000000 | I81: =_xlfn.XLOOKUP("OtherNoncurrentLiabilities",HS_CONSOLIDATED!$C:$C,HS_CONSOLIDATED!H:H,0,0,1) -> 8900000 | J81: =_xlfn.XLOOKUP("OtherNoncurrentLiabilities",HS_CONSOLIDATED!$C:$C,HS_CONSOLIDATED!I:I,0,0,1) -> 7700000 | K81: =_xlfn.XLOOKUP("OtherNoncurrentLiabilities",HS_CONSOLIDATED!$C:$C,HS_CONSOLIDATED!J:J,0,0,1) -> 1900000 | L81: =_xlfn.XLOOKUP("OtherNoncurrentLiabilities",HS_CONSOLIDATED!$C:$C,HS_CONSOLIDATED!K:K,0,0,1) -> 4800000 | M81: =_xlfn.XLOOKUP("OtherNoncurrentLiabilities",HS_CONSOLIDATED!$C:$C,HS_CONSOLIDATED!L:L,0,0,1) -> 4800000 | N81: =_xlfn.XLOOKUP("OtherNoncurrentLiabilities",HS_CONSOLIDATED!$C:$C,HS_CONSOLIDATED!M:M,0,0,1) -> 4500000
B82: Total non-current liabilities | E82: =IFERROR(SUM(E76:E76)+SUM(E78:E78)+SUM(E80:E81),0) -> 0 | F82: =IFERROR(SUM(F76:F76)+SUM(F78:F78)+SUM(F80:F81),0) -> 52336600000 | G82: =IFERROR(SUM(G76:G76)+SUM(G78:G78)+SUM(G80:G81),0) -> 79214500000 | H82: =IFERROR(SUM(H76:H76)+SUM(H78:H78)+SUM(H80:H81),0) -> 64247900000 | I82: =IFERROR(SUM(I76:I76)+SUM(I78:I78)+SUM(I80:I81),0) -> 10270200000 | J82: =IFERROR(SUM(J76:J76)+SUM(J78:J78)+SUM(J80:J81),0) -> 61880200000 | K82: =IFERROR(SUM(K76:K76)+SUM(K78:K78)+SUM(K80:K81),0) -> 58022700000 | L82: =IFERROR(SUM(L76:L76)+SUM(L78:L78)+SUM(L80:L81),0) -> 17234500000 | ... N82: =IFERROR(SUM(N76:N76)+SUM(N78:N78)+SUM(N80:N81),0) -> 9392300000
B83: Current liabilities
B84: Current financial liabilities
C85: Borrowings, current | E85: =_xlfn.XLOOKUP("BorrowingsCurrent",HS_CONSOLIDATED!$C:$C,HS_CONSOLIDATED!D:D,0,0,1) -> 0 | F85: =_xlfn.XLOOKUP("BorrowingsCurrent",HS_CONSOLIDATED!$C:$C,HS_CONSOLIDATED!E:E,0,0,1) -> 20763800000 | G85: =_xlfn.XLOOKUP("BorrowingsCurrent",HS_CONSOLIDATED!$C:$C,HS_CONSOLIDATED!F:F,0,0,1) -> 38894500000 | H85: =_xlfn.XLOOKUP("BorrowingsCurrent",HS_CONSOLIDATED!$C:$C,HS_CONSOLIDATED!G:G,0,0,1) -> 33797900000 | I85: =_xlfn.XLOOKUP("BorrowingsCurrent",HS_CONSOLIDATED!$C:$C,HS_CONSOLIDATED!H:H,0,0,1) -> 88438500000 | J85: =_xlfn.XLOOKUP("BorrowingsCurrent",HS_CONSOLIDATED!$C:$C,HS_CONSOLIDATED!I:I,0,0,1) -> 1753400000 | K85: =_xlfn.XLOOKUP("BorrowingsCurrent",HS_CONSOLIDATED!$C:$C,HS_CONSOLIDATED!J:J,0,0,1) -> 7981200000 | L85: =_xlfn.XLOOKUP("BorrowingsCurrent",HS_CONSOLIDATED!$C:$C,HS_CONSOLIDATED!K:K,0,0,1) -> 3876100000 | M85: =_xlfn.XLOOKUP("BorrowingsCurrent",HS_CONSOLIDATED!$C:$C,HS_CONSOLIDATED!L:L,0,0,1) -> 600800000 | N85: =_xlfn.XLOOKUP("BorrowingsCurrent",HS_CONSOLIDATED!$C:$C,HS_CONSOLIDATED!M:M,0,0,1) -> 1541400000
C86: Trade payables, current
D87: Total trade payables, current | E87: =_xlfn.XLOOKUP("TradePayablesCurrent",HS_CONSOLIDATED!$C:$C,HS_CONSOLIDATED!D:D,0,0,1) -> 0 | F87: =_xlfn.XLOOKUP("TradePayablesCurrent",HS_CONSOLIDATED!$C:$C,HS_CONSOLIDATED!E:E,0,0,1) -> 48122500000 | G87: =_xlfn.XLOOKUP("TradePayablesCurrent",HS_CONSOLIDATED!$C:$C,HS_CONSOLIDATED!F:F,0,0,1) -> 25266000000 | H87: =_xlfn.XLOOKUP("TradePayablesCurrent",HS_CONSOLIDATED!$C:$C,HS_CONSOLIDATED!G:G,0,0,1) -> 21751900000 | I87: =_xlfn.XLOOKUP("TradePayablesCurrent",HS_CONSOLIDATED!$C:$C,HS_CONSOLIDATED!H:H,0,0,1) -> 12981800000 | J87: =_xlfn.XLOOKUP("TradePayablesCurrent",HS_CONSOLIDATED!$C:$C,HS_CONSOLIDATED!I:I,0,0,1) -> 15819900000 | K87: =_xlfn.XLOOKUP("TradePayablesCurrent",HS_CONSOLIDATED!$C:$C,HS_CONSOLIDATED!J:J,0,0,1) -> 18404900000 | L87: =_xlfn.XLOOKUP("TradePayablesCurrent",HS_CONSOLIDATED!$C:$C,HS_CONSOLIDATED!K:K,0,0,1) -> 8946400000 | M87: =_xlfn.XLOOKUP("TradePayablesCurrent",HS_CONSOLIDATED!$C:$C,HS_CONSOLIDATED!L:L,0,0,1) -> 17957800000 | N87: =_xlfn.XLOOKUP("TradePayablesCurrent",HS_CONSOLIDATED!$C:$C,HS_CONSOLIDATED!M:M,0,0,1) -> 29351400000
C88: Total other current financial liabilities | E88: =_xlfn.XLOOKUP("OtherCurrentFinancialLiabilities",HS_CONSOLIDATED!$C:$C,HS_CONSOLIDATED!D:D,0,0,1) -> 0 | F88: =_xlfn.XLOOKUP("OtherCurrentFinancialLiabilities",HS_CONSOLIDATED!$C:$C,HS_CONSOLIDATED!E:E,0,0,1) -> 49265400000 | G88: =_xlfn.XLOOKUP("OtherCurrentFinancialLiabilities",HS_CONSOLIDATED!$C:$C,HS_CONSOLIDATED!F:F,0,0,1) -> 15979300000 | H88: =_xlfn.XLOOKUP("OtherCurrentFinancialLiabilities",HS_CONSOLIDATED!$C:$C,HS_CONSOLIDATED!G:G,0,0,1) -> 30606500000 | I88: =_xlfn.XLOOKUP("OtherCurrentFinancialLiabilities",HS_CONSOLIDATED!$C:$C,HS_CONSOLIDATED!H:H,0,0,1) -> 53105400000 | J88: =_xlfn.XLOOKUP("OtherCurrentFinancialLiabilities",HS_CONSOLIDATED!$C:$C,HS_CONSOLIDATED!I:I,0,0,1) -> 10241800000 | K88: =_xlfn.XLOOKUP("OtherCurrentFinancialLiabilities",HS_CONSOLIDATED!$C:$C,HS_CONSOLIDATED!J:J,0,0,1) -> 3803800000 | L88: =_xlfn.XLOOKUP("OtherCurrentFinancialLiabilities",HS_CONSOLIDATED!$C:$C,HS_CONSOLIDATED!K:K,0,0,1) -> 2165300000 | M88: =_xlfn.XLOOKUP("OtherCurrentFinancialLiabilities",HS_CONSOLIDATED!$C:$C,HS_CONSOLIDATED!L:L,0,0,1) -> 1889300000 | N88: =_xlfn.XLOOKUP("OtherCurrentFinancialLiabilities",HS_CONSOLIDATED!$C:$C,HS_CONSOLIDATED!M:M,0,0,1) -> 4140400000
B89: Total current financial liabilities | E89: =_xlfn.XLOOKUP("CurrentFinancialLiabilities",HS_CONSOLIDATED!$C:$C,HS_CONSOLIDATED!D:D,0,0,1) -> 0 | F89: =_xlfn.XLOOKUP("CurrentFinancialLiabilities",HS_CONSOLIDATED!$C:$C,HS_CONSOLIDATED!E:E,0,0,1) -> 118151700000 | G89: =_xlfn.XLOOKUP("CurrentFinancialLiabilities",HS_CONSOLIDATED!$C:$C,HS_CONSOLIDATED!F:F,0,0,1) -> 80139800000 | H89: =_xlfn.XLOOKUP("CurrentFinancialLiabilities",HS_CONSOLIDATED!$C:$C,HS_CONSOLIDATED!G:G,0,0,1) -> 86156300000 | I89: =_xlfn.XLOOKUP("CurrentFinancialLiabilities",HS_CONSOLIDATED!$C:$C,HS_CONSOLIDATED!H:H,0,0,1) -> 154525700000 | J89: =_xlfn.XLOOKUP("CurrentFinancialLiabilities",HS_CONSOLIDATED!$C:$C,HS_CONSOLIDATED!I:I,0,0,1) -> 27815100000 | K89: =_xlfn.XLOOKUP("CurrentFinancialLiabilities",HS_CONSOLIDATED!$C:$C,HS_CONSOLIDATED!J:J,0,0,1) -> 30189900000 | L89: =_xlfn.XLOOKUP("CurrentFinancialLiabilities",HS_CONSOLIDATED!$C:$C,HS_CONSOLIDATED!K:K,0,0,1) -> 14987800000 | M89: =_xlfn.XLOOKUP("CurrentFinancialLiabilities",HS_CONSOLIDATED!$C:$C,HS_CONSOLIDATED!L:L,0,0,1) -> 20447900000 | N89: =_xlfn.XLOOKUP("CurrentFinancialLiabilities",HS_CONSOLIDATED!$C:$C,HS_CONSOLIDATED!M:M,0,0,1) -> 35033200000
C90: Total other current liabilities | E90: =_xlfn.XLOOKUP("OtherCurrentLiabilities",HS_CONSOLIDATED!$C:$C,HS_CONSOLIDATED!D:D,0,0,1) -> 0 | F90: =_xlfn.XLOOKUP("OtherCurrentLiabilities",HS_CONSOLIDATED!$C:$C,HS_CONSOLIDATED!E:E,0,0,1) -> 11221300000 | G90: =_xlfn.XLOOKUP("OtherCurrentLiabilities",HS_CONSOLIDATED!$C:$C,HS_CONSOLIDATED!F:F,0,0,1) -> 10363800000 | H90: =_xlfn.XLOOKUP("OtherCurrentLiabilities",HS_CONSOLIDATED!$C:$C,HS_CONSOLIDATED!G:G,0,0,1) -> 15940600000 | I90: =_xlfn.XLOOKUP("OtherCurrentLiabilities",HS_CONSOLIDATED!$C:$C,HS_CONSOLIDATED!H:H,0,0,1) -> 3869400000 | J90: =_xlfn.XLOOKUP("OtherCurrentLiabilities",HS_CONSOLIDATED!$C:$C,HS_CONSOLIDATED!I:I,0,0,1) -> 4931300000 | K90: =_xlfn.XLOOKUP("OtherCurrentLiabilities",HS_CONSOLIDATED!$C:$C,HS_CONSOLIDATED!J:J,0,0,1) -> 5582900000 | L90: =_xlfn.XLOOKUP("OtherCurrentLiabilities",HS_CONSOLIDATED!$C:$C,HS_CONSOLIDATED!K:K,0,0,1) -> 6311700000 | M90: =_xlfn.XLOOKUP("OtherCurrentLiabilities",HS_CONSOLIDATED!$C:$C,HS_CONSOLIDATED!L:L,0,0,1) -> 4105200000 | N90: =_xlfn.XLOOKUP("OtherCurrentLiabilities",HS_CONSOLIDATED!$C:$C,HS_CONSOLIDATED!M:M,0,0,1) -> 18391200000
C91: Provisions, current | E91: =_xlfn.XLOOKUP("ProvisionsCurrent",HS_CONSOLIDATED!$C:$C,HS_CONSOLIDATED!D:D,0,0,1) -> 0 | F91: =_xlfn.XLOOKUP("ProvisionsCurrent",HS_CONSOLIDATED!$C:$C,HS_CONSOLIDATED!E:E,0,0,1) -> 8217900000 | G91: =_xlfn.XLOOKUP("ProvisionsCurrent",HS_CONSOLIDATED!$C:$C,HS_CONSOLIDATED!F:F,0,0,1) -> 8185800000 | H91: =_xlfn.XLOOKUP("ProvisionsCurrent",HS_CONSOLIDATED!$C:$C,HS_CONSOLIDATED!G:G,0,0,1) -> 7395200000 | I91: =_xlfn.XLOOKUP("ProvisionsCurrent",HS_CONSOLIDATED!$C:$C,HS_CONSOLIDATED!H:H,0,0,1) -> 7056600000 | J91: =_xlfn.XLOOKUP("ProvisionsCurrent",HS_CONSOLIDATED!$C:$C,HS_CONSOLIDATED!I:I,0,0,1) -> 5391400000 | K91: =_xlfn.XLOOKUP("ProvisionsCurrent",HS_CONSOLIDATED!$C:$C,HS_CONSOLIDATED!J:J,0,0,1) -> 6571200000 | L91: =_xlfn.XLOOKUP("ProvisionsCurrent",HS_CONSOLIDATED!$C:$C,HS_CONSOLIDATED!K:K,0,0,1) -> 5708400000 | M91: =_xlfn.XLOOKUP("ProvisionsCurrent",HS_CONSOLIDATED!$C:$C,HS_CONSOLIDATED!L:L,0,0,1) -> 5515800000 | N91: =_xlfn.XLOOKUP("ProvisionsCurrent",HS_CONSOLIDATED!$C:$C,HS_CONSOLIDATED!M:M,0,0,1) -> 5637300000
C92: Current tax liabilities | E92: =_xlfn.XLOOKUP("CurrentTaxLiabilities",HS_CONSOLIDATED!$C:$C,HS_CONSOLIDATED!D:D,0,0,1) -> 0 | F92: =_xlfn.XLOOKUP("CurrentTaxLiabilities",HS_CONSOLIDATED!$C:$C,HS_CONSOLIDATED!E:E,0,0,1) -> 0 | G92: =_xlfn.XLOOKUP("CurrentTaxLiabilities",HS_CONSOLIDATED!$C:$C,HS_CONSOLIDATED!F:F,0,0,1) -> 0 | H92: =_xlfn.XLOOKUP("CurrentTaxLiabilities",HS_CONSOLIDATED!$C:$C,HS_CONSOLIDATED!G:G,0,0,1) -> 0 | I92: =_xlfn.XLOOKUP("CurrentTaxLiabilities",HS_CONSOLIDATED!$C:$C,HS_CONSOLIDATED!H:H,0,0,1) -> 0 | J92: =_xlfn.XLOOKUP("CurrentTaxLiabilities",HS_CONSOLIDATED!$C:$C,HS_CONSOLIDATED!I:I,0,0,1) -> 0 | K92: =_xlfn.XLOOKUP("CurrentTaxLiabilities",HS_CONSOLIDATED!$C:$C,HS_CONSOLIDATED!J:J,0,0,1) -> 0 | L92: =_xlfn.XLOOKUP("CurrentTaxLiabilities",HS_CONSOLIDATED!$C:$C,HS_CONSOLIDATED!K:K,0,0,1) -> 0 | M92: =_xlfn.XLOOKUP("CurrentTaxLiabilities",HS_CONSOLIDATED!$C:$C,HS_CONSOLIDATED!L:L,0,0,1) -> 19600000 | N92: =_xlfn.XLOOKUP("CurrentTaxLiabilities",HS_CONSOLIDATED!$C:$C,HS_CONSOLIDATED!M:M,0,0,1) -> 84700000
B93: Total current liabilities | E93: =IFERROR(SUM(E85:E85)+SUM(E87:E88)+SUM(E90:E92),0) -> 0 | F93: =IFERROR(SUM(F85:F85)+SUM(F87:F88)+SUM(F90:F92),0) -> 137590900000 | G93: =IFERROR(SUM(G85:G85)+SUM(G87:G88)+SUM(G90:G92),0) -> 98689400000 | H93: =IFERROR(SUM(H85:H85)+SUM(H87:H88)+SUM(H90:H92),0) -> 109492100000 | I93: =IFERROR(SUM(I85:I85)+SUM(I87:I88)+SUM(I90:I92),0) -> 165451700000 | J93: =IFERROR(SUM(J85:J85)+SUM(J87:J88)+SUM(J90:J92),0) -> 38137800000 | K93: =IFERROR(SUM(K85:K85)+SUM(K87:K88)+SUM(K90:K92),0) -> 42344000000 | L93: =IFERROR(SUM(L85:L85)+SUM(L87:L88)+SUM(L90:L92),0) -> 27007900000 | ... N93: =IFERROR(SUM(N85:N85)+SUM(N87:N88)+SUM(N90:N92),0) -> 59146400000
C94: Liabilities directly associated with assets in disposal group classified as held for sale | E94: =_xlfn.XLOOKUP("LiabilitiesDirectlyAssociatedWithAssetsInDisposalGroupClassifiedAsHeldForSale",HS_CONSOLIDATED!$C:$C,HS_CONSOLIDATED!D:D,0,0,1) -> 0 | F94: =_xlfn.XLOOKUP("LiabilitiesDirectlyAssociatedWithAssetsInDisposalGroupClassifiedAsHeldForSale",HS_CONSOLIDATED!$C:$C,HS_CONSOLIDATED!E:E,0,0,1) -> 0 | G94: =_xlfn.XLOOKUP("LiabilitiesDirectlyAssociatedWithAssetsInDisposalGroupClassifiedAsHeldForSale",HS_CONSOLIDATED!$C:$C,HS_CONSOLIDATED!F:F,0,0,1) -> 2868400000 | H94: =_xlfn.XLOOKUP("LiabilitiesDirectlyAssociatedWithAssetsInDisposalGroupClassifiedAsHeldForSale",HS_CONSOLIDATED!$C:$C,HS_CONSOLIDATED!G:G,0,0,1) -> 0 | I94: =_xlfn.XLOOKUP("LiabilitiesDirectlyAssociatedWithAssetsInDisposalGroupClassifiedAsHeldForSale",HS_CONSOLIDATED!$C:$C,HS_CONSOLIDATED!H:H,0,0,1) -> 0 | J94: =_xlfn.XLOOKUP("LiabilitiesDirectlyAssociatedWithAssetsInDisposalGroupClassifiedAsHeldForSale",HS_CONSOLIDATED!$C:$C,HS_CONSOLIDATED!I:I,0,0,1) -> 0 | K94: =_xlfn.XLOOKUP("LiabilitiesDirectlyAssociatedWithAssetsInDisposalGroupClassifiedAsHeldForSale",HS_CONSOLIDATED!$C:$C,HS_CONSOLIDATED!J:J,0,0,1) -> 0 | L94: =_xlfn.XLOOKUP("LiabilitiesDirectlyAssociatedWithAssetsInDisposalGroupClassifiedAsHeldForSale",HS_CONSOLIDATED!$C:$C,HS_CONSOLIDATED!K:K,0,0,1) -> 0 | M94: =_xlfn.XLOOKUP("LiabilitiesDirectlyAssociatedWithAssetsInDisposalGroupClassifiedAsHeldForSale",HS_CONSOLIDATED!$C:$C,HS_CONSOLIDATED!L:L,0,0,1) -> 0 | N94: =_xlfn.XLOOKUP("LiabilitiesDirectlyAssociatedWithAssetsInDisposalGroupClassifiedAsHeldForSale",HS_CONSOLIDATED!$C:$C,HS_CONSOLIDATED!M:M,0,0,1) -> 0
B95: Liabilities | E95: =IFERROR(SUM(E93:E94)+E82,0) -> 0 | F95: =IFERROR(SUM(F93:F94)+F82,0) -> 189927500000 | G95: =IFERROR(SUM(G93:G94)+G82,0) -> 180772300000 | H95: =IFERROR(SUM(H93:H94)+H82,0) -> 173740000000 | I95: =IFERROR(SUM(I93:I94)+I82,0) -> 175721900000 | J95: =IFERROR(SUM(J93:J94)+J82,0) -> 100018000000 | K95: =IFERROR(SUM(K93:K94)+K82,0) -> 100366700000 | L95: =IFERROR(SUM(L93:L94)+L82,0) -> 44242400000 | ... N95: =IFERROR(SUM(N93:N94)+N82,0) -> 68538700000
B96: Total equity and liabilities | E96: =IFERROR(E72+E95,0) -> 0 | F96: =IFERROR(F72+F95,0) -> 121601000000 | G96: =IFERROR(G72+G95,0) -> 111205700000 | H96: =IFERROR(H72+H95,0) -> 88709100000 | I96: =IFERROR(I72+I95,0) -> 65303500000 | J96: =IFERROR(J72+J95,0) -> 66010900000 | K96: =IFERROR(K72+K95,0) -> 64748600000 | L96: =IFERROR(L72+L95,0) -> 55233800000 | ... N96: =IFERROR(N72+N95,0) -> 129595900000
B97: BALANCE CHECK (Total Assets − Total Equity & Liabilities) | E97: =E65-E96 -> 0 | F97: =F65-F96 -> 0 | G97: =G65-G96 -> 0 | H97: =H65-H96 -> 0 | I97: =I65-I96 -> 0 | J97: =J65-J96 -> 0 | K97: =K65-K96 -> 0 | L97: =L65-L96 -> 0 | ... N97: =N65-N96 -> 0
A98: # | B98: Statement of Cash Flows
B99: Cash flows from used in operating activities
C100: Total profit before tax | E100: =_xlfn.XLOOKUP("ProfitBeforeTax",HS_CONSOLIDATED!$C:$C,HS_CONSOLIDATED!D:D,0,0,1) -> 0 | F100: =_xlfn.XLOOKUP("ProfitBeforeTax",HS_CONSOLIDATED!$C:$C,HS_CONSOLIDATED!E:E,0,0,1) -> 9115900000 | G100: =_xlfn.XLOOKUP("ProfitBeforeTax",HS_CONSOLIDATED!$C:$C,HS_CONSOLIDATED!F:F,0,0,1) -> -3907400000 | H100: =_xlfn.XLOOKUP("ProfitBeforeTax",HS_CONSOLIDATED!$C:$C,HS_CONSOLIDATED!G:G,0,0,1) -> -15429900000 | I100: =_xlfn.XLOOKUP("ProfitBeforeTax",HS_CONSOLIDATED!$C:$C,HS_CONSOLIDATED!H:H,0,0,1) -> -26839500000 | J100: =_xlfn.XLOOKUP("ProfitBeforeTax",HS_CONSOLIDATED!$C:$C,HS_CONSOLIDATED!I:I,0,0,1) -> 1049700000 | K100: =_xlfn.XLOOKUP("ProfitBeforeTax",HS_CONSOLIDATED!$C:$C,HS_CONSOLIDATED!J:J,0,0,1) -> 4000000 | L100: =_xlfn.XLOOKUP("ProfitBeforeTax",HS_CONSOLIDATED!$C:$C,HS_CONSOLIDATED!K:K,0,0,1) -> 28917100000 | M100: =_xlfn.XLOOKUP("ProfitBeforeTax",HS_CONSOLIDATED!$C:$C,HS_CONSOLIDATED!L:L,0,0,1) -> 6594900000 | N100: =_xlfn.XLOOKUP("ProfitBeforeTax",HS_CONSOLIDATED!$C:$C,HS_CONSOLIDATED!M:M,0,0,1) -> 14466300000
C101: Adjustments for reconcile profit (loss)
D102: Adjustments for finance costs | E102: =_xlfn.XLOOKUP("AdjustmentsForFinanceCosts",HS_CONSOLIDATED!$C:$C,HS_CONSOLIDATED!D:D,0,0,1) -> 0 | F102: =_xlfn.XLOOKUP("AdjustmentsForFinanceCosts",HS_CONSOLIDATED!$C:$C,HS_CONSOLIDATED!E:E,0,0,1) -> 11485000000 | G102: =_xlfn.XLOOKUP("AdjustmentsForFinanceCosts",HS_CONSOLIDATED!$C:$C,HS_CONSOLIDATED!F:F,0,0,1) -> 14012500000 | H102: =_xlfn.XLOOKUP("AdjustmentsForFinanceCosts",HS_CONSOLIDATED!$C:$C,HS_CONSOLIDATED!G:G,0,0,1) -> 11795000000 | I102: =_xlfn.XLOOKUP("AdjustmentsForFinanceCosts",HS_CONSOLIDATED!$C:$C,HS_CONSOLIDATED!H:H,0,0,1) -> 12901200000 | J102: =_xlfn.XLOOKUP("AdjustmentsForFinanceCosts",HS_CONSOLIDATED!$C:$C,HS_CONSOLIDATED!I:I,0,0,1) -> 9573700000 | K102: =_xlfn.XLOOKUP("AdjustmentsForFinanceCosts",HS_CONSOLIDATED!$C:$C,HS_CONSOLIDATED!J:J,0,0,1) -> 7025700000 | L102: =_xlfn.XLOOKUP("AdjustmentsForFinanceCosts",HS_CONSOLIDATED!$C:$C,HS_CONSOLIDATED!K:K,0,0,1) -> 3829700000 | M102: =_xlfn.XLOOKUP("AdjustmentsForFinanceCosts",HS_CONSOLIDATED!$C:$C,HS_CONSOLIDATED!L:L,0,0,1) -> 1056500000 | N102: =_xlfn.XLOOKUP("AdjustmentsForFinanceCosts",HS_CONSOLIDATED!$C:$C,HS_CONSOLIDATED!M:M,0,0,1) -> 1056800000
...

Sheet HIST_STAND
A1: Suzlon — Derived Financial Model
A2: Green = cross-sheet formula (XLOOKUP against raw data) | Black = same-sheet formula (subtotal/total)
A5: # | B5: Statement of Profit and Loss | E5: FY? | F5: FY2017 | G5: FY2018 | H5: FY2019 | I5: FY2020 | J5: FY2021 | K5: FY2022 | L5: FY2023 | M5: FY2024 | N5: FY2025
B6: Income [Abstract]
C7: Total revenue from operations | E7: =_xlfn.XLOOKUP("RevenueFromOperations",HS_STANDALONE!$C:$C,HS_STANDALONE!D:D,0,0,1) -> 0 | F7: =_xlfn.XLOOKUP("RevenueFromOperations",HS_STANDALONE!$C:$C,HS_STANDALONE!E:E,0,0,1) -> 92456800000 | G7: =_xlfn.XLOOKUP("RevenueFromOperations",HS_STANDALONE!$C:$C,HS_STANDALONE!F:F,0,0,1) -> 61664800000 | H7: =_xlfn.XLOOKUP("RevenueFromOperations",HS_STANDALONE!$C:$C,HS_STANDALONE!G:G,0,0,1) -> 25435000000 | I7: =_xlfn.XLOOKUP("RevenueFromOperations",HS_STANDALONE!$C:$C,HS_STANDALONE!H:H,0,0,1) -> 3759500000 | J7: =_xlfn.XLOOKUP("RevenueFromOperations",HS_STANDALONE!$C:$C,HS_STANDALONE!I:I,0,0,1) -> 12473100000 | K7: =_xlfn.XLOOKUP("RevenueFromOperations",HS_STANDALONE!$C:$C,HS_STANDALONE!J:J,0,0,1) -> 40400400000 | L7: =_xlfn.XLOOKUP("RevenueFromOperations",HS_STANDALONE!$C:$C,HS_STANDALONE!K:K,0,0,1) -> 35904400000 | M7: =_xlfn.XLOOKUP("RevenueFromOperations",HS_STANDALONE!$C:$C,HS_STANDALONE!L:L,0,0,1) -> 38602500000 | N7: =_xlfn.XLOOKUP("RevenueFromOperations",HS_STANDALONE!$C:$C,HS_STANDALONE!M:M,0,0,1) -> 101977200000
C8: Total other income | E8: =_xlfn.XLOOKUP("OtherIncome",HS_STANDALONE!$C:$C,HS_STANDALONE!D:D,0,0,1) -> 0 | F8: =_xlfn.XLOOKUP("OtherIncome",HS_STANDALONE!$C:$C,HS_STANDALONE!E:E,0,0,1) -> 4009700000 | G8: =_xlfn.XLOOKUP("OtherIncome",HS_STANDALONE!$C:$C,HS_STANDALONE!F:F,0,0,1) -> 3691600000 | H8: =_xlfn.XLOOKUP("OtherIncome",HS_STANDALONE!$C:$C,HS_STANDALONE!G:G,0,0,1) -> 4359800000 | I8: =_xlfn.XLOOKUP("OtherIncome",HS_STANDALONE!$C:$C,HS_STANDALONE!H:H,0,0,1) -> 2361800000 | J8: =_xlfn.XLOOKUP("OtherIncome",HS_STANDALONE!$C:$C,HS_STANDALONE!I:I,0,0,1) -> 697500000 | K8: =_xlfn.XLOOKUP("OtherIncome",HS_STANDALONE!$C:$C,HS_STANDALONE!J:J,0,0,1) -> 630200000 | L8: =_xlfn.XLOOKUP("OtherIncome",HS_STANDALONE!$C:$C,HS_STANDALONE!K:K,0,0,1) -> 1922200000 | M8: =_xlfn.XLOOKUP("OtherIncome",HS_STANDALONE!$C:$C,HS_STANDALONE!L:L,0,0,1) -> 1928800000 | N8: =_xlfn.XLOOKUP("OtherIncome",HS_STANDALONE!$C:$C,HS_STANDALONE!M:M,0,0,1) -> 1023100000
C9: Total income | E9: =IFERROR(SUM(E7:E8),0) -> 0 | F9: =IFERROR(SUM(F7:F8),0) -> 96466500000 | G9: =IFERROR(SUM(G7:G8),0) -> 65356400000 | H9: =IFERROR(SUM(H7:H8),0) -> 29794800000 | I9: =IFERROR(SUM(I7:I8),0) -> 6121300000 | J9: =IFERROR(SUM(J7:J8),0) -> 13170600000 | K9: =IFERROR(SUM(K7:K8),0) -> 41030600000 | L9: =IFERROR(SUM(L7:L8),0) -> 37826600000 | ... N9: =IFERROR(SUM(N7:N8),0) -> 103000300000
B10: COGS
C11: Cost of materials consumed | E11: =-_xlfn.XLOOKUP("CostOfMaterialsConsumed",HS_STANDALONE!$C:$C,HS_STANDALONE!D:D,0,0,1) -> 0 | F11: =-_xlfn.XLOOKUP("CostOfMaterialsConsumed",HS_STANDALONE!$C:$C,HS_STANDALONE!E:E,0,0,1) -> -58734400000 | G11: =-_xlfn.XLOOKUP("CostOfMaterialsConsumed",HS_STANDALONE!$C:$C,HS_STANDALONE!F:F,0,0,1) -> -27451000000 | H11: =-_xlfn.XLOOKUP("CostOfMaterialsConsumed",HS_STANDALONE!$C:$C,HS_STANDALONE!G:G,0,0,1) -> -15179200000 | I11: =-_xlfn.XLOOKUP("CostOfMaterialsConsumed",HS_STANDALONE!$C:$C,HS_STANDALONE!H:H,0,0,1) -> -2730600000 | J11: =-_xlfn.XLOOKUP("CostOfMaterialsConsumed",HS_STANDALONE!$C:$C,HS_STANDALONE!I:I,0,0,1) -> -6855100000 | K11: =-_xlfn.XLOOKUP("CostOfMaterialsConsumed",HS_STANDALONE!$C:$C,HS_STANDALONE!J:J,0,0,1) -> -30843300000 | L11: =-_xlfn.XLOOKUP("CostOfMaterialsConsumed",HS_STANDALONE!$C:$C,HS_STANDALONE!K:K,0,0,1) -> -26629700000 | M11: =-_xlfn.XLOOKUP("CostOfMaterialsConsumed",HS_STANDALONE!$C:$C,HS_STANDALONE!L:L,0,0,1) -> -28531300000 | N11: =-_xlfn.XLOOKUP("CostOfMaterialsConsumed",HS_STANDALONE!$C:$C,HS_STANDALONE!M:M,0,0,1) -> -69868900000
C12: Purchases of stock-in-trade | E12: =-_xlfn.XLOOKUP("PurchasesOfStockInTrade",HS_STANDALONE!$C:$C,HS_STANDALONE!D:D,0,0,1) -> 0 | F12: =-_xlfn.XLOOKUP("PurchasesOfStockInTrade",HS_STANDALONE!$C:$C,HS_STANDALONE!E:E,0,0,1) -> -4919900000 | G12: =-_xlfn.XLOOKUP("PurchasesOfStockInTrade",HS_STANDALONE!$C:$C,HS_STANDALONE!F:F,0,0,1) -> -9879500000 | H12: =-_xlfn.XLOOKUP("PurchasesOfStockInTrade",HS_STANDALONE!$C:$C,HS_STANDALONE!G:G,0,0,1) -> -58100000 | I12: =-_xlfn.XLOOKUP("PurchasesOfStockInTrade",HS_STANDALONE!$C:$C,HS_STANDALONE!H:H,0,0,1) -> 0 | J12: =-_xlfn.XLOOKUP("PurchasesOfStockInTrade",HS_STANDALONE!$C:$C,HS_STANDALONE!I:I,0,0,1) -> 0 | K12: =-_xlfn.XLOOKUP("PurchasesOfStockInTrade",HS_STANDALONE!$C:$C,HS_STANDALONE!J:J,0,0,1) -> 0 | L12: =-_xlfn.XLOOKUP("PurchasesOfStockInTrade",HS_STANDALONE!$C:$C,HS_STANDALONE!K:K,0,0,1) -> 0 | M12: =-_xlfn.XLOOKUP("PurchasesOfStockInTrade",HS_STANDALONE!$C:$C,HS_STANDALONE!L:L,0,0,1) -> 0 | N12: =-_xlfn.XLOOKUP("PurchasesOfStockInTrade",HS_STANDALONE!$C:$C,HS_STANDALONE!M:M,0,0,1) -> 0
C13: Total changes in inventories of finished goods, work-in-progress and stock-in-trade | E13: =-_xlfn.XLOOKUP("ChangesInInventoriesOfFinishedGoodsWorkInProgressAndStockInTrade",HS_STANDALONE!$C:$C,HS_STANDALONE!D:D,0,0,1) -> 0 | F13: =-_xlfn.XLOOKUP("ChangesInInventoriesOfFinishedGoodsWorkInProgressAndStockInTrade",HS_STANDALONE!$C:$C,HS_STANDALONE!E:E,0,0,1) -> 8235700000 | G13: =-_xlfn.XLOOKUP("ChangesInInventoriesOfFinishedGoodsWorkInProgressAndStockInTrade",HS_STANDALONE!$C:$C,HS_STANDALONE!F:F,0,0,1) -> -3853000000 | H13: =-_xlfn.XLOOKUP("ChangesInInventoriesOfFinishedGoodsWorkInProgressAndStockInTrade",HS_STANDALONE!$C:$C,HS_STANDALONE!G:G,0,0,1) -> -1960000000 | I13: =-_xlfn.XLOOKUP("ChangesInInventoriesOfFinishedGoodsWorkInProgressAndStockInTrade",HS_STANDALONE!$C:$C,HS_STANDALONE!H:H,0,0,1) -> -1083100000 | J13: =-_xlfn.XLOOKUP("ChangesInInventoriesOfFinishedGoodsWorkInProgressAndStockInTrade",HS_STANDALONE!$C:$C,HS_STANDALONE!I:I,0,0,1) -> -630100000 | K13: =-_xlfn.XLOOKUP("ChangesInInventoriesOfFinishedGoodsWorkInProgressAndStockInTrade",HS_STANDALONE!$C:$C,HS_STANDALONE!J:J,0,0,1) -> -96700000 | L13: =-_xlfn.XLOOKUP("ChangesInInventoriesOfFinishedGoodsWorkInProgressAndStockInTrade",HS_STANDALONE!$C:$C,HS_STANDALONE!K:K,0,0,1) -> -775300000 | M13: =-_xlfn.XLOOKUP("ChangesInInventoriesOfFinishedGoodsWorkInProgressAndStockInTrade",HS_STANDALONE!$C:$C,HS_STANDALONE!L:L,0,0,1) -> 452900000 | N13: =-_xlfn.XLOOKUP("ChangesInInventoriesOfFinishedGoodsWorkInProgressAndStockInTrade",HS_STANDALONE!$C:$C,HS_STANDALONE!M:M,0,0,1) -> 2691700000
B14: Gross Profit | E14: =IFERROR(E9+SUM(E11:E13),0) -> 0 | F14: =IFERROR(F9+SUM(F11:F13),0) -> 41047900000 | G14: =IFERROR(G9+SUM(G11:G13),0) -> 24172900000 | H14: =IFERROR(H9+SUM(H11:H13),0) -> 12597500000 | I14: =IFERROR(I9+SUM(I11:I13),0) -> 2307600000 | J14: =IFERROR(J9+SUM(J11:J13),0) -> 5685400000 | K14: =IFERROR(K9+SUM(K11:K13),0) -> 10090600000 | L14: =IFERROR(L9+SUM(L11:L13),0) -> 10421600000 | ... N14: =IFERROR(N9+SUM(N11:N13),0) -> 35823100000
C15: SG&A | E15: =-_xlfn.XLOOKUP("EmployeeBenefitExpense",HS_STANDALONE!$C:$C,HS_STANDALONE!D:D,0,0,1)-_xlfn.XLOOKUP("ExpenditureOnProductionTransportationAndOtherExpenditurePertainingToExplorationAndProductionActivities",HS_STANDALONE!$C:$C,HS_STANDALONE!D:D,0,0,1) -> 0 | F15: =-_xlfn.XLOOKUP("EmployeeBenefitExpense",HS_STANDALONE!$C:$C,HS_STANDALONE!E:E,0,0,1)-_xlfn.XLOOKUP("ExpenditureOnProductionTransportationAndOtherExpenditurePertainingToExplorationAndProductionActivities",HS_STANDALONE!$C:$C,HS_STANDALONE!E:E,0,0,1) -> -4151900000 | G15: =-_xlfn.XLOOKUP("EmployeeBenefitExpense",HS_STANDALONE!$C:$C,HS_STANDALONE!F:F,0,0,1)-_xlfn.XLOOKUP("ExpenditureOnProductionTransportationAndOtherExpenditurePertainingToExplorationAndProductionActivities",HS_STANDALONE!$C:$C,HS_STANDALONE!F:F,0,0,1) -> -2784800000 | H15: =-_xlfn.XLOOKUP("EmployeeBenefitExpense",HS_STANDALONE!$C:$C,HS_STANDALONE!G:G,0,0,1)-_xlfn.XLOOKUP("ExpenditureOnProductionTransportationAndOtherExpenditurePertainingToExplorationAndProductionActivities",HS_STANDALONE!$C:$C,HS_STANDALONE!G:G,0,0,1) -> -3265400000 | I15: =-_xlfn.XLOOKUP("EmployeeBenefitExpense",HS_STANDALONE!$C:$C,HS_STANDALONE!H:H,0,0,1)-_xlfn.XLOOKUP("ExpenditureOnProductionTransportationAndOtherExpenditurePertainingToExplorationAndProductionActivities",HS_STANDALONE!$C:$C,HS_STANDALONE!H:H,0,0,1) -> -2714800000 | J15: =-_xlfn.XLOOKUP("EmployeeBenefitExpense",HS_STANDALONE!$C:$C,HS_STANDALONE!I:I,0,0,1)-_xlfn.XLOOKUP("ExpenditureOnProductionTransportationAndOtherExpenditurePertainingToExplorationAndProductionActivities",HS_STANDALONE!$C:$C,HS_STANDALONE!I:I,0,0,1) -> -1829700000 | K15: =-_xlfn.XLOOKUP("EmployeeBenefitExpense",HS_STANDALONE!$C:$C,HS_STANDALONE!J:J,0,0,1)-_xlfn.XLOOKUP("ExpenditureOnProductionTransportationAndOtherExpenditurePertainingToExplorationAndProductionActivities",HS_STANDALONE!$C:$C,HS_STANDALONE!J:J,0,0,1) -> -2256200000 | L15: =-_xlfn.XLOOKUP("EmployeeBenefitExpense",HS_STANDALONE!$C:$C,HS_STANDALONE!K:K,0,0,1)-_xlfn.XLOOKUP("ExpenditureOnProductionTransportationAndOtherExpenditurePertainingToExplorationAndProductionActivities",HS_STANDALONE!$C:$C,HS_STANDALONE!K:K,0,0,1) -> -2525100000 | M15: =-_xlfn.XLOOKUP("EmployeeBenefitExpense",HS_STANDALONE!$C:$C,HS_STANDALONE!L:L,0,0,1)-_xlfn.XLOOKUP("ExpenditureOnProductionTransportationAndOtherExpenditurePertainingToExplorationAndProductionActivities",HS_STANDALONE!$C:$C,HS_STANDALONE!L:L,0,0,1) -> -3123600000 | N15: =-_xlfn.XLOOKUP("EmployeeBenefitExpense",HS_STANDALONE!$C:$C,HS_STANDALONE!M:M,0,0,1)-_xlfn.XLOOKUP("ExpenditureOnProductionTransportationAndOtherExpenditurePertainingToExplorationAndProductionActivities",HS_STANDALONE!$C:$C,HS_STANDALONE!M:M,0,0,1) -> -7917500000
C16: Total other expenses | E16: =-_xlfn.XLOOKUP("OtherExpenses",HS_STANDALONE!$C:$C,HS_STANDALONE!D:D,0,0,1) -> 0 | F16: =-_xlfn.XLOOKUP("OtherExpenses",HS_STANDALONE!$C:$C,HS_STANDALONE!E:E,0,0,1) -> -14534700000 | G16: =-_xlfn.XLOOKUP("OtherExpenses",HS_STANDALONE!$C:$C,HS_STANDALONE!F:F,0,0,1) -> -11054300000 | H16: =-_xlfn.XLOOKUP("OtherExpenses",HS_STANDALONE!$C:$C,HS_STANDALONE!G:G,0,0,1) -> -6812500000 | I16: =-_xlfn.XLOOKUP("OtherExpenses",HS_STANDALONE!$C:$C,HS_STANDALONE!H:H,0,0,1) -> -6204900000 | J16: =-_xlfn.XLOOKUP("OtherExpenses",HS_STANDALONE!$C:$C,HS_STANDALONE!I:I,0,0,1) -> -4159900000 | K16: =-_xlfn.XLOOKUP("OtherExpenses",HS_STANDALONE!$C:$C,HS_STANDALONE!J:J,0,0,1) -> -6510200000 | L16: =-_xlfn.XLOOKUP("OtherExpenses",HS_STANDALONE!$C:$C,HS_STANDALONE!K:K,0,0,1) -> -5373700000 | M16: =-_xlfn.XLOOKUP("OtherExpenses",HS_STANDALONE!$C:$C,HS_STANDALONE!L:L,0,0,1) -> -5194000000 | N16: =-_xlfn.XLOOKUP("OtherExpenses",HS_STANDALONE!$C:$C,HS_STANDALONE!M:M,0,0,1) -> -10239900000
B17: EBITDA | E17: =IFERROR(SUM(E14:E16),0) -> 0 | F17: =IFERROR(SUM(F14:F16),0) -> 22361300000 | G17: =IFERROR(SUM(G14:G16),0) -> 10333800000 | H17: =IFERROR(SUM(H14:H16),0) -> 2519600000 | I17: =IFERROR(SUM(I14:I16),0) -> -6612100000 | J17: =IFERROR(SUM(J14:J16),0) -> -304200000 | K17: =IFERROR(SUM(K14:K16),0) -> 1324200000 | L17: =IFERROR(SUM(L14:L16),0) -> 2522800000 | ... N17: =IFERROR(SUM(N14:N16),0) -> 17665700000
C18: D&A | E18: =-_xlfn.XLOOKUP("DepreciationDepletionAndAmortisationExpense",HS_STANDALONE!$C:$C,HS_STANDALONE!D:D,0,0,1) -> 0 | F18: =-_xlfn.XLOOKUP("DepreciationDepletionAndAmortisationExpense",HS_STANDALONE!$C:$C,HS_STANDALONE!E:E,0,0,1) -> -4139900000 | G18: =-_xlfn.XLOOKUP("DepreciationDepletionAndAmortisationExpense",HS_STANDALONE!$C:$C,HS_STANDALONE!F:F,0,0,1) -> -4192800000 | H18: =-_xlfn.XLOOKUP("DepreciationDepletionAndAmortisationExpense",HS_STANDALONE!$C:$C,HS_STANDALONE!G:G,0,0,1) -> -4389100000 | I18: =-_xlfn.XLOOKUP("DepreciationDepletionAndAmortisationExpense",HS_STANDALONE!$C:$C,HS_STANDALONE!H:H,0,0,1) -> -6821500000 | J18: =-_xlfn.XLOOKUP("DepreciationDepletionAndAmortisationExpense",HS_STANDALONE!$C:$C,HS_STANDALONE!I:I,0,0,1) -> -1865000000 | K18: =-_xlfn.XLOOKUP("DepreciationDepletionAndAmortisationExpense",HS_STANDALONE!$C:$C,HS_STANDALONE!J:J,0,0,1) -> -1851300000 | L18: =-_xlfn.XLOOKUP("DepreciationDepletionAndAmortisationExpense",HS_STANDALONE!$C:$C,HS_STANDALONE!K:K,0,0,1) -> -1900400000 | M18: =-_xlfn.XLOOKUP("DepreciationDepletionAndAmortisationExpense",HS_STANDALONE!$C:$C,HS_STANDALONE!L:L,0,0,1) -> -1195700000 | N18: =-_xlfn.XLOOKUP("DepreciationDepletionAndAmortisationExpense",HS_STANDALONE!$C:$C,HS_STANDALONE!M:M,0,0,1) -> -1668500000
B19: EBIT | E19: =IFERROR(SUM(E17:E18),0) -> 0 | F19: =IFERROR(SUM(F17:F18),0) -> 18221400000 | G19: =IFERROR(SUM(G17:G18),0) -> 6141000000 | H19: =IFERROR(SUM(H17:H18),0) -> -1869500000 | I19: =IFERROR(SUM(I17:I18),0) -> -13433600000 | J19: =IFERROR(SUM(J17:J18),0) -> -2169200000 | K19: =IFERROR(SUM(K17:K18),0) -> -527100000 | L19: =IFERROR(SUM(L17:L18),0) -> 622400000 | ... N19: =IFERROR(SUM(N17:N18),0) -> 15997200000
C20: Total finance costs | E20: =-_xlfn.XLOOKUP("FinanceCosts",HS_STANDALONE!$C:$C,HS_STANDALONE!D:D,0,0,1) -> 0 | F20: =-_xlfn.XLOOKUP("FinanceCosts",HS_STANDALONE!$C:$C,HS_STANDALONE!E:E,0,0,1) -> -9307100000 | G20: =-_xlfn.XLOOKUP("FinanceCosts",HS_STANDALONE!$C:$C,HS_STANDALONE!F:F,0,0,1) -> -12228400000 | H20: =-_xlfn.XLOOKUP("FinanceCosts",HS_STANDALONE!$C:$C,HS_STANDALONE!G:G,0,0,1) -> -9436500000 | I20: =-_xlfn.XLOOKUP("FinanceCosts",HS_STANDALONE!$C:$C,HS_STANDALONE!H:H,0,0,1) -> -11405700000 | J20: =-_xlfn.XLOOKUP("FinanceCosts",HS_STANDALONE!$C:$C,HS_STANDALONE!I:I,0,0,1) -> -9830700000 | K20: =-_xlfn.XLOOKUP("FinanceCosts",HS_STANDALONE!$C:$C,HS_STANDALONE!J:J,0,0,1) -> -7770800000 | L20: =-_xlfn.XLOOKUP("FinanceCosts",HS_STANDALONE!$C:$C,HS_STANDALONE!K:K,0,0,1) -> -4415600000 | M20: =-_xlfn.XLOOKUP("FinanceCosts",HS_STANDALONE!$C:$C,HS_STANDALONE!L:L,0,0,1) -> -2256700000 | N20: =-_xlfn.XLOOKUP("FinanceCosts",HS_STANDALONE!$C:$C,HS_STANDALONE!M:M,0,0,1) -> -2288600000
C21: Exceptional items before tax | E21: =_xlfn.XLOOKUP("ExceptionalItemsBeforeTax",HS_STANDALONE!$C:$C,HS_STANDALONE!D:D,0,0,1) -> 0 | F21: =_xlfn.XLOOKUP("ExceptionalItemsBeforeTax",HS_STANDALONE!$C:$C,HS_STANDALONE!E:E,0,0,1) -> -5357800000 | G21: =_xlfn.XLOOKUP("ExceptionalItemsBeforeTax",HS_STANDALONE!$C:$C,HS_STANDALONE!F:F,0,0,1) -> -5460000000 | H21: =_xlfn.XLOOKUP("ExceptionalItemsBeforeTax",HS_STANDALONE!$C:$C,HS_STANDALONE!G:G,0,0,1) -> -62813800000 | I21: =_xlfn.XLOOKUP("ExceptionalItemsBeforeTax",HS_STANDALONE!$C:$C,HS_STANDALONE!H:H,0,0,1) -> -7920500000 | J21: =_xlfn.XLOOKUP("ExceptionalItemsBeforeTax",HS_STANDALONE!$C:$C,HS_STANDALONE!I:I,0,0,1) -> 8015900000 | K21: =_xlfn.XLOOKUP("ExceptionalItemsBeforeTax",HS_STANDALONE!$C:$C,HS_STANDALONE!J:J,0,0,1) -> -828700000 | L21: =_xlfn.XLOOKUP("ExceptionalItemsBeforeTax",HS_STANDALONE!$C:$C,HS_STANDALONE!K:K,0,0,1) -> 25420800000 | M21: =_xlfn.XLOOKUP("ExceptionalItemsBeforeTax",HS_STANDALONE!$C:$C,HS_STANDALONE!L:L,0,0,1) -> 251400000 | N21: =_xlfn.XLOOKUP("ExceptionalItemsBeforeTax",HS_STANDALONE!$C:$C,HS_STANDALONE!M:M,0,0,1) -> 1028600000
B22: EBT | E22: =IFERROR(SUM(E19:E21),0) -> 0 | F22: =IFERROR(SUM(F19:F21),0) -> 3556500000 | G22: =IFERROR(SUM(G19:G21),0) -> -11547400000 | H22: =IFERROR(SUM(H19:H21),0) -> -74119800000 | I22: =IFERROR(SUM(I19:I21),0) -> -32759800000 | J22: =IFERROR(SUM(J19:J21),0) -> -3984000000 | K22: =IFERROR(SUM(K19:K21),0) -> -9126600000 | L22: =IFERROR(SUM(L19:L21),0) -> 21627600000 | ... N22: =IFERROR(SUM(N19:N21),0) -> 14737200000
C23: Total current tax | E23: =-_xlfn.XLOOKUP("CurrentTax",HS_STANDALONE!$C:$C,HS_STANDALONE!D:D,0,0,1) -> 0 | F23: =-_xlfn.XLOOKUP("CurrentTax",HS_STANDALONE!$C:$C,HS_STANDALONE!E:E,0,0,1) -> 500000 | G23: =-_xlfn.XLOOKUP("CurrentTax",HS_STANDALONE!$C:$C,HS_STANDALONE!F:F,0,0,1) -> -14000000 | H23: =-_xlfn.XLOOKUP("CurrentTax",HS_STANDALONE!$C:$C,HS_STANDALONE!G:G,0,0,1) -> -13500000 | I23: =-_xlfn.XLOOKUP("CurrentTax",HS_STANDALONE!$C:$C,HS_STANDALONE!H:H,0,0,1) -> -6500000 | J23: =-_xlfn.XLOOKUP("CurrentTax",HS_STANDALONE!$C:$C,HS_STANDALONE!I:I,0,0,1) -> 0 | K23: =-_xlfn.XLOOKUP("CurrentTax",HS_STANDALONE!$C:$C,HS_STANDALONE!J:J,0,0,1) -> 0 | L23: =-_xlfn.XLOOKUP("CurrentTax",HS_STANDALONE!$C:$C,HS_STANDALONE!K:K,0,0,1) -> 0 | M23: =-_xlfn.XLOOKUP("CurrentTax",HS_STANDALONE!$C:$C,HS_STANDALONE!L:L,0,0,1) -> 0 | N23: =-_xlfn.XLOOKUP("CurrentTax",HS_STANDALONE!$C:$C,HS_STANDALONE!M:M,0,0,1) -> -70500000
C24: Deferred tax | E24: =-_xlfn.XLOOKUP("DeferredTax",HS_STANDALONE!$C:$C,HS_STANDALONE!D:D,0,0,1) -> 0 | F24: =-_xlfn.XLOOKUP("DeferredTax",HS_STANDALONE!$C:$C,HS_STANDALONE!E:E,0,0,1) -> 0 | G24: =-_xlfn.XLOOKUP("DeferredTax",HS_STANDALONE!$C:$C,HS_STANDALONE!F:F,0,0,1) -> 0 | H24: =-_xlfn.XLOOKUP("DeferredTax",HS_STANDALONE!$C:$C,HS_STANDALONE!G:G,0,0,1) -> 0 | I24: =-_xlfn.XLOOKUP("DeferredTax",HS_STANDALONE!$C:$C,HS_STANDALONE!H:H,0,0,1) -> 0 | J24: =-_xlfn.XLOOKUP("DeferredTax",HS_STANDALONE!$C:$C,HS_STANDALONE!I:I,0,0,1) -> 0 | K24: =-_xlfn.XLOOKUP("DeferredTax",HS_STANDALONE!$C:$C,HS_STANDALONE!J:J,0,0,1) -> 0 | L24: =-_xlfn.XLOOKUP("DeferredTax",HS_STANDALONE!$C:$C,HS_STANDALONE!K:K,0,0,1) -> 0 | M24: =-_xlfn.XLOOKUP("DeferredTax",HS_STANDALONE!$C:$C,HS_STANDALONE!L:L,0,0,1) -> 0 | N24: =-_xlfn.XLOOKUP("DeferredTax",HS_STANDALONE!$C:$C,HS_STANDALONE!M:M,0,0,1) -> 6380500000
C25: Total tax expense | E25: =IFERROR(SUM(E23:E24),0) -> 0 | F25: =IFERROR(SUM(F23:F24),0) -> 500000 | G25: =IFERROR(SUM(G23:G24),0) -> -14000000 | H25: =IFERROR(SUM(H23:H24),0) -> -13500000 | I25: =IFERROR(SUM(I23:I24),0) -> -6500000 | J25: =IFERROR(SUM(J23:J24),0) -> 0 | K25: =IFERROR(SUM(K23:K24),0) -> 0 | L25: =IFERROR(SUM(L23:L24),0) -> 0 | ... N25: =IFERROR(SUM(N23:N24),0) -> 6310000000
B26: NETINCOME | E26: =IFERROR(E25+E22,0) -> 0 | F26: =IFERROR(F25+F22,0) -> 3557000000 | G26: =IFERROR(G25+G22,0) -> -11561400000 | H26: =IFERROR(H25+H22,0) -> -74133300000 | I26: =IFERROR(I25+I22,0) -> -32766300000 | J26: =IFERROR(J25+J22,0) -> -3984000000 | K26: =IFERROR(K25+K22,0) -> -9126600000 | L26: =IFERROR(L25+L22,0) -> 21627600000 | ... N26: =IFERROR(N25+N22,0) -> 21047200000
A27: # | B27: Balance Sheet
B28: Assets [Abstract]
B29: Non-current assets [Abstract]
C30: Operating
D31: Property, plant and equipment at end of period | E31: =_xlfn.XLOOKUP("PropertyPlantAndEquipment",HS_STANDALONE!$C:$C,HS_STANDALONE!D:D,0,0,1) -> 0 | F31: =_xlfn.XLOOKUP("PropertyPlantAndEquipment",HS_STANDALONE!$C:$C,HS_STANDALONE!E:E,0,0,1) -> 9261500000 | G31: =_xlfn.XLOOKUP("PropertyPlantAndEquipment",HS_STANDALONE!$C:$C,HS_STANDALONE!F:F,0,0,1) -> 8097900000 | H31: =_xlfn.XLOOKUP("PropertyPlantAndEquipment",HS_STANDALONE!$C:$C,HS_STANDALONE!G:G,0,0,1) -> 7369100000 | I31: =_xlfn.XLOOKUP("PropertyPlantAndEquipment",HS_STANDALONE!$C:$C,HS_STANDALONE!H:H,0,0,1) -> 5872900000 | J31: =_xlfn.XLOOKUP("PropertyPlantAndEquipment",HS_STANDALONE!$C:$C,HS_STANDALONE!I:I,0,0,1) -> 5309000000 | K31: =_xlfn.XLOOKUP("PropertyPlantAndEquipment",HS_STANDALONE!$C:$C,HS_STANDALONE!J:J,0,0,1) -> 5257400000 | L31: =_xlfn.XLOOKUP("PropertyPlantAndEquipment",HS_STANDALONE!$C:$C,HS_STANDALONE!K:K,0,0,1) -> 4342600000 | M31: =_xlfn.XLOOKUP("PropertyPlantAndEquipment",HS_STANDALONE!$C:$C,HS_STANDALONE!L:L,0,0,1) -> 5079500000 | N31: =_xlfn.XLOOKUP("PropertyPlantAndEquipment",HS_STANDALONE!$C:$C,HS_STANDALONE!M:M,0,0,1) -> 6153700000
D32: Capital work-in-progress | E32: =_xlfn.XLOOKUP("CapitalWorkInProgress",HS_STANDALONE!$C:$C,HS_STANDALONE!D:D,0,0,1) -> 0 | F32: =_xlfn.XLOOKUP("CapitalWorkInProgress",HS_STANDALONE!$C:$C,HS_STANDALONE!E:E,0,0,1) -> 727300000 | G32: =_xlfn.XLOOKUP("CapitalWorkInProgress",HS_STANDALONE!$C:$C,HS_STANDALONE!F:F,0,0,1) -> 1120600000 | H32: =_xlfn.XLOOKUP("CapitalWorkInProgress",HS_STANDALONE!$C:$C,HS_STANDALONE!G:G,0,0,1) -> 1297400000 | I32: =_xlfn.XLOOKUP("CapitalWorkInProgress",HS_STANDALONE!$C:$C,HS_STANDALONE!H:H,0,0,1) -> 1046000000 | J32: =_xlfn.XLOOKUP("CapitalWorkInProgress",HS_STANDALONE!$C:$C,HS_STANDALONE!I:I,0,0,1) -> 963400000 | K32: =_xlfn.XLOOKUP("CapitalWorkInProgress",HS_STANDALONE!$C:$C,HS_STANDALONE!J:J,0,0,1) -> 76300000 | L32: =_xlfn.XLOOKUP("CapitalWorkInProgress",HS_STANDALONE!$C:$C,HS_STANDALONE!K:K,0,0,1) -> 8700000 | M32: =_xlfn.XLOOKUP("CapitalWorkInProgress",HS_STANDALONE!$C:$C,HS_STANDALONE!L:L,0,0,1) -> 33700000 | N32: =_xlfn.XLOOKUP("CapitalWorkInProgress",HS_STANDALONE!$C:$C,HS_STANDALONE!M:M,0,0,1) -> 596000000
D33: Goodwill at end of period | E33: =_xlfn.XLOOKUP("Goodwill",HS_STANDALONE!$C:$C,HS_STANDALONE!D:D,0,0,1) -> 0 | F33: =_xlfn.XLOOKUP("Goodwill",HS_STANDALONE!$C:$C,HS_STANDALONE!E:E,0,0,1) -> 6433600000 | G33: =_xlfn.XLOOKUP("Goodwill",HS_STANDALONE!$C:$C,HS_STANDALONE!F:F,0,0,1) -> 4718000000 | H33: =_xlfn.XLOOKUP("Goodwill",HS_STANDALONE!$C:$C,HS_STANDALONE!G:G,0,0,1) -> 3002400000 | I33: =_xlfn.XLOOKUP("Goodwill",HS_STANDALONE!$C:$C,HS_STANDALONE!H:H,0,0,1) -> 0 | J33: =_xlfn.XLOOKUP("Goodwill",HS_STANDALONE!$C:$C,HS_STANDALONE!I:I,0,0,1) -> 0 | K33: =_xlfn.XLOOKUP("Goodwill",HS_STANDALONE!$C:$C,HS_STANDALONE!J:J,0,0,1) -> 0 | L33: =_xlfn.XLOOKUP("Goodwill",HS_STANDALONE!$C:$C,HS_STANDALONE!K:K,0,0,1) -> 0 | M33: =_xlfn.XLOOKUP("Goodwill",HS_STANDALONE!$C:$C,HS_STANDALONE!L:L,0,0,1) -> 0 | N33: =_xlfn.XLOOKUP("Goodwill",HS_STANDALONE!$C:$C,HS_STANDALONE!M:M,0,0,1) -> 0
D34: Other intangible assets at end of period | E34: =_xlfn.XLOOKUP("OtherIntangibleAssets",HS_STANDALONE!$C:$C,HS_STANDALONE!D:D,0,0,1) -> 0 | F34: =_xlfn.XLOOKUP("OtherIntangibleAssets",HS_STANDALONE!$C:$C,HS_STANDALONE!E:E,0,0,1) -> 1858800000 | G34: =_xlfn.XLOOKUP("OtherIntangibleAssets",HS_STANDALONE!$C:$C,HS_STANDALONE!F:F,0,0,1) -> 1476100000 | H34: =_xlfn.XLOOKUP("OtherIntangibleAssets",HS_STANDALONE!$C:$C,HS_STANDALONE!G:G,0,0,1) -> 3297700000 | I34: =_xlfn.XLOOKUP("OtherIntangibleAssets",HS_STANDALONE!$C:$C,HS_STANDALONE!H:H,0,0,1) -> 2705900000 | J34: =_xlfn.XLOOKUP("OtherIntangibleAssets",HS_STANDALONE!$C:$C,HS_STANDALONE!I:I,0,0,1) -> 1942400000 | K34: =_xlfn.XLOOKUP("OtherIntangibleAssets",HS_STANDALONE!$C:$C,HS_STANDALONE!J:J,0,0,1) -> 1247000000 | L34: =_xlfn.XLOOKUP("OtherIntangibleAssets",HS_STANDALONE!$C:$C,HS_STANDALONE!K:K,0,0,1) -> 629000000 | M34: =_xlfn.XLOOKUP("OtherIntangibleAssets",HS_STANDALONE!$C:$C,HS_STANDALONE!L:L,0,0,1) -> 536400000 | N34: =_xlfn.XLOOKUP("OtherIntangibleAssets",HS_STANDALONE!$C:$C,HS_STANDALONE!M:M,0,0,1) -> 913500000
D35: Intangible assets under development | E35: =_xlfn.XLOOKUP("IntangibleAssetsUnderDevelopment",HS_STANDALONE!$C:$C,HS_STANDALONE!D:D,0,0,1) -> 0 | F35: =_xlfn.XLOOKUP("IntangibleAssetsUnderDevelopment",HS_STANDALONE!$C:$C,HS_STANDALONE!E:E,0,0,1) -> 555300000 | G35: =_xlfn.XLOOKUP("IntangibleAssetsUnderDevelopment",HS_STANDALONE!$C:$C,HS_STANDALONE!F:F,0,0,1) -> 1798200000 | H35: =_xlfn.XLOOKUP("IntangibleAssetsUnderDevelopment",HS_STANDALONE!$C:$C,HS_STANDALONE!G:G,0,0,1) -> 104100000 | I35: =_xlfn.XLOOKUP("IntangibleAssetsUnderDevelopment",HS_STANDALONE!$C:$C,HS_STANDALONE!H:H,0,0,1) -> 123000000 | J35: =_xlfn.XLOOKUP("IntangibleAssetsUnderDevelopment",HS_STANDALONE!$C:$C,HS_STANDALONE!I:I,0,0,1) -> 35200000 | K35: =_xlfn.XLOOKUP("IntangibleAssetsUnderDevelopment",HS_STANDALONE!$C:$C,HS_STANDALONE!J:J,0,0,1) -> 44200000 | L35: =_xlfn.XLOOKUP("IntangibleAssetsUnderDevelopment",HS_STANDALONE!$C:$C,HS_STANDALONE!K:K,0,0,1) -> 34300000 | M35: =_xlfn.XLOOKUP("IntangibleAssetsUnderDevelopment",HS_STANDALONE!$C:$C,HS_STANDALONE!L:L,0,0,1) -> 35100000 | N35: =_xlfn.XLOOKUP("IntangibleAssetsUnderDevelopment",HS_STANDALONE!$C:$C,HS_STANDALONE!M:M,0,0,1) -> 163500000
D36: Trade receivables, non-current | E36: =_xlfn.XLOOKUP("TradeReceivablesNoncurrent",HS_STANDALONE!$C:$C,HS_STANDALONE!D:D,0,0,1) -> 0 | F36: =_xlfn.XLOOKUP("TradeReceivablesNoncurrent",HS_STANDALONE!$C:$C,HS_STANDALONE!E:E,0,0,1) -> 346400000 | G36: =_xlfn.XLOOKUP("TradeReceivablesNoncurrent",HS_STANDALONE!$C:$C,HS_STANDALONE!F:F,0,0,1) -> 48400000 | H36: =_xlfn.XLOOKUP("TradeReceivablesNoncurrent",HS_STANDALONE!$C:$C,HS_STANDALONE!G:G,0,0,1) -> 0 | I36: =_xlfn.XLOOKUP("TradeReceivablesNoncurrent",HS_STANDALONE!$C:$C,HS_STANDALONE!H:H,0,0,1) -> 0 | J36: =_xlfn.XLOOKUP("TradeReceivablesNoncurrent",HS_STANDALONE!$C:$C,HS_STANDALONE!I:I,0,0,1) -> 0 | K36: =_xlfn.XLOOKUP("TradeReceivablesNoncurrent",HS_STANDALONE!$C:$C,HS_STANDALONE!J:J,0,0,1) -> 0 | L36: =_xlfn.XLOOKUP("TradeReceivablesNoncurrent",HS_STANDALONE!$C:$C,HS_STANDALONE!K:K,0,0,1) -> 0 | M36: =_xlfn.XLOOKUP("TradeReceivablesNoncurrent",HS_STANDALONE!$C:$C,HS_STANDALONE!L:L,0,0,1) -> 0 | N36: =_xlfn.XLOOKUP("TradeReceivablesNoncurrent",HS_STANDALONE!$C:$C,HS_STANDALONE!M:M,0,0,1) -> 0
D37: Total other non-current assets | E37: =_xlfn.XLOOKUP("OtherNoncurrentAssets",HS_STANDALONE!$C:$C,HS_STANDALONE!D:D,0,0,1) -> 0 | F37: =_xlfn.XLOOKUP("OtherNoncurrentAssets",HS_STANDALONE!$C:$C,HS_STANDALONE!E:E,0,0,1) -> 317100000 | G37: =_xlfn.XLOOKUP("OtherNoncurrentAssets",HS_STANDALONE!$C:$C,HS_STANDALONE!F:F,0,0,1) -> 269600000 | H37: =_xlfn.XLOOKUP("OtherNoncurrentAssets",HS_STANDALONE!$C:$C,HS_STANDALONE!G:G,0,0,1) -> 186700000 | I37: =_xlfn.XLOOKUP("OtherNoncurrentAssets",HS_STANDALONE!$C:$C,HS_STANDALONE!H:H,0,0,1) -> 725800000 | J37: =_xlfn.XLOOKUP("OtherNoncurrentAssets",HS_STANDALONE!$C:$C,HS_STANDALONE!I:I,0,0,1) -> 652200000 | K37: =_xlfn.XLOOKUP("OtherNoncurrentAssets",HS_STANDALONE!$C:$C,HS_STANDALONE!J:J,0,0,1) -> 692900000 | L37: =_xlfn.XLOOKUP("OtherNoncurrentAssets",HS_STANDALONE!$C:$C,HS_STANDALONE!K:K,0,0,1) -> 713100000 | M37: =_xlfn.XLOOKUP("OtherNoncurrentAssets",HS_STANDALONE!$C:$C,HS_STANDALONE!L:L,0,0,1) -> 421200000 | N37: =_xlfn.XLOOKUP("OtherNoncurrentAssets",HS_STANDALONE!$C:$C,HS_STANDALONE!M:M,0,0,1) -> 625400000
C38: Total Operating | E38: =IFERROR(SUM(E31:E37),0) -> 0 | F38: =IFERROR(SUM(F31:F37),0) -> 19500000000 | G38: =IFERROR(SUM(G31:G37),0) -> 17528800000 | H38: =IFERROR(SUM(H31:H37),0) -> 15257400000 | I38: =IFERROR(SUM(I31:I37),0) -> 10473600000 | J38: =IFERROR(SUM(J31:J37),0) -> 8902200000 | K38: =IFERROR(SUM(K31:K37),0) -> 7317800000 | L38: =IFERROR(SUM(L31:L37),0) -> 5727700000 | ... N38: =IFERROR(SUM(N31:N37),0) -> 8452100000
C39: Non-Operating
D40: Investment property at end of period | E40: =_xlfn.XLOOKUP("InvestmentProperty",HS_STANDALONE!$C:$C,HS_STANDALONE!D:D,0,0,1) -> 0 | F40: =_xlfn.XLOOKUP("InvestmentProperty",HS_STANDALONE!$C:$C,HS_STANDALONE!E:E,0,0,1) -> 341400000 | G40: =_xlfn.XLOOKUP("InvestmentProperty",HS_STANDALONE!$C:$C,HS_STANDALONE!F:F,0,0,1) -> 407900000 | H40: =_xlfn.XLOOKUP("InvestmentProperty",HS_STANDALONE!$C:$C,HS_STANDALONE!G:G,0,0,1) -> 373600000 | I40: =_xlfn.XLOOKUP("InvestmentProperty",HS_STANDALONE!$C:$C,HS_STANDALONE!H:H,0,0,1) -> 346700000 | J40: =_xlfn.XLOOKUP("InvestmentProperty",HS_STANDALONE!$C:$C,HS_STANDALONE!I:I,0,0,1) -> 326400000 | K40: =_xlfn.XLOOKUP("InvestmentProperty",HS_STANDALONE!$C:$C,HS_STANDALONE!J:J,0,0,1) -> 308600000 | L40: =_xlfn.XLOOKUP("InvestmentProperty",HS_STANDALONE!$C:$C,HS_STANDALONE!K:K,0,0,1) -> 292100000 | M40: =_xlfn.XLOOKUP("InvestmentProperty",HS_STANDALONE!$C:$C,HS_STANDALONE!L:L,0,0,1) -> 270100000 | N40: =_xlfn.XLOOKUP("InvestmentProperty",HS_STANDALONE!$C:$C,HS_STANDALONE!M:M,0,0,1) -> 257500000
D41: Investments accounted for using equity method | E41: =_xlfn.XLOOKUP("InvestmentsAccountedForUsingEquityMethod",HS_STANDALONE!$C:$C,HS_STANDALONE!D:D,0,0,1) -> 0 | F41: =_xlfn.XLOOKUP("InvestmentsAccountedForUsingEquityMethod",HS_STANDALONE!$C:$C,HS_STANDALONE!E:E,0,0,1) -> 0 | G41: =_xlfn.XLOOKUP("InvestmentsAccountedForUsingEquityMethod",HS_STANDALONE!$C:$C,HS_STANDALONE!F:F,0,0,1) -> 1155400000 | H41: =_xlfn.XLOOKUP("InvestmentsAccountedForUsingEquityMethod",HS_STANDALONE!$C:$C,HS_STANDALONE!G:G,0,0,1) -> 0 | I41: =_xlfn.XLOOKUP("InvestmentsAccountedForUsingEquityMethod",HS_STANDALONE!$C:$C,HS_STANDALONE!H:H,0,0,1) -> 298000000 | J41: =_xlfn.XLOOKUP("InvestmentsAccountedForUsingEquityMethod",HS_STANDALONE!$C:$C,HS_STANDALONE!I:I,0,0,1) -> 298000000 | K41: =_xlfn.XLOOKUP("InvestmentsAccountedForUsingEquityMethod",HS_STANDALONE!$C:$C,HS_STANDALONE!J:J,0,0,1) -> 0 | L41: =_xlfn.XLOOKUP("InvestmentsAccountedForUsingEquityMethod",HS_STANDALONE!$C:$C,HS_STANDALONE!K:K,0,0,1) -> 0 | M41: =_xlfn.XLOOKUP("InvestmentsAccountedForUsingEquityMethod",HS_STANDALONE!$C:$C,HS_STANDALONE!L:L,0,0,1) -> 0 | N41: =_xlfn.XLOOKUP("InvestmentsAccountedForUsingEquityMethod",HS_STANDALONE!$C:$C,HS_STANDALONE!M:M,0,0,1) -> 0
D42: Non-current investments | E42: =_xlfn.XLOOKUP("NoncurrentInvestments",HS_STANDALONE!$C:$C,HS_STANDALONE!D:D,0,0,1) -> 0 | F42: =_xlfn.XLOOKUP("NoncurrentInvestments",HS_STANDALONE!$C:$C,HS_STANDALONE!E:E,0,0,1) -> 31667700000 | G42: =_xlfn.XLOOKUP("NoncurrentInvestments",HS_STANDALONE!$C:$C,HS_STANDALONE!F:F,0,0,1) -> 27629200000 | H42: =_xlfn.XLOOKUP("NoncurrentInvestments",HS_STANDALONE!$C:$C,HS_STANDALONE!G:G,0,0,1) -> 20085800000 | I42: =_xlfn.XLOOKUP("NoncurrentInvestments",HS_STANDALONE!$C:$C,HS_STANDALONE!H:H,0,0,1) -> 17521500000 | J42: =_xlfn.XLOOKUP("NoncurrentInvestments",HS_STANDALONE!$C:$C,HS_STANDALONE!I:I,0,0,1) -> 17508400000 | K42: =_xlfn.XLOOKUP("NoncurrentInvestments",HS_STANDALONE!$C:$C,HS_STANDALONE!J:J,0,0,1) -> 17519800000 | L42: =_xlfn.XLOOKUP("NoncurrentInvestments",HS_STANDALONE!$C:$C,HS_STANDALONE!K:K,0,0,1) -> 17539000000 | M42: =_xlfn.XLOOKUP("NoncurrentInvestments",HS_STANDALONE!$C:$C,HS_STANDALONE!L:L,0,0,1) -> 17564600000 | N42: =_xlfn.XLOOKUP("NoncurrentInvestments",HS_STANDALONE!$C:$C,HS_STANDALONE!M:M,0,0,1) -> 12776900000
D43: Loans, non-current | E43: =_xlfn.XLOOKUP("LoansNoncurrent",HS_STANDALONE!$C:$C,HS_STANDALONE!D:D,0,0,1) -> 0 | F43: =_xlfn.XLOOKUP("LoansNoncurrent",HS_STANDALONE!$C:$C,HS_STANDALONE!E:E,0,0,1) -> 11292400000 | G43: =_xlfn.XLOOKUP("LoansNoncurrent",HS_STANDALONE!$C:$C,HS_STANDALONE!F:F,0,0,1) -> 9975300000 | H43: =_xlfn.XLOOKUP("LoansNoncurrent",HS_STANDALONE!$C:$C,HS_STANDALONE!G:G,0,0,1) -> 6599200000 | I43: =_xlfn.XLOOKUP("LoansNoncurrent",HS_STANDALONE!$C:$C,HS_STANDALONE!H:H,0,0,1) -> 4191600000 | J43: =_xlfn.XLOOKUP("LoansNoncurrent",HS_STANDALONE!$C:$C,HS_STANDALONE!I:I,0,0,1) -> 2899700000 | K43: =_xlfn.XLOOKUP("LoansNoncurrent",HS_STANDALONE!$C:$C,HS_STANDALONE!J:J,0,0,1) -> 525100000 | L43: =_xlfn.XLOOKUP("LoansNoncurrent",HS_STANDALONE!$C:$C,HS_STANDALONE!K:K,0,0,1) -> 12444200000 | M43: =_xlfn.XLOOKUP("LoansNoncurrent",HS_STANDALONE!$C:$C,HS_STANDALONE!L:L,0,0,1) -> 9790700000 | N43: =_xlfn.XLOOKUP("LoansNoncurrent",HS_STANDALONE!$C:$C,HS_STANDALONE!M:M,0,0,1) -> 1390600000
D44: Total other non-current financial assets | E44: =_xlfn.XLOOKUP("OtherNoncurrentFinancialAssets",HS_STANDALONE!$C:$C,HS_STANDALONE!D:D,0,0,1) -> 0 | F44: =_xlfn.XLOOKUP("OtherNoncurrentFinancialAssets",HS_STANDALONE!$C:$C,HS_STANDALONE!E:E,0,0,1) -> 6204600000 | G44: =_xlfn.XLOOKUP("OtherNoncurrentFinancialAssets",HS_STANDALONE!$C:$C,HS_STANDALONE!F:F,0,0,1) -> 4882200000 | H44: =_xlfn.XLOOKUP("OtherNoncurrentFinancialAssets",HS_STANDALONE!$C:$C,HS_STANDALONE!G:G,0,0,1) -> 4176900000 | I44: =_xlfn.XLOOKUP("OtherNoncurrentFinancialAssets",HS_STANDALONE!$C:$C,HS_STANDALONE!H:H,0,0,1) -> 2288300000 | J44: =_xlfn.XLOOKUP("OtherNoncurrentFinancialAssets",HS_STANDALONE!$C:$C,HS_STANDALONE!I:I,0,0,1) -> 3453000000 | K44: =_xlfn.XLOOKUP("OtherNoncurrentFinancialAssets",HS_STANDALONE!$C:$C,HS_STANDALONE!J:J,0,0,1) -> 2286700000 | L44: =_xlfn.XLOOKUP("OtherNoncurrentFinancialAssets",HS_STANDALONE!$C:$C,HS_STANDALONE!K:K,0,0,1) -> 3833900000 | M44: =_xlfn.XLOOKUP("OtherNoncurrentFinancialAssets",HS_STANDALONE!$C:$C,HS_STANDALONE!L:L,0,0,1) -> 8416700000 | N44: =_xlfn.XLOOKUP("OtherNoncurrentFinancialAssets",HS_STANDALONE!$C:$C,HS_STANDALONE!M:M,0,0,1) -> 10626700000
D45: Deferred tax assets (net) | E45: =_xlfn.XLOOKUP("DeferredTaxAssetsNet",HS_STANDALONE!$C:$C,HS_STANDALONE!D:D,0,0,1) -> 0 | F45: =_xlfn.XLOOKUP("DeferredTaxAssetsNet",HS_STANDALONE!$C:$C,HS_STANDALONE!E:E,0,0,1) -> 0 | G45: =_xlfn.XLOOKUP("DeferredTaxAssetsNet",HS_STANDALONE!$C:$C,HS_STANDALONE!F:F,0,0,1) -> 0 | H45: =_xlfn.XLOOKUP("DeferredTaxAssetsNet",HS_STANDALONE!$C:$C,HS_STANDALONE!G:G,0,0,1) -> 0 | I45: =_xlfn.XLOOKUP("DeferredTaxAssetsNet",HS_STANDALONE!$C:$C,HS_STANDALONE!H:H,0,0,1) -> 0 | J45: =_xlfn.XLOOKUP("DeferredTaxAssetsNet",HS_STANDALONE!$C:$C,HS_STANDALONE!I:I,0,0,1) -> 0 | K45: =_xlfn.XLOOKUP("DeferredTaxAssetsNet",HS_STANDALONE!$C:$C,HS_STANDALONE!J:J,0,0,1) -> 0 | L45: =_xlfn.XLOOKUP("DeferredTaxAssetsNet",HS_STANDALONE!$C:$C,HS_STANDALONE!K:K,0,0,1) -> 0 | M45: =_xlfn.XLOOKUP("DeferredTaxAssetsNet",HS_STANDALONE!$C:$C,HS_STANDALONE!L:L,0,0,1) -> 0 | N45: =_xlfn.XLOOKUP("DeferredTaxAssetsNet",HS_STANDALONE!$C:$C,HS_STANDALONE!M:M,0,0,1) -> 6380500000
C46: Total Non-Operating | E46: =IFERROR(SUM(E40:E45),0) -> 0 | F46: =IFERROR(SUM(F40:F45),0) -> 49506100000 | G46: =IFERROR(SUM(G40:G45),0) -> 44050000000 | H46: =IFERROR(SUM(H40:H45),0) -> 31235500000 | I46: =IFERROR(SUM(I40:I45),0) -> 24646100000 | J46: =IFERROR(SUM(J40:J45),0) -> 24485500000 | K46: =IFERROR(SUM(K40:K45),0) -> 20640200000 | L46: =IFERROR(SUM(L40:L45),0) -> 34109200000 | ... N46: =IFERROR(SUM(N40:N45),0) -> 31432200000
C47: Total non-current financial assets | E47: =_xlfn.XLOOKUP("NoncurrentFinancialAssets",HS_STANDALONE!$C:$C,HS_STANDALONE!D:D,0,0,1) -> 0 | F47: =_xlfn.XLOOKUP("NoncurrentFinancialAssets",HS_STANDALONE!$C:$C,HS_STANDALONE!E:E,0,0,1) -> 49511100000 | G47: =_xlfn.XLOOKUP("NoncurrentFinancialAssets",HS_STANDALONE!$C:$C,HS_STANDALONE!F:F,0,0,1) -> 42535100000 | H47: =_xlfn.XLOOKUP("NoncurrentFinancialAssets",HS_STANDALONE!$C:$C,HS_STANDALONE!G:G,0,0,1) -> 30861900000 | I47: =_xlfn.XLOOKUP("NoncurrentFinancialAssets",HS_STANDALONE!$C:$C,HS_STANDALONE!H:H,0,0,1) -> 24001400000 | J47: =_xlfn.XLOOKUP("NoncurrentFinancialAssets",HS_STANDALONE!$C:$C,HS_STANDALONE!I:I,0,0,1) -> 23861100000 | K47: =_xlfn.XLOOKUP("NoncurrentFinancialAssets",HS_STANDALONE!$C:$C,HS_STANDALONE!J:J,0,0,1) -> 20331600000 | L47: =_xlfn.XLOOKUP("NoncurrentFinancialAssets",HS_STANDALONE!$C:$C,HS_STANDALONE!K:K,0,0,1) -> 33817100000 | M47: =_xlfn.XLOOKUP("NoncurrentFinancialAssets",HS_STANDALONE!$C:$C,HS_STANDALONE!L:L,0,0,1) -> 35772000000 | N47: =_xlfn.XLOOKUP("NoncurrentFinancialAssets",HS_STANDALONE!$C:$C,HS_STANDALONE!M:M,0,0,1) -> 24794200000
B48: Total Non-Current Assets | E48: =IFERROR(E46+E38,0) -> 0 | F48: =IFERROR(F46+F38,0) -> 69006100000 | G48: =IFERROR(G46+G38,0) -> 61578800000 | H48: =IFERROR(H46+H38,0) -> 46492900000 | I48: =IFERROR(I46+I38,0) -> 35119700000 | J48: =IFERROR(J46+J38,0) -> 33387700000 | K48: =IFERROR(K46+K38,0) -> 27958000000 | L48: =IFERROR(L46+L38,0) -> 39836900000 | ... N48: =IFERROR(N46+N38,0) -> 39884300000
B49: Current Assets
C50: Operating
D51: Inventories | E51: =_xlfn.XLOOKUP("Inventories",HS_STANDALONE!$C:$C,HS_STANDALONE!D:D,0,0,1) -> 0 | F51: =_xlfn.XLOOKUP("Inventories",HS_STANDALONE!$C:$C,HS_STANDALONE!E:E,0,0,1) -> 22758700000 | G51: =_xlfn.XLOOKUP("Inventories",HS_STANDALONE!$C:$C,HS_STANDALONE!F:F,0,0,1) -> 15518100000 | H51: =_xlfn.XLOOKUP("Inventories",HS_STANDALONE!$C:$C,HS_STANDALONE!G:G,0,0,1) -> 11803400000 | I51: =_xlfn.XLOOKUP("Inventories",HS_STANDALONE!$C:$C,HS_STANDALONE!H:H,0,0,1) -> 8971400000 | J51: =_xlfn.XLOOKUP("Inventories",HS_STANDALONE!$C:$C,HS_STANDALONE!I:I,0,0,1) -> 8619300000 | K51: =_xlfn.XLOOKUP("Inventories",HS_STANDALONE!$C:$C,HS_STANDALONE!J:J,0,0,1) -> 11674700000 | L51: =_xlfn.XLOOKUP("Inventories",HS_STANDALONE!$C:$C,HS_STANDALONE!K:K,0,0,1) -> 7604200000 | M51: =_xlfn.XLOOKUP("Inventories",HS_STANDALONE!$C:$C,HS_STANDALONE!L:L,0,0,1) -> 11884500000 | N51: =_xlfn.XLOOKUP("Inventories",HS_STANDALONE!$C:$C,HS_STANDALONE!M:M,0,0,1) -> 28571100000
D52: Trade receivables, current | E52: =_xlfn.XLOOKUP("TradeReceivablesCurrent",HS_STANDALONE!$C:$C,HS_STANDALONE!D:D,0,0,1) -> 0 | F52: =_xlfn.XLOOKUP("TradeReceivablesCurrent",HS_STANDALONE!$C:$C,HS_STANDALONE!E:E,0,0,1) -> 23068800000 | G52: =_xlfn.XLOOKUP("TradeReceivablesCurrent",HS_STANDALONE!$C:$C,HS_STANDALONE!F:F,0,0,1) -> 18919300000 | H52: =_xlfn.XLOOKUP("TradeReceivablesCurrent",HS_STANDALONE!$C:$C,HS_STANDALONE!G:G,0,0,1) -> 10906100000 | I52: =_xlfn.XLOOKUP("TradeReceivablesCurrent",HS_STANDALONE!$C:$C,HS_STANDALONE!H:H,0,0,1) -> 4254000000 | J52: =_xlfn.XLOOKUP("TradeReceivablesCurrent",HS_STANDALONE!$C:$C,HS_STANDALONE!I:I,0,0,1) -> 3793000000 | K52: =_xlfn.XLOOKUP("TradeReceivablesCurrent",HS_STANDALONE!$C:$C,HS_STANDALONE!J:J,0,0,1) -> 6676300000 | L52: =_xlfn.XLOOKUP("TradeReceivablesCurrent",HS_STANDALONE!$C:$C,HS_STANDALONE!K:K,0,0,1) -> 5463200000 | M52: =_xlfn.XLOOKUP("TradeReceivablesCurrent",HS_STANDALONE!$C:$C,HS_STANDALONE!L:L,0,0,1) -> 11156300000 | N52: =_xlfn.XLOOKUP("TradeReceivablesCurrent",HS_STANDALONE!$C:$C,HS_STANDALONE!M:M,0,0,1) -> 36829000000
D53: Total other current assets | E53: =_xlfn.XLOOKUP("OtherCurrentAssets",HS_STANDALONE!$C:$C,HS_STANDALONE!D:D,0,0,1) -> 0 | F53: =_xlfn.XLOOKUP("OtherCurrentAssets",HS_STANDALONE!$C:$C,HS_STANDALONE!E:E,0,0,1) -> 2029400000 | G53: =_xlfn.XLOOKUP("OtherCurrentAssets",HS_STANDALONE!$C:$C,HS_STANDALONE!F:F,0,0,1) -> 2817600000 | H53: =_xlfn.XLOOKUP("OtherCurrentAssets",HS_STANDALONE!$C:$C,HS_STANDALONE!G:G,0,0,1) -> 4995600000 | I53: =_xlfn.XLOOKUP("OtherCurrentAssets",HS_STANDALONE!$C:$C,HS_STANDALONE!H:H,0,0,1) -> 3557200000 | J53: =_xlfn.XLOOKUP("OtherCurrentAssets",HS_STANDALONE!$C:$C,HS_STANDALONE!I:I,0,0,1) -> 4367200000 | K53: =_xlfn.XLOOKUP("OtherCurrentAssets",HS_STANDALONE!$C:$C,HS_STANDALONE!J:J,0,0,1) -> 4100300000 | L53: =_xlfn.XLOOKUP("OtherCurrentAssets",HS_STANDALONE!$C:$C,HS_STANDALONE!K:K,0,0,1) -> 3630100000 | M53: =_xlfn.XLOOKUP("OtherCurrentAssets",HS_STANDALONE!$C:$C,HS_STANDALONE!L:L,0,0,1) -> 3062500000 | N53: =_xlfn.XLOOKUP("OtherCurrentAssets",HS_STANDALONE!$C:$C,HS_STANDALONE!M:M,0,0,1) -> 5836400000
C54: Total Operating | E54: =IFERROR(SUM(E51:E53),0) -> 0 | F54: =IFERROR(SUM(F51:F53),0) -> 47856900000 | G54: =IFERROR(SUM(G51:G53),0) -> 37255000000 | H54: =IFERROR(SUM(H51:H53),0) -> 27705100000 | I54: =IFERROR(SUM(I51:I53),0) -> 16782600000 | J54: =IFERROR(SUM(J51:J53),0) -> 16779500000 | K54: =IFERROR(SUM(K51:K53),0) -> 22451300000 | L54: =IFERROR(SUM(L51:L53),0) -> 16697500000 | ... N54: =IFERROR(SUM(N51:N53),0) -> 71236500000
C55: Non-Operating
D56: Current investments | E56: =_xlfn.XLOOKUP("CurrentInvestments",HS_STANDALONE!$C:$C,HS_STANDALONE!D:D,0,0,1) -> 0 | F56: =_xlfn.XLOOKUP("CurrentInvestments",HS_STANDALONE!$C:$C,HS_STANDALONE!E:E,0,0,1) -> 4811000000 | G56: =_xlfn.XLOOKUP("CurrentInvestments",HS_STANDALONE!$C:$C,HS_STANDALONE!F:F,0,0,1) -> 0 | H56: =_xlfn.XLOOKUP("CurrentInvestments",HS_STANDALONE!$C:$C,HS_STANDALONE!G:G,0,0,1) -> 0 | I56: =_xlfn.XLOOKUP("CurrentInvestments",HS_STANDALONE!$C:$C,HS_STANDALONE!H:H,0,0,1) -> 0 | J56: =_xlfn.XLOOKUP("CurrentInvestments",HS_STANDALONE!$C:$C,HS_STANDALONE!I:I,0,0,1) -> 0 | K56: =_xlfn.XLOOKUP("CurrentInvestments",HS_STANDALONE!$C:$C,HS_STANDALONE!J:J,0,0,1) -> 0 | L56: =_xlfn.XLOOKUP("CurrentInvestments",HS_STANDALONE!$C:$C,HS_STANDALONE!K:K,0,0,1) -> 0 | M56: =_xlfn.XLOOKUP("CurrentInvestments",HS_STANDALONE!$C:$C,HS_STANDALONE!L:L,0,0,1) -> 0 | N56: =_xlfn.XLOOKUP("CurrentInvestments",HS_STANDALONE!$C:$C,HS_STANDALONE!M:M,0,0,1) -> 0
D57: Cash and cash equivalents at end of period | E57: =_xlfn.XLOOKUP("CashAndCashEquivalents",HS_STANDALONE!$C:$C,HS_STANDALONE!D:D,0,0,1) -> 0 | F57: =_xlfn.XLOOKUP("CashAndCashEquivalents",HS_STANDALONE!$C:$C,HS_STANDALONE!E:E,0,0,1) -> 1533800000 | G57: =_xlfn.XLOOKUP("CashAndCashEquivalents",HS_STANDALONE!$C:$C,HS_STANDALONE!F:F,0,0,1) -> 4467000000 | H57: =_xlfn.XLOOKUP("CashAndCashEquivalents",HS_STANDALONE!$C:$C,HS_STANDALONE!G:G,0,0,1) -> 162000000 | I57: =_xlfn.XLOOKUP("CashAndCashEquivalents",HS_STANDALONE!$C:$C,HS_STANDALONE!H:H,0,0,1) -> 362800000 | J57: =_xlfn.XLOOKUP("CashAndCashEquivalents",HS_STANDALONE!$C:$C,HS_STANDALONE!I:I,0,0,1) -> 1936500000 | K57: =_xlfn.XLOOKUP("CashAndCashEquivalents",HS_STANDALONE!$C:$C,HS_STANDALONE!J:J,0,0,1) -> 4100200000 | L57: =_xlfn.XLOOKUP("CashAndCashEquivalents",HS_STANDALONE!$C:$C,HS_STANDALONE!K:K,0,0,1) -> 2906300000 | M57: =_xlfn.XLOOKUP("CashAndCashEquivalents",HS_STANDALONE!$C:$C,HS_STANDALONE!L:L,0,0,1) -> 2631300000 | N57: =_xlfn.XLOOKUP("CashAndCashEquivalents",HS_STANDALONE!$C:$C,HS_STANDALONE!M:M,0,0,1) -> 9968000000
D58: Loans, current | E58: =_xlfn.XLOOKUP("LoansCurrent",HS_STANDALONE!$C:$C,HS_STANDALONE!D:D,0,0,1) -> 0 | F58: =_xlfn.XLOOKUP("LoansCurrent",HS_STANDALONE!$C:$C,HS_STANDALONE!E:E,0,0,1) -> 17866300000 | G58: =_xlfn.XLOOKUP("LoansCurrent",HS_STANDALONE!$C:$C,HS_STANDALONE!F:F,0,0,1) -> 19507300000 | H58: =_xlfn.XLOOKUP("LoansCurrent",HS_STANDALONE!$C:$C,HS_STANDALONE!G:G,0,0,1) -> 7328600000 | I58: =_xlfn.XLOOKUP("LoansCurrent",HS_STANDALONE!$C:$C,HS_STANDALONE!H:H,0,0,1) -> 3781400000 | J58: =_xlfn.XLOOKUP("LoansCurrent",HS_STANDALONE!$C:$C,HS_STANDALONE!I:I,0,0,1) -> 212800000 | K58: =_xlfn.XLOOKUP("LoansCurrent",HS_STANDALONE!$C:$C,HS_STANDALONE!J:J,0,0,1) -> 523500000 | L58: =_xlfn.XLOOKUP("LoansCurrent",HS_STANDALONE!$C:$C,HS_STANDALONE!K:K,0,0,1) -> 6100000 | M58: =_xlfn.XLOOKUP("LoansCurrent",HS_STANDALONE!$C:$C,HS_STANDALONE!L:L,0,0,1) -> 2500000 | N58: =_xlfn.XLOOKUP("LoansCurrent",HS_STANDALONE!$C:$C,HS_STANDALONE!M:M,0,0,1) -> 2700000
D59: Total other current financial assets | E59: =_xlfn.XLOOKUP("OtherCurrentFinancialAssets",HS_STANDALONE!$C:$C,HS_STANDALONE!D:D,0,0,1) -> 0 | F59: =_xlfn.XLOOKUP("OtherCurrentFinancialAssets",HS_STANDALONE!$C:$C,HS_STANDALONE!E:E,0,0,1) -> 1032300000 | G59: =_xlfn.XLOOKUP("OtherCurrentFinancialAssets",HS_STANDALONE!$C:$C,HS_STANDALONE!F:F,0,0,1) -> 1955400000 | H59: =_xlfn.XLOOKUP("OtherCurrentFinancialAssets",HS_STANDALONE!$C:$C,HS_STANDALONE!G:G,0,0,1) -> 2758100000 | I59: =_xlfn.XLOOKUP("OtherCurrentFinancialAssets",HS_STANDALONE!$C:$C,HS_STANDALONE!H:H,0,0,1) -> 708300000 | J59: =_xlfn.XLOOKUP("OtherCurrentFinancialAssets",HS_STANDALONE!$C:$C,HS_STANDALONE!I:I,0,0,1) -> 838800000 | K59: =_xlfn.XLOOKUP("OtherCurrentFinancialAssets",HS_STANDALONE!$C:$C,HS_STANDALONE!J:J,0,0,1) -> 763600000 | L59: =_xlfn.XLOOKUP("OtherCurrentFinancialAssets",HS_STANDALONE!$C:$C,HS_STANDALONE!K:K,0,0,1) -> 755000000 | M59: =_xlfn.XLOOKUP("OtherCurrentFinancialAssets",HS_STANDALONE!$C:$C,HS_STANDALONE!L:L,0,0,1) -> 761500000 | N59: =_xlfn.XLOOKUP("OtherCurrentFinancialAssets",HS_STANDALONE!$C:$C,HS_STANDALONE!M:M,0,0,1) -> 1856300000
D60: Current tax assets, Current | E60: =_xlfn.XLOOKUP("CurrentTaxAssetsCurrent",HS_STANDALONE!$C:$C,HS_STANDALONE!D:D,0,0,1) -> 0 | F60: =_xlfn.XLOOKUP("CurrentTaxAssetsCurrent",HS_STANDALONE!$C:$C,HS_STANDALONE!E:E,0,0,1) -> 153900000 | G60: =_xlfn.XLOOKUP("CurrentTaxAssetsCurrent",HS_STANDALONE!$C:$C,HS_STANDALONE!F:F,0,0,1) -> 62700000 | H60: =_xlfn.XLOOKUP("CurrentTaxAssetsCurrent",HS_STANDALONE!$C:$C,HS_STANDALONE!G:G,0,0,1) -> 42700000 | I60: =_xlfn.XLOOKUP("CurrentTaxAssetsCurrent",HS_STANDALONE!$C:$C,HS_STANDALONE!H:H,0,0,1) -> 44800000 | J60: =_xlfn.XLOOKUP("CurrentTaxAssetsCurrent",HS_STANDALONE!$C:$C,HS_STANDALONE!I:I,0,0,1) -> 44800000 | K60: =_xlfn.XLOOKUP("CurrentTaxAssetsCurrent",HS_STANDALONE!$C:$C,HS_STANDALONE!J:J,0,0,1) -> 600000 | L60: =_xlfn.XLOOKUP("CurrentTaxAssetsCurrent",HS_STANDALONE!$C:$C,HS_STANDALONE!K:K,0,0,1) -> 0 | M60: =_xlfn.XLOOKUP("CurrentTaxAssetsCurrent",HS_STANDALONE!$C:$C,HS_STANDALONE!L:L,0,0,1) -> 0 | N60: =_xlfn.XLOOKUP("CurrentTaxAssetsCurrent",HS_STANDALONE!$C:$C,HS_STANDALONE!M:M,0,0,1) -> 496800000
C61: Total Non-Operating | E61: =IFERROR(SUM(E56:E60),0) -> 0 | F61: =IFERROR(SUM(F56:F60),0) -> 25397300000 | G61: =IFERROR(SUM(G56:G60),0) -> 25992400000 | H61: =IFERROR(SUM(H56:H60),0) -> 10291400000 | I61: =IFERROR(SUM(I56:I60),0) -> 4897300000 | J61: =IFERROR(SUM(J56:J60),0) -> 3032900000 | K61: =IFERROR(SUM(K56:K60),0) -> 5387900000 | L61: =IFERROR(SUM(L56:L60),0) -> 3667400000 | ... N61: =IFERROR(SUM(N56:N60),0) -> 12323800000
C62: Total current financial assets | E62: =_xlfn.XLOOKUP("CurrentFinancialAssets",HS_STANDALONE!$C:$C,HS_STANDALONE!D:D,0,0,1) -> 0 | F62: =_xlfn.XLOOKUP("CurrentFinancialAssets",HS_STANDALONE!$C:$C,HS_STANDALONE!E:E,0,0,1) -> 48312200000 | G62: =_xlfn.XLOOKUP("CurrentFinancialAssets",HS_STANDALONE!$C:$C,HS_STANDALONE!F:F,0,0,1) -> 44849000000 | H62: =_xlfn.XLOOKUP("CurrentFinancialAssets",HS_STANDALONE!$C:$C,HS_STANDALONE!G:G,0,0,1) -> 21154800000 | I62: =_xlfn.XLOOKUP("CurrentFinancialAssets",HS_STANDALONE!$C:$C,HS_STANDALONE!H:H,0,0,1) -> 9106500000 | J62: =_xlfn.XLOOKUP("CurrentFinancialAssets",HS_STANDALONE!$C:$C,HS_STANDALONE!I:I,0,0,1) -> 6781100000 | K62: =_xlfn.XLOOKUP("CurrentFinancialAssets",HS_STANDALONE!$C:$C,HS_STANDALONE!J:J,0,0,1) -> 12063600000 | L62: =_xlfn.XLOOKUP("CurrentFinancialAssets",HS_STANDALONE!$C:$C,HS_STANDALONE!K:K,0,0,1) -> 9130600000 | M62: =_xlfn.XLOOKUP("CurrentFinancialAssets",HS_STANDALONE!$C:$C,HS_STANDALONE!L:L,0,0,1) -> 14551600000 | N62: =_xlfn.XLOOKUP("CurrentFinancialAssets",HS_STANDALONE!$C:$C,HS_STANDALONE!M:M,0,0,1) -> 48656000000
B63: Total Current Assets | E63: =IFERROR(E61+E54,0) -> 0 | F63: =IFERROR(F61+F54,0) -> 73254200000 | G63: =IFERROR(G61+G54,0) -> 63247400000 | H63: =IFERROR(H61+H54,0) -> 37996500000 | I63: =IFERROR(I61+I54,0) -> 21679900000 | J63: =IFERROR(J61+J54,0) -> 19812400000 | K63: =IFERROR(K61+K54,0) -> 27839200000 | L63: =IFERROR(L61+L54,0) -> 20364900000 | ... N63: =IFERROR(N61+N54,0) -> 83560300000
C64: Non-current assets classified as held for sale | E64: =_xlfn.XLOOKUP("NoncurrentAssetsOrDisposalGroupsClassifiedAsHeldForSaleOrAsHeldForDistributionToOwners",HS_STANDALONE!$C:$C,HS_STANDALONE!D:D,0,0,1) -> 0 | F64: =_xlfn.XLOOKUP("NoncurrentAssetsOrDisposalGroupsClassifiedAsHeldForSaleOrAsHeldForDistributionToOwners",HS_STANDALONE!$C:$C,HS_STANDALONE!E:E,0,0,1) -> 0 | G64: =_xlfn.XLOOKUP("NoncurrentAssetsOrDisposalGroupsClassifiedAsHeldForSaleOrAsHeldForDistributionToOwners",HS_STANDALONE!$C:$C,HS_STANDALONE!F:F,0,0,1) -> 3584000000 | H64: =_xlfn.XLOOKUP("NoncurrentAssetsOrDisposalGroupsClassifiedAsHeldForSaleOrAsHeldForDistributionToOwners",HS_STANDALONE!$C:$C,HS_STANDALONE!G:G,0,0,1) -> 738300000 | I64: =_xlfn.XLOOKUP("NoncurrentAssetsOrDisposalGroupsClassifiedAsHeldForSaleOrAsHeldForDistributionToOwners",HS_STANDALONE!$C:$C,HS_STANDALONE!H:H,0,0,1) -> 434400000 | J64: =_xlfn.XLOOKUP("NoncurrentAssetsOrDisposalGroupsClassifiedAsHeldForSaleOrAsHeldForDistributionToOwners",HS_STANDALONE!$C:$C,HS_STANDALONE!I:I,0,0,1) -> 420300000 | K64: =_xlfn.XLOOKUP("NoncurrentAssetsOrDisposalGroupsClassifiedAsHeldForSaleOrAsHeldForDistributionToOwners",HS_STANDALONE!$C:$C,HS_STANDALONE!J:J,0,0,1) -> 955400000 | L64: =_xlfn.XLOOKUP("NoncurrentAssetsOrDisposalGroupsClassifiedAsHeldForSaleOrAsHeldForDistributionToOwners",HS_STANDALONE!$C:$C,HS_STANDALONE!K:K,0,0,1) -> 278100000 | M64: =_xlfn.XLOOKUP("NoncurrentAssetsOrDisposalGroupsClassifiedAsHeldForSaleOrAsHeldForDistributionToOwners",HS_STANDALONE!$C:$C,HS_STANDALONE!L:L,0,0,1) -> 0 | N64: =_xlfn.XLOOKUP("NoncurrentAssetsOrDisposalGroupsClassifiedAsHeldForSaleOrAsHeldForDistributionToOwners",HS_STANDALONE!$C:$C,HS_STANDALONE!M:M,0,0,1) -> 0
B65: Total Assets | E65: =IFERROR(SUM(E63:E64)+E48,0) -> 0 | F65: =IFERROR(SUM(F63:F64)+F48,0) -> 142260300000 | G65: =IFERROR(SUM(G63:G64)+G48,0) -> 128410200000 | H65: =IFERROR(SUM(H63:H64)+H48,0) -> 85227700000 | I65: =IFERROR(SUM(I63:I64)+I48,0) -> 57234000000 | J65: =IFERROR(SUM(J63:J64)+J48,0) -> 53620400000 | K65: =IFERROR(SUM(K63:K64)+K48,0) -> 56752600000 | L65: =IFERROR(SUM(L63:L64)+L48,0) -> 60479900000 | ... N65: =IFERROR(SUM(N63:N64)+N48,0) -> 123444600000
B66: Equity and Liabilities
B67: Equity attributable to owners of parent
C68: Equity share capital at end of period | E68: =_xlfn.XLOOKUP("EquityShareCapital",HS_STANDALONE!$C:$C,HS_STANDALONE!D:D,0,0,1) -> 0 | F68: =_xlfn.XLOOKUP("EquityShareCapital",HS_STANDALONE!$C:$C,HS_STANDALONE!E:E,0,0,1) -> 10048800000 | G68: =_xlfn.XLOOKUP("EquityShareCapital",HS_STANDALONE!$C:$C,HS_STANDALONE!F:F,0,0,1) -> 10639500000 | H68: =_xlfn.XLOOKUP("EquityShareCapital",HS_STANDALONE!$C:$C,HS_STANDALONE!G:G,0,0,1) -> 10639500000 | I68: =_xlfn.XLOOKUP("EquityShareCapital",HS_STANDALONE!$C:$C,HS_STANDALONE!H:H,0,0,1) -> 10639500000 | J68: =_xlfn.XLOOKUP("EquityShareCapital",HS_STANDALONE!$C:$C,HS_STANDALONE!I:I,0,0,1) -> 17016000000 | K68: =_xlfn.XLOOKUP("EquityShareCapital",HS_STANDALONE!$C:$C,HS_STANDALONE!J:J,0,0,1) -> 18434900000 | L68: =_xlfn.XLOOKUP("EquityShareCapital",HS_STANDALONE!$C:$C,HS_STANDALONE!K:K,0,0,1) -> 24544000000 | M68: =_xlfn.XLOOKUP("EquityShareCapital",HS_STANDALONE!$C:$C,HS_STANDALONE!L:L,0,0,1) -> 27217200000 | N68: =_xlfn.XLOOKUP("EquityShareCapital",HS_STANDALONE!$C:$C,HS_STANDALONE!M:M,0,0,1) -> 27317900000
C69: Other equity | E69: =_xlfn.XLOOKUP("OtherEquity",HS_STANDALONE!$C:$C,HS_STANDALONE!D:D,0,0,1) -> 0 | F69: =_xlfn.XLOOKUP("OtherEquity",HS_STANDALONE!$C:$C,HS_STANDALONE!E:E,0,0,1) -> 175900000 | G69: =_xlfn.XLOOKUP("OtherEquity",HS_STANDALONE!$C:$C,HS_STANDALONE!F:F,0,0,1) -> -7103400000 | H69: =_xlfn.XLOOKUP("OtherEquity",HS_STANDALONE!$C:$C,HS_STANDALONE!G:G,0,0,1) -> -80869300000 | I69: =_xlfn.XLOOKUP("OtherEquity",HS_STANDALONE!$C:$C,HS_STANDALONE!H:H,0,0,1) -> -113422400000 | J69: =_xlfn.XLOOKUP("OtherEquity",HS_STANDALONE!$C:$C,HS_STANDALONE!I:I,0,0,1) -> -56804300000 | K69: =_xlfn.XLOOKUP("OtherEquity",HS_STANDALONE!$C:$C,HS_STANDALONE!J:J,0,0,1) -> -57355800000 | L69: =_xlfn.XLOOKUP("OtherEquity",HS_STANDALONE!$C:$C,HS_STANDALONE!K:K,0,0,1) -> -10350100000 | M69: =_xlfn.XLOOKUP("OtherEquity",HS_STANDALONE!$C:$C,HS_STANDALONE!L:L,0,0,1) -> 8851300000 | N69: =_xlfn.XLOOKUP("OtherEquity",HS_STANDALONE!$C:$C,HS_STANDALONE!M:M,0,0,1) -> 27972100000
B70: Total equity attributable to owners of parent | E70: =IFERROR(SUM(E68:E69),0) -> 0 | F70: =IFERROR(SUM(F68:F69),0) -> 10224700000 | G70: =IFERROR(SUM(G68:G69),0) -> 3536100000 | H70: =IFERROR(SUM(H68:H69),0) -> -70229800000 | I70: =IFERROR(SUM(I68:I69),0) -> -102782900000 | J70: =IFERROR(SUM(J68:J69),0) -> -39788300000 | K70: =IFERROR(SUM(K68:K69),0) -> -38920900000 | L70: =IFERROR(SUM(L68:L69),0) -> 14193900000 | ... N70: =IFERROR(SUM(N68:N69),0) -> 55290000000
B71: Equity at end of period | E71: =IFERROR(SUM(E70:E70),0) -> 0 | F71: =IFERROR(SUM(F70:F70),0) -> 10224700000 | G71: =IFERROR(SUM(G70:G70),0) -> 3536100000 | H71: =IFERROR(SUM(H70:H70),0) -> -70229800000 | I71: =IFERROR(SUM(I70:I70),0) -> -102782900000 | J71: =IFERROR(SUM(J70:J70),0) -> -39788300000 | K71: =IFERROR(SUM(K70:K70),0) -> -38920900000 | L71: =IFERROR(SUM(L70:L70),0) -> 14193900000 | ... N71: =IFERROR(SUM(N70:N70),0) -> 55290000000
B72: Liabilities
B73: Non-current liabilities
B74: Non-current financial liabilities
C75: Borrowings, non-current | E75: =_xlfn.XLOOKUP("BorrowingsNoncurrent",HS_STANDALONE!$C:$C,HS_STANDALONE!D:D,0,0,1) -> 0 | F75: =_xlfn.XLOOKUP("BorrowingsNoncurrent",HS_STANDALONE!$C:$C,HS_STANDALONE!E:E,0,0,1) -> 40385400000 | G75: =_xlfn.XLOOKUP("BorrowingsNoncurrent",HS_STANDALONE!$C:$C,HS_STANDALONE!F:F,0,0,1) -> 33629500000 | H75: =_xlfn.XLOOKUP("BorrowingsNoncurrent",HS_STANDALONE!$C:$C,HS_STANDALONE!G:G,0,0,1) -> 18425300000 | I75: =_xlfn.XLOOKUP("BorrowingsNoncurrent",HS_STANDALONE!$C:$C,HS_STANDALONE!H:H,0,0,1) -> 6536600000 | J75: =_xlfn.XLOOKUP("BorrowingsNoncurrent",HS_STANDALONE!$C:$C,HS_STANDALONE!I:I,0,0,1) -> 42928800000 | K75: =_xlfn.XLOOKUP("BorrowingsNoncurrent",HS_STANDALONE!$C:$C,HS_STANDALONE!J:J,0,0,1) -> 37746900000 | L75: =_xlfn.XLOOKUP("BorrowingsNoncurrent",HS_STANDALONE!$C:$C,HS_STANDALONE!K:K,0,0,1) -> 20089800000 | M75: =_xlfn.XLOOKUP("BorrowingsNoncurrent",HS_STANDALONE!$C:$C,HS_STANDALONE!L:L,0,0,1) -> 6361800000 | N75: =_xlfn.XLOOKUP("BorrowingsNoncurrent",HS_STANDALONE!$C:$C,HS_STANDALONE!M:M,0,0,1) -> 0
C76: Trade payables, non-current
C77: Total other non-current financial liabilities | E77: =_xlfn.XLOOKUP("OtherNoncurrentFinancialLiabilities",HS_STANDALONE!$C:$C,HS_STANDALONE!D:D,0,0,1) -> 0 | F77: =_xlfn.XLOOKUP("OtherNoncurrentFinancialLiabilities",HS_STANDALONE!$C:$C,HS_STANDALONE!E:E,0,0,1) -> 2015900000 | G77: =_xlfn.XLOOKUP("OtherNoncurrentFinancialLiabilities",HS_STANDALONE!$C:$C,HS_STANDALONE!F:F,0,0,1) -> 94800000 | H77: =_xlfn.XLOOKUP("OtherNoncurrentFinancialLiabilities",HS_STANDALONE!$C:$C,HS_STANDALONE!G:G,0,0,1) -> 64900000 | I77: =_xlfn.XLOOKUP("OtherNoncurrentFinancialLiabilities",HS_STANDALONE!$C:$C,HS_STANDALONE!H:H,0,0,1) -> 678500000 | J77: =_xlfn.XLOOKUP("OtherNoncurrentFinancialLiabilities",HS_STANDALONE!$C:$C,HS_STANDALONE!I:I,0,0,1) -> 21200300000 | K77: =_xlfn.XLOOKUP("OtherNoncurrentFinancialLiabilities",HS_STANDALONE!$C:$C,HS_STANDALONE!J:J,0,0,1) -> 23948700000 | L77: =_xlfn.XLOOKUP("OtherNoncurrentFinancialLiabilities",HS_STANDALONE!$C:$C,HS_STANDALONE!K:K,0,0,1) -> 83800000 | M77: =_xlfn.XLOOKUP("OtherNoncurrentFinancialLiabilities",HS_STANDALONE!$C:$C,HS_STANDALONE!L:L,0,0,1) -> 190500000 | N77: =_xlfn.XLOOKUP("OtherNoncurrentFinancialLiabilities",HS_STANDALONE!$C:$C,HS_STANDALONE!M:M,0,0,1) -> 6409100000
C78: Total non-current financial liabilities | E78: =_xlfn.XLOOKUP("NoncurrentFinancialLiabilities",HS_STANDALONE!$C:$C,HS_STANDALONE!D:D,0,0,1) -> 0 | F78: =_xlfn.XLOOKUP("NoncurrentFinancialLiabilities",HS_STANDALONE!$C:$C,HS_STANDALONE!E:E,0,0,1) -> 42401300000 | G78: =_xlfn.XLOOKUP("NoncurrentFinancialLiabilities",HS_STANDALONE!$C:$C,HS_STANDALONE!F:F,0,0,1) -> 33724300000 | H78: =_xlfn.XLOOKUP("NoncurrentFinancialLiabilities",HS_STANDALONE!$C:$C,HS_STANDALONE!G:G,0,0,1) -> 18490200000 | I78: =_xlfn.XLOOKUP("NoncurrentFinancialLiabilities",HS_STANDALONE!$C:$C,HS_STANDALONE!H:H,0,0,1) -> 7215100000 | J78: =_xlfn.XLOOKUP("NoncurrentFinancialLiabilities",HS_STANDALONE!$C:$C,HS_STANDALONE!I:I,0,0,1) -> 64129100000 | K78: =_xlfn.XLOOKUP("NoncurrentFinancialLiabilities",HS_STANDALONE!$C:$C,HS_STANDALONE!J:J,0,0,1) -> 61695600000 | L78: =_xlfn.XLOOKUP("NoncurrentFinancialLiabilities",HS_STANDALONE!$C:$C,HS_STANDALONE!K:K,0,0,1) -> 20173600000 | M78: =_xlfn.XLOOKUP("NoncurrentFinancialLiabilities",HS_STANDALONE!$C:$C,HS_STANDALONE!L:L,0,0,1) -> 6552300000 | N78: =_xlfn.XLOOKUP("NoncurrentFinancialLiabilities",HS_STANDALONE!$C:$C,HS_STANDALONE!M:M,0,0,1) -> 6409100000
D79: Provisions, non-current | E79: =_xlfn.XLOOKUP("ProvisionsNoncurrent",HS_STANDALONE!$C:$C,HS_STANDALONE!D:D,0,0,1) -> 0 | F79: =_xlfn.XLOOKUP("ProvisionsNoncurrent",HS_STANDALONE!$C:$C,HS_STANDALONE!E:E,0,0,1) -> 582700000 | G79: =_xlfn.XLOOKUP("ProvisionsNoncurrent",HS_STANDALONE!$C:$C,HS_STANDALONE!F:F,0,0,1) -> 876200000 | H79: =_xlfn.XLOOKUP("ProvisionsNoncurrent",HS_STANDALONE!$C:$C,HS_STANDALONE!G:G,0,0,1) -> 40340600000 | I79: =_xlfn.XLOOKUP("ProvisionsNoncurrent",HS_STANDALONE!$C:$C,HS_STANDALONE!H:H,0,0,1) -> 798800000 | J79: =_xlfn.XLOOKUP("ProvisionsNoncurrent",HS_STANDALONE!$C:$C,HS_STANDALONE!I:I,0,0,1) -> 651700000 | K79: =_xlfn.XLOOKUP("ProvisionsNoncurrent",HS_STANDALONE!$C:$C,HS_STANDALONE!J:J,0,0,1) -> 1129600000 | L79: =_xlfn.XLOOKUP("ProvisionsNoncurrent",HS_STANDALONE!$C:$C,HS_STANDALONE!K:K,0,0,1) -> 1448300000 | M79: =_xlfn.XLOOKUP("ProvisionsNoncurrent",HS_STANDALONE!$C:$C,HS_STANDALONE!L:L,0,0,1) -> 1441400000 | N79: =_xlfn.XLOOKUP("ProvisionsNoncurrent",HS_STANDALONE!$C:$C,HS_STANDALONE!M:M,0,0,1) -> 1479600000
D80: Total other non-current liabilities | E80: =_xlfn.XLOOKUP("OtherNoncurrentLiabilities",HS_STANDALONE!$C:$C,HS_STANDALONE!D:D,0,0,1) -> 0 | F80: =_xlfn.XLOOKUP("OtherNoncurrentLiabilities",HS_STANDALONE!$C:$C,HS_STANDALONE!E:E,0,0,1) -> 400200000 | G80: =_xlfn.XLOOKUP("OtherNoncurrentLiabilities",HS_STANDALONE!$C:$C,HS_STANDALONE!F:F,0,0,1) -> 299900000 | H80: =_xlfn.XLOOKUP("OtherNoncurrentLiabilities",HS_STANDALONE!$C:$C,HS_STANDALONE!G:G,0,0,1) -> 117000000 | I80: =_xlfn.XLOOKUP("OtherNoncurrentLiabilities",HS_STANDALONE!$C:$C,HS_STANDALONE!H:H,0,0,1) -> 8900000 | J80: =_xlfn.XLOOKUP("OtherNoncurrentLiabilities",HS_STANDALONE!$C:$C,HS_STANDALONE!I:I,0,0,1) -> 7700000 | K80: =_xlfn.XLOOKUP("OtherNoncurrentLiabilities",HS_STANDALONE!$C:$C,HS_STANDALONE!J:J,0,0,1) -> 1900000 | L80: =_xlfn.XLOOKUP("OtherNoncurrentLiabilities",HS_STANDALONE!$C:$C,HS_STANDALONE!K:K,0,0,1) -> 4800000 | M80: =_xlfn.XLOOKUP("OtherNoncurrentLiabilities",HS_STANDALONE!$C:$C,HS_STANDALONE!L:L,0,0,1) -> 4800000 | N80: =_xlfn.XLOOKUP("OtherNoncurrentLiabilities",HS_STANDALONE!$C:$C,HS_STANDALONE!M:M,0,0,1) -> 4500000
B81: Total non-current liabilities | E81: =IFERROR(SUM(E75:E75)+SUM(E77:E77)+SUM(E79:E80),0) -> 0 | F81: =IFERROR(SUM(F75:F75)+SUM(F77:F77)+SUM(F79:F80),0) -> 43384200000 | G81: =IFERROR(SUM(G75:G75)+SUM(G77:G77)+SUM(G79:G80),0) -> 34900400000 | H81: =IFERROR(SUM(H75:H75)+SUM(H77:H77)+SUM(H79:H80),0) -> 58947800000 | I81: =IFERROR(SUM(I75:I75)+SUM(I77:I77)+SUM(I79:I80),0) -> 8022800000 | J81: =IFERROR(SUM(J75:J75)+SUM(J77:J77)+SUM(J79:J80),0) -> 64788500000 | K81: =IFERROR(SUM(K75:K75)+SUM(K77:K77)+SUM(K79:K80),0) -> 62827100000 | L81: =IFERROR(SUM(L75:L75)+SUM(L77:L77)+SUM(L79:L80),0) -> 21626700000 | ... N81: =IFERROR(SUM(N75:N75)+SUM(N77:N77)+SUM(N79:N80),0) -> 7893200000
B82: Current liabilities
B83: Current financial liabilities
C84: Borrowings, current | E84: =_xlfn.XLOOKUP("BorrowingsCurrent",HS_STANDALONE!$C:$C,HS_STANDALONE!D:D,0,0,1) -> 0 | F84: =_xlfn.XLOOKUP("BorrowingsCurrent",HS_STANDALONE!$C:$C,HS_STANDALONE!E:E,0,0,1) -> 19757000000 | G84: =_xlfn.XLOOKUP("BorrowingsCurrent",HS_STANDALONE!$C:$C,HS_STANDALONE!F:F,0,0,1) -> 37667400000 | H84: =_xlfn.XLOOKUP("BorrowingsCurrent",HS_STANDALONE!$C:$C,HS_STANDALONE!G:G,0,0,1) -> 32579800000 | I84: =_xlfn.XLOOKUP("BorrowingsCurrent",HS_STANDALONE!$C:$C,HS_STANDALONE!H:H,0,0,1) -> 82606900000 | J84: =_xlfn.XLOOKUP("BorrowingsCurrent",HS_STANDALONE!$C:$C,HS_STANDALONE!I:I,0,0,1) -> 2000000000 | K84: =_xlfn.XLOOKUP("BorrowingsCurrent",HS_STANDALONE!$C:$C,HS_STANDALONE!J:J,0,0,1) -> 0 | L84: =_xlfn.XLOOKUP("BorrowingsCurrent",HS_STANDALONE!$C:$C,HS_STANDALONE!K:K,0,0,1) -> 3230200000 | M84: =_xlfn.XLOOKUP("BorrowingsCurrent",HS_STANDALONE!$C:$C,HS_STANDALONE!L:L,0,0,1) -> 0 | N84: =_xlfn.XLOOKUP("BorrowingsCurrent",HS_STANDALONE!$C:$C,HS_STANDALONE!M:M,0,0,1) -> 0
C85: Trade payables, current
D86: Total trade payables, current | E86: =_xlfn.XLOOKUP("TradePayablesCurrent",HS_STANDALONE!$C:$C,HS_STANDALONE!D:D,0,0,1) -> 0 | F86: =_xlfn.XLOOKUP("TradePayablesCurrent",HS_STANDALONE!$C:$C,HS_STANDALONE!E:E,0,0,1) -> 46546400000 | G86: =_xlfn.XLOOKUP("TradePayablesCurrent",HS_STANDALONE!$C:$C,HS_STANDALONE!F:F,0,0,1) -> 24340800000 | H86: =_xlfn.XLOOKUP("TradePayablesCurrent",HS_STANDALONE!$C:$C,HS_STANDALONE!G:G,0,0,1) -> 17933400000 | I86: =_xlfn.XLOOKUP("TradePayablesCurrent",HS_STANDALONE!$C:$C,HS_STANDALONE!H:H,0,0,1) -> 11578600000 | J86: =_xlfn.XLOOKUP("TradePayablesCurrent",HS_STANDALONE!$C:$C,HS_STANDALONE!I:I,0,0,1) -> 13724500000 | K86: =_xlfn.XLOOKUP("TradePayablesCurrent",HS_STANDALONE!$C:$C,HS_STANDALONE!J:J,0,0,1) -> 18159400000 | L86: =_xlfn.XLOOKUP("TradePayablesCurrent",HS_STANDALONE!$C:$C,HS_STANDALONE!K:K,0,0,1) -> 10620900000 | M86: =_xlfn.XLOOKUP("TradePayablesCurrent",HS_STANDALONE!$C:$C,HS_STANDALONE!L:L,0,0,1) -> 19388100000 | N86: =_xlfn.XLOOKUP("TradePayablesCurrent",HS_STANDALONE!$C:$C,HS_STANDALONE!M:M,0,0,1) -> 33332000000
C87: Total other current financial liabilities | E87: =_xlfn.XLOOKUP("OtherCurrentFinancialLiabilities",HS_STANDALONE!$C:$C,HS_STANDALONE!D:D,0,0,1) -> 0 | F87: =_xlfn.XLOOKUP("OtherCurrentFinancialLiabilities",HS_STANDALONE!$C:$C,HS_STANDALONE!E:E,0,0,1) -> 6787600000 | G87: =_xlfn.XLOOKUP("OtherCurrentFinancialLiabilities",HS_STANDALONE!$C:$C,HS_STANDALONE!F:F,0,0,1) -> 13378300000 | H87: =_xlfn.XLOOKUP("OtherCurrentFinancialLiabilities",HS_STANDALONE!$C:$C,HS_STANDALONE!G:G,0,0,1) -> 26912000000 | I87: =_xlfn.XLOOKUP("OtherCurrentFinancialLiabilities",HS_STANDALONE!$C:$C,HS_STANDALONE!H:H,0,0,1) -> 49280000000 | J87: =_xlfn.XLOOKUP("OtherCurrentFinancialLiabilities",HS_STANDALONE!$C:$C,HS_STANDALONE!I:I,0,0,1) -> 5282000000 | K87: =_xlfn.XLOOKUP("OtherCurrentFinancialLiabilities",HS_STANDALONE!$C:$C,HS_STANDALONE!J:J,0,0,1) -> 7075000000 | L87: =_xlfn.XLOOKUP("OtherCurrentFinancialLiabilities",HS_STANDALONE!$C:$C,HS_STANDALONE!K:K,0,0,1) -> 2262000000 | M87: =_xlfn.XLOOKUP("OtherCurrentFinancialLiabilities",HS_STANDALONE!$C:$C,HS_STANDALONE!L:L,0,0,1) -> 1985300000 | N87: =_xlfn.XLOOKUP("OtherCurrentFinancialLiabilities",HS_STANDALONE!$C:$C,HS_STANDALONE!M:M,0,0,1) -> 3819400000
B88: Total current financial liabilities | E88: =_xlfn.XLOOKUP("CurrentFinancialLiabilities",HS_STANDALONE!$C:$C,HS_STANDALONE!D:D,0,0,1) -> 0 | F88: =_xlfn.XLOOKUP("CurrentFinancialLiabilities",HS_STANDALONE!$C:$C,HS_STANDALONE!E:E,0,0,1) -> 73091000000 | G88: =_xlfn.XLOOKUP("CurrentFinancialLiabilities",HS_STANDALONE!$C:$C,HS_STANDALONE!F:F,0,0,1) -> 75386500000 | H88: =_xlfn.XLOOKUP("CurrentFinancialLiabilities",HS_STANDALONE!$C:$C,HS_STANDALONE!G:G,0,0,1) -> 77425200000 | I88: =_xlfn.XLOOKUP("CurrentFinancialLiabilities",HS_STANDALONE!$C:$C,HS_STANDALONE!H:H,0,0,1) -> 143465500000 | J88: =_xlfn.XLOOKUP("CurrentFinancialLiabilities",HS_STANDALONE!$C:$C,HS_STANDALONE!I:I,0,0,1) -> 21006500000 | K88: =_xlfn.XLOOKUP("CurrentFinancialLiabilities",HS_STANDALONE!$C:$C,HS_STANDALONE!J:J,0,0,1) -> 25234400000 | L88: =_xlfn.XLOOKUP("CurrentFinancialLiabilities",HS_STANDALONE!$C:$C,HS_STANDALONE!K:K,0,0,1) -> 16113100000 | M88: =_xlfn.XLOOKUP("CurrentFinancialLiabilities",HS_STANDALONE!$C:$C,HS_STANDALONE!L:L,0,0,1) -> 21373400000 | N88: =_xlfn.XLOOKUP("CurrentFinancialLiabilities",HS_STANDALONE!$C:$C,HS_STANDALONE!M:M,0,0,1) -> 37151400000
C89: Total other current liabilities | E89: =_xlfn.XLOOKUP("OtherCurrentLiabilities",HS_STANDALONE!$C:$C,HS_STANDALONE!D:D,0,0,1) -> 0 | F89: =_xlfn.XLOOKUP("OtherCurrentLiabilities",HS_STANDALONE!$C:$C,HS_STANDALONE!E:E,0,0,1) -> 8691200000 | G89: =_xlfn.XLOOKUP("OtherCurrentLiabilities",HS_STANDALONE!$C:$C,HS_STANDALONE!F:F,0,0,1) -> 7627900000 | H89: =_xlfn.XLOOKUP("OtherCurrentLiabilities",HS_STANDALONE!$C:$C,HS_STANDALONE!G:G,0,0,1) -> 12749300000 | I89: =_xlfn.XLOOKUP("OtherCurrentLiabilities",HS_STANDALONE!$C:$C,HS_STANDALONE!H:H,0,0,1) -> 2747000000 | J89: =_xlfn.XLOOKUP("OtherCurrentLiabilities",HS_STANDALONE!$C:$C,HS_STANDALONE!I:I,0,0,1) -> 3222400000 | K89: =_xlfn.XLOOKUP("OtherCurrentLiabilities",HS_STANDALONE!$C:$C,HS_STANDALONE!J:J,0,0,1) -> 3659400000 | L89: =_xlfn.XLOOKUP("OtherCurrentLiabilities",HS_STANDALONE!$C:$C,HS_STANDALONE!K:K,0,0,1) -> 4034200000 | M89: =_xlfn.XLOOKUP("OtherCurrentLiabilities",HS_STANDALONE!$C:$C,HS_STANDALONE!L:L,0,0,1) -> 1927900000 | N89: =_xlfn.XLOOKUP("OtherCurrentLiabilities",HS_STANDALONE!$C:$C,HS_STANDALONE!M:M,0,0,1) -> 17537500000
C90: Provisions, current | E90: =_xlfn.XLOOKUP("ProvisionsCurrent",HS_STANDALONE!$C:$C,HS_STANDALONE!D:D,0,0,1) -> 0 | F90: =_xlfn.XLOOKUP("ProvisionsCurrent",HS_STANDALONE!$C:$C,HS_STANDALONE!E:E,0,0,1) -> 6869200000 | G90: =_xlfn.XLOOKUP("ProvisionsCurrent",HS_STANDALONE!$C:$C,HS_STANDALONE!F:F,0,0,1) -> 6959300000 | H90: =_xlfn.XLOOKUP("ProvisionsCurrent",HS_STANDALONE!$C:$C,HS_STANDALONE!G:G,0,0,1) -> 6335200000 | I90: =_xlfn.XLOOKUP("ProvisionsCurrent",HS_STANDALONE!$C:$C,HS_STANDALONE!H:H,0,0,1) -> 5781600000 | J90: =_xlfn.XLOOKUP("ProvisionsCurrent",HS_STANDALONE!$C:$C,HS_STANDALONE!I:I,0,0,1) -> 4391300000 | K90: =_xlfn.XLOOKUP("ProvisionsCurrent",HS_STANDALONE!$C:$C,HS_STANDALONE!J:J,0,0,1) -> 3952600000 | L90: =_xlfn.XLOOKUP("ProvisionsCurrent",HS_STANDALONE!$C:$C,HS_STANDALONE!K:K,0,0,1) -> 4512000000 | M90: =_xlfn.XLOOKUP("ProvisionsCurrent",HS_STANDALONE!$C:$C,HS_STANDALONE!L:L,0,0,1) -> 4278300000 | N90: =_xlfn.XLOOKUP("ProvisionsCurrent",HS_STANDALONE!$C:$C,HS_STANDALONE!M:M,0,0,1) -> 5502000000
C91: Current tax liabilities | E91: =_xlfn.XLOOKUP("CurrentTaxLiabilities",HS_STANDALONE!$C:$C,HS_STANDALONE!D:D,0,0,1) -> 0 | F91: =_xlfn.XLOOKUP("CurrentTaxLiabilities",HS_STANDALONE!$C:$C,HS_STANDALONE!E:E,0,0,1) -> 0 | G91: =_xlfn.XLOOKUP("CurrentTaxLiabilities",HS_STANDALONE!$C:$C,HS_STANDALONE!F:F,0,0,1) -> 0 | H91: =_xlfn.XLOOKUP("CurrentTaxLiabilities",HS_STANDALONE!$C:$C,HS_STANDALONE!G:G,0,0,1) -> 0 | I91: =_xlfn.XLOOKUP("CurrentTaxLiabilities",HS_STANDALONE!$C:$C,HS_STANDALONE!H:H,0,0,1) -> 0 | J91: =_xlfn.XLOOKUP("CurrentTaxLiabilities",HS_STANDALONE!$C:$C,HS_STANDALONE!I:I,0,0,1) -> 0 | K91: =_xlfn.XLOOKUP("CurrentTaxLiabilities",HS_STANDALONE!$C:$C,HS_STANDALONE!J:J,0,0,1) -> 0 | L91: =_xlfn.XLOOKUP("CurrentTaxLiabilities",HS_STANDALONE!$C:$C,HS_STANDALONE!K:K,0,0,1) -> 0 | M91: =_xlfn.XLOOKUP("CurrentTaxLiabilities",HS_STANDALONE!$C:$C,HS_STANDALONE!L:L,0,0,1) -> 0 | N91: =_xlfn.XLOOKUP("CurrentTaxLiabilities",HS_STANDALONE!$C:$C,HS_STANDALONE!M:M,0,0,1) -> 70500000
B92: Total current liabilities | E92: =IFERROR(SUM(E84:E84)+SUM(E86:E87)+SUM(E89:E91),0) -> 0 | F92: =IFERROR(SUM(F84:F84)+SUM(F86:F87)+SUM(F89:F91),0) -> 88651400000 | G92: =IFERROR(SUM(G84:G84)+SUM(G86:G87)+SUM(G89:G91),0) -> 89973700000 | H92: =IFERROR(SUM(H84:H84)+SUM(H86:H87)+SUM(H89:H91),0) -> 96509700000 | I92: =IFERROR(SUM(I84:I84)+SUM(I86:I87)+SUM(I89:I91),0) -> 151994100000 | J92: =IFERROR(SUM(J84:J84)+SUM(J86:J87)+SUM(J89:J91),0) -> 28620200000 | K92: =IFERROR(SUM(K84:K84)+SUM(K86:K87)+SUM(K89:K91),0) -> 32846400000 | L92: =IFERROR(SUM(L84:L84)+SUM(L86:L87)+SUM(L89:L91),0) -> 24659300000 | ... N92: =IFERROR(SUM(N84:N84)+SUM(N86:N87)+SUM(N89:N91),0) -> 60261400000
B93: Liabilities | E93: =IFERROR(SUM(E92:E92)+E81,0) -> 0 | F93: =IFERROR(SUM(F92:F92)+F81,0) -> 132035600000 | G93: =IFERROR(SUM(G92:G92)+G81,0) -> 124874100000 | H93: =IFERROR(SUM(H92:H92)+H81,0) -> 155457500000 | I93: =IFERROR(SUM(I92:I92)+I81,0) -> 160016900000 | J93: =IFERROR(SUM(J92:J92)+J81,0) -> 93408700000 | K93: =IFERROR(SUM(K92:K92)+K81,0) -> 95673500000 | L93: =IFERROR(SUM(L92:L92)+L81,0) -> 46286000000 | ... N93: =IFERROR(SUM(N92:N92)+N81,0) -> 68154600000
B94: Total equity and liabilities | E94: =IFERROR(E71+E93,0) -> 0 | F94: =IFERROR(F71+F93,0) -> 142260300000 | G94: =IFERROR(G71+G93,0) -> 128410200000 | H94: =IFERROR(H71+H93,0) -> 85227700000 | I94: =IFERROR(I71+I93,0) -> 57234000000 | J94: =IFERROR(J71+J93,0) -> 53620400000 | K94: =IFERROR(K71+K93,0) -> 56752600000 | L94: =IFERROR(L71+L93,0) -> 60479900000 | ... N94: =IFERROR(N71+N93,0) -> 123444600000
B95: BALANCE CHECK (Total Assets − Total Equity & Liabilities) | E95: =E65-E94 -> 0 | F95: =F65-F94 -> 0 | G95: =G65-G94 -> 0 | H95: =H65-H94 -> 0 | I95: =I65-I94 -> 0 | J95: =J65-J94 -> 0 | K95: =K65-K94 -> 0 | L95: =L65-L94 -> 0 | ... N95: =N65-N94 -> 0
A96: # | B96: Statement of Cash Flows
B97: Cash flows from used in operating activities
C98: Total profit before tax | E98: =_xlfn.XLOOKUP("ProfitBeforeTax",HS_STANDALONE!$C:$C,HS_STANDALONE!D:D,0,0,1) -> 0 | F98: =_xlfn.XLOOKUP("ProfitBeforeTax",HS_STANDALONE!$C:$C,HS_STANDALONE!E:E,0,0,1) -> 3556500000 | G98: =_xlfn.XLOOKUP("ProfitBeforeTax",HS_STANDALONE!$C:$C,HS_STANDALONE!F:F,0,0,1) -> -11547400000 | H98: =_xlfn.XLOOKUP("ProfitBeforeTax",HS_STANDALONE!$C:$C,HS_STANDALONE!G:G,0,0,1) -> -74119800000 | I98: =_xlfn.XLOOKUP("ProfitBeforeTax",HS_STANDALONE!$C:$C,HS_STANDALONE!H:H,0,0,1) -> -32759800000 | J98: =_xlfn.XLOOKUP("ProfitBeforeTax",HS_STANDALONE!$C:$C,HS_STANDALONE!I:I,0,0,1) -> -3984000000 | K98: =_xlfn.XLOOKUP("ProfitBeforeTax",HS_STANDALONE!$C:$C,HS_STANDALONE!J:J,0,0,1) -> -9126600000 | L98: =_xlfn.XLOOKUP("ProfitBeforeTax",HS_STANDALONE!$C:$C,HS_STANDALONE!K:K,0,0,1) -> 21627600000 | M98: =_xlfn.XLOOKUP("ProfitBeforeTax",HS_STANDALONE!$C:$C,HS_STANDALONE!L:L,0,0,1) -> 934300000 | N98: =_xlfn.XLOOKUP("ProfitBeforeTax",HS_STANDALONE!$C:$C,HS_STANDALONE!M:M,0,0,1) -> 14737200000
C99: Adjustments for reconcile profit (loss)
D100: Adjustments for finance costs | E100: =_xlfn.XLOOKUP("AdjustmentsForFinanceCosts",HS_STANDALONE!$C:$C,HS_STANDALONE!D:D,0,0,1) -> 0 | F100: =_xlfn.XLOOKUP("AdjustmentsForFinanceCosts",HS_STANDALONE!$C:$C,HS_STANDALONE!E:E,0,0,1) -> 8057100000 | G100: =_xlfn.XLOOKUP("AdjustmentsForFinanceCosts",HS_STANDALONE!$C:$C,HS_STANDALONE!F:F,0,0,1) -> 0 | H100: =_xlfn.XLOOKUP("AdjustmentsForFinanceCosts",HS_STANDALONE!$C:$C,HS_STANDALONE!G:G,0,0,1) -> 0 | I100: =_xlfn.XLOOKUP("AdjustmentsForFinanceCosts",HS_STANDALONE!$C:$C,HS_STANDALONE!H:H,0,0,1) -> 0 | J100: =_xlfn.XLOOKUP("AdjustmentsForFinanceCosts",HS_STANDALONE!$C:$C,HS_STANDALONE!I:I,0,0,1) -> 0 | K100: =_xlfn.XLOOKUP("AdjustmentsForFinanceCosts",HS_STANDALONE!$C:$C,HS_STANDALONE!J:J,0,0,1) -> 0 | L100: =_xlfn.XLOOKUP("AdjustmentsForFinanceCosts",HS_STANDALONE!$C:$C,HS_STANDALONE!K:K,0,0,1) -> 0 | M100: =_xlfn.XLOOKUP("AdjustmentsForFinanceCosts",HS_STANDALONE!$C:$C,HS_STANDALONE!L:L,0,0,1) -> 0 | N100: =_xlfn.XLOOKUP("AdjustmentsForFinanceCosts",HS_STANDALONE!$C:$C,HS_STANDALONE!M:M,0,0,1) -> 840100000
D101: Adjustments for decrease (increase) in inventories | E101: =_xlfn.XLOOKUP("AdjustmentsForDecreaseIncreaseInInventories",HS_STANDALONE!$C:$C,HS_STANDALONE!D:D,0,0,1) -> 0 | F101: =_xlfn.XLOOKUP("AdjustmentsForDecreaseIncreaseInInventories",HS_STANDALONE!$C:$C,HS_STANDALONE!E:E,0,0,1) -> -8747100000 | G101: =_xlfn.XLOOKUP("AdjustmentsForDecreaseIncreaseInInventories",HS_STANDALONE!$C:$C,HS_STANDALONE!F:F,0,0,1) -> 7240600000 | H101: =_xlfn.XLOOKUP("AdjustmentsForDecreaseIncreaseInInventories",HS_STANDALONE!$C:$C,HS_STANDALONE!G:G,0,0,1) -> 3714600000 | I101: =_xlfn.XLOOKUP("AdjustmentsForDecreaseIncreaseInInventories",HS_STANDALONE!$C:$C,HS_STANDALONE!H:H,0,0,1) -> 2832000000 | J101: =_xlfn.XLOOKUP("AdjustmentsForDecreaseIncreaseInInventories",HS_STANDALONE!$C:$C,HS_STANDALONE!I:I,0,0,1) -> 352000000 | K101: =_xlfn.XLOOKUP("AdjustmentsForDecreaseIncreaseInInventories",HS_STANDALONE!$C:$C,HS_STANDALONE!J:J,0,0,1) -> -3055300000 | L101: =_xlfn.XLOOKUP("AdjustmentsForDecreaseIncreaseInInventories",HS_STANDALONE!$C:$C,HS_STANDALONE!K:K,0,0,1) -> 4070500000 | M101: =_xlfn.XLOOKUP("AdjustmentsForDecreaseIncreaseInInventories",HS_STANDALONE!$C:$C,HS_STANDALONE!L:L,0,0,1) -> -4280300000 | N101: =_xlfn.XLOOKUP("AdjustmentsForDecreaseIncreaseInInventories",HS_STANDALONE!$C:$C,HS_STANDALONE!M:M,0,0,1) -> -7910200000
D102: Adjustments for decrease (increase) in trade receivables, current | E102: =_xlfn.XLOOKUP("AdjustmentsForDecreaseIncreaseInTradeReceivablesCurrent",HS_STANDALONE!$C:$C,HS_STANDALONE!D:D,0,0,1) -> 0 | F102: =_xlfn.XLOOKUP("AdjustmentsForDecreaseIncreaseInTradeReceivablesCurrent",HS_STANDALONE!$C:$C,HS_STANDALONE!E:E,0,0,1) -> -4388400000 | G102: =_xlfn.XLOOKUP("AdjustmentsForDecreaseIncreaseInTradeReceivablesCurrent",HS_STANDALONE!$C:$C,HS_STANDALONE!F:F,0,0,1) -> 4566500000 | H102: =_xlfn.XLOOKUP("AdjustmentsForDecreaseIncreaseInTradeReceivablesCurrent",HS_STANDALONE!$C:$C,HS_STANDALONE!G:G,0,0,1) -> 8188900000 | I102: =_xlfn.XLOOKUP("AdjustmentsForDecreaseIncreaseInTradeReceivablesCurrent",HS_STANDALONE!$C:$C,HS_STANDALONE!H:H,0,0,1) -> 4936500000 | J102: =_xlfn.XLOOKUP("AdjustmentsForDecreaseIncreaseInTradeReceivablesCurrent",HS_STANDALONE!$C:$C,HS_STANDALONE!I:I,0,0,1) -> 220000000 | K102: =_xlfn.XLOOKUP("AdjustmentsForDecreaseIncreaseInTradeReceivablesCurrent",HS_STANDALONE!$C:$C,HS_STANDALONE!J:J,0,0,1) -> -3001900000 | L102: =_xlfn.XLOOKUP("AdjustmentsForDecreaseIncreaseInTradeReceivablesCurrent",HS_STANDALONE!$C:$C,HS_STANDALONE!K:K,0,0,1) -> 1249900000 | M102: =_xlfn.XLOOKUP("AdjustmentsForDecreaseIncreaseInTradeReceivablesCurrent",HS_STANDALONE!$C:$C,HS_STANDALONE!L:L,0,0,1) -> -5686800000 | N102: =_xlfn.XLOOKUP("AdjustmentsForDecreaseIncreaseInTradeReceivablesCurrent",HS_STANDALONE!$C:$C,HS_STANDALONE!M:M,0,0,1) -> -20523900000
...

Sheet RATIO_ANALYSIS
A1: Suzlon — Ratio Analysis (Consolidated)
A2: Each ratio shown as Name = Numerator / Denominator, values computed once and reused (Green = first pull/computation from Derived Sheet, Black = same-sheet reuse) | Result appears on the right | Single-year figures (no opening/closing average)
A5: # | F5: FY? | G5: FY2017 | H5: FY2018 | I5: FY2019 | J5: FY2020 | K5: FY2021 | L5: FY2022 | M5: FY2023 | N5: FY2024 | O5: FY2025 | Q5: FY? | R5: FY2017 | S5: FY2018 | T5: FY2019 | U5: FY2020 | V5: FY2021 | W5: FY2022 | X5: FY2023 | Y5: FY2024 | Z5: FY2025
A6: # | B6: Profitability and Return Ratios
B7: Return on Equity | C7: = | D7: Net Income | E7: = | F7: =HIST_CON!E26 -> 0 | G7: =HIST_CON!F26 -> 8998900000 | H7: =HIST_CON!G26 -> -3891800000 | I7: =HIST_CON!H26 -> -15310900000 | J7: =HIST_CON!I26 -> -26913900000 | K7: =HIST_CON!J26 -> 1003400000 | L7: =HIST_CON!K26 -> -1661900000 | M7: =HIST_CON!L26 -> 28872900000 | ... O7: =HIST_CON!N26 -> 20716300000 | P7: = | Q7: =IF(F8=0,"",F7/F8) | R7: =IF(G8=0,"",G7/G8) -> -0.13170439 | S7: =IF(H8=0,"",H7/H8) -> 0.055943513 | T7: =IF(I8=0,"",I7/I8) -> 0.18006278 | U7: =IF(J8=0,"",J7/J8) -> 0.2437447 | V7: =IF(K8=0,"",K7/K8) -> -0.029505603 | W7: =IF(L8=0,"",L7/L8) -> 0.046658862 | X7: =IF(M8=0,"",M7/M8) -> 2.6268628 | ... Z7: =IF(O8=0,"",O7/O8) -> 0.33929332
D8: Equity | F8: =HIST_CON!E72 -> 0 | G8: =HIST_CON!F72 -> -68326500000 | H8: =HIST_CON!G72 -> -69566600000 | I8: =HIST_CON!H72 -> -85030900000 | J8: =HIST_CON!I72 -> -110418400000 | K8: =HIST_CON!J72 -> -34007100000 | L8: =HIST_CON!K72 -> -35618100000 | M8: =HIST_CON!L72 -> 10991400000 | ... O8: =HIST_CON!N72 -> 61057200000
B10: Return on Assets | C10: = | D10: Net Income | E10: = | F10: =+F7 -> 0 | G10: =+G7 -> 8998900000 | H10: =+H7 -> -3891800000 | I10: =+I7 -> -15310900000 | J10: =+J7 -> -26913900000 | K10: =+K7 -> 1003400000 | L10: =+L7 -> -1661900000 | M10: =+M7 -> 28872900000 | ... O10: =+O7 -> 20716300000 | P10: = | Q10: =IF(F11=0,"",F10/F11) | R10: =IF(G11=0,"",G10/G11) -> 0.074003503 | S10: =IF(H11=0,"",H10/H11) -> -0.034996408 | T10: =IF(I11=0,"",I10/I11) -> -0.17259672 | U10: =IF(J11=0,"",J10/J11) -> -0.41213564 | V10: =IF(K11=0,"",K10/K11) -> 0.01520052 | W10: =IF(L11=0,"",L10/L11) -> -0.025666964 | X10: =IF(M11=0,"",M10/M11) -> 0.5227397 | ... Z10: =IF(O11=0,"",O10/O11) -> 0.15985305
D11: Total Assets | F11: =HIST_CON!E65 -> 0 | G11: =HIST_CON!F65 -> 121601000000 | H11: =HIST_CON!G65 -> 111205700000 | I11: =HIST_CON!H65 -> 88709100000 | J11: =HIST_CON!I65 -> 65303500000 | K11: =HIST_CON!J65 -> 66010900000 | L11: =HIST_CON!K65 -> 64748600000 | M11: =HIST_CON!L65 -> 55233800000 | ... O11: =HIST_CON!N65 -> 129595900000
B13: Return on Net Assets | C13: = | D13: Net Income | E13: = | F13: =+F7 -> 0 | G13: =+G7 -> 8998900000 | H13: =+H7 -> -3891800000 | I13: =+I7 -> -15310900000 | J13: =+J7 -> -26913900000 | K13: =+K7 -> 1003400000 | L13: =+L7 -> -1661900000 | M13: =+M7 -> 28872900000 | ... O13: =+O7 -> 20716300000 | P13: = | Q13: =IF(F14=0,"",F13/F14) | R13: =IF(G14=0,"",G13/G14) -> -0.28402301 | S13: =IF(H14=0,"",H13/H14) -> 0.51697662 | T13: =IF(I14=0,"",I13/I14) -> 0.45339971 | U13: =IF(J14=0,"",J13/J14) -> 0.24798147 | V13: =IF(K14=0,"",K13/K14) -> 0.052275391 | W13: =IF(L14=0,"",L13/L14) -> -0.098218718 | X13: =IF(M14=0,"",M13/M14) -> 1.3006748 | ... Z13: =IF(O14=0,"",O13/O14) -> 0.49809215
D14: Net PP&E + Net Working Capital | F14: =HIST_CON!E31+(HIST_CON!E63-HIST_CON!E93) -> 0 | G14: =HIST_CON!F31+(HIST_CON!F63-HIST_CON!F93) -> -31683700000 | H14: =HIST_CON!G31+(HIST_CON!G63-HIST_CON!G93) -> -7528000000 | I14: =HIST_CON!H31+(HIST_CON!H63-HIST_CON!H93) -> -33769100000 | J14: =HIST_CON!I31+(HIST_CON!I63-HIST_CON!I93) -> -108531900000 | K14: =HIST_CON!J31+(HIST_CON!J63-HIST_CON!J93) -> 19194500000 | L14: =HIST_CON!K31+(HIST_CON!K63-HIST_CON!K93) -> 16920400000 | M14: =HIST_CON!L31+(HIST_CON!L63-HIST_CON!L93) -> 22198400000 | ... O14: =HIST_CON!N31+(HIST_CON!N63-HIST_CON!N93) -> 41591300000
B16: Return on Invested Capital | C16: = | D16: NOPAT (= EBIT × (1 − Tax Expense / EBT)) | E16: = | F16: =HIST_CON!E19*(1-(-HIST_CON!E25/HIST_CON!E22)) -> #DIV/0! | G16: =HIST_CON!F19*(1-(-HIST_CON!F25/HIST_CON!F22)) -> 2.1709541e+10 | H16: =HIST_CON!G19*(1-(-HIST_CON!G25/HIST_CON!G22)) -> 7.3766313e+09 | I16: =HIST_CON!H19*(1-(-HIST_CON!H25/HIST_CON!H22)) -> -2.983313e+09 | J16: =HIST_CON!I19*(1-(-HIST_CON!I25/HIST_CON!I22)) -> -1.2542372e+10 | K16: =HIST_CON!J19*(1-(-HIST_CON!J25/HIST_CON!J22)) -> 2.8272422e+09 | L16: =HIST_CON!K19*(1-(-HIST_CON!K25/HIST_CON!K22)) -> -2708066050000 | M16: =HIST_CON!L19*(1-(-HIST_CON!L25/HIST_CON!L22)) -> 5.9096532e+09 | ... O16: =HIST_CON!N19*(1-(-HIST_CON!N25/HIST_CON!N22)) -> 2.4365134e+10 | P16: = | Q16: =IF(F17=0,"",F16/F17) | R16: =IF(G17=0,"",G16/G17) -> -8.6351145 | S16: =IF(H17=0,"",H16/H17) -> 0.18135853 | T16: =IF(I17=0,"",I16/I17) -> -0.28515159 | U16: =IF(J17=0,"",J16/J17) -> 0.87187597 | V16: =IF(K17=0,"",K16/K17) -> 0.11133812 | W16: =IF(L17=0,"",L16/L17) -> -116.30987 | X16: =IF(M17=0,"",M16/M17) -> 0.22412981 | ... Z16: =IF(O17=0,"",O16/O17) -> 0.46179148
D17: Invested Capital (= Debt + Equity − Cash) | F17: =(HIST_CON!E76+HIST_CON!E85+0+0)+HIST_CON!E72-HIST_CON!E57 -> 0 | G17: =(HIST_CON!F76+HIST_CON!F85+0+0)+HIST_CON!F72-HIST_CON!F57 -> -2514100000 | H17: =(HIST_CON!G76+HIST_CON!G85+0+0)+HIST_CON!G72-HIST_CON!G57 -> 40674300000 | I17: =(HIST_CON!H76+HIST_CON!H85+0+0)+HIST_CON!H72-HIST_CON!H57 -> 10462200000 | J17: =(HIST_CON!I76+HIST_CON!I85+0+0)+HIST_CON!I72-HIST_CON!I57 -> -14385500000 | K17: =(HIST_CON!J76+HIST_CON!J85+0+0)+HIST_CON!J72-HIST_CON!J57 -> 25393300000 | L17: =(HIST_CON!K76+HIST_CON!K85+0+0)+HIST_CON!K72-HIST_CON!K57 -> 23283200000 | M17: =(HIST_CON!L76+HIST_CON!L85+0+0)+HIST_CON!L72-HIST_CON!L57 -> 26367100000 | ... O17: =(HIST_CON!N76+HIST_CON!N85+0+0)+HIST_CON!N72-HIST_CON!N57 -> 52762200000
B19: Gross Margin | C19: = | D19: Gross Profit | E19: = | F19: =HIST_CON!E14 -> 0 | G19: =HIST_CON!F14 -> 52603000000 | H19: =HIST_CON!G14 -> 32973000000 | I19: =HIST_CON!H14 -> 20762900000 | J19: =HIST_CON!I14 -> 11269100000 | K19: =HIST_CON!J14 -> 17883200000 | L19: =HIST_CON!K14 -> 22724100000 | M19: =HIST_CON!L14 -> 22075000000 | ... O19: =HIST_CON!N14 -> 41065300000 | P19: = | Q19: =IF(F20=0,"",F19/F20) | R19: =IF(G20=0,"",G19/G20) -> 0.41372872 | S19: =IF(H20=0,"",H19/H20) -> 0.39565194 | T19: =IF(I20=0,"",I19/I20) -> 0.41321753 | U19: =IF(J20=0,"",J19/J20) -> 0.37906723 | V19: =IF(K20=0,"",K19/K20) -> 0.53450976 | W19: =IF(L20=0,"",L19/L20) -> 0.34525767 | X19: =IF(M20=0,"",M19/M20) -> 0.36973267 | ... Z19: =IF(O20=0,"",O19/O20) -> 0.37710083
D20: Revenue | F20: =HIST_CON!E7 -> 0 | G20: =HIST_CON!F7 -> 127143700000 | H20: =HIST_CON!G7 -> 83338400000 | I20: =HIST_CON!H7 -> 50246900000 | J20: =HIST_CON!I7 -> 29728500000 | K20: =HIST_CON!J7 -> 33457200000 | L20: =HIST_CON!K7 -> 65817800000 | M20: =HIST_CON!L7 -> 59705300000 | ... O20: =HIST_CON!N7 -> 108897400000
B22: SG&A % of Revenue | C22: = | D22: SG&A | E22: = | F22: =-HIST_CON!E15 -> 0 | G22: =-HIST_CON!F15 -> 10464800000 | H22: =-HIST_CON!G15 -> 8046800000 | I22: =-HIST_CON!H15 -> 8741600000 | J22: =-HIST_CON!I15 -> 7962500000 | K22: =-HIST_CON!J15 -> 5532100000 | L22: =-HIST_CON!K15 -> 5453600000 | M22: =-HIST_CON!L15 -> 6092200000 | ... O22: =-HIST_CON!N15 -> 9415300000 | P22: = | Q22: =IF(F23=0,"",F22/F23) | R22: =IF(G23=0,"",G22/G23) -> 0.08230687 | S22: =IF(H23=0,"",H22/H23) -> 0.096555729 | T22: =IF(I23=0,"",I22/I23) -> 0.17397292 | U22: =IF(J23=0,"",J22/J23) -> 0.26784062 | V22: =IF(K23=0,"",K22/K23) -> 0.16534856 | W22: =IF(L23=0,"",L22/L23) -> 0.082859044 | X22: =IF(M23=0,"",M22/M23) -> 0.10203784 | ... Z22: =IF(O23=0,"",O22/O23) -> 0.086460283
D23: Revenue | F23: =+F20 -> 0 | G23: =+G20 -> 127143700000 | H23: =+H20 -> 83338400000 | I23: =+I20 -> 50246900000 | J23: =+J20 -> 29728500000 | K23: =+K20 -> 33457200000 | L23: =+L20 -> 65817800000 | M23: =+M20 -> 59705300000 | ... O23: =+O20 -> 108897400000
B25: Other Operating Expenses % of Revenue | C25: = | D25: Other Operating Expenses | E25: = | F25: =-HIST_CON!E16 -> 0 | G25: =-HIST_CON!F16 -> 16256100000 | H25: =-HIST_CON!G16 -> 14103900000 | I25: =-HIST_CON!H16 -> 11609300000 | J25: =-HIST_CON!I16 -> 11628200000 | K25: =-HIST_CON!J16 -> 6809600000 | L25: =-HIST_CON!K16 -> 8154100000 | M25: =-HIST_CON!L16 -> 7467300000 | ... O25: =-HIST_CON!N16 -> 12043800000 | P25: = | Q25: =IF(F26=0,"",F25/F26) | R25: =IF(G26=0,"",G25/G26) -> 0.12785612 | S25: =IF(H26=0,"",H25/H26) -> 0.16923651 | T25: =IF(I26=0,"",I25/I26) -> 0.2310451 | U25: =IF(J26=0,"",J25/J26) -> 0.39114654 | V25: =IF(K26=0,"",K25/K26) -> 0.20353168 | W25: =IF(L26=0,"",L25/L26) -> 0.12388898 | X25: =IF(M26=0,"",M25/M26) -> 0.1250693 | ... Z25: =IF(O26=0,"",O25/O26) -> 0.11059768
D26: Revenue | F26: =+F20 -> 0 | G26: =+G20 -> 127143700000 | H26: =+H20 -> 83338400000 | I26: =+I20 -> 50246900000 | J26: =+J20 -> 29728500000 | K26: =+K20 -> 33457200000 | L26: =+L20 -> 65817800000 | M26: =+M20 -> 59705300000 | ... O26: =+O20 -> 108897400000
B28: EBITDA Margin | C28: = | D28: EBITDA | E28: = | F28: =HIST_CON!E17 -> 0 | G28: =HIST_CON!F17 -> 25882100000 | H28: =HIST_CON!G17 -> 10822300000 | I28: =HIST_CON!H17 -> 412000000 | J28: =HIST_CON!I17 -> -8321600000 | K28: =HIST_CON!J17 -> 5541500000 | L28: =HIST_CON!K17 -> 9116400000 | M28: =HIST_CON!L17 -> 8515500000 | ... O28: =HIST_CON!N17 -> 19606200000 | P28: = | Q28: =IF(F29=0,"",F28/F29) | R28: =IF(G29=0,"",G28/G29) -> 0.20356573 | S28: =IF(H29=0,"",H28/H29) -> 0.1298597 | T28: =IF(I29=0,"",I28/I29) -> 0.0081995108 | U28: =IF(J29=0,"",J28/J29) -> -0.27991994 | V28: =IF(K29=0,"",K28/K29) -> 0.16562952 | W28: =IF(L29=0,"",L28/L29) -> 0.13850964 | X28: =IF(M29=0,"",M28/M29) -> 0.14262553 | ... Z28: =IF(O29=0,"",O28/O29) -> 0.18004287
D29: Revenue | F29: =+F20 -> 0 | G29: =+G20 -> 127143700000 | H29: =+H20 -> 83338400000 | I29: =+I20 -> 50246900000 | J29: =+J20 -> 29728500000 | K29: =+K20 -> 33457200000 | L29: =+L20 -> 65817800000 | M29: =+M20 -> 59705300000 | ... O29: =+O20 -> 108897400000
B31: Check | Q31: =IF(ABS(Q19-Q22-Q25-Q28)<0.0001,"OK","Error") -> #VALUE! | R31: =IF(ABS(R19-R22-R25-R28)<0.0001,"OK","Error") -> OK | S31: =IF(ABS(S19-S22-S25-S28)<0.0001,"OK","Error") -> OK | T31: =IF(ABS(T19-T22-T25-T28)<0.0001,"OK","Error") -> OK | U31: =IF(ABS(U19-U22-U25-U28)<0.0001,"OK","Error") -> OK | V31: =IF(ABS(V19-V22-V25-V28)<0.0001,"OK","Error") -> OK | W31: =IF(ABS(W19-W22-W25-W28)<0.0001,"OK","Error") -> OK | X31: =IF(ABS(X19-X22-X25-X28)<0.0001,"OK","Error") -> OK | ... Z31: =IF(ABS(Z19-Z22-Z25-Z28)<0.0001,"OK","Error") -> OK
B33: Depreciation % of Revenue | C33: = | D33: Depreciation & Amortisation | E33: = | F33: =-HIST_CON!E18 -> 0 | G33: =-HIST_CON!F18 -> 3890300000 | H33: =-HIST_CON!G18 -> 3416100000 | I33: =-HIST_CON!H18 -> 3418500000 | J33: =-HIST_CON!I18 -> 4186100000 | K33: =-HIST_CON!J18 -> 2583800000 | L33: =-HIST_CON!K18 -> 2598400000 | M33: =-HIST_CON!L18 -> 2596800000 | ... O33: =-HIST_CON!N18 -> 2591900000 | P33: = | Q33: =IF(F34=0,"",F33/F34) | R33: =IF(G34=0,"",G33/G34) -> 0.030597662 | S33: =IF(H34=0,"",H33/H34) -> 0.040990708 | T33: =IF(I34=0,"",I33/I34) -> 0.068034048 | U33: =IF(J34=0,"",J33/J34) -> 0.14081101 | V33: =IF(K34=0,"",K33/K34) -> 0.077227024 | W33: =IF(L34=0,"",L33/L34) -> 0.039478682 | X33: =IF(M34=0,"",M33/M34) -> 0.043493626 | ... Z33: =IF(O34=0,"",O33/O34) -> 0.023801303
D34: Revenue | F34: =+F20 -> 0 | G34: =+G20 -> 127143700000 | H34: =+H20 -> 83338400000 | I34: =+I20 -> 50246900000 | J34: =+J20 -> 29728500000 | K34: =+K20 -> 33457200000 | L34: =+L20 -> 65817800000 | M34: =+M20 -> 59705300000 | ... O34: =+O20 -> 108897400000
B36: EBIT Margin | C36: = | D36: EBIT | E36: = | F36: =HIST_CON!E19 -> 0 | G36: =HIST_CON!F19 -> 21991800000 | H36: =HIST_CON!G19 -> 7406200000 | I36: =HIST_CON!H19 -> -3006500000 | J36: =HIST_CON!I19 -> -12507700000 | K36: =HIST_CON!J19 -> 2957700000 | L36: =HIST_CON!K19 -> 6518000000 | M36: =HIST_CON!L19 -> 5918700000 | ... O36: =HIST_CON!N19 -> 17014300000 | P36: = | Q36: =IF(F37=0,"",F36/F37) | R36: =IF(G37=0,"",G36/G37) -> 0.17296807 | S36: =IF(H37=0,"",H36/H37) -> 0.088868997 | T36: =IF(I37=0,"",I36/I37) -> -0.059834537 | U36: =IF(J37=0,"",J36/J37) -> -0.42073095 | V36: =IF(K37=0,"",K36/K37) -> 0.088402496 | W36: =IF(L37=0,"",L36/L37) -> 0.099030961 | X36: =IF(M37=0,"",M36/M37) -> 0.099131903 | ... Z36: =IF(O37=0,"",O36/O37) -> 0.15624156
D37: Revenue | F37: =+F20 -> 0 | G37: =+G20 -> 127143700000 | H37: =+H20 -> 83338400000 | I37: =+I20 -> 50246900000 | J37: =+J20 -> 29728500000 | K37: =+K20 -> 33457200000 | L37: =+L20 -> 65817800000 | M37: =+M20 -> 59705300000 | ... O37: =+O20 -> 108897400000
B39: Check | Q39: =IF(ABS(Q28-Q33-Q36)<0.0001,"OK","Error") -> #VALUE! | R39: =IF(ABS(R28-R33-R36)<0.0001,"OK","Error") -> OK | S39: =IF(ABS(S28-S33-S36)<0.0001,"OK","Error") -> OK | T39: =IF(ABS(T28-T33-T36)<0.0001,"OK","Error") -> OK | U39: =IF(ABS(U28-U33-U36)<0.0001,"OK","Error") -> OK | V39: =IF(ABS(V28-V33-V36)<0.0001,"OK","Error") -> OK | W39: =IF(ABS(W28-W33-W36)<0.0001,"OK","Error") -> OK | X39: =IF(ABS(X28-X33-X36)<0.0001,"OK","Error") -> OK | ... Z39: =IF(ABS(Z28-Z33-Z36)<0.0001,"OK","Error") -> OK
B41: Other Non-Operating Expense % of Revenue | C41: = | D41: Finance Costs + Exceptional Items (net) | E41: = | F41: =-(HIST_CON!E20+HIST_CON!E21) -> 0 | G41: =-(HIST_CON!F20+HIST_CON!F21) -> 12875900000 | H41: =-(HIST_CON!G20+HIST_CON!G21) -> 11313600000 | I41: =-(HIST_CON!H20+HIST_CON!H21) -> 12423400000 | J41: =-(HIST_CON!I20+HIST_CON!I21) -> 14331800000 | K41: =-(HIST_CON!J20+HIST_CON!J21) -> 1908000000 | L41: =-(HIST_CON!K20+HIST_CON!K21) -> 6514000000 | M41: =-(HIST_CON!L20+HIST_CON!L21) -> -22998400000 | ... O41: =-(HIST_CON!N20+HIST_CON!N21) -> 2548000000 | P41: = | Q41: =IF(F42=0,"",F41/F42) | R41: =IF(G42=0,"",G41/G42) -> 0.10127045 | S41: =IF(H42=0,"",H41/H42) -> 0.13575495 | T41: =IF(I42=0,"",I41/I42) -> 0.24724709 | U41: =IF(J42=0,"",J41/J42) -> 0.48208958 | V41: =IF(K42=0,"",K41/K42) -> 0.057028084 | W41: =IF(L42=0,"",L41/L42) -> 0.098970187 | X41: =IF(M42=0,"",M41/M42) -> -0.38519863 | ... Z41: =IF(O42=0,"",O41/O42) -> 0.023398171
D42: Revenue | F42: =+F20 -> 0 | G42: =+G20 -> 127143700000 | H42: =+H20 -> 83338400000 | I42: =+I20 -> 50246900000 | J42: =+J20 -> 29728500000 | K42: =+K20 -> 33457200000 | L42: =+L20 -> 65817800000 | M42: =+M20 -> 59705300000 | ... O42: =+O20 -> 108897400000
B44: EBT Margin | C44: = | D44: EBT (Pre-Tax Income) | E44: = | F44: =HIST_CON!E22 -> 0 | G44: =HIST_CON!F22 -> 9115900000 | H44: =HIST_CON!G22 -> -3907400000 | I44: =HIST_CON!H22 -> -15429900000 | J44: =HIST_CON!I22 -> -26839500000 | K44: =HIST_CON!J22 -> 1049700000 | L44: =HIST_CON!K22 -> 4000000 | M44: =HIST_CON!L22 -> 28917100000 | ... O44: =HIST_CON!N22 -> 14466300000 | P44: = | Q44: =IF(F45=0,"",F44/F45) | R44: =IF(G45=0,"",G44/G45) -> 0.071697615 | S44: =IF(H45=0,"",H44/H45) -> -0.046885949 | T44: =IF(I45=0,"",I44/I45) -> -0.30708163 | U44: =IF(J45=0,"",J44/J45) -> -0.90282053 | V44: =IF(K45=0,"",K44/K45) -> 0.031374413 | W44: =IF(L45=0,"",L44/L45) -> 6.0773833e-05 | X44: =IF(M45=0,"",M44/M45) -> 0.48433054 | ... Z44: =IF(O45=0,"",O44/O45) -> 0.13284339
D45: Revenue | F45: =+F20 -> 0 | G45: =+G20 -> 127143700000 | H45: =+H20 -> 83338400000 | I45: =+I20 -> 50246900000 | J45: =+J20 -> 29728500000 | K45: =+K20 -> 33457200000 | L45: =+L20 -> 65817800000 | M45: =+M20 -> 59705300000 | ... O45: =+O20 -> 108897400000
B47: Check | Q47: =IF(ABS(Q36-Q41-Q44)<0.0001,"OK","Error") -> #VALUE! | R47: =IF(ABS(R36-R41-R44)<0.0001,"OK","Error") -> OK | S47: =IF(ABS(S36-S41-S44)<0.0001,"OK","Error") -> OK | T47: =IF(ABS(T36-T41-T44)<0.0001,"OK","Error") -> OK | U47: =IF(ABS(U36-U41-U44)<0.0001,"OK","Error") -> OK | V47: =IF(ABS(V36-V41-V44)<0.0001,"OK","Error") -> OK | W47: =IF(ABS(W36-W41-W44)<0.0001,"OK","Error") -> OK | X47: =IF(ABS(X36-X41-X44)<0.0001,"OK","Error") -> OK | ... Z47: =IF(ABS(Z36-Z41-Z44)<0.0001,"OK","Error") -> OK
B49: Tax % of Revenue | C49: = | D49: Total Tax Expense | E49: = | F49: =-HIST_CON!E25 -> 0 | G49: =-HIST_CON!F25 -> 117000000 | H49: =-HIST_CON!G25 -> -15600000 | I49: =-HIST_CON!H25 -> -119000000 | J49: =-HIST_CON!I25 -> 74400000 | K49: =-HIST_CON!J25 -> 46300000 | L49: =-HIST_CON!K25 -> 1665900000 | M49: =-HIST_CON!L25 -> 44200000 | ... O49: =-HIST_CON!N25 -> -6250000000 | P49: = | Q49: =IF(F50=0,"",F49/F50) | R49: =IF(G50=0,"",G49/G50) -> 0.00092021862 | S49: =IF(H50=0,"",H49/H50) -> -0.00018718862 | T49: =IF(I50=0,"",I49/I50) -> -0.0023683053 | U49: =IF(J50=0,"",J49/J50) -> 0.002502649 | V49: =IF(K50=0,"",K49/K50) -> 0.0013838576 | W49: =IF(L50=0,"",L49/L50) -> 0.025310782 | X49: =IF(M50=0,"",M49/M50) -> 0.00074030279 | ... Z49: =IF(O50=0,"",O49/O50) -> -0.057393473
D50: Revenue | F50: =+F20 -> 0 | G50: =+G20 -> 127143700000 | H50: =+H20 -> 83338400000 | I50: =+I20 -> 50246900000 | J50: =+J20 -> 29728500000 | K50: =+K20 -> 33457200000 | L50: =+L20 -> 65817800000 | M50: =+M20 -> 59705300000 | ... O50: =+O20 -> 108897400000
B52: Net Profit Margin | C52: = | D52: Net Income | E52: = | F52: =+F7 -> 0 | G52: =+G7 -> 8998900000 | H52: =+H7 -> -3891800000 | I52: =+I7 -> -15310900000 | J52: =+J7 -> -26913900000 | K52: =+K7 -> 1003400000 | L52: =+L7 -> -1661900000 | M52: =+M7 -> 28872900000 | ... O52: =+O7 -> 20716300000 | P52: = | Q52: =IF(F53=0,"",F52/F53) | R52: =IF(G53=0,"",G52/G53) -> 0.070777396 | S52: =IF(H53=0,"",H52/H53) -> -0.046698761 | T52: =IF(I53=0,"",I52/I53) -> -0.30471333 | U52: =IF(J53=0,"",J52/J53) -> -0.90532317 | V52: =IF(K53=0,"",K52/K53) -> 0.029990555 | W52: =IF(L53=0,"",L52/L53) -> -0.025250008 | X52: =IF(M53=0,"",M52/M53) -> 0.48359023 | ... Z52: =IF(O53=0,"",O52/O53) -> 0.19023687
D53: Revenue | F53: =+F20 -> 0 | G53: =+G20 -> 127143700000 | H53: =+H20 -> 83338400000 | I53: =+I20 -> 50246900000 | J53: =+J20 -> 29728500000 | K53: =+K20 -> 33457200000 | L53: =+L20 -> 65817800000 | M53: =+M20 -> 59705300000 | ... O53: =+O20 -> 108897400000
B55: Check | Q55: =IF(ABS(Q44-Q49-Q52)<0.0001,"OK","Error") -> #VALUE! | R55: =IF(ABS(R44-R49-R52)<0.0001,"OK","Error") -> OK | S55: =IF(ABS(S44-S49-S52)<0.0001,"OK","Error") -> OK | T55: =IF(ABS(T44-T49-T52)<0.0001,"OK","Error") -> OK | U55: =IF(ABS(U44-U49-U52)<0.0001,"OK","Error") -> OK | V55: =IF(ABS(V44-V49-V52)<0.0001,"OK","Error") -> OK | W55: =IF(ABS(W44-W49-W52)<0.0001,"OK","Error") -> OK | X55: =IF(ABS(X44-X49-X52)<0.0001,"OK","Error") -> OK | ... Z55: =IF(ABS(Z44-Z49-Z52)<0.0001,"OK","Error") -> OK
B57: Effective Tax Rate | C57: = | D57: Total Tax Expense | E57: = | F57: =+F49 -> 0 | G57: =+G49 -> 117000000 | H57: =+H49 -> -15600000 | I57: =+I49 -> -119000000 | J57: =+J49 -> 74400000 | K57: =+K49 -> 46300000 | L57: =+L49 -> 1665900000 | M57: =+M49 -> 44200000 | ... O57: =+O49 -> -6250000000 | P57: = | Q57: =IF(F58=0,"",F57/F58) | R57: =IF(G58=0,"",G57/G58) -> 0.012834717 | S57: =IF(H58=0,"",H57/H58) -> 0.0039924246 | T57: =IF(I58=0,"",I57/I58) -> 0.0077122988 | U57: =IF(J58=0,"",J57/J58) -> -0.0027720338 | V57: =IF(K58=0,"",K57/K58) -> 0.04410784 | W57: =IF(L58=0,"",L57/L58) -> 416.475 | X57: =IF(M58=0,"",M57/M58) -> 0.0015285074 | ... Z57: =IF(O58=0,"",O57/O58) -> -0.4320386
D58: EBT (Pre-Tax Income) | F58: =+F44 -> 0 | G58: =+G44 -> 9115900000 | H58: =+H44 -> -3907400000 | I58: =+I44 -> -15429900000 | J58: =+J44 -> -26839500000 | K58: =+K44 -> 1049700000 | L58: =+L44 -> 4000000 | M58: =+M44 -> 28917100000 | ... O58: =+O44 -> 14466300000
B60: Tax Burden | C60: = | D60: Net Income | E60: = | F60: =+F7 -> 0 | G60: =+G7 -> 8998900000 | H60: =+H7 -> -3891800000 | I60: =+I7 -> -15310900000 | J60: =+J7 -> -26913900000 | K60: =+K7 -> 1003400000 | L60: =+L7 -> -1661900000 | M60: =+M7 -> 28872900000 | ... O60: =+O7 -> 20716300000 | P60: = | Q60: =IF(F61=0,"",F60/F61) | R60: =IF(G61=0,"",G60/G61) -> 0.98716528 | S60: =IF(H61=0,"",H60/H61) -> 0.99600758 | T60: =IF(I61=0,"",I60/I61) -> 0.9922877 | U60: =IF(J61=0,"",J60/J61) -> 1.002772 | V60: =IF(K61=0,"",K60/K61) -> 0.95589216 | W60: =IF(L61=0,"",L60/L61) -> -415.475 | X60: =IF(M61=0,"",M60/M61) -> 0.99847149 | ... Z60: =IF(O61=0,"",O60/O61) -> 1.4320386
D61: EBT (Pre-Tax Income) | F61: =+F44 -> 0 | G61: =+G44 -> 9115900000 | H61: =+H44 -> -3907400000 | I61: =+I44 -> -15429900000 | J61: =+J44 -> -26839500000 | K61: =+K44 -> 1049700000 | L61: =+L44 -> 4000000 | M61: =+M44 -> 28917100000 | ... O61: =+O44 -> 14466300000
B63: Effective Interest Rate | C63: = | D63: Finance Costs (absolute) | E63: = | F63: =ABS(HIST_CON!E20) -> 0 | G63: =ABS(HIST_CON!F20) -> 12875900000 | H63: =ABS(HIST_CON!G20) -> 15809800000 | I63: =ABS(HIST_CON!H20) -> 12699100000 | J63: =ABS(HIST_CON!I20) -> 13672900000 | K63: =ABS(HIST_CON!J20) -> 9962600000 | L63: =ABS(HIST_CON!K20) -> 7345200000 | M63: =ABS(HIST_CON!L20) -> 4207600000 | ... O63: =ABS(HIST_CON!N20) -> 2548000000 | P63: = | Q63: =IF(F64=0,"",F63/F64) | R63: =IF(G64=0,"",G63/G64) -> 0.18613893 | S63: =IF(H64=0,"",H63/H64) -> 0.13623078 | T63: =IF(I64=0,"",I63/I64) -> 0.13195337 | U63: =IF(J64=0,"",J63/J64) -> 0.14116701 | V63: =IF(K64=0,"",K63/K64) -> 0.16062129 | W63: =IF(L64=0,"",L63/L64) -> 0.11493828 | X63: =IF(M64=0,"",M63/M64) -> 0.22088531 | ... Z63: =IF(O64=0,"",O63/O64) -> 0.8993047
D64: Total Debt (= Borrowings + Lease Liabilities) | F64: =(HIST_CON!E76+HIST_CON!E85+0+0) -> 0 | G64: =(HIST_CON!F76+HIST_CON!F85+0+0) -> 69173600000 | H64: =(HIST_CON!G76+HIST_CON!G85+0+0) -> 116051600000 | I64: =(HIST_CON!H76+HIST_CON!H85+0+0) -> 96239300000 | J64: =(HIST_CON!I76+HIST_CON!I85+0+0) -> 96856200000 | K64: =(HIST_CON!J76+HIST_CON!J85+0+0) -> 62025400000 | L64: =(HIST_CON!K76+HIST_CON!K85+0+0) -> 63905600000 | M64: =(HIST_CON!L76+HIST_CON!L85+0+0) -> 19048800000 | ... O64: =(HIST_CON!N76+HIST_CON!N85+0+0) -> 2833300000
B66: Interest Burden | C66: = | D66: EBT (Pre-Tax Income) | E66: = | F66: =+F44 -> 0 | G66: =+G44 -> 9115900000 | H66: =+H44 -> -3907400000 | I66: =+I44 -> -15429900000 | J66: =+J44 -> -26839500000 | K66: =+K44 -> 1049700000 | L66: =+L44 -> 4000000 | M66: =+M44 -> 28917100000 | ... O66: =+O44 -> 14466300000 | P66: = | Q66: =IF(F67=0,"",F66/F67) | R66: =IF(G67=0,"",G66/G67) -> 0.41451359 | S66: =IF(H67=0,"",H66/H67) -> -0.527585 | T66: =IF(I67=0,"",I66/I67) -> 5.1321803 | U66: =IF(J67=0,"",J66/J67) -> 2.1458382 | V66: =IF(K67=0,"",K66/K67) -> 0.35490415 | W66: =IF(L67=0,"",L66/L67) -> 0.00061368518 | X66: =IF(M67=0,"",M66/M67) -> 4.8857181 | ... Z66: =IF(O67=0,"",O66/O67) -> 0.85024362
D67: EBIT | F67: =+F36 -> 0 | G67: =+G36 -> 21991800000 | H67: =+H36 -> 7406200000 | I67: =+I36 -> -3006500000 | J67: =+J36 -> -12507700000 | K67: =+K36 -> 2957700000 | L67: =+L36 -> 6518000000 | M67: =+M36 -> 5918700000 | ... O67: =+O36 -> 17014300000
A69: # | B69: Asset Utilization Ratios
B70: Asset Turnover | C70: = | D70: Revenue | E70: = | F70: =+F20 -> 0 | G70: =+G20 -> 127143700000 | H70: =+H20 -> 83338400000 | I70: =+I20 -> 50246900000 | J70: =+J20 -> 29728500000 | K70: =+K20 -> 33457200000 | L70: =+L20 -> 65817800000 | M70: =+M20 -> 59705300000 | ... O70: =+O20 -> 108897400000 | P70: = | Q70: =IF(F71=0,"",F70/F71) | R70: =IF(G71=0,"",G70/G71) -> 1.045581 | S70: =IF(H71=0,"",H70/H71) -> 0.74940763 | T70: =IF(I71=0,"",I70/I71) -> 0.56642329 | U70: =IF(J71=0,"",J70/J71) -> 0.45523594 | V70: =IF(K71=0,"",K70/K71) -> 0.50684357 | W70: =IF(L71=0,"",L70/L71) -> 1.0165131 | X70: =IF(M71=0,"",M70/M71) -> 1.0809559 | ... Z70: =IF(O71=0,"",O70/O71) -> 0.8402843
D71: Total Assets | F71: =+F11 -> 0 | G71: =+G11 -> 121601000000 | H71: =+H11 -> 111205700000 | I71: =+I11 -> 88709100000 | J71: =+J11 -> 65303500000 | K71: =+K11 -> 66010900000 | L71: =+L11 -> 64748600000 | M71: =+M11 -> 55233800000 | ... O71: =+O11 -> 129595900000
B73: PPE Turnover | C73: = | D73: Revenue | E73: = | F73: =+F20 -> 0 | G73: =+G20 -> 127143700000 | H73: =+H20 -> 83338400000 | I73: =+I20 -> 50246900000 | J73: =+J20 -> 29728500000 | K73: =+K20 -> 33457200000 | L73: =+L20 -> 65817800000 | M73: =+M20 -> 59705300000 | ... O73: =+O20 -> 108897400000 | P73: = | Q73: =IF(F74=0,"",F73/F74) | R73: =IF(G74=0,"",G73/G74) -> 8.9526468 | S73: =IF(H74=0,"",H73/H74) -> 6.5759556 | T73: =IF(I74=0,"",I73/I74) -> 4.3795018 | U73: =IF(J74=0,"",J73/J74) -> 2.8355255 | V73: =IF(K74=0,"",K73/K74) -> 3.5771242 | W73: =IF(L74=0,"",L73/L74) -> 7.254009 | X73: =IF(M74=0,"",M73/M74) -> 7.6697668 | ... Z73: =IF(O74=0,"",O73/O74) -> 13.246892
D74: Net PP&E | F74: =HIST_CON!E31 -> 0 | G74: =HIST_CON!F31 -> 14201800000 | H74: =HIST_CON!G31 -> 12673200000 | I74: =HIST_CON!H31 -> 11473200000 | J74: =HIST_CON!I31 -> 10484300000 | K74: =HIST_CON!J31 -> 9353100000 | L74: =HIST_CON!K31 -> 9073300000 | M74: =HIST_CON!L31 -> 7784500000 | ... O74: =HIST_CON!N31 -> 8220600000
B76: Cash Turnover | C76: = | D76: Revenue | E76: = | F76: =+F20 -> 0 | G76: =+G20 -> 127143700000 | H76: =+H20 -> 83338400000 | I76: =+I20 -> 50246900000 | J76: =+J20 -> 29728500000 | K76: =+K20 -> 33457200000 | L76: =+L20 -> 65817800000 | M76: =+M20 -> 59705300000 | ... O76: =+O20 -> 108897400000 | P76: = | Q76: =IF(F77=0,"",F76/F77) | R76: =IF(G77=0,"",G76/G77) -> 37.826877 | S76: =IF(H77=0,"",H76/H77) -> 14.342231 | T76: =IF(I77=0,"",I76/I77) -> 67.337041 | U76: =IF(J77=0,"",J76/J77) -> 36.108952 | V76: =IF(K77=0,"",K76/K77) -> 12.7456 | W76: =IF(L77=0,"",L76/L77) -> 13.152249 | X76: =IF(M77=0,"",M76/M77) -> 16.254744 | ... Z76: =IF(O77=0,"",O76/O77) -> 9.7856276
D77: Cash & Cash Equivalents | F77: =HIST_CON!E57 -> 0 | G77: =HIST_CON!F57 -> 3361200000 | H77: =HIST_CON!G57 -> 5810700000 | I77: =HIST_CON!H57 -> 746200000 | J77: =HIST_CON!I57 -> 823300000 | K77: =HIST_CON!J57 -> 2625000000 | L77: =HIST_CON!K57 -> 5004300000 | M77: =HIST_CON!L57 -> 3673100000 | ... O77: =HIST_CON!N57 -> 11128300000
B79: Cash Days | C79: = | D79: 365 (days) | E79: = | F79: 365 | G79: 365 | H79: 365 | I79: 365 | J79: 365 | K79: 365 | L79: 365 | M79: 365 | N79: 365 | O79: 365 | P79: = | Q79: =IF(F80=0,"",F79/F80) -> #VALUE! | R79: =IF(G80=0,"",G79/G80) -> 9.6492237 | S79: =IF(H80=0,"",H79/H80) -> 25.449319 | T79: =IF(I80=0,"",I79/I80) -> 5.4204936 | U79: =IF(J80=0,"",J79/J80) -> 10.108297 | V79: =IF(K80=0,"",K79/K80) -> 28.637334 | W79: =IF(L80=0,"",L79/L80) -> 27.751908 | X79: =IF(M80=0,"",M79/M80) -> 22.454983 | ... Z79: =IF(O80=0,"",O79/O80) -> 37.2996
D80: Turnover (above) | F80: =+Q76 | G80: =+R76 -> 37.826877 | H80: =+S76 -> 14.342231 | I80: =+T76 -> 67.337041 | J80: =+U76 -> 36.108952 | K80: =+V76 -> 12.7456 | L80: =+W76 -> 13.152249 | M80: =+X76 -> 16.254744 | ... O80: =+Z76 -> 9.7856276
B82: A/R Turnover | C82: = | D82: Revenue | E82: = | F82: =+F20 -> 0 | G82: =+G20 -> 127143700000 | H82: =+H20 -> 83338400000 | I82: =+I20 -> 50246900000 | J82: =+J20 -> 29728500000 | K82: =+K20 -> 33457200000 | L82: =+L20 -> 65817800000 | M82: =+M20 -> 59705300000 | ... O82: =+O20 -> 108897400000 | P82: = | Q82: =IF(F83=0,"",F82/F83) | R82: =IF(G83=0,"",G82/G83) -> 3.5049662 | S82: =IF(H83=0,"",H82/H83) -> 2.7917659 | T82: =IF(I83=0,"",I82/I83) -> 2.6718689 | U82: =IF(J83=0,"",J82/J83) -> 2.1786463 | V82: =IF(K83=0,"",K82/K83) -> 2.8121911 | W82: =IF(L83=0,"",L82/L83) -> 4.7799702 | X82: =IF(M83=0,"",M82/M83) -> 5.1010987 | ... Z82: =IF(O83=0,"",O82/O83) -> 2.8165427
D83: Trade Receivables, Current | F83: =HIST_CON!E52 -> 0 | G83: =HIST_CON!F52 -> 36275300000 | H83: =HIST_CON!G52 -> 29851500000 | I83: =HIST_CON!H52 -> 18805900000 | J83: =HIST_CON!I52 -> 13645400000 | K83: =HIST_CON!J52 -> 11897200000 | L83: =HIST_CON!K52 -> 13769500000 | M83: =HIST_CON!L52 -> 11704400000 | ... O83: =HIST_CON!N52 -> 38663500000
B85: A/R Days | C85: = | D85: 365 (days) | E85: = | F85: 365 | G85: 365 | H85: 365 | I85: 365 | J85: 365 | K85: 365 | L85: 365 | M85: 365 | N85: 365 | O85: 365 | P85: = | Q85: =IF(F86=0,"",F85/F86) -> #VALUE! | R85: =IF(G86=0,"",G85/G86) -> 104.13795 | S85: =IF(H86=0,"",H85/H86) -> 130.74162 | T85: =IF(I86=0,"",I85/I86) -> 136.6085 | U85: =IF(J86=0,"",J85/J86) -> 167.53523 | V85: =IF(K86=0,"",K85/K86) -> 129.79203 | W85: =IF(L86=0,"",L85/L86) -> 76.360308 | X85: =IF(M86=0,"",M85/M86) -> 71.553212 | ... Z85: =IF(O86=0,"",O85/O86) -> 129.5915
D86: Turnover (above) | F86: =+Q82 | G86: =+R82 -> 3.5049662 | H86: =+S82 -> 2.7917659 | I86: =+T82 -> 2.6718689 | J86: =+U82 -> 2.1786463 | K86: =+V82 -> 2.8121911 | L86: =+W82 -> 4.7799702 | M86: =+X82 -> 5.1010987 | ... O86: =+Z82 -> 2.8165427
